Workbook

Sheet Leitura
A1: Expurgos de transformadores — janeiro a agosto de 2026
A2: Como a base foi montada, o que cada termo significa e onde estão as dinâmicas.
A4: 1. Como a base foi extraída
A5: Código operativo | B5: Somente os que começam com 42, 52, 53 ou 57 — a faixa de transformador de distribuição.
A6: Status da SS | B6: Pendente e Atendida.
A7: Esquema de serviço | B7: MC - Substituição de transformador.
A8: Tipo de SS | B8: FORMS, AVISO DE ANOMALIA e SOLICITAÇÃO DE SERVIÇO.
A9: Período | B9: Aberturas de janeiro a agosto de 2026.
A10: Resultado | B10: Deste recorte saíram 227 solicitações expurgadas, que são as linhas da aba Expurgos.
A12: 2. O que é expurgo
A13: Definição | B13: SS que saiu do indicador de transformadores queimados. Cada linha traz o motivo, a categoria apurada na leitura caso a caso e o texto integral da SS e da OS.
A14: Dois grupos | B14: 115 saíram por mérito próprio e estão encerrados. 112 saíram porque a interrupção não fecha na Crítica e dependem de resposta do COPO — podem voltar ao indicador.
A16: 3. Glossário dos termos usados
A17: Sem interrupção registrada | B17: A Crítica não tem nenhuma interrupção neste transformador em data alguma do período.
A18: Fora da janela de 24 h | B18: A interrupção existe na Crítica, mas não cai na janela de 24 horas em torno da SS.
A19: Troca comprovada pela série | B19: O número de série do transformador retirado é diferente do instalado — a substituição de fato ocorreu.
A20: Obra não comprova a troca | B20: A obra, onde o material trocado é registrado, não foi gerada, não executou nada, ou foi encerrada sem transformador no material.
A21: Trocado, mas sem falha | B21: A troca ocorreu e está documentada, mas por decisão de capacidade ou de rede: remanejamento, preventivo, ajuste de tensão.
A22: Não houve troca nenhuma | B22: O registro diz que nada foi substituído: SS de construção, desativação de posto, ou segunda SS do mesmo evento.
A23: Causa externa ao transformador | B23: A reposição não foi por defeito do equipamento: furto, colisão, terceiros, ou o código nem é de transformador de distribuição.
A25: 4. Onde estão as dinâmicas
A26: Din Categoria | B26: Contagem por macro categoria — as cinco famílias de expurgo.
A27: Din Motivo | B27: Macro categoria aberta por motivo — os 19 motivos registrados.
A28: Din Texto x Motivo | B28: Categoria pelo texto da SS aberta por motivo — a visão dos 172 com texto de queima ou avaria.
A29: Planilha1 | B29: As duas dinâmicas que já vinham na base, preservadas como estavam.
A30: Atualizar | B30: As dinâmicas são atualizadas ao abrir. Para forçar: clique com o botão direito sobre a tabela e escolha Atualizar.
A32: 5. Ressalvas
A33: Julho | B33: A Crítica de julho se perdeu. Os 13 expurgos do mês foram lidos só pelo texto, sem conferência de interrupção — o mês não é comparável aos demais.
A34: Fonte da categoria | B34: 191 categorias vieram prontas da esteira das 1.582; 36 foram lidas caso a caso no período de janeiro a agosto.

Sheet Resumo
A1: Resumo dos 227 expurgos
A2: Todos os números saem por fórmula da aba Expurgos — mudou a base, muda aqui.
A3: Visão geral
A4: Situação | B4: SS | C4: %
A5: Com decisão fechada — não retornam ao indicador | B5: =227-B6 | C5: =B5/$B$7
A6: Aguardando o COPO — interrupção não fecha na Crítica | B6: =COUNTIFS(Expurgos!$D$2:$D$228,"Sem interrupção")+COUNTIFS(Expurgos!$D$2:$D$228,"Fora da janela") | C6: =B6/$B$7
A7: Total | B7: =COUNTA(Expurgos!$A$2:$A$228) | C7: =B7/B7
A9: Por macro categoria
A10: Macro categoria | B10: SS | C10: %
A11: Sem interrupção ou fora da janela | B11: =COUNTIFS(Expurgos!$C$2:$C$228,"Sem interrupção comprovada") | C11: =B11/$B$16
A12: Causa externa ao transformador | B12: =COUNTIFS(Expurgos!$C$2:$C$228,"Causa externa ao transformador") | C12: =B12/$B$16
A13: Trocado, mas sem falha | B13: =COUNTIFS(Expurgos!$C$2:$C$228,"Troca sem falha") | C13: =B13/$B$16
A14: Obra não comprova a troca | B14: =COUNTIFS(Expurgos!$C$2:$C$228,"Sem documento") | C14: =B14/$B$16
A15: Não houve troca nenhuma | B15: =COUNTIFS(Expurgos!$C$2:$C$228,"Não houve troca") | C15: =B15/$B$16
A16: Total | B16: =SUM(B11:B15) | C16: =B16/B16
A18: Os 172 com texto de queima ou avaria
A19: Recorte | B19: SS | C19: %
A20: Param na Crítica: sem interrupção ou fora da janela | B20: =(COUNTIFS(Expurgos!$F$2:$F$228,"QUEIMADO",Expurgos!$D$2:$D$228,"Sem interrupção")+COUNTIFS(Expurgos!$F$2:$F$228,"QUEIMADO",Expurgos!$D$2:$D$228,"Fora da janela")+COUNTIFS(Expurgos!$F$2:$F$228,"AVARIADO",Expurgos!$D$2:$D$228,"Sem interrupção")+COUNTIFS(Expurgos!$F$2:$F$228,"AVARIADO",Expurgos!$D$2:$D$228,"Fora da janela")) | C20: =B20/$B$22
A21: Saíram por motivo apurado na leitura | B21: =B22-B20 | C21: =B21/$B$22
A22: Total com texto de queima ou avaria | B22: =(COUNTIFS(Expurgos!$F$2:$F$228,"QUEIMADO")+COUNTIFS(Expurgos!$F$2:$F$228,"AVARIADO")) | C22: =B22/B22
A24: Por mês
A25: Mês | B25: Expurgos no mês | C25: Aguardando o COPO | D25: % do mês
A26: jan | B26: =COUNTIFS(Expurgos!$B$2:$B$228,"jan") | C26: =COUNTIFS(Expurgos!$B$2:$B$228,"jan",Expurgos!$D$2:$D$228,"Sem interrupção")+COUNTIFS(Expurgos!$B$2:$B$228,"jan",Expurgos!$D$2:$D$228,"Fora da janela") | D26: =IF(B26=0,0,C26/B26)
A27: fev | B27: =COUNTIFS(Expurgos!$B$2:$B$228,"fev") | C27: =COUNTIFS(Expurgos!$B$2:$B$228,"fev",Expurgos!$D$2:$D$228,"Sem interrupção")+COUNTIFS(Expurgos!$B$2:$B$228,"fev",Expurgos!$D$2:$D$228,"Fora da janela") | D27: =IF(B27=0,0,C27/B27)
A28: mar | B28: =COUNTIFS(Expurgos!$B$2:$B$228,"mar") | C28: =COUNTIFS(Expurgos!$B$2:$B$228,"mar",Expurgos!$D$2:$D$228,"Sem interrupção")+COUNTIFS(Expurgos!$B$2:$B$228,"mar",Expurgos!$D$2:$D$228,"Fora da janela") | D28: =IF(B28=0,0,C28/B28)
A29: abr | B29: =COUNTIFS(Expurgos!$B$2:$B$228,"abr") | C29: =COUNTIFS(Expurgos!$B$2:$B$228,"abr",Expurgos!$D$2:$D$228,"Sem interrupção")+COUNTIFS(Expurgos!$B$2:$B$228,"abr",Expurgos!$D$2:$D$228,"Fora da janela") | D29: =IF(B29=0,0,C29/B29)
A30: mai | B30: =COUNTIFS(Expurgos!$B$2:$B$228,"mai") | C30: =COUNTIFS(Expurgos!$B$2:$B$228,"mai",Expurgos!$D$2:$D$228,"Sem interrupção")+COUNTIFS(Expurgos!$B$2:$B$228,"mai",Expurgos!$D$2:$D$228,"Fora da janela") | D30: =IF(B30=0,0,C30/B30)
A31: jun | B31: =COUNTIFS(Expurgos!$B$2:$B$228,"jun") | C31: =COUNTIFS(Expurgos!$B$2:$B$228,"jun",Expurgos!$D$2:$D$228,"Sem interrupção")+COUNTIFS(Expurgos!$B$2:$B$228,"jun",Expurgos!$D$2:$D$228,"Fora da janela") | D31: =IF(B31=0,0,C31/B31)
A32: jul | B32: =COUNTIFS(Expurgos!$B$2:$B$228,"jul") | C32: =COUNTIFS(Expurgos!$B$2:$B$228,"jul",Expurgos!$D$2:$D$228,"Sem interrupção")+COUNTIFS(Expurgos!$B$2:$B$228,"jul",Expurgos!$D$2:$D$228,"Fora da janela") | D32: =IF(B32=0,0,C32/B32)
A33: ago | B33: =COUNTIFS(Expurgos!$B$2:$B$228,"ago") | C33: =COUNTIFS(Expurgos!$B$2:$B$228,"ago",Expurgos!$D$2:$D$228,"Sem interrupção")+COUNTIFS(Expurgos!$B$2:$B$228,"ago",Expurgos!$D$2:$D$228,"Fora da janela") | D33: =IF(B33=0,0,C33/B33)
A34: Total | B34: =SUM(B26:B33) | C34: =SUM(C26:C33) | D34: =C34/B34
A35: Julho não é comparável: a Crítica do mês se perdeu e a conferência de interrupção não rodou.
A37: Prova de troca dentro dos 112 pendentes
A38: Situação | B38: SS | C38: %
A39: Troca comprovada pela série | B39: =COUNTIFS(Expurgos!$D$2:$D$228,"Sem interrupção",Expurgos!$U$2:$U$228,"sim")+COUNTIFS(Expurgos!$D$2:$D$228,"Fora da janela",Expurgos!$U$2:$U$228,"sim") | C39: =B39/$B$41
A40: Sem comprovação pela série | B40: =B41-B39 | C40: =B40/$B$41
A41: Total pendente | B41: =B6 | C41: =B41/B41

Sheet Din Categoria
A1: Dinâmica: Categoria
A2: Contagem de SS por macro categoria. Arraste outros campos na lista à direita para explorar.

Sheet Din Motivo
A1: Dinâmica: Motivo
A2: Macro categoria aberta por motivo registrado na leitura caso a caso.

Sheet Din Texto x Motivo
A1: Dinâmica: Texto x Motivo
A2: Categoria pelo texto da SS aberta por motivo — é aqui que se lê a visão dos 172 com texto de queima ou avaria.

Sheet Planilha1
A3: Rótulos de Linha | B3: Contagem de SS | D3: Rótulos de Linha | E3: Contagem de SS
A4: ABALROAMENTO | B4: 5 | D4: AVARIADO | E4: 47
A5: AVARIADO | B5: 47 | D5: Divisão de circuito | E5: 1
A6: CONSTRUCAO | B6: 1 | D6: Falta de fase | E6: 1
A7: DESATIVACAO | B7: 2 | D7: Fora da janela | E7: 5
A8: FURTADO | B8: 30 | D8: Furto | E8: 2
A9: OUTROS | B9: 3 | D9: Preventivo | E9: 3
A10: PREVENTIVO | B10: 9 | D10: Remanejamento | E10: 4
A11: QUEIMADO | B11: 125 | D11: Sem interrupção | E11: 18
A12: SEM OS | B12: 2 | D12: Sem obra | E12: 3
A13: SEM TEXTO | B13: 1 | D13: Sem troca | E13: 5
A14: SOBRECARGA | B14: 1 | D14: Tap / tensão | E14: 5
A15: TRAFO AUXILIAR | B15: 1 | D15: QUEIMADO | E15: 125
A16: Total Geral | B16: 227 | D16: Abalroamento | E16: 2
D17: Dano de terceiros | E17: 1
D18: Erro de cadastro | E18: 2
D19: Falta de fase | E19: 1
D20: Fora da janela | E20: 25
D21: Furto | E21: 4
D22: Melhoria de posto | E22: 1
D23: Obra sem execução | E23: 1
D24: Obra sem transformador | E24: 3
D25: Preventivo | E25: 5
D26: Remanejamento | E26: 8
D27: Sem interrupção | E27: 64
D28: Sem obra | E28: 3
... D33: Total Geral | E33: 172

Sheet Detalhes1
A1: Detalhes do Contagem de SS - Motivo: Sem interrupção, Categoria pelo texto: QUEIMADO
A3: SS | B3: Mês | C3: Macro categoria | D3: Motivo | E3: Resultado | F3: Categoria pelo texto | G3: Fonte da categoria | H3: Categoria da leitura | I3: Trafo | J3: OS | K3: Obra | L3: Abertura | M3: Término | N3: Tipo da SS | O3: Equipe | P3: Localidade | Q3: Origem da SS | R3: Defeito da SS | S3: NS retirado | T3: NS instalado | U3: Prova de troca | V3: Crítica — causa | W3: Crítica — subcausa | X3: TMAE — causa | Y3: TMAE — subcausa | Z3: No Infotrafo | AA3: Origem da leitura | AB3: Por que saiu | AC3: Texto da SS | AD3: Texto da OS
A4: ETO-RD-AR 01225/2026 | B4: ago | C4: Sem interrupção comprovada | D4: Sem interrupção | E4: EXPURGO | F4: QUEIMADO | G4: leitura do texto (jan–ago) | H4: AUSENTE DA CRÍTICA | I4: 5720186077 | J4: ENC-MPAR02 000052/2026 | K4: 612600770 | L4: 2026-08-08 12:30 | M4: 2026-08-09 01:52 | N4: FORMS SUBST DE TRANSFORMADOR | O4: ETO-RD-AR | P4: GOIATINS | Q4: QUEIMADO | R4: NÃO IDENTIFICADO | S4: 978259 | U4: não | Z4: SIM | AA4: Crítica + TMAE de agosto (novo) | AB4: SS de transformador e para-raio queimados em Goiatins e OS do executante com o quadro completo de retirado (ITB, série 978259, 2015) e instalado (ITAM, série C303245, 2026), o que prova a troca física. O defeito de execução foi lançado como sobrecarga, causa de queima. Trafo ausente da crítica, o que é apenas falta de registro de interrupção e não desmente a falha. | AC4: TRANSFORMADOR QUEIMADO, PARA RAIO QUEIMADO.ACESSO A CAMINHONETE | AD4: ETO-RD-AR 1225/2026 TR: 5720186077 TRAFO RETIRADO POTÊNCIA : 15KVA TENSÃO : 34,5KV Nº ENERGISA (CITD) : 0618142 Nº DE SÉRIE : 978259 MARCA : ITB DATA FABRICAÇÃO : 11/2015 IMPEDANCIA : 3,10 POS. TAP : 05 TRAFO INSTALADO POTÊNCIA : 15KVA TENSÃO : 34,5KV Nº ENERGISA (CITD) : 150865 Nº DE SÉRIE : C303245 MARCA : ITAM DATA FABRICAÇÃO : 13/02/2026 IMPEDANCIA : 3,17 POS. TAP : 03
A5: DOLP-RD-PA 00888/2026 | B5: ago | C5: Sem interrupção comprovada | D5: Sem interrupção | E5: EXPURGO | F5: QUEIMADO | G5: leitura do texto (jan–ago) | H5: AUSENTE DA CRÍTICA | I5: 5750729059 | J5: DLP-MPPA01 000293/2026 | L5: 2026-08-22 13:11 | M5: 2026-08-22 18:00 | N5: FORMS SUBST DE TRANSFORMADOR | O5: DOLP-RD-PA | P5: PALMAS | Q5: QUEIMADO | R5: NÃO IDENTIFICADO | S5: 00 | T5: 0 | U5: não | Z5: SIM | AA5: Crítica + TMAE de agosto (novo) | AB5: Trafo de 112,5 kVA queimado em Palmas com 83 clientes penalizados. O texto da OS e copia literal da SS mais a baixa de material e os dados do atendimento, sem relato do executante, e o formulario veio zerado; o caso esta ausente da critica, o que e falta de registro de interrupcao e nao evidencia de que a falha nao ocorreu. A SS foi atendida no mesmo dia por equipe de manutencao com consumo de material. | AC5: segue ss de 01 trafo de 112,500kva da rede de 13.800kv queimado para ser subistituido pela equipe de manutencão acesso livre clientes penaloizados 83 equipe que atendeu 100op04 cel, 63999345829/992270907 favor agilizar o atendimento devido a quantidade de clientes penalizados | AD5: MEDIDO_ 1. Baixado para consumo de material segue ss de 01 trafo de 112,500kva da rede de 13.800kv queimado para ser subistituido pela equipe de manutencão acesso livre clientes penaloizados 83 equipe que atendeu 100op04 cel, 63999345829/992270907 favor agilizar o atendimento devido a quantidade de clientes penalizados DADOS DO ATENDIMENTO: EQUIPE: 833006 - DLP-MPPA01 ENCARREGADO: IBANEZ RODRIGUES DATA: 22/08/2026
A6: ETO-RD-GR 00632/2026 | B6: jun | C6: Sem interrupção comprovada | D6: Sem interrupção | E6: EXPURGO | F6: QUEIMADO | G6: esteira 1.582 | H6: AUSENTE DA CRÍTICA | I6: 5700782153 | J6: ENC-MLGR01 000151/2026 | K6: 712600426 | L6: 2026-06-19 15:57 | M6: 2026-06-20 14:13 | N6: FORMS SUBST DE TRANSFORMADOR | O6: ETO-RD-GR | P6: BERNARDO SAYAO | Q6: QUEIMADO | R6: NÃO IDENTIFICADO | S6: 846016 | T6: 830326 | U6: sim | V6: CONDUTOR DE AT | W6: PARTIDO NA FASE | Z6: SIM | AA6: leitura caso a caso | AB6: Fora do indicador: a Crítica nunca registrou defeito aberto neste transformador — em data nenhuma dos sete meses. O código aparece na base, mas só como interrompido ou manobrado, que é o que acontece com quem fica sem energia por defeito de outro equipamento. | AC6: TRANSFORMADOR DE 10KVA NA 34,5KV, QUEIMADO, ACESSO CAMINHONETE. | AD6: TROCA DE TRAFO QUEIMADO 5700782153 ETO-RD-GR 632/2026 ZONA RURAL - BERNARDO SAYÃO 0153 TRAFO RETIRADO POTÊNCIA : 10KVA TENSÃO : 19.9KV Nº ENERGISA (CITD) : CITD06012557 Nº DE SÉRIE : 896016 MARCA : ITB DATA FABRICAÇÃO : 05/2014 IMPEDANCIA : 3.00 POS. TAP : 01 TRAFO INSTALADO POTÊNCIA : 15KVA TENSÃO : 19.9KV Nº ENERGISA (CITD) : 151971 Nº DE SÉRIE : 830326 MARCA : TRAEL DATA FABRICAÇÃO : 04/2026 IMPEDANCIA : 3.0 POS. TAP : 03 MEDIÇÃO 1: 26.94 MEDIÇÃO 2: 22.75 MEDIÇÃO 3: 18.57 COORDENADA X: 701966 Y: 9118821
A7: ENC-RD-PS 00594/2026 | B7: jun | C7: Sem interrupção comprovada | D7: Sem interrupção | E7: EXPURGO | F7: QUEIMADO | G7: esteira 1.582 | H7: AUSENTE DA CRÍTICA | I7: 5700417110 | J7: ENC-LMPS03 000095/2026 | K7: 212600540 | L7: 2026-06-21 13:30 | M7: 2026-06-22 19:24 | N7: FORMS SUBST DE TRANSFORMADOR | O7: ENC-RD-PS | P7: SANTA RITA DO TOCANTINS | Q7: QUEIMADO | R7: NÃO IDENTIFICADO | S7: 462535 | T7: 822924 | U7: sim | Z7: SIM | AA7: leitura caso a caso | AB7: Fora do indicador: o código não aparece na Crítica em papel nenhum — nem com defeito, nem interrompido, nem manobrado — nos sete meses do acervo; nem o teste do vizinho achou explicação. | AC7: TRAFO 5700417110 DE 5 KVA NA REDE 19.9 KV QUEIMADO ACESSO BOM TROCAR E O POSTE DO TRAFO ID: 47152336 POIS O MESMO NÃO SUPORTA O TRAFO DE 15 E FINO E O POSTE ANTES DA CHAVE TRAFO 0300417110 NO ID: 68938875 PARA FAZER O SERVIÇO TEM ABRIR CHAVE LAMINA PROXIMO AO TRAFO 5700399073. | AD7: SS ENC-RD-PS 594/2026 TRAFO 5700417110 TRAFO RETIRADO POTÊNCIA : 5KVA TENSÃO : 34.5KV Nº ENERGISA (CITD) : 21593 Nº DE SÉRIE : 462535 MARCA : ITB DATA FABRICAÇÃO : 06/2007 IMPEDANCIA : 2.43 POS. TAP : 02 TRAFO INSTALADO' POTÊNCIA : 15KVA TENSÃO : 34.5KV Nº ENERGISA (CITD) : 149489 Nº DE SÉRIE : 822924 MARCA : TRAEL DATA FABRICAÇÃO : 03/2026 IMPEDANCIA : 3.0 POS. TAP : 03
A8: ENC-RD-PS 00546/2026 | B8: jun | C8: Sem interrupção comprovada | D8: Sem interrupção | E8: EXPURGO | F8: QUEIMADO | G8: esteira 1.582 | H8: AUSENTE DA CRÍTICA | I8: 5701119075 | J8: ENC-LMPS03 000087/2026 | K8: 212600505 | L8: 2026-06-01 16:44 | M8: 2026-06-02 17:57 | N8: FORMS SUBST DE TRANSFORMADOR | O8: ENC-RD-PS | P8: DOIS IRMAOS DO TOCANTINS | Q8: AVARIADO | R8: VAZAMENTO DE ÓLEO | S8: 379996 | U8: não | Z8: SIM | AA8: leitura caso a caso | AB8: Fora do indicador: o ativo não existe na base de interrupção. Sem registro de interrupção não há evento a medir. | AC8: 5701119075 15KVA 34,5KV ACESSO BOM E PARA-RAIOS 075OP02 | AD8: SS ENC-RD-PS 546/2026 TRAFO: 5701119075 TRAFO RETIRADO POTÊNCIA : 15KVA TENSÃO : 34.5KV Nº ENERGISA (CITD) : 035368 Nº DE SÉRIE : 379996 MARCA : TRAEL DATA FABRICAÇÃO : 04/2016 IMPEDANCIA : 2.87 POS. TAP : 03 TRAFO INSTALADO' POTÊNCIA : 15KVA TENSÃO : 34.5KV Nº ENERGISA (CITD) : 151648 Nº DE SÉRIE : C 308217 MARCA : ITAM DATA FABRICAÇÃO : 4/2026 IMPEDANCIA : 3.23 POS. TAP : 03
A9: DOLP-RD-PA 00621/2026 | B9: jun | C9: Sem interrupção comprovada | D9: Sem interrupção | E9: EXPURGO | F9: QUEIMADO | G9: esteira 1.582 | H9: AUSENTE DA CRÍTICA | I9: 5711684122 | J9: DLP-MLPA03 000083/2026 | K9: 112600598 | L9: 2026-06-01 12:34 | M9: 2026-05-22 18:00 | N9: FORMS SUBST DE TRANSFORMADOR | O9: DOLP-RD-PA | P9: PALMAS | Q9: QUEIMADO | R9: DESCARGA ATMOSFÉRICA | S9: 361897 | T9: 303259 | U9: sim | Z9: SIM | AA9: leitura caso a caso | AB9: Fora do indicador: o ativo não existe na base de interrupção. Sem registro de interrupção não há evento a medir. | AC9: TRAFO 5711684122 QUEIMADOPOTÊNCIA: 15 KVATENSÃO: 19,9 KVACESSO: LIVRE | AD9: MEDIDO_ EMERGENCIAL_ TRAFO 5711684122 QUEIMADO - POTÊNCIA: 15 KVA - TENSÃO: 19,9 KV - ACESSO: LIVRE DADOS ATENDIMENTO N° DOCUMENTO SS: DOLP-RD-PA 000621/2026 N° DOCUMENTO OS: DLP-MLPA03 000083/2026 TIPO DA INTERVENÇÃO: MANUTENÇÃO TIPO DO SERVIÇO: SUBSTITUIÇÃO DE TRANSFORMADOR E MELHORIA DE MALHA DE ATERRAMENTO DATA PROGRAMADA DA ATIVIDADE: 02/06/2026 HORARIO PREVISTO DA ATIVIDADE: 08:00 ÀS 18:00 CIDADE: PALMAS - CLASSE DE TENSÃO: 19,9KV ALIMENTADOR: LD02059122 - TRANSFORMADOR: 5711684122 EQUIPE: DOLP-MLPA04 CONTATO DA EQUIPE: 63 9295-4214 COMPOSIÇÃO DA EQUIPE: 1
A10: ETO-RD-AR 00872/2026 | B10: mai | C10: Sem interrupção comprovada | D10: Sem interrupção | E10: EXPURGO | F10: QUEIMADO | G10: esteira 1.582 | H10: AUSENTE DA CRÍTICA | I10: 5710241016 | J10: ENC-MLAR01 000202/2026 | K10: 612600532 | L10: 2026-05-17 17:55 | M10: 2026-05-18 16:15 | N10: FORMS SUBST DE TRANSFORMADOR | O10: ETO-RD-AR | P10: WANDERLANDIA | Q10: QUEIMADO | R10: DESCARGA ATMOSFÉRICA | S10: 66567 | T10: 469632 | U10: sim | V10: MEIO AMBIENTE | W10: DESCARGA ATMOSFERICA | Z10: SIM | AA10: leitura caso a caso | AB10: Fora do indicador: a Crítica nunca registrou defeito aberto neste transformador — em data nenhuma dos sete meses. O código aparece na base, mas só como interrompido ou manobrado, que é o que acontece com quem fica sem energia por defeito de outro equipamento. | AC10: Trafo 5710241016 Queimado Potencia: 10 KVATensão: 34,5 KVPara raio: Queimado Acesso: livreEquipe: 004op26 (63)99214-9597 | AD10: ETO-RD-AR 872/2026 TRAFO 5710241016 TRAFO RETIRADO POTÊNCIA : 10 KVA TENSÃO : 34.5 KV Nº ENERGISA (CITD) : ILEGIVEL Nº DE SÉRIE : 66567 MARCA : TRAEL DATA FABRICAÇÃO : 10/2005 IMPEDANCIA : 3,01 POS. TAP : 03 TRAFO INSTALADO POTÊNCIA : 15 KVA TENSÃO : 34.5 KV Nº ENERGISA (CITD) : 149646 Nº DE SÉRIE : 469632 MARCA : TRAEL DATA FABRICAÇÃO : 05/2018 IMPEDANCIA : 2,89 POS. TAP : 05
A11: ETO-RD-AG 00508/2026 | B11: mai | C11: Sem interrupção comprovada | D11: Sem interrupção | E11: EXPURGO | F11: QUEIMADO | G11: esteira 1.582 | H11: AUSENTE DA CRÍTICA | I11: 5701508039 | J11: ENC-MLAG01 000127/2026 | K11: 662600315 | L11: 2026-05-15 13:32 | M11: 2026-05-16 23:48 | N11: FORMS SUBST DE TRANSFORMADOR | O11: ETO-RD-AG | P11: ARAGUATINS | Q11: QUEIMADO | R11: DESCARGA ATMOSFÉRICA | S11: 125111 | U11: não | Z11: SIM | AA11: leitura caso a caso | AB11: Fora do indicador: o ativo não existe na base de interrupção. Sem registro de interrupção não há evento a medir. | AC11: trafo queimado 5701508039 - 15KVA - 34,5KV - para raio queimado - acesso caminhonete. IND CHACARA BOA ESPERANCA - cliente: JUNHO ALVES DE SOUSA - 63992753298REF PROX AO PEQUENO E AO VALDINAR RDR ARAGUATINS | AD11: OS PARA S6BSTITUICAO DE TRAFO QUEIMADO trafo queimado 5701508039 - 15KVA - 34,5KV - para raio queimado - acesso caminhonete. IND CHACARA BOA ESPERANCA - cliente: JUNHO ALVES DE SOUSA - 63992753298 REF PROX AO PEQUENO E AO VALDINAR RDR ARAGUATINS TRAFO Nº 5701508039 TRAFO INSTALADO POTÊNCIA; 05KVA 34,5KV DATA DE FAB; AGOSTO/2008 MARCA; VIJAI Nº CITD; N/A Nº SÉRIE; 125111 POS. DO TAP; 5 IMPEDÃNCIA; 2,99 TRAFO RETIRADO POTÊNCIA; 15KVA 34,5KV DATA DE FAB; 24/01/2026 MARCA; ITAM Nº CITD; 147933 Nº SÉRIE; C.299646 POS. DO TAP; 3] IMPEDÃNCIA; 2,84 ME
A12: ETO-RD-AG 00489/2026 | B12: mai | C12: Sem interrupção comprovada | D12: Sem interrupção | E12: EXPURGO | F12: QUEIMADO | G12: esteira 1.582 | H12: AUSENTE DA CRÍTICA | I12: 5701350103 | J12: ENC-MLAG01 000121/2026 | K12: 662600297 | L12: 2026-05-08 12:16 | M12: 2026-05-11 08:35 | N12: FORMS SUBST DE TRANSFORMADOR | O12: ETO-RD-AG | P12: SAO MIGUEL DO TOCANTINS | Q12: AVARIADO | R12: BUCHA DANIFICADA | S12: 184716 | T12: 828146 | U12: sim | Z12: SIM | AA12: leitura caso a caso | AB12: Fora do indicador: o ativo não existe na base de interrupção. Sem registro de interrupção não há evento a medir. | AC12: Segue SS de transformador 5701350103 Queimado Potencia 10 KVA Tensão: 19.9 KVAcesso livre Fazenda Jangada. Assentamento Camarão II | AD12: OS PARA SUBSTITUICAO DE TRAFO QUEIMADO Segue SS de transformador 5701350103 Queimado Potencia 10 KVA Tensão: 19.9 KV Acesso livre Fazenda Jangada. Assentamento Camarão II TRAFO Nº 5701350103 TRANSFORMAR RETIRADO POTÊNCIA; 05KVA 34,5KV DATA DE FAB; FEV/2011 MARCA; VIJAI Nº CITD; N/A Nº SÉRIE; 184716 POS. DO TAP; 3º IMPEDÂNCIA; 3,14 TRAFO INSTALADO POTÊNCIA; 15KVA 34,5KV DATA DE FAB; FEV/2026 MARCA; TRAEL Nº CITD; 150423 Nº SÉRIE; 828146 POS. DO TAP; 3º IMPEDÂNCIA; 3 MEDIÇÃO; 3,37 / 3,36 / 3,34
A13: DOLP-RD-PA 00588/2026 | B13: mai | C13: Sem interrupção comprovada | D13: Sem interrupção | E13: EXPURGO | F13: QUEIMADO | G13: esteira 1.582 | H13: AUSENTE DA CRÍTICA | I13: 5761649196 | J13: DLP-CTPA01 000043/2026 | K13: 112600559 | L13: 2026-05-24 00:11 | M13: 2026-05-24 18:00 | N13: FORMS SUBST DE TRANSFORMADOR | O13: DOLP-RD-PA | P13: LAGOA DO TOCANTINS | Q13: QUEIMADO | R13: NÃO IDENTIFICADO | S13: 0 | T13: 0 | U13: não | V13: TRANSFORMADOR | W13: QUEIMADO POR CAUSA NAO IDENTIFICADA | Z13: SIM | AA13: leitura caso a caso | AB13: Fora do indicador: a Crítica nunca registrou defeito aberto neste transformador — em data nenhuma dos sete meses. O código aparece na base, mas só como interrompido ou manobrado, que é o que acontece com quem fica sem energia por defeito de outro equipamento. | AC13: TRAFO QUEIMADO | AD13: MEDIDO_ 01. Baixado para consumo de materiais TRAFO QUEIMADO 75kva NA 34,5KV, REFAZER PIRATICS DO TRANSFORMADO OBS: CIRCUITO DO TRANSFROMADO QUEIMADO EST SENDO ENEGISADO POR OUTRO CIRCUITO, FOI FECHADO JUMP NO LOCAL. ATENÇÃO: VERIFICAR CONDIÇOES DO BARRAMENTO É ATERRAMENTO ATIVO:190.02811475 LOOCALIZAÇÃO: 351531 EQUIPE: CTPA-05 ENCARREGADO: JOSE AILTON TEL: 63 99296-7029
A14: DOLP-RD-PA 00552/2026 | B14: mai | C14: Sem interrupção comprovada | D14: Sem interrupção | E14: EXPURGO | F14: QUEIMADO | G14: esteira 1.582 | H14: AUSENTE DA CRÍTICA | I14: 5365343122 | J14: DLP-MLPA01 000157/2026 | K14: 112600511 | L14: 2026-05-12 17:38 | M14: 2026-05-13 18:00 | N14: FORMS SUBST DE TRANSFORMADOR | O14: DOLP-RD-PA | P14: PALMAS | S14: 1600171 | T14: 299975 | U14: sim | Z14: SIM | AA14: leitura caso a caso | AB14: Fora do indicador: o ativo não existe na base de interrupção. Sem registro de interrupção não há evento a medir. | AC14: segue ss de 01 trafo de 25 kvar e 01 para raio queimado da rede de 13.800kv e para raio queimado para ser subistituido pela equipe de manutencão acesso livre equipe que atendeu 059op14 cel, 63992432595/985159679 chave de referencia, 5365343122 | AD14: MEDIDO_ EMERGENCIAL_ segue ss de 01 trafo de 25 kvar e 01 para raio queimado da rede de 13.800kv e para raio queimado para ser subistituido pela equipe de manutencão acesso livre equipe que atendeu 059op14 cel, 63992432595/985159679 chave de referencia, 5365343122 DADOS ATENDIMENTO N° DOCUMENTO SS: DOLP-RD-PA 000552/2026 N° DOCUMENTO OS: DLP-MLPA01 000157/2026 TIPO DA INTERVENÇÃO: MANUTENÇÃO TIPO DO SERVIÇO: SUBSTITUIÇÃO DE TRANSFORMADOR E MELHORIA DE MALHA DE ATERRAMENTO DATA PROGRAMADA DA ATIVIDADE: 13/05/2026 HORARIO PREVISTO DA ATIVIDADE: 08:00 ÀS 18:00 CIDADE: PA
A15: ETO-RD-GU 00440/2026 | B15: abr | C15: Sem interrupção comprovada | D15: Sem interrupção | E15: EXPURGO | F15: QUEIMADO | G15: esteira 1.582 | H15: AUSENTE DA CRÍTICA | I15: 5700284148 | J15: DBM-MLDB05 000086/2026 | K15: 412600378 | L15: 2026-04-07 18:19 | M15: 2026-04-08 20:00 | N15: FORMS SUBST DE TRANSFORMADOR | O15: ETO-RD-GU | P15: SAO VALERIO | Q15: SOBRECARGA PREVENTIVA | R15: NÃO IDENTIFICADO | S15: 1025954 | T15: 827970 | U15: sim | Z15: não | AA15: leitura caso a caso | AB15: Fora do indicador: o ativo não existe na base de interrupção. Sem registro de interrupção não há evento a medir. | AC15: SEGUE SS DE TRAFO QUEIMADO NA RDR DE SAO VALERIO, TRAFO DE 15KVA NA REDE DE 19.9KV, TRAFO E PARARAIO QUEIMADO, ACESSO LIVRE PARA CAMINHONETE. | AD15: SUBSTITUIÇÃO DE TRANSFORMADOR NA RDR DE SÃO VALÉRIO INT: 20264266691405 SS: ETO-RD-GU 440/2026 ESPECIFICAÇÕES DO TRANSFORMADOR TRANSFORMADOR INSTALADO: 15KVA TRANSFORMADOR RETIRADO: 15KVA MEDIÇÕES LOGO APÓS A TROCA VAN: 212.1 VBN: 221.4 VAB: 420 OBS:SUBSTITUIÇÃO DE TRANSFORMADOR AUTORIZADA PELO DIONE. OBS:FOI FEITO A SEGUNDA DESCIDA DO ATERRAMENTO NO TRANSFORMADOR
A16: ETO-RD-GR 00400/2026 | B16: abr | C16: Sem interrupção comprovada | D16: Sem interrupção | E16: EXPURGO | F16: QUEIMADO | G16: esteira 1.582 | H16: AUSENTE DA CRÍTICA | I16: 5700214066 | J16: ENC-MPGR01 000062/2026 | K16: 712600282 | L16: 2026-04-03 10:19 | M16: 2026-04-03 21:05 | N16: FORMS SUBST DE TRANSFORMADOR | O16: ETO-RD-GR | P16: TUPIRATINS | Q16: QUEIMADO | R16: DESCARGA ATMOSFÉRICA | S16: 389793 | T16: 828102 | U16: sim | Z16: não | AA16: leitura caso a caso | AB16: Fora do indicador: o código não aparece na Crítica em papel nenhum — nem com defeito, nem interrompido, nem manobrado — nos sete meses do acervo; nem o teste do vizinho achou explicação. | AC16: acionar equipe de manutencao para troca do poste e transformador no RDR de [0066] TUPIRATINStrafo 5700214066poste 10-300 id.: 49935819 estrutura u3-Tequipe 034op03 | AD16: TROCA DE TRAFO QUEIMADO 5700214066 ETO-RD-GR 400/2026 ZONA RURAL - TUPIRATINS 0066 TRAFO RETIRADO POTÊNCIA : 15KVA TENSÃO : 19.9KV Nº ENERGISA (CITD) : CITD061006 Nº DE SÉRIE : 389793 MARCA : TRAEL DATA FABRICAÇÃO : 06/2016 IMPEDANCIA : 2.92 POS. TAP : 03 TRAFO INSTALADO POTÊNCIA : 15KVA TENSÃO : 19.9KV Nº ENERGISA (CITD) : 150379 Nº DE SÉRIE : 828102 MARCA : TRAEL DATA FABRICAÇÃO : 02/2026 IMPEDANCIA : 3.0 POS. TAP : 03 MEDIÇÃO 1: 00.15 MEDIÇÃO 2: 00.14 MEDIÇÃO 3: 00.12 COORDENADA X: 808852 Y: 9053576
A17: ETO-RD-DP 00248/2026 | B17: abr | C17: Sem interrupção comprovada | D17: Sem interrupção | E17: EXPURGO | F17: QUEIMADO | G17: esteira 1.582 | H17: AUSENTE DA CRÍTICA | I17: 5700456038 | J17: ETO-RD-DP 000760/2026 | K17: 512600133 | L17: 2026-04-19 12:14 | M17: 2026-04-24 12:22 | N17: FORMS SUBST DE TRANSFORMADOR | O17: ETO-RD-DP | P17: TAGUATINGA | Q17: AVARIADO | R17: BUCHA DANIFICADA | S17: 180034 | T17: 820162 | U17: sim | V17: MEIO AMBIENTE | W17: DESCARGA ATMOSFERICA | Z17: SIM | AA17: leitura caso a caso | AB17: Fora do indicador: a Crítica nunca registrou defeito aberto neste transformador — em data nenhuma dos sete meses. O código aparece na base, mas só como interrompido ou manobrado, que é o que acontece com quem fica sem energia por defeito de outro equipamento. | AC17: trafo e para raio queimado 5700456038 15kva 19.9kv faz.oriente rdr de taguatinga equipe 038op01 | AD17: Atendida pela equipe ETO ML DP 02
A18: ETO-RD-AR 00775/2026 | B18: abr | C18: Sem interrupção comprovada | D18: Sem interrupção | E18: EXPURGO | F18: QUEIMADO | G18: esteira 1.582 | H18: AUSENTE DA CRÍTICA | I18: 5700702019 | J18: ENC-MLAR02 000091/2026 | K18: 612600471 | L18: 2026-04-30 11:15 | M18: 2026-04-30 18:12 | N18: FORMS SUBST DE TRANSFORMADOR | O18: ETO-RD-AR | P18: FILADELFIA | Q18: QUEIMADO | R18: VAZAMENTO DE ÓLEO | S18: 126189 | T18: 799422 | U18: sim | Z18: SIM | AA18: leitura caso a caso | AB18: Fora do indicador: o código não aparece na Crítica em papel nenhum — nem com defeito, nem interrompido, nem manobrado — nos sete meses do acervo; nem o teste do vizinho achou explicação. | AC18: Trafo 5700702019 15kvaAcesso: Livre Equipe:019op02Contato da equipe : 99242-6260 | AD18: ETO-RD-AR 775/2026 TRAFO 5700702019 TRAFO RETIRADO POTÊNCIA : 5 KVA TENSÃO : 34.5 KV Nº ENERGISA (CITD) : ILEGIVEL Nº DE SÉRIE : 126189 MARCA : VIJAI DATA FABRICAÇÃO : 09/2008 IMPEDANCIA : 3,13 POS. TAP : 05 TRAFO INSTALADO POTÊNCIA : 15 KVA TENSÃO : 34.5 KV Nº ENERGISA (CITD) : 150762 Nº DE SÉRIE : 799422 MARCA : TRAEL DATA FABRICAÇÃO : 10/2025 IMPEDANCIA : 3,0 POS. TAP : 05
A19: ETO-RD-AR 00773/2026 | B19: abr | C19: Sem interrupção comprovada | D19: Sem interrupção | E19: EXPURGO | F19: QUEIMADO | G19: esteira 1.582 | H19: AUSENTE DA CRÍTICA | I19: 5700290030 | J19: ENC-MLAR05 000206/2026 | K19: 612600472 | L19: 2026-04-29 18:02 | M19: 2026-04-30 15:53 | N19: FORMS SUBST DE TRANSFORMADOR | O19: ETO-RD-AR | P19: PIRAQUE | Q19: QUEIMADO | R19: SOBRECARGA | S19: 185261 | T19: 822886 | U19: sim | Z19: SIM | AA19: leitura caso a caso | AB19: Fora do indicador: o ativo não existe na base de interrupção. Sem registro de interrupção não há evento a medir. | AC19: TRAFO QUEIMADO 5700920030POTENCIA: 5KVATENSÃO: 34,5KVACESSO BOM.PARA-RAIO QUEIMADO.FAZ. MORENA 1 | AD19: ETO-RD-AR 773/2026 TRAFO 5700920030 TRAFO RETIRADO POTÊNCIA : 05 KVA TENSÃO : 34.5 KV Nº ENERGISA (CITD) : 185261 Nº DE SÉRIE : S/N MARCA : S/N DATA FABRICAÇÃO : S/N IMPEDANCIA : S/N POS. TAP : S/N TRAFO INSTALADO POTÊNCIA : 15 KVA TENSÃO : 34.5 KV Nº ENERGISA (CITD) : 14945 Nº DE SÉRIE : 822886 MARCA : TRAEL DATA FABRICAÇÃO : 02/2026 IMPEDANCIA : 3,0 POS. TAP : 05
A20: ETO-RD-AR 00763/2026 | B20: abr | C20: Sem interrupção comprovada | D20: Sem interrupção | E20: EXPURGO | F20: QUEIMADO | G20: esteira 1.582 | H20: AUSENTE DA CRÍTICA | I20: 5710235080 | J20: ENC-MPAR01 000046/2026 | K20: 612600464 | L20: 2026-04-29 08:53 | M20: 2026-04-28 15:50 | N20: AVISO DE ANOMALIA | O20: ETO-RD-AR | P20: DARCINOPOLIS | Q20: QUEIMADO | R20: DESCARGA ATMOSFÉRICA | S20: 690163 | T20: 822876 | U20: sim | Z20: não | AA20: leitura caso a caso | AB20: Fora do indicador: o ativo não existe na base de interrupção. Sem registro de interrupção não há evento a medir. | AC20: NOTA ABERTA PARA CORREÇÃO DA SS 751/2026 POIS O TRAFO QUE ESTAVA QUEIMADO E O 5710235080 | AD20: ETO-RD-AR 763/2026 TRAFO 5710235080 TRAFO RETIRADO POTÊNCIA : 15 KVA TENSÃO : 34.5 KV Nº ENERGISA (CITD) : 39532 Nº DE SÉRIE : 690163 MARCA : ITB DATA FABRICAÇÃO : 08/2010 IMPEDANCIA : 3,19 POS. TAP : 05 TRAFO INSTALADO POTÊNCIA : 15 KVA TENSÃO : 34.5 KV Nº ENERGISA (CITD) : 149441 Nº DE SÉRIE : 822876 MARCA : TRAEL DATA FABRICAÇÃO : 02/2026 IMPEDANCIA : 3,0 POS. TAP : 05 MEDIÇÃO 1:19.38 MEDIÇÃO 2:18.87 MEDIÇÃO 3:15.24
A21: ETO-RD-AR 00702/2026 | B21: abr | C21: Sem interrupção comprovada | D21: Sem interrupção | E21: EXPURGO | F21: QUEIMADO | G21: esteira 1.582 | H21: AUSENTE DA CRÍTICA | I21: 5701086022 | J21: ENC-MLAR01 000190/2026 | K21: 612600425 | L21: 2026-04-18 17:12 | M21: 2026-04-19 11:35 | N21: FORMS SUBST DE TRANSFORMADOR | O21: ETO-RD-AR | P21: BABACULANDIA | Q21: QUEIMADO | R21: DESCARGA ATMOSFÉRICA | S21: E1274 | T21: 827915 | U21: sim | V21: CHAVE FUSIVEL/RELIGADORA | W21: PORTA-FUSIVEL DANIFICADO | X21: CHAVE FUSIVEL/RELIGADORA | Y21: PORTA-FUSIVEL DANIFICADO | Z21: SIM | AA21: leitura caso a caso | AB21: Fora do indicador: o dono mandou mover para ausente da base de interrupções. Conferido na Crítica crua: o código 5701086022 nunca teve defeito aberto nele em data nenhuma — aparece uma vez, e só como manobrado. Entrava pelo TMAE, e o próprio atendimento registra causa CHAVE FUSIVEL/RELIGADORA com subcausa porta-fusível danificado, não falha do transformador. | AC21: Trafo 5701086022 Queimado Potencia: 15 KVATensão: 34,5 KVPara raio: Queimado Acesso: livreEquipe: 022op02 (63)99255-6152Obs.: leva porta fusivel | AD21: ETO-RD-AR 702/2026 TRAFO 5701086022 TRAFO RETIRADO POTÊNCIA : 15 kva TENSÃO : 34.5 KV Nº ENERGISA (CITD) : P50027 Nº DE SÉRIE : E1274 MARCA : ELETROPAULO DATA FABRICAÇÃO : 05/2009 IMPEDANCIA : 3,0 POS. TAP : 03 TRAFO INSTALADO POTÊNCIA : 15 KVA TENSÃO : 34.5 KV Nº ENERGISA (CITD) : 150192 Nº DE SÉRIE : 827915 MARCA : TRAEL DATA FABRICAÇÃO : 02/2026 IMPEDANCIA : 3,0 POS. TAP : 05 MEDIÇÃO 1: 1.15 MEDIÇÃO 2: 2.04 MEDIÇÃO 3: 3.55 SUBST CHAVE FUSIVEL DANIFICADA 03101634022
A22: ETO-RD-AR 00700/2026 | B22: abr | C22: Sem interrupção comprovada | D22: Sem interrupção | E22: EXPURGO | F22: QUEIMADO | G22: esteira 1.582 | H22: AUSENTE DA CRÍTICA | I22: 5710170025 | J22: ENC-MPAR01 000026/2026 | K22: 612600429 | L22: 2026-04-17 14:38 | M22: 2026-04-18 15:56 | N22: FORMS SUBST DE TRANSFORMADOR | O22: ETO-RD-AR | P22: ARAPOEMA | Q22: QUEIMADO | R22: VAZAMENTO DE ÓLEO | S22: 1663552 | T22: 828161 | U22: sim | Z22: SIM | AA22: leitura caso a caso | AB22: Fora do indicador: o ativo não existe na base de interrupção. Sem registro de interrupção não há evento a medir. | AC22: trafo 5710170025 queimado acesso bom para caminhonete 25kvaequipe 025op01 | AD22: ETO-RD-AR 700/2026 TRAFO 5710170025 TRAFO RETIRADO POTÊNCIA : 25 KVA TENSÃO : 34.5 KV Nº ENERGISA (CITD) : ILEGIVEL Nº DE SÉRIE : 186352 MARCA : UNIÃO DATA FABRICAÇÃO : 09/2001 IMPEDANCIA : 3,0 POS. TAP : 03 TRAFO INSTALADO POTÊNCIA : 25 KVA TENSÃO : 34.5 KV Nº ENERGISA (CITD) : 150438 Nº DE SÉRIE : 828161 MARCA : TRAEL DATA FABRICAÇÃO : 02/2026 IMPEDANCIA : 3,0 POS. TAP : 05 MEDIÇÃO 1: MEDIÇÃO 2: MEDIÇÃO 3:
A23: ETO-RD-AR 00658/2026 | B23: abr | C23: Sem interrupção comprovada | D23: Sem interrupção | E23: EXPURGO | F23: QUEIMADO | G23: esteira 1.582 | H23: AUSENTE DA CRÍTICA | I23: 5761134022 | J23: ENC-MLAR01 000177/2026 | K23: 612600400 | L23: 2026-04-10 10:56 | M23: 2026-04-10 14:49 | N23: FORMS SUBST DE TRANSFORMADOR | O23: ETO-RD-AR | P23: BABACULANDIA | Q23: QUEIMADO | R23: NÃO IDENTIFICADO | S23: 581755 | T23: 1319660 | U23: sim | Z23: SIM | AA23: leitura caso a caso | AB23: Fora do indicador: o ativo não existe na base de interrupção. Sem registro de interrupção não há evento a medir. | AC23: trafo 5761134022 75kva 34.5kv queimado | AD23: ETO-RD-AR 658/2026 TRAFO 5761134022 TRAFO RETIRADO POTÊNCIA : 75 KVA TENSÃO : 34.5 KV Nº ENERGISA (CITD) : 303445 Nº DE SÉRIE : 581755 MARCA : TRAEL DATA FABRICAÇÃO : 06/2021 IMPEDANCIA : 4,02 POS. TAP : 04 TRAFO INSTALADO POTÊNCIA : 75 KVA TENSÃO : 34.5 KV Nº ENERGISA (CITD) : 129465 Nº DE SÉRIE : 1319660 MARCA : ROMAGNOLE DATA FABRICAÇÃO : 2021 IMPEDANCIA : 3,99 POS. TAP : 04
A24: ENC-RD-PS 00438/2026 | B24: abr | C24: Sem interrupção comprovada | D24: Sem interrupção | E24: EXPURGO | F24: QUEIMADO | G24: esteira 1.582 | H24: AUSENTE DA CRÍTICA | I24: 5701060070 | J24: ENC-LMPS04 000063/2026 | K24: 212600400 | L24: 2026-04-07 15:20 | M24: 2026-04-08 15:45 | N24: FORMS SUBST DE TRANSFORMADOR | O24: ENC-RD-PS | P24: RIO SONO | Q24: QUEIMADO | R24: DESCARGA ATMOSFÉRICA | S24: 482388 | T24: 827361 | U24: sim | Z24: SIM | AA24: leitura caso a caso | AB24: Fora do indicador: o ativo não existe na base de interrupção. Sem registro de interrupção não há evento a medir. | AC24: Segue SS de trafo 5701096007 queimado para devidas trativas com equipe de manutenção.Potencia 15 kvatensão 34.5kv para raio bomacesso livre OBS: trafo com erro de cadastro, o mesmo esta cadastrado na rededa 13.8 porem em campo esta ligado na rede da 34.5 kv. trafo fica localizado ao lado do trafo 5700487007 | AD24: SS ENC-RD-PS 438/2026 trafo 5700487007 TRAFO RETIRADO POTÊNCIA : 15KVA TENSÃO : 34.5KV Nº ENERGISA (CITD) : 06118154 Nº DE SÉRIE : 482388 MARCA : TRAEL DATA FABRICAÇÃO : AGO/2018 IMPEDANCIA : 2.92 POS. TAP : 03 TRAFO INSTALADO' POTÊNCIA : 15KVA TENSÃO : 34.5KV Nº ENERGISA (CITD) : 150239 Nº DE SÉRIE : 827362 MARCA : TRAEL DATA FABRICAÇÃO : 02/2026 IMPEDANCIA : 3.0 POS. TAP : 03
A25: DOLP-RD-PA 00437/2026 | B25: abr | C25: Sem interrupção comprovada | D25: Sem interrupção | E25: EXPURGO | F25: QUEIMADO | G25: esteira 1.582 | H25: AUSENTE DA CRÍTICA | I25: 5704106122 | J25: DLP-CTPA00 000069/2026 | K25: 112600401 | L25: 2026-04-09 12:30 | M25: 2026-04-09 18:00 | N25: FORMS SUBST DE TRANSFORMADOR | O25: DOLP-RD-PA | P25: PALMAS | Q25: QUEIMADO | R25: DESCARGA ATMOSFÉRICA | S25: 0 | T25: 0 | U25: não | Z25: SIM | AA25: leitura caso a caso | AB25: Fora do indicador: a Crítica nunca registrou defeito aberto neste transformador — em data nenhuma dos sete meses. O código aparece na base, mas só como interrompido ou manobrado, que é o que acontece com quem fica sem energia por defeito de outro equipamento. | AC25: segue nota de trafo queimado, trafo 5704106122, trafo de 45kva, tensao 13800 / 380 V, para raio danificado, acesso livre | AD25: MEDIDO_ 01. Baixado para consumo de material segue nota de trafo queimado, trafo 5704106122, trafo de 45kva, tensao 13800 / 380 V, para raio danificado, acesso livre DADOS DO ATENDIMENTO: EQUIPE: 833021 - DOLP-CT-PA11 ENCARREGADO: PAFILO ANDALECIO DATA: 09/04/2026
A26: DG-RD-PO 00333/2026 | B26: abr | C26: Sem interrupção comprovada | D26: Sem interrupção | E26: EXPURGO | F26: QUEIMADO | G26: esteira 1.582 | H26: AUSENTE DA CRÍTICA | I26: 5700494044 | J26: DG-MLPO02 000062/2026 | K26: 312600263 | L26: 2026-04-14 17:47 | M26: 2026-04-15 11:50 | N26: FORMS SUBST DE TRANSFORMADOR | O26: DG-RD-PO | P26: FATIMA | Q26: QUEIMADO | R26: BUCHA DANIFICADA | S26: 186148 | T26: 827744 | U26: sim | V26: MEIO AMBIENTE | W26: DESCARGA ATMOSFERICA | Z26: SIM | AA26: leitura caso a caso | AB26: Fora do indicador: a Crítica nunca registrou defeito aberto neste transformador — em data nenhuma dos sete meses. O código aparece na base, mas só como interrompido ou manobrado, que é o que acontece com quem fica sem energia por defeito de outro equipamento. | AC26: ss para trocar trafo 5700494044 e para raio queimado POTENCIA: 15KVA 7.9KVACESSO CAMINHONETE, CARRO FICA A 30 METROS DO LOCAL | AD26: medido_ emergencial_ substituição de trafo queimado rdr fatima
A27: ETO-RD-GU 00377/2026 | B27: mar | C27: Sem interrupção comprovada | D27: Sem interrupção | E27: EXPURGO | F27: QUEIMADO | G27: esteira 1.582 | H27: AUSENTE DA CRÍTICA | I27: 5731386073 | J27: ETO-RD-GU 000932/2026 | K27: 412600315 | L27: 2026-03-23 18:27 | M27: 2026-03-25 15:50 | N27: FORMS SUBST DE TRANSFORMADOR | O27: ETO-RD-GU | P27: LAGOA DA CONFUSAO | Q27: QUEIMADO | R27: DESCARGA ATMOSFÉRICA | S27: 368891 | T27: 827891 | U27: sim | V27: TRANSFORMADOR | W27: QUEIMADO POR CAUSA NAO IDENTIFICADA | Z27: SIM | AA27: leitura caso a caso | AB27: Fora do indicador: a Crítica nunca registrou defeito aberto neste transformador — em data nenhuma dos sete meses. O código aparece na base, mas só como interrompido ou manobrado, que é o que acontece com quem fica sem energia por defeito de outro equipamento. | AC27: TRAFO 5731386073 QUEIMADO EM CAMPO DE 15 KVA ACESSO APENAS DE BARCO REGIAO ALAGADAPARA RAIO QUEIMADO . | AD27: SS: ETO-RD-GU 377-2026 LOCALIDADE: LAGOA DA CONFUSÃO FOI FEITO A TROCA DE UM TRANSFORMADOR DE 15KVA POR 15KVA
A28: ETO-RD-AR 00582/2026 | B28: mar | C28: Sem interrupção comprovada | D28: Sem interrupção | E28: EXPURGO | F28: QUEIMADO | G28: esteira 1.582 | H28: AUSENTE DA CRÍTICA | I28: 5710015080 | J28: ENC-MLAR03 000042/2026 | K28: 612600374 | L28: 2026-03-31 20:03 | M28: 2026-04-02 14:50 | N28: FORMS SUBST DE TRANSFORMADOR | O28: ETO-RD-AR | P28: DARCINOPOLIS | Q28: QUEIMADO | R28: SOBRECARGA | S28: 533216 | T28: 828055 | U28: sim | Z28: SIM | AA28: leitura caso a caso | AB28: Fora do indicador: o ativo não existe na base de interrupção. Sem registro de interrupção não há evento a medir. | AC28: Trafo: 5710015080 QueimadoPotência: 15 KVARede: 34.5Pararaio: 34.5Acesso: só pra veículo traçadoSubstituir o mesmo pois está com a bucha primária quebrado por descarga atmosférica | AD28: ETO-RD-AR 582/2026 TRAFO 5710015080 TRAFO RETIRADO POTÊNCIA : 15 KVA TENSÃO : 3465 KV Nº ENERGISA (CITD) : 6123420 Nº DE SÉRIE : 533216 MARCA : TRAEL DATA FABRICAÇÃO : 03/2020 IMPEDANCIA : 3,0 POS. TAP : 05 TRAFO INSTALADO POTÊNCIA : 15 KVA TENSÃO : 34.5 KV Nº ENERGISA (CITD) : 150332 Nº DE SÉRIE : 828055 MARCA : TRAEL DATA FABRICAÇÃO : 02/2026 IMPEDANCIA : 3,0 POS. TAP : 05
A29: ETO-RD-AR 00557/2026 | B29: mar | C29: Sem interrupção comprovada | D29: Sem interrupção | E29: EXPURGO | F29: QUEIMADO | G29: esteira 1.582 | H29: AUSENTE DA CRÍTICA | I29: 5710138077 | J29: ENC-MLAR02 000072/2026 | K29: 612600344 | L29: 2026-03-26 08:51 | M29: 2026-03-27 18:00 | N29: FORMS SUBST DE TRANSFORMADOR | O29: ETO-RD-AR | P29: GOIATINS | Q29: AVARIADO | R29: SOBRECARGA | S29: 69463 | U29: não | Z29: SIM | AA29: leitura caso a caso | AB29: Fora do indicador: o ativo não existe na base de interrupção. Sem registro de interrupção não há evento a medir. | AC29: TR-5710138077 o mesmo não esta entregando a tensão adequadapara queimadopotência 10kvatensão 13,8kvacesso livreequipe 265op0 tel-63992212789 | AD29: ETO-RD-AR 557/2026 TRAFO 5710138077 TRAFO RETIRADO POTÊNCIA : 10 KVA TENSÃO : 13.8 KV Nº ENERGISA (CITD) : ILEGIVEL Nº DE SÉRIE :69463 MARCA : TRAEL DATA FABRICAÇÃO : 11/2005 IMPEDANCIA : 2,57 POS. TAP : 03 TRAFO INSTALADO POTÊNCIA : 15 KVA TENSÃO : 13.8 KV Nº ENERGISA (CITD) : 149841 Nº DE SÉRIE : C292465 MARCA : ITAM DATA FABRICAÇÃO : 10/2025 IMPEDANCIA : 2,75 POS. TAP : 05 OBS: LANÇADO UMA HORA DE DISPONIBILIDADE REFERENTE AO SERVIÇO DA SS 569/2026 PARA SEGURAR POSTE.
A30: ETO-RD-AR 00555/2026 | B30: mar | C30: Sem interrupção comprovada | D30: Sem interrupção | E30: EXPURGO | F30: QUEIMADO | G30: esteira 1.582 | H30: AUSENTE DA CRÍTICA | I30: 5702259004 | J30: ETO-RD-AR 000876/2026 | K30: 612600355 | L30: 2026-03-25 19:39 | M30: 2026-03-26 17:28 | N30: FORMS SUBST DE TRANSFORMADOR | O30: ETO-RD-AR | P30: ARAGUAINA | Q30: QUEIMADO | R30: NÃO IDENTIFICADO | U30: não | Z30: SIM | AA30: leitura caso a caso | AB30: Fora do indicador: a Crítica nunca registrou defeito aberto neste transformador — em data nenhuma dos sete meses. O código aparece na base, mas só como interrompido ou manobrado, que é o que acontece com quem fica sem energia por defeito de outro equipamento. | AC30: trafo queimado 5702259004 queimado 15 kv 19,9 kva para raio Bom acesso bom.fazenda Santa Tereza - UC 3165559-0 cliente: Persio de Freitas Vilela. RDR Arapoema | AD30: trafo queimado 5702259004 queimado 15 kv 19,9 kva para raio Bom acesso bom. fazenda Santa Tereza - UC 3165559-0 cliente: Persio de Freitas Vilela. RDR Arapoema
A31: ETO-RD-AR 00504/2026 | B31: mar | C31: Sem interrupção comprovada | D31: Sem interrupção | E31: EXPURGO | F31: QUEIMADO | G31: esteira 1.582 | H31: AUSENTE DA CRÍTICA | I31: 5752570159 | J31: ENC-MLAR05 000157/2026 | K31: 612600330 | L31: 2026-03-17 20:04 | M31: 2026-03-18 21:24 | N31: FORMS SUBST DE TRANSFORMADOR | O31: ETO-RD-AR | P31: MURICILANDIA | Q31: QUEIMADO | R31: DESCARGA ATMOSFÉRICA | S31: 1298121 | T31: 586769 | U31: sim | V31: CAUSA NAO IDENTIFICADA | W31: CAUSA NAO IDENTIFICADA - ESPECIFICAR | Z31: SIM | AA31: leitura caso a caso | AB31: Fora do indicador: a Crítica nunca registrou defeito aberto neste transformador — em data nenhuma dos sete meses. O código aparece na base, mas só como interrompido ou manobrado, que é o que acontece com quem fica sem energia por defeito de outro equipamento. | AC31: 5752570159 30kva 34.5kv e para raioacesso livre | AD31: ETO-RD-AR 504/2026 TRAFO 5752570159 TRAFO RETIRADO POTÊNCIA : 30 KVA TENSÃO : 34.4 KV Nº ENERGISA (CITD) : 129196 Nº DE SÉRIE : 1298121 MARCA : ROMAGNOLE DATA FABRICAÇÃO : 06/2024 IMPEDANCIA : 3,69 POS. TAP : 4 TRAFO INSTALADO POTÊNCIA : 30 KVA TENSÃO : 34.5 KV Nº ENERGISA (CITD) : 147732 Nº DE SÉRIE : 586769 MARCA : ITAIPU DATA FABRICAÇÃO : 07/2025 IMPEDANCIA : 3,96 POS. TAP : 04 OBS: LANÇADO DISPONIBILIDADE REFERENTE AO DESLOCAMENTO DA SS ETO-RD-AG 224/2026 PARA FAZER MELHORIA,PORÉM NÃO FOI PRECISO DEVIDO NÃO TER TRAFO NO LOCAL.
A32: ETO-RD-AR 00468/2026 | B32: mar | C32: Sem interrupção comprovada | D32: Sem interrupção | E32: EXPURGO | F32: QUEIMADO | G32: esteira 1.582 | H32: AUSENTE DA CRÍTICA | I32: 5301889004 | J32: ENC-MLAR01 000136/2026 | K32: 612600312 | L32: 2026-03-12 19:30 | M32: 2026-03-13 15:30 | N32: FORMS SUBST DE TRANSFORMADOR | O32: ETO-RD-AR | P32: ARAGUAINA | Q32: QUEIMADO | R32: BUCHA DANIFICADA | S32: 141362 | T32: 826192 | U32: sim | Z32: não | AA32: leitura caso a caso | AB32: Fora do indicador: o dono reviu a própria decisão: “se estiver fora daquelas janelas … deverão ser excluídos”. Ele havia mandado incluir por ler queima com SIGCO incorreto; conferido na Crítica crua, o código 5301889004 não aparece em papel nenhum nos sete meses — nem com defeito, nem interrompido, nem manobrado. Nem o 5701889004 que a OS escreve, nem o 570188904 que a SS escreve. Sem registro de interrupção não há evento a medir. | AC32: Trafo 570188904 queimado 15kvaAcesso: Somente caminhonetePara-raio; Queimado Equipe: 004op26 | AD32: ETO-RD-AR 468/2026 TRAFO 5701889004 TRAFO RETIRADO POTÊNCIA : 15 KVA TENSÃO : 13.8 KV Nº ENERGISA (CITD) : 7658 Nº DE SÉRIE : 141362 MARCA : ITB DATA FABRICAÇÃO : 07/9 IMPEDANCIA : 2,43 POS. TAP : 03 TRAFO INSTALADO POTÊNCIA : 15 KVA TENSÃO : 13.8 KV Nº ENERGISA (CITD) : 149974 Nº DE SÉRIE : 826192 MARCA : TRAEL DATA FABRICAÇÃO : 01/2026 IMPEDANCIA : 2,5 POS. TAP : 05
A33: ETO-RD-AR 00437/2026 | B33: mar | C33: Sem interrupção comprovada | D33: Sem interrupção | E33: EXPURGO | F33: QUEIMADO | G33: esteira 1.582 | H33: AUSENTE DA CRÍTICA | I33: 5701771022 | J33: ENC-MLAR03 000007/2026 | K33: 612600271 | L33: 2026-03-07 13:00 | M33: 2026-03-08 13:40 | N33: FORMS SUBST DE TRANSFORMADOR | O33: ETO-RD-AR | P33: BABACULANDIA | Q33: QUEIMADO | R33: DESCARGA ATMOSFÉRICA | S33: 1611007 | T33: 827838 | U33: sim | Z33: SIM | AA33: leitura caso a caso | AB33: Fora do indicador: o ativo não existe na base de interrupção. Sem registro de interrupção não há evento a medir. | AC33: Trafo 5701771022 queimado 15kvaTensão: 34.5Acesso; somente para caminhonteEquipe: 004op27Endereço: Chacara Bela Vista | AD33: ETO-RD-AR 437/2026 TRAFO 5701771022 TRAFO RETIRADO POTÊNCIA : 15 KVA TENSÃO : 34.5 KV Nº ENERGISA (CITD) : 142471 Nº DE SÉRIE : 1611007 MARCA : ITB DATA FABRICAÇÃO : 05/2024 IMPEDANCIA : 2,88 POS. TAP : 05 TRAFO INSTALADO POTÊNCIA : 15 KVA TENSÃO : 34.5 KV Nº ENERGISA (CITD) : 150115 Nº DE SÉRIE : 827838 MARCA : TRAEL DATA FABRICAÇÃO : 02/2026 IMPEDANCIA : 3,0 POS. TAP : 03
A34: DOLP-RD-PA 00003/2026 | B34: jan | C34: Sem interrupção comprovada | D34: Sem interrupção | E34: EXPURGO | F34: QUEIMADO | G34: esteira 1.582 | H34: AUSENTE DA CRÍTICA | I34: 5700121151 | J34: DLP-CTPA01 000001/2026 | K34: 112600438 | L34: 2026-01-02 15:28 | M34: 2026-01-03 17:32 | N34: FORMS SUBST DE TRANSFORMADOR | O34: DOLP-RD-PA | P34: SANTA TEREZA DO TOCANTINS | Q34: QUEIMADO | R34: NÃO IDENTIFICADO | S34: 185859 | T34: 454942 | U34: sim | Z34: SIM | AA34: leitura caso a caso | AB34: Fora do indicador: o ativo não existe na base de interrupção. Sem registro de interrupção não há evento a medir. | AC34: segue ss de 01 trafo de 30 kvar e 03 para raio queimado da rede de 34,500kv para ser subistituido pela equipe de manutencão acesso bom cliente penalizado 01 equipe que atendeu 151op01 cel, 63992629128/984188058 favor agilizar o atendimento devido cliente informar que está com 03 dias sem energia | AD34: MEDIDO_ EMERGENCIAL_ Msegue ss de 01 trafo de 30 kvar e 03 para raio queimado da rede de 34,500kv para ser subistituido pela equipe de manutencão acesso bom cliente penalizado 01 equipe que atendeu 151op01 cel, 63992629128/984188058 favor agilizar o atendimento devido cliente informar que está com 03 dias sem energia EQUIPE: 833007 ENCARREGADO: JOSE AILTON NO TRAFO [5700121151]
A35: ETO-RD-AR 00434/2026 | B35: mar | C35: Sem interrupção comprovada | D35: Sem interrupção | E35: EXPURGO | F35: QUEIMADO | G35: esteira 1.582 | H35: AUSENTE DA CRÍTICA | I35: 5710028040 | J35: ENC-MLAR01 000130/2026 | K35: 612600266 | L35: 2026-03-06 22:17 | M35: 2026-03-07 16:30 | N35: FORMS SUBST DE TRANSFORMADOR | O35: ETO-RD-AR | P35: ARAGOMINAS | Q35: QUEIMADO | R35: DESCARGA ATMOSFÉRICA | S35: 388798 | T35: 974078 | U35: sim | V35: MEIO AMBIENTE | W35: DESCARGA ATMOSFERICA | Z35: SIM | AA35: leitura caso a caso | AB35: Fora do indicador: a Crítica nunca registrou defeito aberto neste transformador — em data nenhuma dos sete meses. O código aparece na base, mas só como interrompido ou manobrado, que é o que acontece com quem fica sem energia por defeito de outro equipamento. | AC35: Trafo 5710028040 Queimado Potencia:15 KVATensão: 13,8 KVPara raio: Queimado Acesso: CamionetaEquipe: 040op36 (63)992870450 | AD35: ETO-RD-AR 434/2026 TRAFO 5710028040 TRAFO RETIRADO POTÊNCIA :15 KVA TENSÃO : 13.8 KV Nº ENERGISA (CITD) : 05100990 Nº DE SÉRIE : 388798 MARCA : TRAEL DATA FABRICAÇÃO : 06/2016 IMPEDANCIA : 2,4 POS. TAP : 04 TRAFO INSTALADO POTÊNCIA : 15 KVA TENSÃO : 13.8 KV Nº ENERGISA (CITD) : 148906 Nº DE SÉRIE : 974078 MARCA : ITB DATA FABRICAÇÃO : 2015 IMPEDANCIA : 2,38 POS. TAP : 05
A36: ENC-RD-PS 00024/2026 | B36: jan | C36: Sem interrupção comprovada | D36: Sem interrupção | E36: EXPURGO | F36: QUEIMADO | G36: esteira 1.582 | H36: AUSENTE DA CRÍTICA | I36: 5700559233 | J36: ENC-LMPS01 000011/2026 | K36: 212600049 | L36: 2026-01-06 18:36 | M36: 2026-01-07 18:56 | N36: FORMS SUBST DE TRANSFORMADOR | O36: ENC-RD-PS | P36: ABREULANDIA | Q36: QUEIMADO | R36: DESCARGA ATMOSFÉRICA | S36: 525292 | U36: não | Z36: SIM | AA36: leitura caso a caso | AB36: Fora do indicador: o ativo não existe na base de interrupção. Sem registro de interrupção não há evento a medir. | AC36: segue SS ´para tratativa com equipe de manutençao subtituir trafo 5700559233 na rdr de abreulandia | AD36: SS ENC-RD-PS 24/2026 trafo 5700559233 TRAFO RETIRADO POTÊNCIA : 15KVA TENSÃO : 34.5KV Nº ENERGISA (CITD) : 122431 Nº DE SÉRIE : 525292 MARCA : TRAEL DATA FABRICAÇÃO : 01/2020 IMPEDANCIA : 2,91 POS. TAP : 03 TRAFO INSTALADO' POTÊNCIA : 25KVA TENSÃO : 34.5KV Nº ENERGISA (CITD) : 144285 Nº DE SÉRIE : Z 260816 MARCA : ITAM DATA FABRICAÇÃO : 12/2024 IMPEDANCIA : 3.15 POS. TAP : 03
A37: ENC-RD-PS 00044/2026 | B37: jan | C37: Sem interrupção comprovada | D37: Sem interrupção | E37: EXPURGO | F37: QUEIMADO | G37: esteira 1.582 | H37: AUSENTE DA CRÍTICA | I37: 5710028046 | J37: ENC-LMPS04 000011/2026 | K37: 212600073 | L37: 2026-01-11 10:38 | M37: 2026-01-12 16:02 | N37: FORMS SUBST DE TRANSFORMADOR | O37: ENC-RD-PS | P37: NOVA ROSALANDIA | Q37: QUEIMADO | R37: DESCARGA ATMOSFÉRICA | S37: 69095 | U37: não | Z37: SIM | AA37: leitura caso a caso | AB37: Fora do indicador: o ativo não existe na base de interrupção. Sem registro de interrupção não há evento a medir. | AC37: TR 571002804610KVA13800PARA RAIO DANIFICADO ACESSO PARA CAMINHONETE (1)UC PENALIZADA EM CAMPO 046OP01 VILSON | AD37: SS ENC-RD-PS 44/2026 TR 5710028046 TRAFO RETIRADO POTÊNCIA : 10KVA TENSÃO : 13.8KV Nº ENERGISA (CITD) : ILEGIVEL Nº DE SÉRIE :69095 MARCA : TRAEL DATA FABRICAÇÃO : 11/2005 IMPEDANCIA : 2.52 POS. TAP : 01 TRAFO INSTALADO' POTÊNCIA : 15KVA TENSÃO : 34.5KV Nº ENERGISA (CITD) : 137057 Nº DE SÉRIE : C237007 MARCA : ITAM DATA FABRICAÇÃO : 2023 IMPEDANCIA : 2.41 POS. TAP : 03
A38: ENC-RD-PS 00054/2026 | B38: jan | C38: Sem interrupção comprovada | D38: Sem interrupção | E38: EXPURGO | F38: QUEIMADO | G38: esteira 1.582 | H38: AUSENTE DA CRÍTICA | I38: 5701203084 | J38: ENC-LMPS04 000013/2026 | K38: 212600080 | L38: 2026-01-12 13:21 | M38: 2026-01-14 16:40 | N38: FORMS SUBST DE TRANSFORMADOR | O38: ENC-RD-PS | P38: DIVINOPOLIS DO TOCANTINS | Q38: QUEIMADO | R38: DESCARGA ATMOSFÉRICA | S38: 451481 | T38: 290390 | U38: sim | Z38: SIM | AA38: leitura caso a caso | AB38: Fora do indicador: a Crítica nunca registrou defeito aberto neste transformador — em data nenhuma dos sete meses. O código aparece na base, mas só como interrompido ou manobrado, que é o que acontece com quem fica sem energia por defeito de outro equipamento. | AC38: Segue ss para tratativa com equipe de manutençao o quanto antes susbtituir trafo 5701203084 queimado na rdr de divinopoles | AD38: SS ENC-RD-PS 54/2026 trafo 5701203084 TRAFO RETIRADO POTÊNCIA : 15KVA TENSÃO : 34.5KV Nº ENERGISA (CITD) : 06110358 Nº DE SÉRIE : 451481 MARCA : TRAEL DATA FABRICAÇÃO : 12/2017 IMPEDANCIA : 2.96 POS. TAP : 03 TRAFO INSTALADO' POTÊNCIA : 15KVA TENSÃO : 34.5KV Nº ENERGISA (CITD) : 149797 Nº DE SÉRIE : 290390 MARCA : ITAM DATA FABRICAÇÃO : 10/2025 IMPEDANCIA : 3.28 POS. TAP : 03
A39: ENC-RD-PS 00057/2026 | B39: jan | C39: Sem interrupção comprovada | D39: Sem interrupção | E39: EXPURGO | F39: QUEIMADO | G39: esteira 1.582 | H39: AUSENTE DA CRÍTICA | I39: 5710441149 | J39: ENC-LMPS04 000012/2026 | K39: 212600077 | L39: 2026-01-12 17:10 | M39: 2026-01-13 20:09 | N39: FORMS SUBST DE TRANSFORMADOR | O39: ENC-RD-PS | P39: CASEARA | Q39: QUEIMADO | R39: DESCARGA ATMOSFÉRICA | S39: 1568543 | T39: 586759 | U39: sim | Z39: SIM | AA39: leitura caso a caso | AB39: Fora do indicador: o ativo não existe na base de interrupção. Sem registro de interrupção não há evento a medir. | AC39: TR 571044114930KVAT 34500PARA RAIO DANIFICADO ACESSO PARA CAMINHAO (1) PENALIZADA WELVIS SUP. DIVINOPOLIS | AD39: SS ENC-RD-PS 57/2026 TRAFO: 5710428084 TRAFO RETIRADO POTÊNCIA : 30KVA TENSÃO : 34.5KV Nº ENERGISA (CITD) : 143090 Nº DE SÉRIE : 1568543 MARCA : ROMAGNOLE DATA FABRICAÇÃO : 11/2024 IMPEDANCIA : 4.86 POS. TAP : 02 TRAFO INSTALADO' POTÊNCIA : 30KVA TENSÃO : 34.5KV Nº ENERGISA (CITD) : 147722 Nº DE SÉRIE : 586759 MARCA : ITAIPU DATA FABRICAÇÃO : 07/2025 IMPEDANCIA : 3.98 POS. TAP : 02
A40: ETO-RD-AR 00001/2026 | B40: jan | C40: Sem interrupção comprovada | D40: Sem interrupção | E40: EXPURGO | F40: QUEIMADO | G40: esteira 1.582 | H40: AUSENTE DA CRÍTICA | I40: 5703016016 | J40: ENC-MLAR01 000013/2026 | K40: 612600021 | L40: 2026-01-02 10:17 | M40: 2026-01-02 18:00 | N40: FORMS SUBST DE TRANSFORMADOR | O40: ETO-RD-AR | P40: WANDERLANDIA | Q40: QUEIMADO | R40: SOBRECARGA | S40: 180489 | T40: 435142 | U40: sim | Z40: SIM | AA40: leitura caso a caso | AB40: Fora do indicador: o ativo não existe na base de interrupção. Sem registro de interrupção não há evento a medir. | AC40: SUBSTITUIR o Trafo 5703016016Lançar vão de rede de 100 metros , cabo AA / 4Instalar chave trafo ELO 0,5HAcesso livrePotencia de 15 kVA | AD40: ETO-RD-AR 01/2026 TRAFO RETIRADO POTÊNCIA : 15 KVA TENSÃO : 34.5 KV Nº ENERGISA (CITD) : ILEGIVEL Nº DE SÉRIE : 180489 MARCA : ABB DATA FABRICAÇÃO : 04/2002 IMPEDANCIA : 2,9 POS. TAP : 03 TRAFO INSTALADO POTÊNCIA : 15 KVA TENSÃO : 34.5 KV Nº ENERGISA (CITD) : 105598 Nº DE SÉRIE : 435142 MARCA : TRAEL DATA FABRICAÇÃO : 2017 IMPEDANCIA : 2,9 POS. TAP : 05
A41: ETO-RD-AG 00249/2026 | B41: mar | C41: Sem interrupção comprovada | D41: Sem interrupção | E41: EXPURGO | F41: QUEIMADO | G41: esteira 1.582 | H41: AUSENTE DA CRÍTICA | I41: 5700696045 | J41: ENC-MLAG01 000060/2026 | K41: 662600154 | L41: 2026-03-03 12:18 | M41: 2026-03-04 18:23 | N41: FORMS SUBST DE TRANSFORMADOR | O41: ETO-RD-AG | P41: AUGUSTINOPOLIS | Q41: QUEIMADO | R41: DESCARGA ATMOSFÉRICA | S41: 566197014 | T41: 183077 | U41: sim | V41: MEIO AMBIENTE | W41: DESCARGA ATMOSFERICA | Z41: SIM | AA41: leitura caso a caso | AB41: Fora do indicador: a Crítica nunca registrou defeito aberto neste transformador — em data nenhuma dos sete meses. O código aparece na base, mas só como interrompido ou manobrado, que é o que acontece com quem fica sem energia por defeito de outro equipamento. | AC41: TROCA DE TRAFO 5700696045 QUEIMADO DE 30KVA DA 34.5 PARA RAIOS QUEIMADO. ACESSO BOMTROCAR JOGO DE CHAVESUBSTITUIR OS GLV'SLEVAR ROLDANA DA BT. | AD41: TROCA DE TRAFO 5700696045 QUEIMADO DE 30KVA DA 34.5 PARA RAIOS QUEIMADO. ACESSO BOM TROCAR JOGO DE CHAVE SUBSTITUIR OS GLV'S LEVAR ROLDANA DA BT. TRAFO Nº 5700696045 TRAFO RETIRADO POTÊNCIA; 30KVA 34,5KV DATA DE FAB; 07/99 REF.; 11/2017 MARCA; SIEMENS - TRAEL Nº CITD; 108243 Nº SÉRIE; 566197014 POS. DO TAP; 2 IMPEDÂNCIA; 13,26 / 13,04 / 12,97 TRAFO INSTALADO POTÊNCIA; 30KVA 34,5KV DATA DE FAB; 12/01 REF.; 04/2024 MARCA; ABB - TRAEL PA Nº CITD; 138765 Nº SÉRIE; 183077 POS. DO TAP; 2 IMPEDÂNCIA;4,17 MEDIÇÃO; 13,26 / 13,04 /12,97 OBS; SUBST JOGO DE 03X CHAV
A42: ETO-RD-AR 00081/2026 | B42: jan | C42: Sem interrupção comprovada | D42: Sem interrupção | E42: EXPURGO | F42: QUEIMADO | G42: esteira 1.582 | H42: AUSENTE DA CRÍTICA | I42: 5704370057 | J42: ENC-MLAR05 000026/2026 | K42: 612600070 | L42: 2026-01-16 08:57 | M42: 2026-01-16 23:00 | N42: FORMS SUBST DE TRANSFORMADOR | O42: ETO-RD-AR | P42: ARAGUAINA | Q42: QUEIMADO | R42: DESCARGA ATMOSFÉRICA | S42: 371054 | T42: 820201 | U42: sim | Z42: SIM | AA42: leitura caso a caso | AB42: Fora do indicador: o ativo não existe na base de interrupção. Sem registro de interrupção não há evento a medir. | AC42: Trafo 5704370057 15 kva queimadoTensão: 19.9Acesso: Livre Endereço: IND FAZENDA NOVO HORIZONTE, 0 - NOVO HORIZONTE 500M DA PISTA | AD42: ETO-RD-AR 81/2026 TRAFO RETIRADO POTÊNCIA : 15 KVA TENSÃO : 34.5 KV Nº ENERGISA (CITD) : ILEGIVEL Nº DE SÉRIE : 371054 MARCA : TOSHIBA DATA FABRICAÇÃO : 11/99 IMPEDANCIA : 3,0 POS. TAP : 03 TRAFO INSTALADO POTÊNCIA : 15 KVA TENSÃO : 34.5 KV Nº ENERGISA (CITD) : 149215 Nº DE SÉRIE : 820201 MARCA : TRAEL DATA FABRICAÇÃO : 11/2025 IMPEDANCIA : 3,0 POS. TAP : 05
A43: ETO-RD-AR 00118/2026 | B43: jan | C43: Sem interrupção comprovada | D43: Sem interrupção | E43: EXPURGO | F43: QUEIMADO | G43: esteira 1.582 | H43: AUSENTE DA CRÍTICA | I43: 5700746004 | J43: ENC-MLAR01 000054/2026 | K43: 612600086 | L43: 2026-01-19 21:44 | M43: 2026-01-20 20:50 | N43: FORMS SUBST DE TRANSFORMADOR | O43: ETO-RD-AR | P43: ARAGUAINA | Q43: QUEIMADO | R43: DESCARGA ATMOSFÉRICA | S43: 1294 | T43: 820197 | U43: sim | Z43: SIM | AA43: leitura caso a caso | AB43: Fora do indicador: o ativo não existe na base de interrupção. Sem registro de interrupção não há evento a medir. | AC43: Trafo 5700746004 queimado 15kvaTensão: 19.9Acesso somente para caminhoneteEquipe: 004op08 | AD43: ETO-RD-AR 118/2026 TRAFO RETIRADO POTÊNCIA : 10 KVA TENSÃO : 34.5 KV Nº ENERGISA (CITD) : ILEGIVEL Nº DE SÉRIE : 1294 MARCA : CROSS DATA FABRICAÇÃO : 04/95 IMPEDANCIA : 2,5 POS. TAP : 04 TRAFO INSTALADO POTÊNCIA : 15 KVA TENSÃO : 34.5 KV Nº ENERGISA (CITD) : 149211 Nº DE SÉRIE : 820197 MARCA : TRAEL DATA FABRICAÇÃO : 11/2025 IMPEDANCIA : 3,0 POS. TAP : 05
A44: ETO-RD-GR 00052/2026 | B44: jan | C44: Sem interrupção comprovada | D44: Sem interrupção | E44: EXPURGO | F44: QUEIMADO | G44: esteira 1.582 | H44: AUSENTE DA CRÍTICA | I44: 5741943048 | J44: ENC-MLGR03 000015/2026 | K44: 712600047 | L44: 2026-01-09 18:59 | M44: 2026-01-10 22:28 | N44: FORMS SUBST DE TRANSFORMADOR | O44: ETO-RD-GR | P44: FORTALEZA DO TABOCAO | Q44: QUEIMADO | R44: DESCARGA ATMOSFÉRICA | S44: 1510147 | T44: 489685 | U44: sim | Z44: SIM | AA44: leitura caso a caso | AB44: Fora do indicador: o ativo não existe na base de interrupção. Sem registro de interrupção não há evento a medir. | AC44: trafo queimado 5710088048, porem em campo esta o trafo 5741943048112.5 kVAacesso livre pararaio queimadoequipe 009op01- 63999201531 | AD44: SUBSTITUIÇÃO DE TRAFO 5710088048 ETO-RD-GR 52/2026 RDR FORTALEZA DO TABOCÃO TRAFO RETIRADO POTÊNCIA : 112,5KV TENSÃO : 34,5KV Nº ENERGISA (CITD) : 138563 Nº DE SÉRIE : 1510147 MARCA : ROMAGNOLE DATA FABRICAÇÃO : 03/2024 IMPEDANCIA : 3,87 POS. TAP : 02 TRAFO INSTALADO POTÊNCIA : 150KVA TENSÃO : 34,5KV Nº ENERGISA (CITD) : 135119 Nº DE SÉRIE : 489685 MARCA : ITAIPU DATA FABRICAÇÃO : 03/2023 IMPEDANCIA : 4,03 POS. TAP : 02 MEDIÇÃO 1: 11,57 MEDIÇÃO 2: 07,98 MEDIÇÃO 3: 06,51 COORDENADA: X: 785308 Y: 9006432 OBS: O TRAFO INFORMADO NA SS É O 5741943048, MAS QUAN
A45: ETO-RD-GR 00095/2026 | B45: jan | C45: Sem interrupção comprovada | D45: Sem interrupção | E45: EXPURGO | F45: QUEIMADO | G45: esteira 1.582 | H45: AUSENTE DA CRÍTICA | I45: 5700396048 | J45: ENC-MLGR03 000031/2026 | K45: 712600063 | L45: 2026-01-16 16:33 | M45: 2026-01-17 02:02 | N45: FORMS SUBST DE TRANSFORMADOR | O45: ETO-RD-GR | P45: FORTALEZA DO TABOCAO | Q45: QUEIMADO | R45: DESCARGA ATMOSFÉRICA | S45: 573184 | T45: 820202 | U45: sim | Z45: SIM | AA45: leitura caso a caso | AB45: Fora do indicador: o código não aparece na Crítica em papel nenhum — nem com defeito, nem interrompido, nem manobrado — nos sete meses do acervo; nem o teste do vizinho achou explicação. | AC45: Trafo: 5700396048 Avariado Potencia: 15 KVATensão: 34,5kPara raio: queimado Acesso: Camioneta Equipe: 009op02 (63)99983-3829Obs. trafo esta com tensão baixa em uma das buchas. | AD45: SUBTITUIÇÃO DE TRAFO 5700396048 FAZ. MASC. ESPERANÇA II RDR DE FORTALEZA DO TABOCÃO TRAFO RETIRADO POTÊNCIA : 15KVA TENSÃO : 34,5KV Nº ENERGISA (CITD) : 127938 Nº DE SÉRIE : 573184 MARCA : TRAEL DATA FABRICAÇÃO : 04/2021 IMPEDANCIA : 3,0 POS. TAP : 02 TRAFO INSTALADO POTÊNCIA : 15KVA TENSÃO : 34,5KV Nº ENERGISA (CITD) : 149216 Nº DE SÉRIE : 820202 MARCA : TRAEL DATA FABRICAÇÃO : 11/2025 IMPEDANCIA : 3,0 POS. TAP : 03 MEDIÇÃO 1: 17,45 MEDIÇÃO 2: 11,57 MEDIÇÃO 3: 10,73 COORD. X: 786636 Y: 9005551
A46: ETO-RD-GR 00140/2026 | B46: jan | C46: Sem interrupção comprovada | D46: Sem interrupção | E46: EXPURGO | F46: QUEIMADO | G46: esteira 1.582 | H46: AUSENTE DA CRÍTICA | I46: 5700922009 | J46: ETO-RD-GR 000231/2026 | K46: 712600101 | L46: 2026-01-28 20:04 | M46: 2026-01-31 08:29 | N46: FORMS SUBST DE TRANSFORMADOR | O46: ETO-RD-GR | P46: GUARAI | Q46: QUEIMADO | R46: DESCARGA ATMOSFÉRICA | U46: não | Z46: SIM | AA46: leitura caso a caso | AB46: Fora do indicador: o ativo não existe na base de interrupção. Sem registro de interrupção não há evento a medir. | AC46: TR-5700922009 Queimadopara raios queiamado potência 10kvatensão 34,5kvacesso livreequipe 009op01 tel-63984566867 | AD46: TR-5700922009 Queimado para raios queiamado potência 10kva tensão 34,5kv acesso livre equipe 009op01 tel-63984566867
A47: ETO-RD-GU 00066/2026 | B47: jan | C47: Sem interrupção comprovada | D47: Sem interrupção | E47: EXPURGO | F47: QUEIMADO | G47: esteira 1.582 | H47: AUSENTE DA CRÍTICA | I47: 5710535094 | J47: DBM-MLDB05 000013/2026 | K47: 412600114 | L47: 2026-01-13 20:52 | M47: 2026-01-15 16:00 | N47: FORMS SUBST DE TRANSFORMADOR | O47: ETO-RD-GU | P47: PEIXE | Q47: QUEIMADO | R47: DESCARGA ATMOSFÉRICA | S47: 225341 | U47: não | Z47: SIM | AA47: leitura caso a caso | AB47: Fora do indicador: a Crítica nunca registrou defeito aberto neste transformador — em data nenhuma dos sete meses. O código aparece na base, mas só como interrompido ou manobrado, que é o que acontece com quem fica sem energia por defeito de outro equipamento. | AC47: transformador e para raio queimado | AD47: SUBSTITUIÇÃO DE TRANSFORMADOR NA RDR DE PEIXE INT: 20264079688074 SS: ETO-RD-GU 66/2026 ESPECIFICAÇÕES DO TRANSFORMADOR TRANSFORMADOR INSTALADO: 15 KVA TRANSFORMADOR RETIRADO: 5 KVA MEDIÇÕES LOGO APÓS A TROCA VAN: 209 OBS:SUBSTITUIÇÃO DE TRANSFORMADOR AUTORIZADA PELO DIONE.
A48: ETO-RD-GU 00073/2026 | B48: jan | C48: Sem interrupção comprovada | D48: Sem interrupção | E48: EXPURGO | F48: QUEIMADO | G48: esteira 1.582 | H48: AUSENTE DA CRÍTICA | I48: 5701108076 | J48: DBM-MLDB03 000008/2026 | K48: 412600116 | L48: 2026-01-14 16:27 | M48: 2026-01-16 12:01 | N48: FORMS SUBST DE TRANSFORMADOR | O48: ETO-RD-GU | P48: CARIRI DO TOCANTINS | Q48: QUEIMADO | R48: DESCARGA ATMOSFÉRICA | S48: 20674 | U48: não | Z48: não | AA48: leitura caso a caso | AB48: Fora do indicador: o ativo não existe na base de interrupção. Sem registro de interrupção não há evento a medir. | AC48: transformador e para raio queimado | AD48: SUBSTITUIÇÃO DE TRANSFORMADOR NA RDR DE DUERE INT: 20264080370563 SS: ETO-RD-GU 73/2026 ESPECIFICAÇÕES DO TRANSFORMADOR TRANSFORMADOR INSTALADO: 15 KVA TRANSFORMADOR RETIRADO: 05 KVA MEDIÇÕES LOGO APÓS A TROCA VAN: 202 VBN: 202 OBS:SUBSTITUIÇÃO DE TRANSFORMADOR AUTORIZADA PELO DIONE.
A49: DG-RD-PO 00179/2026 | B49: fev | C49: Sem interrupção comprovada | D49: Sem interrupção | E49: EXPURGO | F49: QUEIMADO | G49: esteira 1.582 | H49: AUSENTE DA CRÍTICA | I49: 5710046096 | J49: DG-MLPO01 000039/2026 | K49: 312500671 | L49: 2026-02-12 10:28 | M49: 2026-02-12 10:44 | N49: FORMS SUBST DE TRANSFORMADOR | O49: DG-RD-PO | P49: PINDORAMA DO TOCANTINS | Q49: QUEIMADO | R49: DESCARGA ATMOSFÉRICA | S49: 1463815 | T49: 1219870 | U49: sim | Z49: SIM | AA49: leitura caso a caso | AB49: Fora do indicador: o ativo não existe na base de interrupção. Sem registro de interrupção não há evento a medir. | AC49: SEGUE SS PARA SUBSTITUIR TRAFO QEUIMADO NA RDR DE PINDORAMAOBS: NOTA CRIADA PARA SUBST. A SS 800/2025 QUE FOI ABERTA NO TRAFO ERRADO | AD49: medido_ emergencial_ substituição de trafo queimado rdr pindorama obs: OS CRIADA PARA SUBSTITUIR MLPO0190/2025 OBRA 0312500671 TRAFO ERRADO
A50: DG-RD-PO 00180/2026 | B50: fev | C50: Sem interrupção comprovada | D50: Sem interrupção | E50: EXPURGO | F50: QUEIMADO | G50: esteira 1.582 | H50: AUSENTE DA CRÍTICA | I50: 5710046096 | J50: DG-MPDG01 000049/2026 | K50: 312500675 | L50: 2026-02-12 10:44 | M50: 2026-02-12 11:05 | N50: FORMS SUBST DE TRANSFORMADOR | O50: DG-RD-PO | P50: PINDORAMA DO TOCANTINS | Q50: GARANTIA DE TRAFO | R50: DESCARGA ATMOSFÉRICA | S50: 1219870 | T50: 586782 | U50: sim | Z50: não | AA50: leitura caso a caso | AB50: Fora do indicador: o ativo não existe na base de interrupção. Sem registro de interrupção não há evento a medir. | AC50: SEGUE SS PARA SUBSTITUIR TRAFO QUEIMADO OBS: NOTA CRIADA PARA SUBST. SS 814/2025 ABERTA NO TRAFO ERRADO | AD50: medido_ emergencial_ substituição de trafo queimado rdr pindorama obs: OS SUBSITUINDO OS MPDG01 210-2025 OBRA 0312500675 TRAFO ERRADO
A51: ENC-RD-PS 00361/2026 | B51: mar | C51: Sem interrupção comprovada | D51: Sem interrupção | E51: EXPURGO | F51: QUEIMADO | G51: esteira 1.582 | H51: AUSENTE DA CRÍTICA | I51: 5701007008 | J51: ENC-LMPS03 000066/2026 | K51: 212600341 | L51: 2026-03-19 10:47 | M51: 2026-03-19 17:44 | N51: FORMS SUBST DE TRANSFORMADOR | O51: ENC-RD-PS | P51: MIRANORTE | Q51: QUEIMADO | R51: DESCARGA ATMOSFÉRICA | S51: 388932 | T51: 827738 | U51: sim | Z51: SIM | AA51: leitura caso a caso | AB51: Fora do indicador: o ativo não existe na base de interrupção. Sem registro de interrupção não há evento a medir. | AC51: OS:20264186004963Segue SS de TR queimado UC 9222677 e 3635120 TR não cadastrado 15KVA/7.9KV e para-raios queimados.Acesso livre.Localização: https://www.google.com/maps/search/?api=1&query=-9.534713,-48.600728 SS aberta no TR 5701007008 porém o que está queimado é outro.FAZENDA BOA SORTE63984910222 E 992859555LUZENI NERES DE OLIVEIRA SOUSA008OP01 63 99222-7417 | AD51: SS ENC-RD-PS 361/2026 TRAFO: 5701007008 TRAFO RETIRADO POTÊNCIA : 15KVA TENSÃO : 13.8KV Nº ENERGISA (CITD) : ILEGIVEL Nº DE SÉRIE : 388932 MARCA : TRAEL DATA FABRICAÇÃO : 06/2016 IMPEDANCIA : 2.41 POS. TAP : 01 TRAFO INSTALADO' POTÊNCIA : 15KVA TENSÃO : 13.8KV Nº ENERGISA (CITD) : 150015 Nº DE SÉRIE : 827738 MARCA : TRAEL DATA FABRICAÇÃO : 02/2026 IMPEDANCIA : 2.5 POS. TAP : 03
A52: ENC-RD-PS 00177/2026 | B52: fev | C52: Sem interrupção comprovada | D52: Sem interrupção | E52: EXPURGO | F52: QUEIMADO | G52: esteira 1.582 | H52: AUSENTE DA CRÍTICA | I52: 5701299084 | J52: ENC-LMPS04 000027/2026 | K52: 212600157 | L52: 2026-02-02 14:50 | M52: 2026-02-03 19:00 | N52: FORMS SUBST DE TRANSFORMADOR | O52: ENC-RD-PS | P52: DIVINOPOLIS DO TOCANTINS | Q52: QUEIMADO | R52: DESCARGA ATMOSFÉRICA | S52: 111028 | T52: 811235 | U52: sim | V52: PARA-RAIOS | W52: PARA-RAIOS CURTO-CIRCUITADO | Z52: SIM | AA52: leitura caso a caso | AB52: Fora do indicador: a Crítica nunca registrou defeito aberto neste transformador — em data nenhuma dos sete meses. O código aparece na base, mas só como interrompido ou manobrado, que é o que acontece com quem fica sem energia por defeito de outro equipamento. | AC52: Segue ss para tratativa com equipe de manutençao o quanto antessubstituir trafo 5701299084 | AD52: SS ENC-RD-PS 177/2026 trafo 5701299084 TRAFO RETIRADO POTÊNCIA : 10KVA TENSÃO : 34.5KV Nº ENERGISA (CITD) : ILEGIVEL Nº DE SÉRIE : 111028 MARCA : VIJAI DATA FABRICAÇÃO : 02/2011 IMPEDANCIA : 2.90 POS. TAP : 03 TRAFO INSTALADO' POTÊNCIA : 15KVA TENSÃO : 34.5KV Nº ENERGISA (CITD) : 149145 Nº DE SÉRIE : 811235 MARCA : TRAEL DATA FABRICAÇÃO : AGO/2025 IMPEDANCIA : 3.0 POS. TAP : 03
A53: ENC-RD-PS 00246/2026 | B53: fev | C53: Sem interrupção comprovada | D53: Sem interrupção | E53: EXPURGO | F53: QUEIMADO | G53: esteira 1.582 | H53: AUSENTE DA CRÍTICA | I53: 5720337055 | J53: ENC-LMPS04 000039/2026 | K53: 212600217 | L53: 2026-02-17 15:45 | M53: 2026-02-18 16:00 | N53: FORMS SUBST DE TRANSFORMADOR | O53: ENC-RD-PS | P53: ARAGUACEMA | Q53: QUEIMADO | R53: DESCARGA ATMOSFÉRICA | S53: 367926 | T53: 572129 | U53: sim | V53: MEIO AMBIENTE | W53: DESCARGA ATMOSFERICA | X53: TRANSFORMADOR | Y53: QUEIMADO POR DESCARGA ATMOSFERICA | Z53: SIM | AA53: leitura caso a caso | AB53: Fora do indicador: o dono mandou mover para ausente da base de interrupções. Conferido na Crítica crua: o código 5720337055 nunca teve defeito aberto nele em data nenhuma dos sete meses — aparece uma vez, e só como manobrado. O caso entrava pelo TMAE, não pela Crítica: era um F0, atendimento no código do trafo sem ocorrência que o sustentasse. | AC53: TR 572033705515KVAPARA RAIO DANIFIFCADO 34500CAMINHONETE EQUIPE 055OP01 | AD53: SS ENC-RD-PS 246/2026 TR 5720337055 TRAFO RETIRADO POTÊNCIA : 15KVA TENSÃO : 34.5KV Nº ENERGISA (CITD) : ILEGIVEL Nº DE SÉRIE : 367926 MARCA : TOSHIBA DATA FABRICAÇÃO : 06/1999 IMPEDANCIA : 3.0 POS. TAP : 03 TRAFO INSTALADO' POTÊNCIA : 15KVA TENSÃO : 34.5KV Nº ENERGISA (CITD) : 148868 Nº DE SÉRIE : 572129 MARCA : TRAEL DATA FABRICAÇÃO : 2025 IMPEDANCIA : 3.07 POS. TAP : 03
A54: ENC-RD-PS 00259/2026 | B54: fev | C54: Sem interrupção comprovada | D54: Sem interrupção | E54: EXPURGO | F54: QUEIMADO | G54: esteira 1.582 | H54: AUSENTE DA CRÍTICA | I54: 5700191054 | J54: ENC-LMPS01 000074/2026 | K54: 212600238 | L54: 2026-02-20 13:46 | M54: 2026-02-22 07:41 | N54: FORMS SUBST DE TRANSFORMADOR | O54: ENC-RD-PS | P54: PUGMIL | Q54: QUEIMADO | R54: ABALROADO | S54: C241333 | U54: não | V54: POSTE DE AT | W54: ABALROADO | X54: POSTE DE AT | Y54: ABALROADO | Z54: não | AA54: leitura caso a caso | AB54: Fora do indicador: o ativo não existe na base de interrupção. Sem registro de interrupção não há evento a medir. | AC54: substituir poste ID 47042587 10/300 estrutura do TR 5700191054 15KVA 19,9KV ACESSO BOM fotos anexadas na OS 20264131749370 | AD54: SS ENC-RD-PS 259/2026 TR 5700191054 TRAFO RETIRADO POTÊNCIA : 15KVA TENSÃO : 34.5KV Nº ENERGISA (CITD) : 137853 Nº DE SÉRIE : C 241333 MARCA : ITAM DATA FABRICAÇÃO : 09/2023 IMPEDANCIA : 3.0 POS. TAP : 03 TRAFO INSTALADO' POTÊNCIA : 15KVA TENSÃO : 34.5KV Nº ENERGISA (CITD) : 147906 Nº DE SÉRIE : C299631 MARCA : ITAM DATA FABRICAÇÃO : 01/2026 IMPEDANCIA : 3.02 POS. TAP : 03
A55: ETO-RD-AG 00164/2026 | B55: fev | C55: Sem interrupção comprovada | D55: Sem interrupção | E55: EXPURGO | F55: QUEIMADO | G55: esteira 1.582 | H55: AUSENTE DA CRÍTICA | I55: 5700032103 | J55: ENC-MPAG02 000017/2026 | K55: 662600087 | L55: 2026-02-07 19:18 | M55: 2026-02-08 01:55 | N55: FORMS SUBST DE TRANSFORMADOR | O55: ETO-RD-AG | P55: SAO MIGUEL DO TOCANTINS | Q55: QUEIMADO | R55: DESCARGA ATMOSFÉRICA | S55: 990387 | T55: 20084012 | U55: sim | Z55: SIM | AA55: leitura caso a caso | AB55: Fora do indicador: a Crítica nunca registrou defeito aberto neste transformador — em data nenhuma dos sete meses. O código aparece na base, mas só como interrompido ou manobrado, que é o que acontece com quem fica sem energia por defeito de outro equipamento. | AC55: trafo queimado | AD55: trafo queimado TRAFO RETIRADO POTÊNCIA; 112,5KVA 34,5KV DATA DE FAB; 01/2015 - REFORMA; 09/2025 MARCA; ROMAGNOLE - TRAEL-PA Nº CITD; 132844 Nº SÉRIE; 990387 IMPEDÂNCIA; 4,12 POS. TAP; 3 TRAFO INSTALADO POTÊNCIA; 112,5KVA 34,5KV DATA DE FAB; 09/2024 MARCA; TAMURA Nº CITD; 143798 Nº SÉRIE; 20084012 IMPEDÂNCIA; 3,86 POS. TAP; 2º MEDIÇÃO; 5,92 / 5,94 / 06,39
A56: ETO-RD-AR 00207/2026 | B56: fev | C56: Sem interrupção comprovada | D56: Sem interrupção | E56: EXPURGO | F56: QUEIMADO | G56: esteira 1.582 | H56: AUSENTE DA CRÍTICA | I56: 5366985025 | J56: ENC-MLAR05 000089/2026 | K56: 612600141 | L56: 2026-02-02 13:43 | M56: 2026-02-02 18:00 | N56: FORMS SUBST DE TRANSFORMADOR | O56: ETO-RD-AR | P56: ARAPOEMA | Q56: QUEIMADO | R56: DESCARGA ATMOSFÉRICA | S56: C 287221 | T56: 820280 | U56: sim | Z56: SIM | AA56: leitura caso a caso | AB56: Fora do indicador: o ativo não existe na base de interrupção. Sem registro de interrupção não há evento a medir. | AC56: Boa noite,Favor enviar manutenção para subsitutir trafo 5366985025 | AD56: ETO-RD-AR 207/2026 TR: 5366985025 TRAFO RETIRADO POTÊNCIA : 15KVA TENSÃO : 34,5KV Nº ENERGISA (CITD) : 148084 Nº DE SÉRIE : C287221 MARCA : ITAM DATA FABRICAÇÃO : 08/2025 IMPEDANCIA : 3,13 POS. TAP : 03 TRAFO INSTALADO POTÊNCIA : 15KVA TENSÃO : 34,5KV Nº ENERGISA (CITD) : 149294 Nº DE SÉRIE : 820280 MARCA : TRAEL DATA FABRICAÇÃO : 11/2025 IMPEDANCIA : 3,0 POS. TAP : 03
A57: ENC-RD-PS 00358/2026 | B57: mar | C57: Sem interrupção comprovada | D57: Sem interrupção | E57: EXPURGO | F57: QUEIMADO | G57: esteira 1.582 | H57: AUSENTE DA CRÍTICA | I57: 5700460055 | J57: ENC-LMPS04 000054/2026 | K57: 212600327 | L57: 2026-03-17 18:55 | M57: 2026-03-18 18:02 | N57: FORMS SUBST DE TRANSFORMADOR | O57: ENC-RD-PS | P57: ARAGUACEMA | Q57: QUEIMADO | R57: DESCARGA ATMOSFÉRICA | S57: C299635 | T57: 828125 | U57: sim | Z57: SIM | AA57: leitura caso a caso | AB57: Fora do indicador: o ativo não existe na base de interrupção. Sem registro de interrupção não há evento a medir. | AC57: TR 5763273055 15KVAPARA RAIO DANIFICADO ACESSO LIVRE PARA CAMINHONETE 055OP01 ESTEVE NO LOCAL TRAFO NAO AXISTE NO SISTEMA (ERRO CADASTRO) FICA PROX AO TR 5700460055MAIS INFORMAÇOES ENTRA EM CONTATO COM EQUIPE 055OP01 | AD57: SS ENC-RD-PS 358/2026 TR 5763273055 TRAFO NAO AXISTE NO SISTEMA (ERRO CADASTRO) FICA PROX AO TR 5700460055 TRAFO RETIRADO POTÊNCIA : 15KVA TENSÃO : 34.5KV Nº ENERGISA (CITD) : 147908 Nº DE SÉRIE : C299635 MARCA : ITAM DATA FABRICAÇÃO : 01/206 IMPEDANCIA : 2.92 POS. TAP : 03 TRAFO INSTALADO' POTÊNCIA : 15KVA TENSÃO : 34.5KV Nº ENERGISA (CITD) : 150402 Nº DE SÉRIE : 828125 MARCA : TRAEL DATA FABRICAÇÃO : 02/2026 IMPEDANCIA : 3.0 POS. TAP : 03
A58: DOLP-RD-PA 00382/2026 | B58: mar | C58: Sem interrupção comprovada | D58: Sem interrupção | E58: EXPURGO | F58: QUEIMADO | G58: esteira 1.582 | H58: AUSENTE DA CRÍTICA | I58: 5763161196 | J58: DLP-MLPA01 000099/2026 | K58: 112600358 | L58: 2026-03-24 14:14 | M58: 2026-03-23 18:20 | N58: FORMS SUBST DE TRANSFORMADOR | O58: DOLP-RD-PA | P58: LAGOA DO TOCANTINS | Q58: QUEIMADO | R58: DESCARGA ATMOSFÉRICA | S58: 474885 | T58: 1403743 | U58: sim | V58: CAUSA NAO IDENTIFICADA | W58: CAUSA NAO IDENTIFICADA - ESPECIFICAR | Z58: SIM | AA58: leitura caso a caso | AB58: Fora do indicador: a Crítica nunca registrou defeito aberto neste transformador — em data nenhuma dos sete meses. O código aparece na base, mas só como interrompido ou manobrado, que é o que acontece com quem fica sem energia por defeito de outro equipamento. | AC58: SEGUE SS DE TRAFO 5763161196 QUEIMADO NA RDR DE LAGOA DO TOCANTINS. PARA AS DEVIDAS TRATATIVAS COM EQUIPE DE MANUTENÇÃOOBS: LEVAR JOGO DE CHAVE FUSIVEL PARA INSTALAR NA MESMA ESTRUTURA DE TRAFO | AD58: MEDIDO_ EMERGENCIAL_ SEGUE SS DE TRAFO 5763161196 QUEIMADO NA RDR DE LAGOA DO TOCANTINS. PARA AS DEVIDAS TRATATIVAS COM EQUIPE DE MANUTENÇÃO OBS: LEVAR JOGO DE CHAVE FUSIVEL PARA INSTALAR NA MESMA ESTRUTURA DE TRAFO DADOS ATENDIMENTO N° DOCUMENTO SS: DOLP-RD-PA 000382/2026 N° DOCUMENTO OS: DLP-MLPA01 000099/2026 TIPO DA INTERVENÇÃO: MANUTENÇÃO TIPO DO SERVIÇO: SUBSTITUIÇÃO DE TRANSFORMADOR, MELHORIA DE MALHA DE ATERRAMENTO E SUBSTITUIÇÃO DE CHAVE FUSIVEL POTENCIA: 15KVA - CLASSE DE TENSÃO: 34,5KV DATA PROGRAMADA DA ATIVIDADE: 23/03/2026 À 24/03/2026 HORARIO PREVISTO D
A59: ETO-RD-GR 00174/2026 | B59: fev | C59: Sem interrupção comprovada | D59: Sem interrupção | E59: EXPURGO | F59: QUEIMADO | G59: esteira 1.582 | H59: AUSENTE DA CRÍTICA | I59: 5747088104 | J59: ETO-RD-GR 000258/2026 | K59: 712600133 | L59: 2026-02-03 13:24 | M59: 2026-02-06 08:20 | N59: FORMS SUBST DE TRANSFORMADOR | O59: ETO-RD-GR | P59: BOM JESUS DO TOCANTINS | Q59: QUEIMADO | R59: DESCARGA ATMOSFÉRICA | U59: não | Z59: SIM | AA59: leitura caso a caso | AB59: Fora do indicador: o ativo não existe na base de interrupção. Sem registro de interrupção não há evento a medir. | AC59: trafo queimado 5747088104 - 15KVA - 34,5KV - Acesso caminhonete - para raio queimadofazenda conquista - cliente Jose Reis Amario da Silva tel. 9.92521087 rdr Bom Jesus do Tocantins | AD59: trafo queimado 5747088104 - 15KVA - 34,5KV - Acesso caminhonete - para raio queimado fazenda conquista - cliente Jose Reis Amario da Silva tel. 9.92521087 rdr Bom Jesus do Tocantins
A60: ETO-RD-GR 00189/2026 | B60: fev | C60: Sem interrupção comprovada | D60: Sem interrupção | E60: EXPURGO | F60: QUEIMADO | G60: esteira 1.582 | H60: AUSENTE DA CRÍTICA | I60: 5700424154 | J60: ETO-RD-GR 000256/2026 | K60: 712600129 | L60: 2026-02-04 18:05 | M60: 2026-02-05 15:30 | N60: FORMS SUBST DE TRANSFORMADOR | O60: ETO-RD-GR | P60: JUARINA | Q60: QUEIMADO | R60: DESCARGA ATMOSFÉRICA | S60: 457208 | U60: não | Z60: SIM | AA60: leitura caso a caso | AB60: Fora do indicador: o ativo não existe na base de interrupção. Sem registro de interrupção não há evento a medir. | AC60: TR-5700424154 Queimadopara raios queiamdo potência 10kvatensão 34,5kvacesso livreequipe 154op01 tel-63992674347 | AD60: TROCA DE TRAFO QUEIMADO 5700424154 ETO-RD-GR 189/2026 CHÁC. DOIS IRMÃOS - JUARINA 0154 TRAFO RETIRADO POTÊNCIA : 10KVA TENSÃO : 19.9KV Nº ENERGISA (CITD) : 19290 Nº DE SÉRIE : 457208 MARCA : ITB DATA FABRICAÇÃO : 03/2007 IMPEDANCIA : 2.91 POS. TAP : 01 TRAFO INSTALADO POTÊNCIA : 15KVA TENSÃO : 19.9KV Nº ENERGISA (CITD) : 149744 Nº DE SÉRIE : C 290305 MARCA : ITAM DATA FABRICAÇÃO : 10/2025 IMPEDANCIA : 3.10 POS. TAP : 03 MEDIÇÃO 1: 00.71 MEDIÇÃO 2: 00.48 MEDIÇÃO 3: 00.17 COORDENADA X: 708576 Y: 9101849
A61: ETO-RD-GR 00233/2026 | B61: fev | C61: Sem interrupção comprovada | D61: Sem interrupção | E61: EXPURGO | F61: QUEIMADO | G61: esteira 1.582 | H61: AUSENTE DA CRÍTICA | I61: 5700569227 | J61: ETO-RD-GR 000306/2026 | K61: 712600148 | L61: 2026-02-15 13:28 | M61: 2026-02-17 08:23 | N61: FORMS SUBST DE TRANSFORMADOR | O61: ETO-RD-GR | P61: RECURSOLANDIA | Q61: QUEIMADO | R61: DESCARGA ATMOSFÉRICA | U61: não | Z61: SIM | AA61: leitura caso a caso | AB61: Fora do indicador: o ativo não existe na base de interrupção. Sem registro de interrupção não há evento a medir. | AC61: TRAFO 5745261227 SAI COM RDU DO TRAFO 5700013227 E FICA A FRENTE DO TRAFO 5700569227 QUEIMADO PARA RAIO TAMBÉM DE 15 KVA NA NA REDE 19,9 KV ACESSO BOM PARA CAMIONETE FOI FEITO TESTE AVAZIO COSTATADO QUEIMADO COM VAZAMENTO DE ÓLEO | AD61: TRAFO 5745261227 SAI COM RDU DO TRAFO 5700013227 E FICA A FRENTE DO TRAFO 5700569227 QUEIMADO PARA RAIO TAMBÉM DE 15 KVA NA NA REDE 19,9 KV ACESSO BOM PARA CAMIONETE FOI FEITO TESTE AVAZIO COSTATADO QUEIMADO COM VAZAMENTO DE ÓLEO
A62: ETO-RD-GR 00259/2026 | B62: fev | C62: Sem interrupção comprovada | D62: Sem interrupção | E62: EXPURGO | F62: QUEIMADO | G62: esteira 1.582 | H62: AUSENTE DA CRÍTICA | I62: 5710023113 | J62: ETO-RD-GR 000353/2026 | K62: 712600176 | L62: 2026-02-21 13:09 | M62: 2026-02-24 10:44 | N62: FORMS SUBST DE TRANSFORMADOR | O62: ETO-RD-GR | P62: COUTO MAGALHAES | Q62: QUEIMADO | R62: DESCARGA ATMOSFÉRICA | U62: não | Z62: SIM | AA62: leitura caso a caso | AB62: Fora do indicador: o ativo não existe na base de interrupção. Sem registro de interrupção não há evento a medir. | AC62: trafo queimado 5710023113 - 15KVA - 34,5KV acesso caminhonete para raio queimado necessario refazer aterramento IND ASSENTAMEN P.A. UNIAO, 0 - CHA JANDAIAuc 562509263991206181 -RDR COUTO MAGALHAES | AD62: trafo queimado 5710023113 - 15KVA - 34,5KV acesso caminhonete para raio queimado necessario refazer aterramento IND ASSENTAMEN P.A. UNIAO, 0 - CHA JANDAIA uc 5625092 63991206181 -RDR COUTO MAGALHAES
A63: ETO-RD-GR 00292/2026 | B63: fev | C63: Sem interrupção comprovada | D63: Sem interrupção | E63: EXPURGO | F63: QUEIMADO | G63: esteira 1.582 | H63: AUSENTE DA CRÍTICA | I63: 5710447023 | J63: ENC-MLGR03 000084/2026 | K63: 712600196 | L63: 2026-02-26 19:07 | M63: 2026-02-28 03:11 | N63: FORMS SUBST DE TRANSFORMADOR | O63: ETO-RD-GR | P63: COLINAS DO TOCANTINS | Q63: QUEIMADO | R63: DESCARGA ATMOSFÉRICA | S63: 69687 | T63: 1024143 | U63: sim | Z63: SIM | AA63: leitura caso a caso | AB63: Fora do indicador: o ativo não existe na base de interrupção. Sem registro de interrupção não há evento a medir. | AC63: Boa noite,Favor enviar manutenção para substituir trafo queimado 5710447023 | AD63: TROCA DE TRAFO QUEIMADO 5710447023 ETO-RD-GR 292/2026 CHÁC. VITÓRIA - COLINAS 0023 TRAFO RETIRADO POTÊNCIA : 10KVA TENSÃO : 7.9KV Nº ENERGISA (CITD) : ILEGIVEL Nº DE SÉRIE : 69687 MARCA : TRAEL DATA FABRICAÇÃO : 11/2005 IMPEDANCIA : 2.58 POS. TAP : TRAFO INSTALADO POTÊNCIA : 15KVA TENSÃO : 7.9KV Nº ENERGISA (CITD) : 148731 Nº DE SÉRIE : 1024143 MARCA : ITB - TRAEL DATA FABRICAÇÃO : 06/2016 - 11/2025 IMPEDANCIA : 2.46 POS. TAP : 03 MEDIÇÃO 1: 17.45 MEDIÇÃO 2: 12.76 MEDIÇÃO 3: 10.73 COORDENADA X: 779218 Y: 9111665
A64: ETO-RD-GR 00295/2026 | B64: fev | C64: Sem interrupção comprovada | D64: Sem interrupção | E64: EXPURGO | F64: QUEIMADO | G64: esteira 1.582 | H64: AUSENTE DA CRÍTICA | I64: 5710173023 | J64: ENC-MLGR03 000082/2026 | K64: 712600194 | L64: 2026-02-27 15:07 | M64: 2026-02-28 16:52 | N64: FORMS SUBST DE TRANSFORMADOR | O64: ETO-RD-GR | P64: COLINAS DO TOCANTINS | Q64: QUEIMADO | R64: BUCHA DANIFICADA | S64: 182622 | T64: 133927 | U64: sim | Z64: SIM | AA64: leitura caso a caso | AB64: Fora do indicador: a Crítica nunca registrou defeito aberto neste transformador — em data nenhuma dos sete meses. O código aparece na base, mas só como interrompido ou manobrado, que é o que acontece com quem fica sem energia por defeito de outro equipamento. | AC64: Boa tarde,Favor enviar manutenção para subsitutir trafo com bucha secundaria com defeito 5710173023Obs: Necessario substituir cruzeta deterioradaEstrutura: N3 | AD64: TROCA DE TRAFO QUEIMADO 5710173023 ETO-RD-GR 295/2026 FAZ. MARAJÁ DA SERRA - COLINAS 0023 TRAFO RETIRADO POTÊNCIA : 30KVA TENSÃO : 13.8KV Nº ENERGISA (CITD) : ILEGIVEL Nº DE SÉRIE : 182622 MARCA : ABB DATA FABRICAÇÃO : 11/2001 IMPEDANCIA : 3.57 POS. TAP : 01 TRAFO INSTALADO POTÊNCIA : 30KVA TENSÃO : 13.8KV Nº ENERGISA (CITD) : 138478 Nº DE SÉRIE : 133927 MARCA : TRAEL - TRAEL DATA FABRICAÇÃO : 07/2008 - 02/2024 IMPEDANCIA : 3.74 POS. TAP : 02 MEDIÇÃO 1: 09.57 MEDIÇÃO 2: 08.24 MEDIÇÃO 3: 08.08 COORDENADA X: 763074 Y: 9115556
A65: ETO-RD-GU 00218/2026 | B65: fev | C65: Sem interrupção comprovada | D65: Sem interrupção | E65: EXPURGO | F65: QUEIMADO | G65: esteira 1.582 | H65: AUSENTE DA CRÍTICA | I65: 5710863003 | J65: DBM-MLDB04 000059/2026 | K65: 412600221 | L65: 2026-02-16 19:10 | M65: 2026-02-23 08:10 | N65: FORMS SUBST DE TRANSFORMADOR | O65: ETO-RD-GU | P65: GURUPI | Q65: QUEIMADO | R65: DESCARGA ATMOSFÉRICA | S65: 670034 | U65: não | V65: MEIO AMBIENTE | W65: DESCARGA ATMOSFERICA | Z65: SIM | AA65: leitura caso a caso | AB65: Fora do indicador: a Crítica nunca registrou defeito aberto neste transformador — em data nenhuma dos sete meses. O código aparece na base, mas só como interrompido ou manobrado, que é o que acontece com quem fica sem energia por defeito de outro equipamento. | AC65: TRAFO 5710863003 QUEIMADO EM CAMPO DE 15 KVA ACESSO PARA CAMIONETE PARA RAIO QUEIMADO | AD65: SUBSTITUIÇÃO DE TRANSFORMADOR NA RDR DE GURUPI INT: S/N SS: ETO-RD-GU 218/2026 ESPECIFICAÇÕES DO TRANSFORMADOR TRANSFORMADOR INSTALADO: 15KVA TRANSFORMADOR RETIRADO: 15KVA MEDIÇÕES LOGO APÓS A TROCA VAN: 205.7 VBN: 206.4 VAB: 411 OBS:SUBSTITUIÇÃO DE TRANSFORMADOR AUTORIZADA PELO DIONE.
A66: DG-RD-PO 00233/2026 | B66: mar | C66: Sem interrupção comprovada | D66: Sem interrupção | E66: EXPURGO | F66: QUEIMADO | G66: esteira 1.582 | H66: AUSENTE DA CRÍTICA | I66: 5702646001 | J66: DG-MPDG01 000054/2026 | K66: 312600177 | L66: 2026-03-03 08:09 | M66: 2026-03-03 08:45 | N66: AVISO DE ANOMALIA | O66: DG-RD-PO | P66: PORTO NACIONAL | Q66: QUEIMADO | S66: 2695 | T66: 1597377 | U66: sim | Z66: não | AA66: leitura caso a caso | AB66: Fora do indicador: o ativo não existe na base de interrupção. Sem registro de interrupção não há evento a medir. | AC66: segue nota trafo queimado de 45kVA paraio bom | AD66: medido_ emergencial_ substituição de trafo queimado rdu porto obs: cobrando sobre aviso pedrini 21 a 23/02
A67: DG-RD-PO 00243/2026 | B67: mar | C67: Sem interrupção comprovada | D67: Sem interrupção | E67: EXPURGO | F67: QUEIMADO | G67: esteira 1.582 | H67: AUSENTE DA CRÍTICA | I67: 5710079256 | J67: DG-MLPO02 000052/2026 | K67: 312600197 | L67: 2026-03-05 19:31 | M67: 2026-03-08 11:24 | N67: FORMS SUBST DE TRANSFORMADOR | O67: DG-RD-PO | P67: MATEIROS | Q67: QUEIMADO | R67: DESCARGA ATMOSFÉRICA | S67: 332336 | T67: 463560 | U67: sim | Z67: SIM | AA67: leitura caso a caso | AB67: Fora do indicador: o ativo não existe na base de interrupção. Sem registro de interrupção não há evento a medir. | AC67: TR 5710079256 queimado | AD67: medido_ emergencial_ substituição de trafo queimado rdr mateiros

Sheet Detalhes2
A1: Detalhes do Contagem de SS - Motivo: Fora da janela, Categoria pelo texto: QUEIMADO
A3: SS | B3: Mês | C3: Macro categoria | D3: Motivo | E3: Resultado | F3: Categoria pelo texto | G3: Fonte da categoria | H3: Categoria da leitura | I3: Trafo | J3: OS | K3: Obra | L3: Abertura | M3: Término | N3: Tipo da SS | O3: Equipe | P3: Localidade | Q3: Origem da SS | R3: Defeito da SS | S3: NS retirado | T3: NS instalado | U3: Prova de troca | V3: Crítica — causa | W3: Crítica — subcausa | X3: TMAE — causa | Y3: TMAE — subcausa | Z3: No Infotrafo | AA3: Origem da leitura | AB3: Por que saiu | AC3: Texto da SS | AD3: Texto da OS
A4: DG-RD-PO 00064/2026 | B4: jan | C4: Sem interrupção comprovada | D4: Fora da janela | E4: EXPURGO | F4: QUEIMADO | G4: esteira 1.582 | H4: FORA DA JANELA DA CRÍTICA | I4: 5711513001 | J4: DG-MLPO01 000016/2026 | K4: 312600058 | L4: 2026-01-16 03:49 | M4: 2026-01-16 12:25 | N4: FORMS SUBST DE TRANSFORMADOR | O4: DG-RD-PO | P4: PORTO NACIONAL | Q4: AVARIADO | R4: NÃO IDENTIFICADO | S4: 47057 | T4: 1587612 | U4: sim | Z4: SIM | AA4: leitura caso a caso | AB4: Fora do indicador: a SS não cai na janela de nenhuma interrupção. | AC4: Segue nota para envia equipe manutenção substituir Trafo 5711513001 de 10kva e para-raio avariado, Tensão 7,9kv, Rural de Porto Nacional Assentamento P.A. Pau Darco, Chac. Duas Irmãs, Acesso para camionete 4x4.Obs. Informação da equipe 001OP11 Trafo não Funcionando. | AD4: medido_ emergencial_ substituição de trafo queimado rdr porto
A5: DOLP-RD-PA 00122/2026 | B5: jan | C5: Sem interrupção comprovada | D5: Fora da janela | E5: EXPURGO | F5: QUEIMADO | G5: esteira 1.582 | H5: FORA DA JANELA DA CRÍTICA | I5: 5710169006 | J5: DLP-MLPA01 000020/2026 | K5: 112600156 | L5: 2026-01-25 10:13 | M5: 2026-01-26 18:30 | N5: FORMS SUBST DE TRANSFORMADOR | O5: DOLP-RD-PA | P5: TOCANTINIA | Q5: QUEIMADO | R5: NÃO IDENTIFICADO | S5: 358539 | T5: 464890 | U5: sim | Z5: SIM | AA5: leitura caso a caso | AB5: Fora do indicador: a Crítica registra defeito aberto neste transformador, mas em data que não cabe na janela desta SS. | AC5: segue ss de 01 trafo de 15 kvar e 01 para raio queimado da rede de 34.500kv para ser subistituido pela equipe de manutencão cliente penalizado 01 equipe que atendeu 006op01 cel, 63992363662/992379486 acesso livre favor agilizar o atendimento | AD5: MEDIDO_ EMERGENCIAL_ segue ss de 01 trafo de 15 kvar e 01 para raio queimado da rede de 34.500kv para ser subistituido pela equipe de manutencão cliente penalizado 01 equipe que atendeu 006op01 cel, 63992363662/992379486 acesso livre favor agilizar o atendimento DADOS ATENDIMENTO EQUIPE: PALMA11M LIDER: EDUARDO DA SILVA SANTOS CONTATO: 63 9296-7129 DOLP-RD-PA 000122/2026 DATA ATENDIMENTO: 26/01/2026 Atenção! Não intervenha na rede sem autorização do COI (Centro de Operações Integradas)
A6: DOLP-RD-PA 00124/2026 | B6: jan | C6: Sem interrupção comprovada | D6: Fora da janela | E6: EXPURGO | F6: QUEIMADO | G6: esteira 1.582 | H6: FORA DA JANELA DA CRÍTICA | I6: 5711933122 | J6: DLP-MLPA01 000021/2026 | K6: 112600144 | L6: 2026-01-25 12:35 | M6: 2026-01-26 16:04 | N6: FORMS SUBST DE TRANSFORMADOR | O6: DOLP-RD-PA | P6: PALMAS | Q6: QUEIMADO | R6: NÃO IDENTIFICADO | S6: 181042 | T6: 799443 | U6: sim | Z6: SIM | AA6: leitura caso a caso | AB6: Fora do indicador: a SS não cai na janela de nenhuma interrupção. | AC6: segue ss de 01 trafo de 15 kvar e 01 para raio da rede de 34,500kv para ser subistituido pela equipe de manutencão acesso livre cliente penalizado 01 equipe que atendeu 059op12 cel, 63985065407/992621690 favor agilizar o atendimento devido a reclamacão ser doo dia 24-01-2026 09:52 | AD6: MEDIDO_ EMERGENCIAL_ segue ss de 01 trafo de 15 kvar e 01 para raio da rede de 34,500kv para ser subistituido pela equipe de manutencão acesso livre cliente penalizado 01 equipe que atendeu 059op12 cel, 63985065407/992621690 favor agilizar o atendimento devido a reclamacão ser doo dia 24-01-2026 09:52 DADOS ATENDIMENTO EQUIPE: PALMA04M LIDER: OSE RAIMUNDO LOPES DE SOUZA CONTATO: 63 9296-9610 DOLP-RD-PA 000122/2026 DATA ATENDIMENTO: 26/01/2026 Atenção! Não intervenha na rede sem autorização do COI (Centro de Operações Integradas)
A7: ENC-RD-PS 00008/2026 | B7: jan | C7: Sem interrupção comprovada | D7: Fora da janela | E7: EXPURGO | F7: QUEIMADO | G7: esteira 1.582 | H7: FORA DA JANELA DA CRÍTICA | I7: 5700188046 | J7: ENC-LMPS01 000004/2026 | K7: 212600046 | L7: 2026-01-03 18:05 | M7: 2026-01-05 00:35 | N7: FORMS SUBST DE TRANSFORMADOR | O7: ENC-RD-PS | P7: NOVA ROSALANDIA | Q7: QUEIMADO | R7: DESCARGA ATMOSFÉRICA | S7: 565670050 | T7: 136158 | U7: sim | V7: MEIO AMBIENTE | W7: DESCARGA ATMOSFERICA | Z7: SIM | AA7: leitura caso a caso | AB7: Fora do indicador: a SS não cai na janela de nenhuma interrupção. | AC7: TR 5700188046 QUEIMADO 30KVAPARA RAIO DANIFICADO ACESSO LIVRET 34500013OP14 | AD7: SS ENC-RD-PS 08/2026 TR 5700188046 TRAFO RETIRADO POTÊNCIA : 30KVA TENSÃO : 34.5KV Nº ENERGISA (CITD) : ILEGIVEL Nº DE SÉRIE : 565670050 MARCA : SIEMENS DATA FABRICAÇÃO : 07/1999 IMPEDANCIA : 4.15 POS. TAP : 01 TRAFO INSTALADO' POTÊNCIA : 30KVA TENSÃO : 34.5KV Nº ENERGISA (CITD) : 134706 Nº DE SÉRIE : 136158 MARCA : TRAEL DATA FABRICAÇÃO : 08/2008 IMPEDANCIA : 4.15 POS. TAP : 02
A8: ETO-RD-AR 00034/2026 | B8: jan | C8: Sem interrupção comprovada | D8: Fora da janela | E8: EXPURGO | F8: QUEIMADO | G8: esteira 1.582 | H8: FORA DA JANELA DA CRÍTICA | I8: 5700867040 | J8: ENC-MLAR05 000014/2026 | K8: 612600051 | L8: 2026-01-08 10:53 | M8: 2026-01-09 16:30 | N8: FORMS SUBST DE TRANSFORMADOR | O8: ETO-RD-AR | P8: ARAGOMINAS | Q8: QUEIMADO | R8: DESCARGA ATMOSFÉRICA | S8: 432082 | U8: não | Z8: SIM | AA8: leitura caso a caso | AB8: Fora do indicador: a SS não cai na janela de nenhuma interrupção. | AC8: Trafo 5700867040 15kvaTensão: 19.9Equipe: 058op03Endereço: IND ASSENTAMEN P.A. REUNIDAS, 0 - LOTE 37 | AD8: ETO-RD-AR 34/2026 TRAFO RETIRADO POTÊNCIA : 15 KVA TENSÃO : 34.5 KV Nº ENERGISA (CITD) : 06105312 Nº DE SÉRIE : 432082 MARCA : TRAEL DATA FABRICAÇÃO : 06/2017 IMPEDANCIA : 2,9 POS. TAP : 05 TRAFO INSTALADO POTÊNCIA : 15 KVA TENSÃO : 34.5 KV Nº ENERGISA (CITD) : 149686 Nº DE SÉRIE : C 290247 MARCA : ITAM DATA FABRICAÇÃO : 09/2025 IMPEDANCIA : 2,98 POS. TAP : 05 OBS. TRAFO SUBSTITUIDO EM CAMPO E DE 15 KVA COM FORME REALTORIO E BUOOK INFORMADO PELA EQUIPE, POREM NO SISTEMA TRAFO E DE 5 KVA ERRO DE CADATRO.
A9: ETO-RD-AR 00188/2026 | B9: jan | C9: Sem interrupção comprovada | D9: Fora da janela | E9: EXPURGO | F9: QUEIMADO | G9: esteira 1.582 | H9: FORA DA JANELA DA CRÍTICA | I9: 5739688157 | J9: ENC-MLAR01 000075/2026 | K9: 612600125 | L9: 2026-01-30 11:44 | M9: 2026-01-30 21:00 | N9: FORMS SUBST DE TRANSFORMADOR | O9: ETO-RD-AR | P9: ARAGUANA | Q9: QUEIMADO | R9: DESCARGA ATMOSFÉRICA | S9: 379613 | T9: 460390 | U9: sim | Z9: não | AA9: leitura caso a caso | AB9: Fora do indicador: a SS não cai na janela de nenhuma interrupção. | AC9: TRAFO QUEIMADO 5739688157 pararaio queimado acesso caminhonete | AD9: ETO-RD-AR 188/2026 TR: 5739688157 TRAFO RETIRADO POTÊNCIA : 25KVA TENSÃO : 34,5KV Nº ENERGISA (CITD) : ILEGIVEL Nº DE SÉRIE : 379613 MARCA : ITAIPU DATA FABRICAÇÃO : 11/2019 IMPEDANCIA : 2,94 POS. TAP : 03 TRAFO INSTALADO POTÊNCIA : 25KVA TENSÃO : 34,5KV Nº ENERGISA (CITD) : 148698 Nº DE SÉRIE : 460390 MARCA : TRAEL DATA FABRICAÇÃO : 2018 IMPEDANCIA : 2,79 POS. TAP : 03
A10: ETO-RD-AR 00992/2026 | B10: jun | C10: Sem interrupção comprovada | D10: Fora da janela | E10: EXPURGO | F10: QUEIMADO | G10: esteira 1.582 | H10: FORA DA JANELA DA CRÍTICA | I10: 5710093157 | J10: ENC-MLAR01 000242/2026 | K10: 612600627 | L10: 2026-06-18 17:27 | M10: 2026-06-19 16:20 | N10: FORMS SUBST DE TRANSFORMADOR | O10: ETO-RD-AR | P10: ARAGUANA | Q10: QUEIMADO | R10: NÃO IDENTIFICADO | S10: 395690 | U10: não | V10: MEIO AMBIENTE | W10: ARVORE DE PEQUENO/ MEDIO PORTE NA REDE / NA FAIXA | Z10: SIM | AA10: leitura caso a caso | AB10: Fora do indicador: a SS não cai na janela de nenhuma interrupção. | AC10: Trafo 5710093157 45kva queimadoPara-raio: QueimadoAcesso: livreEndereço: IND FAZENDA BARRA DO RIO LONTRA, 0Equipe: 030op01 | AD10: ETO-RD-AR 992/2026 TRAFO 5710093157 TRAFO RETIRADO POTÊNCIA : 45 KVA TENSÃO : 34.5 KV Nº ENERGISA (CITD) : 130805 Nº DE SÉRIE : 395690 MARCA : TRAEL DATA FABRICAÇÃO : 07/2016 IMPEDANCIA : 4,04 POS. TAP : 04 TRAFO INSTALADO POTÊNCIA : 45 KVA TENSÃO : 34.5 KV Nº ENERGISA (CITD) : 107053 Nº DE SÉRIE : EA105A2 MARCA : TRAEL DATA FABRICAÇÃO : 2000 IMPEDANCIA : 4,09 POS. TAP : 04
A11: ETO-RD-GU 00017/2026 | B11: jan | C11: Sem interrupção comprovada | D11: Fora da janela | E11: EXPURGO | F11: QUEIMADO | G11: esteira 1.582 | H11: FORA DA JANELA DA CRÍTICA | I11: 5701363094 | J11: DBM-MLDB06 000006/2026 | K11: 412600029 | L11: 2026-01-04 15:53 | M11: 2026-01-05 18:15 | N11: FORMS SUBST DE TRANSFORMADOR | O11: ETO-RD-GU | P11: PEIXE | Q11: AVARIADO | R11: BUCHA DANIFICADA | S11: 389568 | T11: 802095 | U11: sim | V11: MEIO AMBIENTE | W11: DESCARGA ATMOSFERICA | X11: TRANSFORMADOR | Y11: FALTANDO FASE INTERNAMENTE | Z11: SIM | AA11: leitura caso a caso | AB11: Fora do indicador: o dono mandou os três para ausente da base de interrupções, e para este a Crítica não deixa: o código 5701363094 TEM defeito aberto nele, na ocorrência 20254026190596 de 15/12/2025, subcausa partido na fase — dezenove dias antes desta SS. Não é ausente; é fora da janela, que é a categoria de quem tem registro próprio em outra data. Sai do indicador do mesmo jeito, com o nome que a base sustenta. | AC11: bucha secundaria queimada para raio queimado e chave fusivel com defeito 19,9kv | AD11: SUBSTITUIÇÃO DE TRANSFORMADOR NA RDR DE ARAGUAÇU INT: 20264064884819 SS: ETO-RD-GU 17/2026 ESPECIFICAÇÕES DO TRANSFORMADOR TRANSFORMADOR INSTALADO: 15 KVA TRANSFORMADOR RETIRADO: 15 KVA MEDIÇÕES LOGO APÓS A TROCA VAN: 203 VBN: 204 OBS:SUBSTITUIÇÃO DE TRANSFORMADOR AUTORIZADA PELO DIONE.
A12: DG-RD-PO 00158/2026 | B12: fev | C12: Sem interrupção comprovada | D12: Fora da janela | E12: EXPURGO | F12: QUEIMADO | G12: esteira 1.582 | H12: FORA DA JANELA DA CRÍTICA | I12: 5710045026 | J12: DG-MLPO01 000035/2026 | K12: 312600123 | L12: 2026-02-03 21:03 | M12: 2026-02-04 20:50 | N12: FORMS SUBST DE TRANSFORMADOR | O12: DG-RD-PO | P12: PONTE ALTA DO TOCANTINS | Q12: QUEIMADO | R12: DESCARGA ATMOSFÉRICA | S12: 371259 | T12: 472337 | U12: sim | Z12: SIM | AA12: leitura caso a caso | AB12: Fora do indicador: a SS não cai na janela de nenhuma interrupção. | AC12: TR 571004502615KVATENSAO 19,9PARA RAIO DANIFICADO ACESSO LIVRE 026OP01 | AD12: medido_ emergencial_ TR 5710045026 15KVA TENSAO 19,9 PARA RAIO DANIFICADO ACESSO LIVRE 026OP01
A13: DG-RD-PO 00160/2026 | B13: fev | C13: Sem interrupção comprovada | D13: Fora da janela | E13: EXPURGO | F13: QUEIMADO | G13: esteira 1.582 | H13: FORA DA JANELA DA CRÍTICA | I13: 5753553037 | J13: DG-MPDG01 000048/2026 | K13: 312600110 | L13: 2026-02-04 09:56 | M13: 2026-02-01 14:55 | N13: FORMS SUBST DE TRANSFORMADOR | O13: DG-RD-PO | P13: BREJINHO DE NAZARE | Q13: QUEIMADO | R13: DESCARGA ATMOSFÉRICA | S13: 221122 | T13: 1657795 | U13: sim | Z13: SIM | AA13: leitura caso a caso | AB13: Fora do indicador: a SS não cai na janela de nenhuma interrupção. | AC13: TRAFO 5753553037 E PARA RAIO QUEIMADO POTENCIA: 75KVA 34500ACESSO: LIVRE | AD13: medido_ emergencial_ TRAFO 5753553037 E PARA RAIO QUEIMADO POTENCIA: 75KVA 34500 ACESSO: LIVRE
A14: DG-RD-PO 00178/2026 | B14: fev | C14: Sem interrupção comprovada | D14: Fora da janela | E14: EXPURGO | F14: QUEIMADO | G14: esteira 1.582 | H14: FORA DA JANELA DA CRÍTICA | I14: 5700861026 | J14: DG-MLPO02 000041/2026 | K14: 312600161 | L14: 2026-02-11 23:46 | M14: 2026-02-12 18:43 | N14: FORMS SUBST DE TRANSFORMADOR | O14: DG-RD-PO | P14: PONTE ALTA DO TOCANTINS | Q14: QUEIMADO | R14: DESCARGA ATMOSFÉRICA | S14: 184945 | T14: 339337 | U14: sim | Z14: SIM | AA14: leitura caso a caso | AB14: Fora do indicador: a SS não cai na janela de nenhuma interrupção. | AC14: Trafo 5700861026 de 15kva e para-raio queimado, Tensão 19,9kv, Acesso para camionete 4x, Rural de Ponte Alta, faz. IND FAZENDA PRODUCAO, 0 - LPT-14877 FAZ PRODUCAO | AD14: medido_ emergencial_ substituição de trafo queimado rdr ponte alta
A15: DOLP-RD-PA 00177/2026 | B15: fev | C15: Sem interrupção comprovada | D15: Fora da janela | E15: EXPURGO | F15: QUEIMADO | G15: esteira 1.582 | H15: FORA DA JANELA DA CRÍTICA | I15: 5755307026 | J15: DLP-MLPA01 000032/2026 | K15: 112600258 | L15: 2026-02-03 08:31 | M15: 2026-02-01 12:00 | N15: FORMS SUBST DE TRANSFORMADOR | O15: DOLP-RD-PA | P15: PONTE ALTA DO TOCANTINS | Q15: QUEIMADO | R15: DESCARGA ATMOSFÉRICA | S15: 1026962 | T15: 287170 | U15: sim | Z15: SIM | AA15: leitura caso a caso | AB15: Fora do indicador: a SS não cai na janela de nenhuma interrupção. | AC15: Segundo informações da equipe 026OP03, o 5755307026 de 15kVA, tensão 19.9V, para raio está ok, acesso livre somente pra caminhonete. | AD15: MEDIDO_ EMERGENCIAL_ Segundo informações da equipe 026OP03, o 5755307026 de 15kVA, tensão 19.9V, para raio está ok, acesso livre somente pra caminhonete. TAP 3 DADOS ATENDIMENTO EQUIPE: ENCARREGADO: CONTATO: DOLP-RD-PA 000177/2026 DATA ATENDIMENTO:__ / __ / __ Atenção! Não intervenha na rede sem autorização do COI (Centro de Operações Integradas)
A16: ETO-RD-AR 00204/2026 | B16: fev | C16: Sem interrupção comprovada | D16: Fora da janela | E16: EXPURGO | F16: QUEIMADO | G16: esteira 1.582 | H16: FORA DA JANELA DA CRÍTICA | I16: 5723118030 | J16: ENC-MLAR02 000018/2026 | K16: 612600132 | L16: 2026-02-02 07:07 | M16: 2026-01-31 19:26 | N16: FORMS SUBST DE TRANSFORMADOR | O16: ETO-RD-AR | P16: XAMBIOA | Q16: QUEIMADO | R16: SOBRECARGA | S16: 965782 | T16: 820232 | U16: sim | Z16: SIM | AA16: leitura caso a caso | AB16: Fora do indicador: a SS não cai na janela de nenhuma interrupção. | AC16: EQUIPE 030OP01TRAFO QUEIMADO 5723118030 potencia 10KVA tensão 34.5KV E RECUPERAR BT ROMPIDAACESSO CAMINHONETE | AD16: ETO-RD-AR 204/2026 TR: 5723118030 TRAFO RETIRADO POTÊNCIA : 15KVA TENSÃO : 34,5KV Nº ENERGISA (CITD) : 06016673 Nº DE SÉRIE : 965782 MARCA : ITB DATA FABRICAÇÃO : 08/2015 IMPEDANCIA : 3,14 POS. TAP : 03 TRAFO INSTALADO POTÊNCIA : 15KVA TENSÃO : 34,5KV Nº ENERGISA (CITD) : 149246 Nº DE SÉRIE : 820232 MARCA : TRAEL DATA FABRICAÇÃO : 11/2025 IMPEDANCIA : 3,0 POS. TAP : 03
A17: ETO-RD-AR 00268/2026 | B17: fev | C17: Sem interrupção comprovada | D17: Fora da janela | E17: EXPURGO | F17: QUEIMADO | G17: esteira 1.582 | H17: FORA DA JANELA DA CRÍTICA | I17: 5700382016 | J17: ENC-MLAR01 000077/2026 | K17: 612600167 | L17: 2026-02-08 11:20 | M17: 2026-02-09 18:35 | N17: FORMS SUBST DE TRANSFORMADOR | O17: ETO-RD-AR | P17: WANDERLANDIA | Q17: QUEIMADO | R17: DESCARGA ATMOSFÉRICA | S17: 179561 | T17: 820183 | U17: sim | Z17: SIM | AA17: leitura caso a caso | AB17: Fora do indicador: a SS não cai na janela de nenhuma interrupção. | AC17: trafo queimado, caiu uma descarga no mesmo pararaio queimado | AD17: SS ETO-RD-AR 268/2026 TRAFO 5700382016 TRAFO RETIRADO POTÊNCIA : 15KVA TENSÃO : 34.5KV Nº ENERGISA (CITD) : 145435 Nº DE SÉRIE : 179561 MARCA : TRAEL DATA FABRICAÇÃO : 02/2002 IMPEDANCIA : 2.98 POS. TAP : 03 TRAFO INSTALADO' POTÊNCIA : 15KVA TENSÃO : 34.5KV Nº ENERGISA (CITD) : 149197 Nº DE SÉRIE : 820183 MARCA : TRAEL DATA FABRICAÇÃO : NOV/2025 IMPEDANCIA : 3.0 POS. TAP : 03
A18: ETO-RD-GR 00238/2026 | B18: fev | C18: Sem interrupção comprovada | D18: Fora da janela | E18: EXPURGO | F18: QUEIMADO | G18: esteira 1.582 | H18: FORA DA JANELA DA CRÍTICA | I18: 5710058153 | J18: ETO-RD-GR 000311/2026 | K18: 712600155 | L18: 2026-02-16 12:35 | M18: 2026-02-17 20:56 | N18: FORMS SUBST DE TRANSFORMADOR | O18: ETO-RD-GR | P18: BERNARDO SAYAO | Q18: QUEIMADO | R18: DESCARGA ATMOSFÉRICA | U18: não | Z18: SIM | AA18: leitura caso a caso | AB18: Fora do indicador: a SS não cai na janela de nenhuma interrupção. | AC18: TR-5710058153 Queimadopara raios QUEIMADO potência 15kvatensão 34,5kvacesso CAMINHONETEequipe 025op01 tel-63992452770 | AD18: TR-5710058153 Queimado para raios QUEIMADO potência 15kva tensão 34,5kv acesso CAMINHONETE equipe 025op01 tel-63992452770
A19: DOLP-RD-PA 00338/2026 | B19: mar | C19: Sem interrupção comprovada | D19: Fora da janela | E19: EXPURGO | F19: QUEIMADO | G19: esteira 1.582 | H19: FORA DA JANELA DA CRÍTICA | I19: 5704202122 | J19: DLP-MPPA01 000086/2026 | K19: 112600587 | L19: 2026-03-10 16:17 | M19: 2026-03-23 08:50 | N19: AVISO DE ANOMALIA | O19: DOLP-RD-PA | P19: PALMAS | Q19: QUEIMADO | R19: BUCHA DANIFICADA | S19: 238663 | T19: 267955 | U19: sim | Z19: não | AA19: leitura caso a caso | AB19: Fora do indicador: a SS não cai na janela de nenhuma interrupção. | AC19: Segue esse para substituição de TF queimado (bucha do TF) 5704202122ID: 50688272 | AD19: MEDIDO_ EMERGENCIAL_ Segue esse para substituição de TF queimado (bucha do TF) 5704202122 ID: 50688272 DADOS ATENDIMENTO EQUIPE DOLP-MPPA01 ENCARREGADO - IBANEZ RODRIGUES CONTATO - (63) 99295-9499 SS DOLP-RD-PA 338/2026 ATENDIMENTO REALIZADO DIA 07/03/2026 EM CONJUNTO COM A SS DOLP-RD-PA 324/2026. *********** Parecer do COCM - ordem de serviço baixada sistemicamente, empreiteira estará fazendo as baixa de material e lançamento de mão de obra.
A20: ENC-RD-PS 00376/2026 | B20: mar | C20: Sem interrupção comprovada | D20: Fora da janela | E20: EXPURGO | F20: QUEIMADO | G20: esteira 1.582 | H20: FORA DA JANELA DA CRÍTICA | I20: 5700368012 | J20: ENC-LMPS04 000055/2026 | K20: 212600335 | L20: 2026-03-20 18:48 | M20: 2026-03-21 12:00 | N20: FORMS SUBST DE TRANSFORMADOR | O20: ENC-RD-PS | P20: DIVINOPOLIS DO TOCANTINS | Q20: QUEIMADO | R20: DESCARGA ATMOSFÉRICA | S20: 473642 | T20: 828112 | U20: sim | Z20: SIM | AA20: leitura caso a caso | AB20: Fora do indicador: a SS não cai na janela de nenhuma interrupção. | AC20: Segue ss para tratativa com equipe de manutençao o quanto antessubstituir trafo 5700368012 queimado na rdr de divinopoles | AD20: SS ENC-RD-PS 376/2026 trafo 5700368012 TRAFO RETIRADO POTÊNCIA : 5KVA TENSÃO : 34.5KV Nº ENERGISA (CITD) : 23196 Nº DE SÉRIE : 473642 MARCA : ITB DATA FABRICAÇÃO : 07/2007 IMPEDANCIA : 2.81 POS. TAP : 03 TRAFO INSTALADO' POTÊNCIA : 15KVA TENSÃO : 34.5KV Nº ENERGISA (CITD) : 150389 Nº DE SÉRIE : 828112 MARCA : TRAEL DATA FABRICAÇÃO : 02/2026 IMPEDANCIA : 3.0 POS. TAP : 03
A21: ENC-RD-PS 00601/2026 | B21: jun | C21: Sem interrupção comprovada | D21: Fora da janela | E21: EXPURGO | F21: QUEIMADO | G21: esteira 1.582 | H21: FORA DA JANELA DA CRÍTICA | I21: 5753306085 | J21: ENC-LMPS01 000152/2026 | K21: 212600554 | L21: 2026-06-24 12:13 | M21: 2026-06-25 12:55 | N21: FORMS SUBST DE TRANSFORMADOR | O21: ENC-RD-PS | P21: MONTE SANTO DO TOCANTINS | Q21: QUEIMADO | R21: SOBRECARGA | S21: 182924 | T21: 602384 | U21: sim | Z21: SIM | AA21: leitura caso a caso | AB21: Fora do indicador: a Crítica registra defeito aberto neste transformador, mas em data que não cabe na janela desta SS. | AC21: TRAFO QUEIMADO 5753306085 30KVA 34,5KV, QUE ATENDE GARIMPO. CARGAS A REVELIA | AD21: SS ENC-RD-PS 601/2026 TRAFO 5753306085 TRAFO RETIRADO POTÊNCIA : 30KVA TENSÃO : 34.5KV Nº ENERGISA (CITD) : 109811 Nº DE SÉRIE : 182924 MARCA : TRAEL DATA FABRICAÇÃO : 01/2001 IMPEDANCIA : 4.06 POS. TAP : 04 TRAFO INSTALADO' POTÊNCIA : 75KVA TENSÃO : 34.5KV Nº ENERGISA (CITD) : 149918 Nº DE SÉRIE : 602384 MARCA : ITAIPU DATA FABRICAÇÃO : 01/2026 IMPEDANCIA : 3.77 POS. TAP : 02
A22: ETO-RD-AR 00551/2026 | B22: mar | C22: Sem interrupção comprovada | D22: Fora da janela | E22: EXPURGO | F22: QUEIMADO | G22: esteira 1.582 | H22: FORA DA JANELA DA CRÍTICA | I22: 5700322060 | J22: ENC-MLAR01 000152/2026 | K22: 612600337 | L22: 2026-03-24 17:26 | M22: 2026-03-25 12:10 | N22: FORMS SUBST DE TRANSFORMADOR | O22: ETO-RD-AR | P22: NOVA OLINDA | Q22: QUEIMADO | R22: NÃO IDENTIFICADO | S22: 178008 | U22: não | Z22: SIM | AA22: leitura caso a caso | AB22: Fora do indicador: a SS não cai na janela de nenhuma interrupção. | AC22: SEGUE SS DE TRAFO QUEIMADO NA RDR DE NOVA OLINDA, TRAFO DE 15KVA NA REDE DE 7.8KV, PARA RAIO QUEIMADO E ACESSO LIVRE. | AD22: ETO-RD-AR 551/2026 TRAFO 5700322060 TRAFO RETIRADO POTÊNCIA : 15 KVA TENSÃO : 13.8 KV Nº ENERGISA (CITD) : P8322 Nº DE SÉRIE : 178008 MARCA : ABB DATA FABRICAÇÃO : 02/2001 IMPEDANCIA : 2,36 POS. TAP : 03 TRAFO INSTALADO POTÊNCIA : 15 KVA TENSÃO : 13.8 KV Nº ENERGISA (CITD) : 149855 Nº DE SÉRIE : C297819 MARCA : ITAM DATA FABRICAÇÃO : 12/2025 IMPEDANCIA : 2,61 POS. TAP : 05
A23: ETO-RD-AR 00583/2026 | B23: mar | C23: Sem interrupção comprovada | D23: Fora da janela | E23: EXPURGO | F23: QUEIMADO | G23: esteira 1.582 | H23: FORA DA JANELA DA CRÍTICA | I23: 5700799193 | J23: ENC-MLAR03 000036/2026 | K23: 612600363 | L23: 2026-03-31 20:47 | M23: 2026-04-01 18:43 | N23: FORMS SUBST DE TRANSFORMADOR | O23: ETO-RD-AR | P23: CAMPOS LINDOS | Q23: QUEIMADO | R23: DESCARGA ATMOSFÉRICA | S23: 179110 | T23: 827956 | U23: sim | Z23: SIM | AA23: leitura caso a caso | AB23: Fora do indicador: a SS não cai na janela de nenhuma interrupção. | AC23: Trafo 5700799193 15kvaPara-raio: Queimado Endereço: fazenda arueira saindo povoado RanchariaEquipe: 193op02 | AD23: ETO-RD-AR 583/2026 TRAFO 5700799193 TRAFO RETIRADO POTÊNCIA : 5 KVA TENSÃO : 34.5 KV Nº ENERGISA (CITD) : ILEGIVEL Nº DE SÉRIE : 179110 MARCA : VIJAI DATA FABRICAÇÃO : 09/2010 IMPEDANCIA : 3,17 POS. TAP : 05 TRAFO INSTALADO POTÊNCIA : 15 KVA TENSÃO : 34.5 KV Nº ENERGISA (CITD) : 150233 Nº DE SÉRIE : 827956 MARCA : TRAEL DATA FABRICAÇÃO : 02/2026 IMPEDANCIA : 3,0 POS. TAP : 05
A24: ETO-RD-DP 00214/2026 | B24: mar | C24: Sem interrupção comprovada | D24: Fora da janela | E24: EXPURGO | F24: QUEIMADO | G24: esteira 1.582 | H24: FORA DA JANELA DA CRÍTICA | I24: 5700230116 | J24: ETO-MLDP01 000075/2026 | K24: 512600126 | L24: 2026-03-23 13:59 | M24: 2026-03-25 13:30 | N24: FORMS SUBST DE TRANSFORMADOR | O24: ETO-RD-DP | P24: PINDORAMA DO TOCANTINS | Q24: QUEIMADO | R24: DESCARGA ATMOSFÉRICA | S24: 587813 | T24: 251616 | U24: sim | Z24: SIM | AA24: leitura caso a caso | AB24: Fora do indicador: a SS não cai na janela de nenhuma interrupção. | AC24: TRANSFORMADOR QUEIMADO 5700230116 5kva e para raio queimado na 19,9 acesso caminhonete equipe 096op01 992400102 | AD24: TRANSFORMADOR QUEIMADO 5700230116 5kva e para raio queimado na 19,9 acesso caminhonete equipe 096op01 992400102
A25: DOLP-RD-PA 00643/2026 | B25: jun | C25: Sem interrupção comprovada | D25: Fora da janela | E25: EXPURGO | F25: QUEIMADO | G25: esteira 1.582 | H25: FORA DA JANELA DA CRÍTICA | I25: 5746488122 | J25: DLP-CTPA00 000107/2026 | K25: 112600604 | L25: 2026-06-07 14:26 | M25: 2026-06-07 18:00 | N25: FORMS SUBST DE TRANSFORMADOR | O25: DOLP-RD-PA | P25: PALMAS | Q25: QUEIMADO | R25: BUCHA DANIFICADA | S25: 437872 | T25: 606278 | U25: sim | Z25: SIM | AA25: leitura caso a caso | AB25: Fora do indicador: a SS não cai na janela de nenhuma interrupção. | AC25: segue nota de trafo queimado, trafo 5745488122, trafo de 45kva, tensao 34,500kv, bitola caboAA / 2, para raio danificado, acesso livre, elo 2H. ramal do piabanha | AD25: MEDIDO_ EMERGENCIAL_ segue nota de trafo queimado, trafo 5745488122, trafo de 45kva, tensao 34,500kv, bitola caboAA / 2, para raio danificado, acesso livre, elo 2H. ramal do piabanha
A26: ETO-RD-GU 00390/2026 | B26: mar | C26: Sem interrupção comprovada | D26: Fora da janela | E26: EXPURGO | F26: QUEIMADO | G26: esteira 1.582 | H26: FORA DA JANELA DA CRÍTICA | I26: 5700039076 | J26: DBM-MLDB03 000067/2026 | K26: 412600331 | L26: 2026-03-26 10:34 | M26: 2026-03-29 13:49 | N26: FORMS SUBST DE TRANSFORMADOR | O26: ETO-RD-GU | P26: DUERE | Q26: QUEIMADO | R26: NÃO IDENTIFICADO | S26: 1574224 | T26: 828021 | U26: sim | Z26: SIM | AA26: leitura caso a caso | AB26: Fora do indicador: a SS não cai na janela de nenhuma interrupção. | AC26: SEGUE SS DE TRAFO QUEIMADO NA RDR DE DUERE, TRAFO DE 15KVA NA REDE DE 19.9KV, PARA RAIO QUEIMADO E ACESSO LIVRE. | AD26: SUBSTITUIÇÃO DE TRANSFORMADOR NA RDR DE PEIXE SS: ETO-D-GU 390/2026 ESPECIFICAÇÕES DO TRANSFORMADOR TRANSFORMADOR INSTALADO: 15 KVA TRANSFORMADOR RETIRADO: 15 KVA MEDIÇÕES LOGO APÓS A TROCA VAN: 208 VBN: 209 OBS:SUBSTITUIÇÃO DE TRANSFORMADOR AUTORIZADA PELO DIONE.
A27: ENC-RD-PS 00481/2026 | B27: abr | C27: Sem interrupção comprovada | D27: Fora da janela | E27: EXPURGO | F27: QUEIMADO | G27: esteira 1.582 | H27: FORA DA JANELA DA CRÍTICA | I27: 5701214055 | J27: ENC-LMPS03 000077/2026 | K27: 212600452 | L27: 2026-04-28 09:30 | M27: 2026-04-30 21:05 | N27: FORMS SUBST DE TRANSFORMADOR | O27: ENC-RD-PS | P27: ARAGUACEMA | Q27: QUEIMADO | R27: VAZAMENTO DE ÓLEO | S27: 723749 | U27: não | Z27: SIM | AA27: leitura caso a caso | AB27: Fora do indicador: a SS não cai na janela de nenhuma interrupção. | AC27: TR 5701214055QUEIMADO ACESSO LIVRE CAMINHONETE 5KVATENSAO 34500PARA RAIO DANIFICADO 055OP01 | AD27: SS ENC-RD-PS 481/2026 TR 5701214055 TRAFO RETIRADO POTÊNCIA : 5KVA TENSÃO : 34.5KV Nº ENERGISA (CITD) : 06003407 Nº DE SÉRIE : 723749 MARCA : ITB DATA FABRICAÇÃO : 03/2011 IMPEDANCIA : 3.21 POS. TAP : 03 TRAFO INSTALADO' POTÊNCIA : 15KVA TENSÃO : 34.5KV Nº ENERGISA (CITD) : 150972 Nº DE SÉRIE : C303352 MARCA : ITAM DATA FABRICAÇÃO : 02/2026 IMPEDANCIA : 2.91 POS. TAP : 03
A28: ETO-RD-GR 00466/2026 | B28: abr | C28: Sem interrupção comprovada | D28: Fora da janela | E28: EXPURGO | F28: QUEIMADO | G28: esteira 1.582 | H28: FORA DA JANELA DA CRÍTICA | I28: 5710404111 | J28: ENC-MLGR01 000116/2026 | K28: 712600315 | L28: 2026-04-22 07:20 | M28: 2026-04-21 16:43 | N28: FORMS SUBST DE TRANSFORMADOR | O28: ETO-RD-GR | P28: PEQUIZEIRO | Q28: QUEIMADO | R28: DESCARGA ATMOSFÉRICA | S28: 178699 | T28: 827778 | U28: sim | X28: TRANSFORMADOR | Y28: QUEIMADO POR DESCARGA ATMOSFERICA | Z28: SIM | AA28: leitura caso a caso | AB28: Fora do indicador: a SS não cai na janela de nenhuma interrupção. | AC28: TRAFO QUEIMADO DE 15KVA DA 19.9. PARA RAIOS QUEIMADO. ACESSO BOM. 01 CLIENTE PENALIZADO. | AD28: TROCA DE TRAFO QUEIMADO 5710404111 ETO-RD-GR 466/2026 ZONA RURAL - PEQUIZEIRO 0111 TRAFO RETIRADO POTÊNCIA : 15KVA TENSÃO : 19.9KV Nº ENERGISA (CITD) : CI2706004935 Nº DE SÉRIE : 178699 MARCA : ABB - IMTEL DATA FABRICAÇÃO : 01/2002 - 03/2013 IMPEDANCIA : 3 POS. TAP : 01 TRAFO INSTALADO POTÊNCIA : 15KVA TENSÃO : 19.9KV Nº ENERGISA (CITD) : 150055 Nº DE SÉRIE : 827778 MARCA : TRAEL DATA FABRICAÇÃO : 02/2026 IMPEDANCIA : 3.0 POS. TAP : 02 MEDIÇÃO 1: 25.58 MEDIÇÃO 2: 21.53 MEDIÇÃO 3: 16.40 COORDENADA X: 731871 Y: 9093269

Sheet Expurgos
A1: SS | B1: Mês | C1: Macro categoria | D1: Motivo | E1: Resultado | F1: Categoria pelo texto | G1: Fonte da categoria | H1: Categoria da leitura | I1: Trafo | J1: OS | K1: Obra | L1: Abertura | M1: Término | N1: Tipo da SS | O1: Equipe | P1: Localidade | Q1: Origem da SS | R1: Defeito da SS | S1: NS retirado | T1: NS instalado | U1: Prova de troca | V1: Crítica — causa | W1: Crítica — subcausa | X1: TMAE — causa | Y1: TMAE — subcausa | Z1: No Infotrafo | AA1: Origem da leitura | AB1: Por que saiu | AC1: Texto da SS | AD1: Texto da OS
A2: DG-RD-PO 00064/2026 | B2: jan | C2: Sem interrupção comprovada | D2: Fora da janela | E2: EXPURGO | F2: QUEIMADO | G2: esteira 1.582 | H2: FORA DA JANELA DA CRÍTICA | I2: 5711513001 | J2: DG-MLPO01 000016/2026 | K2: 312600058 | L2: 2026-01-16 03:49 | M2: 2026-01-16 12:25 | N2: FORMS SUBST DE TRANSFORMADOR | O2: DG-RD-PO | P2: PORTO NACIONAL | Q2: AVARIADO | R2: NÃO IDENTIFICADO | S2: 47057 | T2: 1587612 | U2: sim | Z2: SIM | AA2: leitura caso a caso | AB2: Fora do indicador: a SS não cai na janela de nenhuma interrupção. | AC2: Segue nota para envia equipe manutenção substituir Trafo 5711513001 de 10kva e para-raio avariado, Tensão 7,9kv, Rural de Porto Nacional Assentamento P.A. Pau Darco, Chac. Duas Irmãs, Acesso para camionete 4x4.Obs. Informação da equipe 001OP11 Trafo não Funcionando. | AD2: medido_ emergencial_ substituição de trafo queimado rdr porto
A3: DOLP-RD-PA 00122/2026 | B3: jan | C3: Sem interrupção comprovada | D3: Fora da janela | E3: EXPURGO | F3: QUEIMADO | G3: esteira 1.582 | H3: FORA DA JANELA DA CRÍTICA | I3: 5710169006 | J3: DLP-MLPA01 000020/2026 | K3: 112600156 | L3: 2026-01-25 10:13 | M3: 2026-01-26 18:30 | N3: FORMS SUBST DE TRANSFORMADOR | O3: DOLP-RD-PA | P3: TOCANTINIA | Q3: QUEIMADO | R3: NÃO IDENTIFICADO | S3: 358539 | T3: 464890 | U3: sim | Z3: SIM | AA3: leitura caso a caso | AB3: Fora do indicador: a Crítica registra defeito aberto neste transformador, mas em data que não cabe na janela desta SS. | AC3: segue ss de 01 trafo de 15 kvar e 01 para raio queimado da rede de 34.500kv para ser subistituido pela equipe de manutencão cliente penalizado 01 equipe que atendeu 006op01 cel, 63992363662/992379486 acesso livre favor agilizar o atendimento | AD3: MEDIDO_ EMERGENCIAL_ segue ss de 01 trafo de 15 kvar e 01 para raio queimado da rede de 34.500kv para ser subistituido pela equipe de manutencão cliente penalizado 01 equipe que atendeu 006op01 cel, 63992363662/992379486 acesso livre favor agilizar o atendimento DADOS ATENDIMENTO EQUIPE: PALMA11M LIDER: EDUARDO DA SILVA SANTOS CONTATO: 63 9296-7129 DOLP-RD-PA 000122/2026 DATA ATENDIMENTO: 26/01/2026 Atenção! Não intervenha na rede sem autorização do COI (Centro de Operações Integradas)
A4: DOLP-RD-PA 00124/2026 | B4: jan | C4: Sem interrupção comprovada | D4: Fora da janela | E4: EXPURGO | F4: QUEIMADO | G4: esteira 1.582 | H4: FORA DA JANELA DA CRÍTICA | I4: 5711933122 | J4: DLP-MLPA01 000021/2026 | K4: 112600144 | L4: 2026-01-25 12:35 | M4: 2026-01-26 16:04 | N4: FORMS SUBST DE TRANSFORMADOR | O4: DOLP-RD-PA | P4: PALMAS | Q4: QUEIMADO | R4: NÃO IDENTIFICADO | S4: 181042 | T4: 799443 | U4: sim | Z4: SIM | AA4: leitura caso a caso | AB4: Fora do indicador: a SS não cai na janela de nenhuma interrupção. | AC4: segue ss de 01 trafo de 15 kvar e 01 para raio da rede de 34,500kv para ser subistituido pela equipe de manutencão acesso livre cliente penalizado 01 equipe que atendeu 059op12 cel, 63985065407/992621690 favor agilizar o atendimento devido a reclamacão ser doo dia 24-01-2026 09:52 | AD4: MEDIDO_ EMERGENCIAL_ segue ss de 01 trafo de 15 kvar e 01 para raio da rede de 34,500kv para ser subistituido pela equipe de manutencão acesso livre cliente penalizado 01 equipe que atendeu 059op12 cel, 63985065407/992621690 favor agilizar o atendimento devido a reclamacão ser doo dia 24-01-2026 09:52 DADOS ATENDIMENTO EQUIPE: PALMA04M LIDER: OSE RAIMUNDO LOPES DE SOUZA CONTATO: 63 9296-9610 DOLP-RD-PA 000122/2026 DATA ATENDIMENTO: 26/01/2026 Atenção! Não intervenha na rede sem autorização do COI (Centro de Operações Integradas)
A5: ENC-RD-PS 00008/2026 | B5: jan | C5: Sem interrupção comprovada | D5: Fora da janela | E5: EXPURGO | F5: QUEIMADO | G5: esteira 1.582 | H5: FORA DA JANELA DA CRÍTICA | I5: 5700188046 | J5: ENC-LMPS01 000004/2026 | K5: 212600046 | L5: 2026-01-03 18:05 | M5: 2026-01-05 00:35 | N5: FORMS SUBST DE TRANSFORMADOR | O5: ENC-RD-PS | P5: NOVA ROSALANDIA | Q5: QUEIMADO | R5: DESCARGA ATMOSFÉRICA | S5: 565670050 | T5: 136158 | U5: sim | V5: MEIO AMBIENTE | W5: DESCARGA ATMOSFERICA | Z5: SIM | AA5: leitura caso a caso | AB5: Fora do indicador: a SS não cai na janela de nenhuma interrupção. | AC5: TR 5700188046 QUEIMADO 30KVAPARA RAIO DANIFICADO ACESSO LIVRET 34500013OP14 | AD5: SS ENC-RD-PS 08/2026 TR 5700188046 TRAFO RETIRADO POTÊNCIA : 30KVA TENSÃO : 34.5KV Nº ENERGISA (CITD) : ILEGIVEL Nº DE SÉRIE : 565670050 MARCA : SIEMENS DATA FABRICAÇÃO : 07/1999 IMPEDANCIA : 4.15 POS. TAP : 01 TRAFO INSTALADO' POTÊNCIA : 30KVA TENSÃO : 34.5KV Nº ENERGISA (CITD) : 134706 Nº DE SÉRIE : 136158 MARCA : TRAEL DATA FABRICAÇÃO : 08/2008 IMPEDANCIA : 4.15 POS. TAP : 02
A6: ETO-RD-AR 00034/2026 | B6: jan | C6: Sem interrupção comprovada | D6: Fora da janela | E6: EXPURGO | F6: QUEIMADO | G6: esteira 1.582 | H6: FORA DA JANELA DA CRÍTICA | I6: 5700867040 | J6: ENC-MLAR05 000014/2026 | K6: 612600051 | L6: 2026-01-08 10:53 | M6: 2026-01-09 16:30 | N6: FORMS SUBST DE TRANSFORMADOR | O6: ETO-RD-AR | P6: ARAGOMINAS | Q6: QUEIMADO | R6: DESCARGA ATMOSFÉRICA | S6: 432082 | U6: não | Z6: SIM | AA6: leitura caso a caso | AB6: Fora do indicador: a SS não cai na janela de nenhuma interrupção. | AC6: Trafo 5700867040 15kvaTensão: 19.9Equipe: 058op03Endereço: IND ASSENTAMEN P.A. REUNIDAS, 0 - LOTE 37 | AD6: ETO-RD-AR 34/2026 TRAFO RETIRADO POTÊNCIA : 15 KVA TENSÃO : 34.5 KV Nº ENERGISA (CITD) : 06105312 Nº DE SÉRIE : 432082 MARCA : TRAEL DATA FABRICAÇÃO : 06/2017 IMPEDANCIA : 2,9 POS. TAP : 05 TRAFO INSTALADO POTÊNCIA : 15 KVA TENSÃO : 34.5 KV Nº ENERGISA (CITD) : 149686 Nº DE SÉRIE : C 290247 MARCA : ITAM DATA FABRICAÇÃO : 09/2025 IMPEDANCIA : 2,98 POS. TAP : 05 OBS. TRAFO SUBSTITUIDO EM CAMPO E DE 15 KVA COM FORME REALTORIO E BUOOK INFORMADO PELA EQUIPE, POREM NO SISTEMA TRAFO E DE 5 KVA ERRO DE CADATRO.
A7: ETO-RD-AR 00188/2026 | B7: jan | C7: Sem interrupção comprovada | D7: Fora da janela | E7: EXPURGO | F7: QUEIMADO | G7: esteira 1.582 | H7: FORA DA JANELA DA CRÍTICA | I7: 5739688157 | J7: ENC-MLAR01 000075/2026 | K7: 612600125 | L7: 2026-01-30 11:44 | M7: 2026-01-30 21:00 | N7: FORMS SUBST DE TRANSFORMADOR | O7: ETO-RD-AR | P7: ARAGUANA | Q7: QUEIMADO | R7: DESCARGA ATMOSFÉRICA | S7: 379613 | T7: 460390 | U7: sim | Z7: não | AA7: leitura caso a caso | AB7: Fora do indicador: a SS não cai na janela de nenhuma interrupção. | AC7: TRAFO QUEIMADO 5739688157 pararaio queimado acesso caminhonete | AD7: ETO-RD-AR 188/2026 TR: 5739688157 TRAFO RETIRADO POTÊNCIA : 25KVA TENSÃO : 34,5KV Nº ENERGISA (CITD) : ILEGIVEL Nº DE SÉRIE : 379613 MARCA : ITAIPU DATA FABRICAÇÃO : 11/2019 IMPEDANCIA : 2,94 POS. TAP : 03 TRAFO INSTALADO POTÊNCIA : 25KVA TENSÃO : 34,5KV Nº ENERGISA (CITD) : 148698 Nº DE SÉRIE : 460390 MARCA : TRAEL DATA FABRICAÇÃO : 2018 IMPEDANCIA : 2,79 POS. TAP : 03
A8: ETO-RD-GR 00023/2026 | B8: jan | C8: Sem interrupção comprovada | D8: Fora da janela | E8: EXPURGO | F8: AVARIADO | G8: esteira 1.582 | H8: FORA DA JANELA DA CRÍTICA | I8: 5700005195 | J8: ENC-MLGR03 000024/2026 | K8: 712600051 | L8: 2026-01-05 12:18 | M8: 2026-01-08 14:34 | N8: FORMS SUBST DE TRANSFORMADOR | O8: ETO-RD-GR | P8: CENTENARIO | Q8: AVARIADO | R8: VAZAMENTO DE ÓLEO | S8: 361653 | T8: 1587002 | U8: sim | Z8: SIM | AA8: leitura caso a caso | AB8: Fora do indicador: a SS não cai na janela de nenhuma interrupção. | AC8: Trafo: 5700005195 vazamento de oleo Potencia: 75 KVATensão: 34,5 KV Para raio: queimado Acesso: livre Equipe: 227op01 (63) 99999-8761/99928-1276Obs. tem que tracar estrutura N1 completa e chave 34,5 KV que atende o trafo. substituir cabos do pirastique. | AD8: SUBSTITUIDO UM TRAFO 5700005195 ETO-RD-GR 23/2026 RDU DE CENTENARIO TRAFO RETIRADO POTÊNCIA : 75KVA TENSÃO : 34,5KV Nº ENERGISA (CITD) : 06101301 Nº DE SÉRIE : 361653 MARCA : TRAEL DATA FABRICAÇÃO : 09/2015 IMPEDANCIA : 4,12 POS. TAP : 2 TRAFO INSTALADO POTÊNCIA : 112,5KVA TENSÃO : 34,5KV Nº ENERGISA (CITD) : 143940 Nº DE SÉRIE : 1587002 MARCA : ROMAGNOLE DATA FABRICAÇÃO : 01/2025 IMPEDANCIA : 3,95 POS. TAP : 2 MEDIÇÃO 1: 16,55 MEDIÇÃO 2: 10,02 MEDIÇÃO 3: 03,10 COORDENADA X: 902885 Y: 9007850
A9: ETO-RD-GU 00017/2026 | B9: jan | C9: Sem interrupção comprovada | D9: Fora da janela | E9: EXPURGO | F9: QUEIMADO | G9: esteira 1.582 | H9: FORA DA JANELA DA CRÍTICA | I9: 5701363094 | J9: DBM-MLDB06 000006/2026 | K9: 412600029 | L9: 2026-01-04 15:53 | M9: 2026-01-05 18:15 | N9: FORMS SUBST DE TRANSFORMADOR | O9: ETO-RD-GU | P9: PEIXE | Q9: AVARIADO | R9: BUCHA DANIFICADA | S9: 389568 | T9: 802095 | U9: sim | V9: MEIO AMBIENTE | W9: DESCARGA ATMOSFERICA | X9: TRANSFORMADOR | Y9: FALTANDO FASE INTERNAMENTE | Z9: SIM | AA9: leitura caso a caso | AB9: Fora do indicador: o dono mandou os três para ausente da base de interrupções, e para este a Crítica não deixa: o código 5701363094 TEM defeito aberto nele, na ocorrência 20254026190596 de 15/12/2025, subcausa partido na fase — dezenove dias antes desta SS. Não é ausente; é fora da janela, que é a categoria de quem tem registro próprio em outra data. Sai do indicador do mesmo jeito, com o nome que a base sustenta. | AC9: bucha secundaria queimada para raio queimado e chave fusivel com defeito 19,9kv | AD9: SUBSTITUIÇÃO DE TRANSFORMADOR NA RDR DE ARAGUAÇU INT: 20264064884819 SS: ETO-RD-GU 17/2026 ESPECIFICAÇÕES DO TRANSFORMADOR TRANSFORMADOR INSTALADO: 15 KVA TRANSFORMADOR RETIRADO: 15 KVA MEDIÇÕES LOGO APÓS A TROCA VAN: 203 VBN: 204 OBS:SUBSTITUIÇÃO DE TRANSFORMADOR AUTORIZADA PELO DIONE.
A10: DG-RD-PO 00158/2026 | B10: fev | C10: Sem interrupção comprovada | D10: Fora da janela | E10: EXPURGO | F10: QUEIMADO | G10: esteira 1.582 | H10: FORA DA JANELA DA CRÍTICA | I10: 5710045026 | J10: DG-MLPO01 000035/2026 | K10: 312600123 | L10: 2026-02-03 21:03 | M10: 2026-02-04 20:50 | N10: FORMS SUBST DE TRANSFORMADOR | O10: DG-RD-PO | P10: PONTE ALTA DO TOCANTINS | Q10: QUEIMADO | R10: DESCARGA ATMOSFÉRICA | S10: 371259 | T10: 472337 | U10: sim | Z10: SIM | AA10: leitura caso a caso | AB10: Fora do indicador: a SS não cai na janela de nenhuma interrupção. | AC10: TR 571004502615KVATENSAO 19,9PARA RAIO DANIFICADO ACESSO LIVRE 026OP01 | AD10: medido_ emergencial_ TR 5710045026 15KVA TENSAO 19,9 PARA RAIO DANIFICADO ACESSO LIVRE 026OP01
A11: DG-RD-PO 00160/2026 | B11: fev | C11: Sem interrupção comprovada | D11: Fora da janela | E11: EXPURGO | F11: QUEIMADO | G11: esteira 1.582 | H11: FORA DA JANELA DA CRÍTICA | I11: 5753553037 | J11: DG-MPDG01 000048/2026 | K11: 312600110 | L11: 2026-02-04 09:56 | M11: 2026-02-01 14:55 | N11: FORMS SUBST DE TRANSFORMADOR | O11: DG-RD-PO | P11: BREJINHO DE NAZARE | Q11: QUEIMADO | R11: DESCARGA ATMOSFÉRICA | S11: 221122 | T11: 1657795 | U11: sim | Z11: SIM | AA11: leitura caso a caso | AB11: Fora do indicador: a SS não cai na janela de nenhuma interrupção. | AC11: TRAFO 5753553037 E PARA RAIO QUEIMADO POTENCIA: 75KVA 34500ACESSO: LIVRE | AD11: medido_ emergencial_ TRAFO 5753553037 E PARA RAIO QUEIMADO POTENCIA: 75KVA 34500 ACESSO: LIVRE
A12: DG-RD-PO 00178/2026 | B12: fev | C12: Sem interrupção comprovada | D12: Fora da janela | E12: EXPURGO | F12: QUEIMADO | G12: esteira 1.582 | H12: FORA DA JANELA DA CRÍTICA | I12: 5700861026 | J12: DG-MLPO02 000041/2026 | K12: 312600161 | L12: 2026-02-11 23:46 | M12: 2026-02-12 18:43 | N12: FORMS SUBST DE TRANSFORMADOR | O12: DG-RD-PO | P12: PONTE ALTA DO TOCANTINS | Q12: QUEIMADO | R12: DESCARGA ATMOSFÉRICA | S12: 184945 | T12: 339337 | U12: sim | Z12: SIM | AA12: leitura caso a caso | AB12: Fora do indicador: a SS não cai na janela de nenhuma interrupção. | AC12: Trafo 5700861026 de 15kva e para-raio queimado, Tensão 19,9kv, Acesso para camionete 4x, Rural de Ponte Alta, faz. IND FAZENDA PRODUCAO, 0 - LPT-14877 FAZ PRODUCAO | AD12: medido_ emergencial_ substituição de trafo queimado rdr ponte alta
A13: DOLP-RD-PA 00177/2026 | B13: fev | C13: Sem interrupção comprovada | D13: Fora da janela | E13: EXPURGO | F13: QUEIMADO | G13: esteira 1.582 | H13: FORA DA JANELA DA CRÍTICA | I13: 5755307026 | J13: DLP-MLPA01 000032/2026 | K13: 112600258 | L13: 2026-02-03 08:31 | M13: 2026-02-01 12:00 | N13: FORMS SUBST DE TRANSFORMADOR | O13: DOLP-RD-PA | P13: PONTE ALTA DO TOCANTINS | Q13: QUEIMADO | R13: DESCARGA ATMOSFÉRICA | S13: 1026962 | T13: 287170 | U13: sim | Z13: SIM | AA13: leitura caso a caso | AB13: Fora do indicador: a SS não cai na janela de nenhuma interrupção. | AC13: Segundo informações da equipe 026OP03, o 5755307026 de 15kVA, tensão 19.9V, para raio está ok, acesso livre somente pra caminhonete. | AD13: MEDIDO_ EMERGENCIAL_ Segundo informações da equipe 026OP03, o 5755307026 de 15kVA, tensão 19.9V, para raio está ok, acesso livre somente pra caminhonete. TAP 3 DADOS ATENDIMENTO EQUIPE: ENCARREGADO: CONTATO: DOLP-RD-PA 000177/2026 DATA ATENDIMENTO:__ / __ / __ Atenção! Não intervenha na rede sem autorização do COI (Centro de Operações Integradas)
A14: ETO-RD-AR 00204/2026 | B14: fev | C14: Sem interrupção comprovada | D14: Fora da janela | E14: EXPURGO | F14: QUEIMADO | G14: esteira 1.582 | H14: FORA DA JANELA DA CRÍTICA | I14: 5723118030 | J14: ENC-MLAR02 000018/2026 | K14: 612600132 | L14: 2026-02-02 07:07 | M14: 2026-01-31 19:26 | N14: FORMS SUBST DE TRANSFORMADOR | O14: ETO-RD-AR | P14: XAMBIOA | Q14: QUEIMADO | R14: SOBRECARGA | S14: 965782 | T14: 820232 | U14: sim | Z14: SIM | AA14: leitura caso a caso | AB14: Fora do indicador: a SS não cai na janela de nenhuma interrupção. | AC14: EQUIPE 030OP01TRAFO QUEIMADO 5723118030 potencia 10KVA tensão 34.5KV E RECUPERAR BT ROMPIDAACESSO CAMINHONETE | AD14: ETO-RD-AR 204/2026 TR: 5723118030 TRAFO RETIRADO POTÊNCIA : 15KVA TENSÃO : 34,5KV Nº ENERGISA (CITD) : 06016673 Nº DE SÉRIE : 965782 MARCA : ITB DATA FABRICAÇÃO : 08/2015 IMPEDANCIA : 3,14 POS. TAP : 03 TRAFO INSTALADO POTÊNCIA : 15KVA TENSÃO : 34,5KV Nº ENERGISA (CITD) : 149246 Nº DE SÉRIE : 820232 MARCA : TRAEL DATA FABRICAÇÃO : 11/2025 IMPEDANCIA : 3,0 POS. TAP : 03
A15: ETO-RD-AR 00268/2026 | B15: fev | C15: Sem interrupção comprovada | D15: Fora da janela | E15: EXPURGO | F15: QUEIMADO | G15: esteira 1.582 | H15: FORA DA JANELA DA CRÍTICA | I15: 5700382016 | J15: ENC-MLAR01 000077/2026 | K15: 612600167 | L15: 2026-02-08 11:20 | M15: 2026-02-09 18:35 | N15: FORMS SUBST DE TRANSFORMADOR | O15: ETO-RD-AR | P15: WANDERLANDIA | Q15: QUEIMADO | R15: DESCARGA ATMOSFÉRICA | S15: 179561 | T15: 820183 | U15: sim | Z15: SIM | AA15: leitura caso a caso | AB15: Fora do indicador: a SS não cai na janela de nenhuma interrupção. | AC15: trafo queimado, caiu uma descarga no mesmo pararaio queimado | AD15: SS ETO-RD-AR 268/2026 TRAFO 5700382016 TRAFO RETIRADO POTÊNCIA : 15KVA TENSÃO : 34.5KV Nº ENERGISA (CITD) : 145435 Nº DE SÉRIE : 179561 MARCA : TRAEL DATA FABRICAÇÃO : 02/2002 IMPEDANCIA : 2.98 POS. TAP : 03 TRAFO INSTALADO' POTÊNCIA : 15KVA TENSÃO : 34.5KV Nº ENERGISA (CITD) : 149197 Nº DE SÉRIE : 820183 MARCA : TRAEL DATA FABRICAÇÃO : NOV/2025 IMPEDANCIA : 3.0 POS. TAP : 03
A16: ETO-RD-GR 00238/2026 | B16: fev | C16: Sem interrupção comprovada | D16: Fora da janela | E16: EXPURGO | F16: QUEIMADO | G16: esteira 1.582 | H16: FORA DA JANELA DA CRÍTICA | I16: 5710058153 | J16: ETO-RD-GR 000311/2026 | K16: 712600155 | L16: 2026-02-16 12:35 | M16: 2026-02-17 20:56 | N16: FORMS SUBST DE TRANSFORMADOR | O16: ETO-RD-GR | P16: BERNARDO SAYAO | Q16: QUEIMADO | R16: DESCARGA ATMOSFÉRICA | U16: não | Z16: SIM | AA16: leitura caso a caso | AB16: Fora do indicador: a SS não cai na janela de nenhuma interrupção. | AC16: TR-5710058153 Queimadopara raios QUEIMADO potência 15kvatensão 34,5kvacesso CAMINHONETEequipe 025op01 tel-63992452770 | AD16: TR-5710058153 Queimado para raios QUEIMADO potência 15kva tensão 34,5kv acesso CAMINHONETE equipe 025op01 tel-63992452770
A17: DOLP-RD-PA 00338/2026 | B17: mar | C17: Sem interrupção comprovada | D17: Fora da janela | E17: EXPURGO | F17: QUEIMADO | G17: esteira 1.582 | H17: FORA DA JANELA DA CRÍTICA | I17: 5704202122 | J17: DLP-MPPA01 000086/2026 | K17: 112600587 | L17: 2026-03-10 16:17 | M17: 2026-03-23 08:50 | N17: AVISO DE ANOMALIA | O17: DOLP-RD-PA | P17: PALMAS | Q17: QUEIMADO | R17: BUCHA DANIFICADA | S17: 238663 | T17: 267955 | U17: sim | Z17: não | AA17: leitura caso a caso | AB17: Fora do indicador: a SS não cai na janela de nenhuma interrupção. | AC17: Segue esse para substituição de TF queimado (bucha do TF) 5704202122ID: 50688272 | AD17: MEDIDO_ EMERGENCIAL_ Segue esse para substituição de TF queimado (bucha do TF) 5704202122 ID: 50688272 DADOS ATENDIMENTO EQUIPE DOLP-MPPA01 ENCARREGADO - IBANEZ RODRIGUES CONTATO - (63) 99295-9499 SS DOLP-RD-PA 338/2026 ATENDIMENTO REALIZADO DIA 07/03/2026 EM CONJUNTO COM A SS DOLP-RD-PA 324/2026. *********** Parecer do COCM - ordem de serviço baixada sistemicamente, empreiteira estará fazendo as baixa de material e lançamento de mão de obra.
A18: ENC-RD-PS 00376/2026 | B18: mar | C18: Sem interrupção comprovada | D18: Fora da janela | E18: EXPURGO | F18: QUEIMADO | G18: esteira 1.582 | H18: FORA DA JANELA DA CRÍTICA | I18: 5700368012 | J18: ENC-LMPS04 000055/2026 | K18: 212600335 | L18: 2026-03-20 18:48 | M18: 2026-03-21 12:00 | N18: FORMS SUBST DE TRANSFORMADOR | O18: ENC-RD-PS | P18: DIVINOPOLIS DO TOCANTINS | Q18: QUEIMADO | R18: DESCARGA ATMOSFÉRICA | S18: 473642 | T18: 828112 | U18: sim | Z18: SIM | AA18: leitura caso a caso | AB18: Fora do indicador: a SS não cai na janela de nenhuma interrupção. | AC18: Segue ss para tratativa com equipe de manutençao o quanto antessubstituir trafo 5700368012 queimado na rdr de divinopoles | AD18: SS ENC-RD-PS 376/2026 trafo 5700368012 TRAFO RETIRADO POTÊNCIA : 5KVA TENSÃO : 34.5KV Nº ENERGISA (CITD) : 23196 Nº DE SÉRIE : 473642 MARCA : ITB DATA FABRICAÇÃO : 07/2007 IMPEDANCIA : 2.81 POS. TAP : 03 TRAFO INSTALADO' POTÊNCIA : 15KVA TENSÃO : 34.5KV Nº ENERGISA (CITD) : 150389 Nº DE SÉRIE : 828112 MARCA : TRAEL DATA FABRICAÇÃO : 02/2026 IMPEDANCIA : 3.0 POS. TAP : 03
A19: ETO-RD-AR 00463/2026 | B19: mar | C19: Sem interrupção comprovada | D19: Fora da janela | E19: EXPURGO | F19: AVARIADO | G19: esteira 1.582 | H19: FORA DA JANELA DA CRÍTICA | I19: 5701543077 | J19: ENC-MLAR05 000152/2026 | K19: 612600303 | L19: 2026-03-11 21:10 | M19: 2026-03-12 15:50 | N19: FORMS SUBST DE TRANSFORMADOR | O19: ETO-RD-AR | P19: GOIATINS | Q19: AVARIADO | R19: VAZAMENTO DE ÓLEO | S19: 239355 | T19: 379977 | U19: sim | Z19: não | AA19: leitura caso a caso | AB19: Fora do indicador: a SS não cai na janela de nenhuma interrupção. | AC19: TR-5701543077 vazando oleo para raios bompotência 5kvatensão 34,5kvacesso livreequipe 077op02 tel-63992409718 | AD19: ETO-RD-AR 463/2026 TRAFO 5701543077 TRAFO RETIRADO POTÊNCIA : 5 KVA TENSÃO : 13.8 KV Nº ENERGISA (CITD) : 014435 Nº DE SÉRIE : 239355 MARCA : TRAEL DATA FABRICAÇÃO : 10/2011 IMPEDANCIA : 2,81 POS. TAP : 03 TRAFO INSTALADO POTÊNCIA : 15 KVA TENSÃO : 13.8 KV Nº ENERGISA (CITD) : 148725 Nº DE SÉRIE : 379977 MARCA : TRAEL DATA FABRICAÇÃO : 04/2016 IMPEDANCIA : 2,73 POS. TAP : 05
A20: ETO-RD-AR 00551/2026 | B20: mar | C20: Sem interrupção comprovada | D20: Fora da janela | E20: EXPURGO | F20: QUEIMADO | G20: esteira 1.582 | H20: FORA DA JANELA DA CRÍTICA | I20: 5700322060 | J20: ENC-MLAR01 000152/2026 | K20: 612600337 | L20: 2026-03-24 17:26 | M20: 2026-03-25 12:10 | N20: FORMS SUBST DE TRANSFORMADOR | O20: ETO-RD-AR | P20: NOVA OLINDA | Q20: QUEIMADO | R20: NÃO IDENTIFICADO | S20: 178008 | U20: não | Z20: SIM | AA20: leitura caso a caso | AB20: Fora do indicador: a SS não cai na janela de nenhuma interrupção. | AC20: SEGUE SS DE TRAFO QUEIMADO NA RDR DE NOVA OLINDA, TRAFO DE 15KVA NA REDE DE 7.8KV, PARA RAIO QUEIMADO E ACESSO LIVRE. | AD20: ETO-RD-AR 551/2026 TRAFO 5700322060 TRAFO RETIRADO POTÊNCIA : 15 KVA TENSÃO : 13.8 KV Nº ENERGISA (CITD) : P8322 Nº DE SÉRIE : 178008 MARCA : ABB DATA FABRICAÇÃO : 02/2001 IMPEDANCIA : 2,36 POS. TAP : 03 TRAFO INSTALADO POTÊNCIA : 15 KVA TENSÃO : 13.8 KV Nº ENERGISA (CITD) : 149855 Nº DE SÉRIE : C297819 MARCA : ITAM DATA FABRICAÇÃO : 12/2025 IMPEDANCIA : 2,61 POS. TAP : 05
A21: ETO-RD-AR 00583/2026 | B21: mar | C21: Sem interrupção comprovada | D21: Fora da janela | E21: EXPURGO | F21: QUEIMADO | G21: esteira 1.582 | H21: FORA DA JANELA DA CRÍTICA | I21: 5700799193 | J21: ENC-MLAR03 000036/2026 | K21: 612600363 | L21: 2026-03-31 20:47 | M21: 2026-04-01 18:43 | N21: FORMS SUBST DE TRANSFORMADOR | O21: ETO-RD-AR | P21: CAMPOS LINDOS | Q21: QUEIMADO | R21: DESCARGA ATMOSFÉRICA | S21: 179110 | T21: 827956 | U21: sim | Z21: SIM | AA21: leitura caso a caso | AB21: Fora do indicador: a SS não cai na janela de nenhuma interrupção. | AC21: Trafo 5700799193 15kvaPara-raio: Queimado Endereço: fazenda arueira saindo povoado RanchariaEquipe: 193op02 | AD21: ETO-RD-AR 583/2026 TRAFO 5700799193 TRAFO RETIRADO POTÊNCIA : 5 KVA TENSÃO : 34.5 KV Nº ENERGISA (CITD) : ILEGIVEL Nº DE SÉRIE : 179110 MARCA : VIJAI DATA FABRICAÇÃO : 09/2010 IMPEDANCIA : 3,17 POS. TAP : 05 TRAFO INSTALADO POTÊNCIA : 15 KVA TENSÃO : 34.5 KV Nº ENERGISA (CITD) : 150233 Nº DE SÉRIE : 827956 MARCA : TRAEL DATA FABRICAÇÃO : 02/2026 IMPEDANCIA : 3,0 POS. TAP : 05
A22: ETO-RD-DP 00214/2026 | B22: mar | C22: Sem interrupção comprovada | D22: Fora da janela | E22: EXPURGO | F22: QUEIMADO | G22: esteira 1.582 | H22: FORA DA JANELA DA CRÍTICA | I22: 5700230116 | J22: ETO-MLDP01 000075/2026 | K22: 512600126 | L22: 2026-03-23 13:59 | M22: 2026-03-25 13:30 | N22: FORMS SUBST DE TRANSFORMADOR | O22: ETO-RD-DP | P22: PINDORAMA DO TOCANTINS | Q22: QUEIMADO | R22: DESCARGA ATMOSFÉRICA | S22: 587813 | T22: 251616 | U22: sim | Z22: SIM | AA22: leitura caso a caso | AB22: Fora do indicador: a SS não cai na janela de nenhuma interrupção. | AC22: TRANSFORMADOR QUEIMADO 5700230116 5kva e para raio queimado na 19,9 acesso caminhonete equipe 096op01 992400102 | AD22: TRANSFORMADOR QUEIMADO 5700230116 5kva e para raio queimado na 19,9 acesso caminhonete equipe 096op01 992400102
A23: ETO-RD-GR 00387/2026 | B23: mar | C23: Sem interrupção comprovada | D23: Fora da janela | E23: EXPURGO | F23: AVARIADO | G23: esteira 1.582 | H23: FORA DA JANELA DA CRÍTICA | I23: 5700018155 | J23: ENC-MLAR03 000028/2026 | K23: 712600276 | L23: 2026-03-27 09:49 | M23: 2026-03-27 17:00 | N23: FORMS SUBST DE TRANSFORMADOR | O23: ETO-RD-GR | P23: PALMEIRANTE | Q23: AVARIADO | R23: VAZAMENTO DE ÓLEO | S23: 352737 | T23: 827950 | U23: sim | X23: CHAVE FUSIVEL/RELIGADORA | Y23: PORTA-FUSIVEL DANIFICADO | Z23: SIM | AA23: leitura caso a caso | AB23: Fora do indicador: a SS não cai na janela de nenhuma interrupção. | AC23: trafo 5700018155 com vazamento de óleo - 25KVA - 19,9KV - para raio queimado substituir poste 10/200 estrutura U1/S1 - danificado na base. RDU do Povoado Cicilândia RDR Palmeirante | AD23: TROCA DE TRAFO AVARIADO 5700018155 ETO-RD-GR 387/2026 ZONA RURAL - PALMEIRANTE 0155 TRAFO RETIRADO POTÊNCIA : 25KVA TENSÃO : 19.9KV Nº ENERGISA (CITD) : ILEGIVEL Nº DE SÉRIE : 352737 MARCA : TRAEL DATA FABRICAÇÃO : 10/2015 IMPEDANCIA : 2.84 POS. TAP : 03 TRAFO INSTALADO POTÊNCIA : 15KVA TENSÃO : 19.9KV Nº ENERGISA (CITD) : 150227 Nº DE SÉRIE : 827950 MARCA : TRAEL DATA FABRICAÇÃO : 02/2026 IMPEDANCIA : 3.0 POS. TAP : 03 MEDIÇÃO 1: 07.95 MEDIÇÃO 2: 06.50 MEDIÇÃO 3: 05.83 COORDENADA X: 828148 Y: 9148054 SERVIÇO EM CONJUNTO COM A OS ENC-MLAR03 29/2026.
A24: ETO-RD-GU 00390/2026 | B24: mar | C24: Sem interrupção comprovada | D24: Fora da janela | E24: EXPURGO | F24: QUEIMADO | G24: esteira 1.582 | H24: FORA DA JANELA DA CRÍTICA | I24: 5700039076 | J24: DBM-MLDB03 000067/2026 | K24: 412600331 | L24: 2026-03-26 10:34 | M24: 2026-03-29 13:49 | N24: FORMS SUBST DE TRANSFORMADOR | O24: ETO-RD-GU | P24: DUERE | Q24: QUEIMADO | R24: NÃO IDENTIFICADO | S24: 1574224 | T24: 828021 | U24: sim | Z24: SIM | AA24: leitura caso a caso | AB24: Fora do indicador: a SS não cai na janela de nenhuma interrupção. | AC24: SEGUE SS DE TRAFO QUEIMADO NA RDR DE DUERE, TRAFO DE 15KVA NA REDE DE 19.9KV, PARA RAIO QUEIMADO E ACESSO LIVRE. | AD24: SUBSTITUIÇÃO DE TRANSFORMADOR NA RDR DE PEIXE SS: ETO-D-GU 390/2026 ESPECIFICAÇÕES DO TRANSFORMADOR TRANSFORMADOR INSTALADO: 15 KVA TRANSFORMADOR RETIRADO: 15 KVA MEDIÇÕES LOGO APÓS A TROCA VAN: 208 VBN: 209 OBS:SUBSTITUIÇÃO DE TRANSFORMADOR AUTORIZADA PELO DIONE.
A25: ENC-RD-PS 00481/2026 | B25: abr | C25: Sem interrupção comprovada | D25: Fora da janela | E25: EXPURGO | F25: QUEIMADO | G25: esteira 1.582 | H25: FORA DA JANELA DA CRÍTICA | I25: 5701214055 | J25: ENC-LMPS03 000077/2026 | K25: 212600452 | L25: 2026-04-28 09:30 | M25: 2026-04-30 21:05 | N25: FORMS SUBST DE TRANSFORMADOR | O25: ENC-RD-PS | P25: ARAGUACEMA | Q25: QUEIMADO | R25: VAZAMENTO DE ÓLEO | S25: 723749 | U25: não | Z25: SIM | AA25: leitura caso a caso | AB25: Fora do indicador: a SS não cai na janela de nenhuma interrupção. | AC25: TR 5701214055QUEIMADO ACESSO LIVRE CAMINHONETE 5KVATENSAO 34500PARA RAIO DANIFICADO 055OP01 | AD25: SS ENC-RD-PS 481/2026 TR 5701214055 TRAFO RETIRADO POTÊNCIA : 5KVA TENSÃO : 34.5KV Nº ENERGISA (CITD) : 06003407 Nº DE SÉRIE : 723749 MARCA : ITB DATA FABRICAÇÃO : 03/2011 IMPEDANCIA : 3.21 POS. TAP : 03 TRAFO INSTALADO' POTÊNCIA : 15KVA TENSÃO : 34.5KV Nº ENERGISA (CITD) : 150972 Nº DE SÉRIE : C303352 MARCA : ITAM DATA FABRICAÇÃO : 02/2026 IMPEDANCIA : 2.91 POS. TAP : 03
A26: ETO-RD-AR 00774/2026 | B26: abr | C26: Sem interrupção comprovada | D26: Fora da janela | E26: EXPURGO | F26: AVARIADO | G26: esteira 1.582 | H26: FORA DA JANELA DA CRÍTICA | I26: 5743290004 | J26: ENC-MLAR03 000058/2026 | K26: 612600477 | L26: 2026-04-30 11:05 | M26: 2026-04-30 16:30 | N26: FORMS SUBST DE TRANSFORMADOR | O26: ETO-RD-AR | P26: ARAGUAINA | Q26: AVARIADO | R26: VAZAMENTO DE ÓLEO | S26: 457539 | T26: 330076 | U26: sim | Z26: SIM | AA26: leitura caso a caso | AB26: Fora do indicador: a SS não cai na janela de nenhuma interrupção. | AC26: Trafo 5743290004 75kvaAcesso: livra na RDU de AraguainaSetor: Costa esmeraldoEquipe: de manutenção encontrou o defeito vazando oléo e saindo fumaça pela bucha que foi feito reparo | AD26: ETO-RD-AR 774/2026 TRAFO 5743290004 TRAFO RETIRADO POTÊNCIA : 75 KVA TENSÃO : 13.8 KV Nº ENERGISA (CITD) : 126527 Nº DE SÉRIE : 457539 MARCA : POTENCIAL DATA FABRICAÇÃO : 02/2018 IMPEDANCIA : 3,5 POS. TAP : 04 TRAFO INSTALADO POTÊNCIA : 75 KVA TENSÃO : 13.8 KV Nº ENERGISA (CITD) : 148662 Nº DE SÉRIE : 330076 MARCA : TRAEL DATA FABRICAÇÃO : 10/2024 IMPEDANCIA : 3,52 POS. TAP :
A27: ETO-RD-GR 00466/2026 | B27: abr | C27: Sem interrupção comprovada | D27: Fora da janela | E27: EXPURGO | F27: QUEIMADO | G27: esteira 1.582 | H27: FORA DA JANELA DA CRÍTICA | I27: 5710404111 | J27: ENC-MLGR01 000116/2026 | K27: 712600315 | L27: 2026-04-22 07:20 | M27: 2026-04-21 16:43 | N27: FORMS SUBST DE TRANSFORMADOR | O27: ETO-RD-GR | P27: PEQUIZEIRO | Q27: QUEIMADO | R27: DESCARGA ATMOSFÉRICA | S27: 178699 | T27: 827778 | U27: sim | X27: TRANSFORMADOR | Y27: QUEIMADO POR DESCARGA ATMOSFERICA | Z27: SIM | AA27: leitura caso a caso | AB27: Fora do indicador: a SS não cai na janela de nenhuma interrupção. | AC27: TRAFO QUEIMADO DE 15KVA DA 19.9. PARA RAIOS QUEIMADO. ACESSO BOM. 01 CLIENTE PENALIZADO. | AD27: TROCA DE TRAFO QUEIMADO 5710404111 ETO-RD-GR 466/2026 ZONA RURAL - PEQUIZEIRO 0111 TRAFO RETIRADO POTÊNCIA : 15KVA TENSÃO : 19.9KV Nº ENERGISA (CITD) : CI2706004935 Nº DE SÉRIE : 178699 MARCA : ABB - IMTEL DATA FABRICAÇÃO : 01/2002 - 03/2013 IMPEDANCIA : 3 POS. TAP : 01 TRAFO INSTALADO POTÊNCIA : 15KVA TENSÃO : 19.9KV Nº ENERGISA (CITD) : 150055 Nº DE SÉRIE : 827778 MARCA : TRAEL DATA FABRICAÇÃO : 02/2026 IMPEDANCIA : 3.0 POS. TAP : 02 MEDIÇÃO 1: 25.58 MEDIÇÃO 2: 21.53 MEDIÇÃO 3: 16.40 COORDENADA X: 731871 Y: 9093269
A28: ETO-RD-GU 00429/2026 | B28: abr | C28: Sem interrupção comprovada | D28: Fora da janela | E28: EXPURGO | F28: AVARIADO | G28: esteira 1.582 | H28: FORA DA JANELA DA CRÍTICA | I28: 5710235032 | J28: DBM-MLDB03 000075/2026 | K28: 412600345 | L28: 2026-04-06 10:49 | M28: 2026-04-06 22:00 | N28: FORMS SUBST DE TRANSFORMADOR | O28: ETO-RD-GU | P28: NOVO PLANALTO | Q28: QUEIMADO | R28: BUCHA DANIFICADA | S28: 536046 | T28: 828113 | U28: sim | V28: POSTE DE AT | W28: QUEBRADO | Z28: não | AA28: leitura caso a caso | AB28: Fora do indicador: a SS não cai na janela de nenhuma interrupção. | AC28: trafo 5710235032 queimado de 15 kva rdr de araguaçu tensão 19.9 kv acesso livre e poste quebrado id 42840335 10/300 cabo AA / 4. | AD28: SUBSTITUIÇÃO DE TRANSFORMADOR NA RDR DE ARAGUAÇU INT: 20264257975458 SS: ETO-RD-GU 429/2026 ESPECIFICAÇÕES DO TRANSFORMADOR TRANSFORMADOR INSTALADO: 15 KVA TRANSFORMADOR RETIRADO: 15 KVA MEDIÇÕES LOGO APÓS A TROCA VAN: 223 VBN: 221 OBS:SUBSTITUIÇÃO DE TRANSFORMADOR AUTORIZADA PELO DIONE.
A29: DOLP-RD-PA 00643/2026 | B29: jun | C29: Sem interrupção comprovada | D29: Fora da janela | E29: EXPURGO | F29: QUEIMADO | G29: esteira 1.582 | H29: FORA DA JANELA DA CRÍTICA | I29: 5746488122 | J29: DLP-CTPA00 000107/2026 | K29: 112600604 | L29: 2026-06-07 14:26 | M29: 2026-06-07 18:00 | N29: FORMS SUBST DE TRANSFORMADOR | O29: DOLP-RD-PA | P29: PALMAS | Q29: QUEIMADO | R29: BUCHA DANIFICADA | S29: 437872 | T29: 606278 | U29: sim | Z29: SIM | AA29: leitura caso a caso | AB29: Fora do indicador: a SS não cai na janela de nenhuma interrupção. | AC29: segue nota de trafo queimado, trafo 5745488122, trafo de 45kva, tensao 34,500kv, bitola caboAA / 2, para raio danificado, acesso livre, elo 2H. ramal do piabanha | AD29: MEDIDO_ EMERGENCIAL_ segue nota de trafo queimado, trafo 5745488122, trafo de 45kva, tensao 34,500kv, bitola caboAA / 2, para raio danificado, acesso livre, elo 2H. ramal do piabanha
A30: ENC-RD-PS 00601/2026 | B30: jun | C30: Sem interrupção comprovada | D30: Fora da janela | E30: EXPURGO | F30: QUEIMADO | G30: esteira 1.582 | H30: FORA DA JANELA DA CRÍTICA | I30: 5753306085 | J30: ENC-LMPS01 000152/2026 | K30: 212600554 | L30: 2026-06-24 12:13 | M30: 2026-06-25 12:55 | N30: FORMS SUBST DE TRANSFORMADOR | O30: ENC-RD-PS | P30: MONTE SANTO DO TOCANTINS | Q30: QUEIMADO | R30: SOBRECARGA | S30: 182924 | T30: 602384 | U30: sim | Z30: SIM | AA30: leitura caso a caso | AB30: Fora do indicador: a Crítica registra defeito aberto neste transformador, mas em data que não cabe na janela desta SS. | AC30: TRAFO QUEIMADO 5753306085 30KVA 34,5KV, QUE ATENDE GARIMPO. CARGAS A REVELIA | AD30: SS ENC-RD-PS 601/2026 TRAFO 5753306085 TRAFO RETIRADO POTÊNCIA : 30KVA TENSÃO : 34.5KV Nº ENERGISA (CITD) : 109811 Nº DE SÉRIE : 182924 MARCA : TRAEL DATA FABRICAÇÃO : 01/2001 IMPEDANCIA : 4.06 POS. TAP : 04 TRAFO INSTALADO' POTÊNCIA : 75KVA TENSÃO : 34.5KV Nº ENERGISA (CITD) : 149918 Nº DE SÉRIE : 602384 MARCA : ITAIPU DATA FABRICAÇÃO : 01/2026 IMPEDANCIA : 3.77 POS. TAP : 02
A31: ETO-RD-AR 00992/2026 | B31: jun | C31: Sem interrupção comprovada | D31: Fora da janela | E31: EXPURGO | F31: QUEIMADO | G31: esteira 1.582 | H31: FORA DA JANELA DA CRÍTICA | I31: 5710093157 | J31: ENC-MLAR01 000242/2026 | K31: 612600627 | L31: 2026-06-18 17:27 | M31: 2026-06-19 16:20 | N31: FORMS SUBST DE TRANSFORMADOR | O31: ETO-RD-AR | P31: ARAGUANA | Q31: QUEIMADO | R31: NÃO IDENTIFICADO | S31: 395690 | U31: não | V31: MEIO AMBIENTE | W31: ARVORE DE PEQUENO/ MEDIO PORTE NA REDE / NA FAIXA | Z31: SIM | AA31: leitura caso a caso | AB31: Fora do indicador: a SS não cai na janela de nenhuma interrupção. | AC31: Trafo 5710093157 45kva queimadoPara-raio: QueimadoAcesso: livreEndereço: IND FAZENDA BARRA DO RIO LONTRA, 0Equipe: 030op01 | AD31: ETO-RD-AR 992/2026 TRAFO 5710093157 TRAFO RETIRADO POTÊNCIA : 45 KVA TENSÃO : 34.5 KV Nº ENERGISA (CITD) : 130805 Nº DE SÉRIE : 395690 MARCA : TRAEL DATA FABRICAÇÃO : 07/2016 IMPEDANCIA : 4,04 POS. TAP : 04 TRAFO INSTALADO POTÊNCIA : 45 KVA TENSÃO : 34.5 KV Nº ENERGISA (CITD) : 107053 Nº DE SÉRIE : EA105A2 MARCA : TRAEL DATA FABRICAÇÃO : 2000 IMPEDANCIA : 4,09 POS. TAP : 04
A32: DOLP-RD-PA 00003/2026 | B32: jan | C32: Sem interrupção comprovada | D32: Sem interrupção | E32: EXPURGO | F32: QUEIMADO | G32: esteira 1.582 | H32: AUSENTE DA CRÍTICA | I32: 5700121151 | J32: DLP-CTPA01 000001/2026 | K32: 112600438 | L32: 2026-01-02 15:28 | M32: 2026-01-03 17:32 | N32: FORMS SUBST DE TRANSFORMADOR | O32: DOLP-RD-PA | P32: SANTA TEREZA DO TOCANTINS | Q32: QUEIMADO | R32: NÃO IDENTIFICADO | S32: 185859 | T32: 454942 | U32: sim | Z32: SIM | AA32: leitura caso a caso | AB32: Fora do indicador: o ativo não existe na base de interrupção. Sem registro de interrupção não há evento a medir. | AC32: segue ss de 01 trafo de 30 kvar e 03 para raio queimado da rede de 34,500kv para ser subistituido pela equipe de manutencão acesso bom cliente penalizado 01 equipe que atendeu 151op01 cel, 63992629128/984188058 favor agilizar o atendimento devido cliente informar que está com 03 dias sem energia | AD32: MEDIDO_ EMERGENCIAL_ Msegue ss de 01 trafo de 30 kvar e 03 para raio queimado da rede de 34,500kv para ser subistituido pela equipe de manutencão acesso bom cliente penalizado 01 equipe que atendeu 151op01 cel, 63992629128/984188058 favor agilizar o atendimento devido cliente informar que está com 03 dias sem energia EQUIPE: 833007 ENCARREGADO: JOSE AILTON NO TRAFO [5700121151]
A33: DOLP-RD-PA 00125/2026 | B33: jan | C33: Sem interrupção comprovada | D33: Sem interrupção | E33: EXPURGO | F33: AVARIADO | G33: esteira 1.582 | H33: AUSENTE DA CRÍTICA | I33: 5700307083 | J33: DLP-MLPA03 000004/2026 | K33: 112600148 | L33: 2026-01-25 20:09 | M33: 2026-01-26 20:40 | N33: FORMS SUBST DE TRANSFORMADOR | O33: DOLP-RD-PA | P33: APARECIDA DO RIO NEGRO | Q33: QUEIMADO | R33: VAZAMENTO DE ÓLEO | S33: 497936 | T33: 1615822 | U33: sim | V33: MEIO AMBIENTE | W33: ARVORE DE GRANDE PORTE NA REDE / NA FAIXA | Z33: SIM | AA33: leitura caso a caso | AB33: Fora do indicador: a Crítica nunca registrou defeito aberto neste transformador — em data nenhuma dos sete meses. O código aparece na base, mas só como interrompido ou manobrado, que é o que acontece com quem fica sem energia por defeito de outro equipamento. | AC33: Segue SS para atendimento com equipe de manutenção , substituir trafo 5700307083 com VAZ. DE OLEO na RDR de aparecida do rio negro , acesso para CAMIONETE , para-raio queimado , tensão 34,5, potencia 5 kva | AD33: MEDIDO_ EMERGENCIAL_ Segue SS para atendimento com equipe de manutenção , substituir trafo 5700307083 com VAZ. DE OLEO na RDR de aparecida do rio negro , acesso para CAMIONETE , para-raio queimado , tensão 34,5, potencia 5 kva DADOS ATENDIMENTO EQUIPE: PALMA08M LIDER: OLESMAR OLIVEIRA DE SOUZA CONTATO: 63 9296-9567 DOLP-RD-PA 000125/2026 DATA ATENDIMENTO: 268 Atenção! Não intervenha na rede sem autorização do COI (Centro de Operações Integradas)
A34: ENC-RD-PS 00024/2026 | B34: jan | C34: Sem interrupção comprovada | D34: Sem interrupção | E34: EXPURGO | F34: QUEIMADO | G34: esteira 1.582 | H34: AUSENTE DA CRÍTICA | I34: 5700559233 | J34: ENC-LMPS01 000011/2026 | K34: 212600049 | L34: 2026-01-06 18:36 | M34: 2026-01-07 18:56 | N34: FORMS SUBST DE TRANSFORMADOR | O34: ENC-RD-PS | P34: ABREULANDIA | Q34: QUEIMADO | R34: DESCARGA ATMOSFÉRICA | S34: 525292 | U34: não | Z34: SIM | AA34: leitura caso a caso | AB34: Fora do indicador: o ativo não existe na base de interrupção. Sem registro de interrupção não há evento a medir. | AC34: segue SS ´para tratativa com equipe de manutençao subtituir trafo 5700559233 na rdr de abreulandia | AD34: SS ENC-RD-PS 24/2026 trafo 5700559233 TRAFO RETIRADO POTÊNCIA : 15KVA TENSÃO : 34.5KV Nº ENERGISA (CITD) : 122431 Nº DE SÉRIE : 525292 MARCA : TRAEL DATA FABRICAÇÃO : 01/2020 IMPEDANCIA : 2,91 POS. TAP : 03 TRAFO INSTALADO' POTÊNCIA : 25KVA TENSÃO : 34.5KV Nº ENERGISA (CITD) : 144285 Nº DE SÉRIE : Z 260816 MARCA : ITAM DATA FABRICAÇÃO : 12/2024 IMPEDANCIA : 3.15 POS. TAP : 03
A35: ENC-RD-PS 00044/2026 | B35: jan | C35: Sem interrupção comprovada | D35: Sem interrupção | E35: EXPURGO | F35: QUEIMADO | G35: esteira 1.582 | H35: AUSENTE DA CRÍTICA | I35: 5710028046 | J35: ENC-LMPS04 000011/2026 | K35: 212600073 | L35: 2026-01-11 10:38 | M35: 2026-01-12 16:02 | N35: FORMS SUBST DE TRANSFORMADOR | O35: ENC-RD-PS | P35: NOVA ROSALANDIA | Q35: QUEIMADO | R35: DESCARGA ATMOSFÉRICA | S35: 69095 | U35: não | Z35: SIM | AA35: leitura caso a caso | AB35: Fora do indicador: o ativo não existe na base de interrupção. Sem registro de interrupção não há evento a medir. | AC35: TR 571002804610KVA13800PARA RAIO DANIFICADO ACESSO PARA CAMINHONETE (1)UC PENALIZADA EM CAMPO 046OP01 VILSON | AD35: SS ENC-RD-PS 44/2026 TR 5710028046 TRAFO RETIRADO POTÊNCIA : 10KVA TENSÃO : 13.8KV Nº ENERGISA (CITD) : ILEGIVEL Nº DE SÉRIE :69095 MARCA : TRAEL DATA FABRICAÇÃO : 11/2005 IMPEDANCIA : 2.52 POS. TAP : 01 TRAFO INSTALADO' POTÊNCIA : 15KVA TENSÃO : 34.5KV Nº ENERGISA (CITD) : 137057 Nº DE SÉRIE : C237007 MARCA : ITAM DATA FABRICAÇÃO : 2023 IMPEDANCIA : 2.41 POS. TAP : 03
A36: ENC-RD-PS 00054/2026 | B36: jan | C36: Sem interrupção comprovada | D36: Sem interrupção | E36: EXPURGO | F36: QUEIMADO | G36: esteira 1.582 | H36: AUSENTE DA CRÍTICA | I36: 5701203084 | J36: ENC-LMPS04 000013/2026 | K36: 212600080 | L36: 2026-01-12 13:21 | M36: 2026-01-14 16:40 | N36: FORMS SUBST DE TRANSFORMADOR | O36: ENC-RD-PS | P36: DIVINOPOLIS DO TOCANTINS | Q36: QUEIMADO | R36: DESCARGA ATMOSFÉRICA | S36: 451481 | T36: 290390 | U36: sim | Z36: SIM | AA36: leitura caso a caso | AB36: Fora do indicador: a Crítica nunca registrou defeito aberto neste transformador — em data nenhuma dos sete meses. O código aparece na base, mas só como interrompido ou manobrado, que é o que acontece com quem fica sem energia por defeito de outro equipamento. | AC36: Segue ss para tratativa com equipe de manutençao o quanto antes susbtituir trafo 5701203084 queimado na rdr de divinopoles | AD36: SS ENC-RD-PS 54/2026 trafo 5701203084 TRAFO RETIRADO POTÊNCIA : 15KVA TENSÃO : 34.5KV Nº ENERGISA (CITD) : 06110358 Nº DE SÉRIE : 451481 MARCA : TRAEL DATA FABRICAÇÃO : 12/2017 IMPEDANCIA : 2.96 POS. TAP : 03 TRAFO INSTALADO' POTÊNCIA : 15KVA TENSÃO : 34.5KV Nº ENERGISA (CITD) : 149797 Nº DE SÉRIE : 290390 MARCA : ITAM DATA FABRICAÇÃO : 10/2025 IMPEDANCIA : 3.28 POS. TAP : 03
A37: ENC-RD-PS 00057/2026 | B37: jan | C37: Sem interrupção comprovada | D37: Sem interrupção | E37: EXPURGO | F37: QUEIMADO | G37: esteira 1.582 | H37: AUSENTE DA CRÍTICA | I37: 5710441149 | J37: ENC-LMPS04 000012/2026 | K37: 212600077 | L37: 2026-01-12 17:10 | M37: 2026-01-13 20:09 | N37: FORMS SUBST DE TRANSFORMADOR | O37: ENC-RD-PS | P37: CASEARA | Q37: QUEIMADO | R37: DESCARGA ATMOSFÉRICA | S37: 1568543 | T37: 586759 | U37: sim | Z37: SIM | AA37: leitura caso a caso | AB37: Fora do indicador: o ativo não existe na base de interrupção. Sem registro de interrupção não há evento a medir. | AC37: TR 571044114930KVAT 34500PARA RAIO DANIFICADO ACESSO PARA CAMINHAO (1) PENALIZADA WELVIS SUP. DIVINOPOLIS | AD37: SS ENC-RD-PS 57/2026 TRAFO: 5710428084 TRAFO RETIRADO POTÊNCIA : 30KVA TENSÃO : 34.5KV Nº ENERGISA (CITD) : 143090 Nº DE SÉRIE : 1568543 MARCA : ROMAGNOLE DATA FABRICAÇÃO : 11/2024 IMPEDANCIA : 4.86 POS. TAP : 02 TRAFO INSTALADO' POTÊNCIA : 30KVA TENSÃO : 34.5KV Nº ENERGISA (CITD) : 147722 Nº DE SÉRIE : 586759 MARCA : ITAIPU DATA FABRICAÇÃO : 07/2025 IMPEDANCIA : 3.98 POS. TAP : 02
A38: ETO-RD-AR 00001/2026 | B38: jan | C38: Sem interrupção comprovada | D38: Sem interrupção | E38: EXPURGO | F38: QUEIMADO | G38: esteira 1.582 | H38: AUSENTE DA CRÍTICA | I38: 5703016016 | J38: ENC-MLAR01 000013/2026 | K38: 612600021 | L38: 2026-01-02 10:17 | M38: 2026-01-02 18:00 | N38: FORMS SUBST DE TRANSFORMADOR | O38: ETO-RD-AR | P38: WANDERLANDIA | Q38: QUEIMADO | R38: SOBRECARGA | S38: 180489 | T38: 435142 | U38: sim | Z38: SIM | AA38: leitura caso a caso | AB38: Fora do indicador: o ativo não existe na base de interrupção. Sem registro de interrupção não há evento a medir. | AC38: SUBSTITUIR o Trafo 5703016016Lançar vão de rede de 100 metros , cabo AA / 4Instalar chave trafo ELO 0,5HAcesso livrePotencia de 15 kVA | AD38: ETO-RD-AR 01/2026 TRAFO RETIRADO POTÊNCIA : 15 KVA TENSÃO : 34.5 KV Nº ENERGISA (CITD) : ILEGIVEL Nº DE SÉRIE : 180489 MARCA : ABB DATA FABRICAÇÃO : 04/2002 IMPEDANCIA : 2,9 POS. TAP : 03 TRAFO INSTALADO POTÊNCIA : 15 KVA TENSÃO : 34.5 KV Nº ENERGISA (CITD) : 105598 Nº DE SÉRIE : 435142 MARCA : TRAEL DATA FABRICAÇÃO : 2017 IMPEDANCIA : 2,9 POS. TAP : 05
A39: ETO-RD-AR 00024/2026 | B39: jan | C39: Sem interrupção comprovada | D39: Sem interrupção | E39: EXPURGO | F39: AVARIADO | G39: esteira 1.582 | H39: AUSENTE DA CRÍTICA | I39: 5756806060 | J39: ENC-MLAR05 000003/2026 | K39: 612600048 | L39: 2026-01-06 20:40 | M39: 2026-01-08 16:12 | N39: FORMS SUBST DE TRANSFORMADOR | O39: ETO-RD-AR | P39: NOVA OLINDA | Q39: AVARIADO | R39: VAZAMENTO DE ÓLEO | S39: 255447 | T39: 16294 | U39: sim | Z39: SIM | AA39: leitura caso a caso | AB39: Fora do indicador: o código não aparece na Crítica em papel nenhum — nem com defeito, nem interrompido, nem manobrado — nos sete meses do acervo; nem o teste do vizinho achou explicação. | AC39: TRAFO 5756806060 75KVA 13.8KV COM VAZAMENTO DE OLEO, ATENDE UMA ESCOLA DR. HELIO DE SOU BUENO NA RDU DE NOVA OLINDA | AD39: ETO-RD-AR 24/2026 TRAFO RETIRADO POTÊNCIA : 75 KVA TENSÃO : 13.8 KV Nº ENERGISA (CITD) : 146534 Nº DE SÉRIE : 255447 MARCA : TRAEL DATA FABRICAÇÃO : 07/2023 IMPEDANCIA : 3,51 POS. TAP : 04 TRAFO INSTALADO POTÊNCIA : 75 KVA TENSÃO : 13.8 KV Nº ENERGISA (CITD) : 147780 Nº DE SÉRIE : 16294 MARCA : TRAEL DATA FABRICAÇÃO : 02/2013 IMPEDANCIA : 3,09 POS. TAP : 04
A40: ETO-RD-AR 00081/2026 | B40: jan | C40: Sem interrupção comprovada | D40: Sem interrupção | E40: EXPURGO | F40: QUEIMADO | G40: esteira 1.582 | H40: AUSENTE DA CRÍTICA | I40: 5704370057 | J40: ENC-MLAR05 000026/2026 | K40: 612600070 | L40: 2026-01-16 08:57 | M40: 2026-01-16 23:00 | N40: FORMS SUBST DE TRANSFORMADOR | O40: ETO-RD-AR | P40: ARAGUAINA | Q40: QUEIMADO | R40: DESCARGA ATMOSFÉRICA | S40: 371054 | T40: 820201 | U40: sim | Z40: SIM | AA40: leitura caso a caso | AB40: Fora do indicador: o ativo não existe na base de interrupção. Sem registro de interrupção não há evento a medir. | AC40: Trafo 5704370057 15 kva queimadoTensão: 19.9Acesso: Livre Endereço: IND FAZENDA NOVO HORIZONTE, 0 - NOVO HORIZONTE 500M DA PISTA | AD40: ETO-RD-AR 81/2026 TRAFO RETIRADO POTÊNCIA : 15 KVA TENSÃO : 34.5 KV Nº ENERGISA (CITD) : ILEGIVEL Nº DE SÉRIE : 371054 MARCA : TOSHIBA DATA FABRICAÇÃO : 11/99 IMPEDANCIA : 3,0 POS. TAP : 03 TRAFO INSTALADO POTÊNCIA : 15 KVA TENSÃO : 34.5 KV Nº ENERGISA (CITD) : 149215 Nº DE SÉRIE : 820201 MARCA : TRAEL DATA FABRICAÇÃO : 11/2025 IMPEDANCIA : 3,0 POS. TAP : 05
A41: ETO-RD-AR 00118/2026 | B41: jan | C41: Sem interrupção comprovada | D41: Sem interrupção | E41: EXPURGO | F41: QUEIMADO | G41: esteira 1.582 | H41: AUSENTE DA CRÍTICA | I41: 5700746004 | J41: ENC-MLAR01 000054/2026 | K41: 612600086 | L41: 2026-01-19 21:44 | M41: 2026-01-20 20:50 | N41: FORMS SUBST DE TRANSFORMADOR | O41: ETO-RD-AR | P41: ARAGUAINA | Q41: QUEIMADO | R41: DESCARGA ATMOSFÉRICA | S41: 1294 | T41: 820197 | U41: sim | Z41: SIM | AA41: leitura caso a caso | AB41: Fora do indicador: o ativo não existe na base de interrupção. Sem registro de interrupção não há evento a medir. | AC41: Trafo 5700746004 queimado 15kvaTensão: 19.9Acesso somente para caminhoneteEquipe: 004op08 | AD41: ETO-RD-AR 118/2026 TRAFO RETIRADO POTÊNCIA : 10 KVA TENSÃO : 34.5 KV Nº ENERGISA (CITD) : ILEGIVEL Nº DE SÉRIE : 1294 MARCA : CROSS DATA FABRICAÇÃO : 04/95 IMPEDANCIA : 2,5 POS. TAP : 04 TRAFO INSTALADO POTÊNCIA : 15 KVA TENSÃO : 34.5 KV Nº ENERGISA (CITD) : 149211 Nº DE SÉRIE : 820197 MARCA : TRAEL DATA FABRICAÇÃO : 11/2025 IMPEDANCIA : 3,0 POS. TAP : 05
A42: ETO-RD-GR 00052/2026 | B42: jan | C42: Sem interrupção comprovada | D42: Sem interrupção | E42: EXPURGO | F42: QUEIMADO | G42: esteira 1.582 | H42: AUSENTE DA CRÍTICA | I42: 5741943048 | J42: ENC-MLGR03 000015/2026 | K42: 712600047 | L42: 2026-01-09 18:59 | M42: 2026-01-10 22:28 | N42: FORMS SUBST DE TRANSFORMADOR | O42: ETO-RD-GR | P42: FORTALEZA DO TABOCAO | Q42: QUEIMADO | R42: DESCARGA ATMOSFÉRICA | S42: 1510147 | T42: 489685 | U42: sim | Z42: SIM | AA42: leitura caso a caso | AB42: Fora do indicador: o ativo não existe na base de interrupção. Sem registro de interrupção não há evento a medir. | AC42: trafo queimado 5710088048, porem em campo esta o trafo 5741943048112.5 kVAacesso livre pararaio queimadoequipe 009op01- 63999201531 | AD42: SUBSTITUIÇÃO DE TRAFO 5710088048 ETO-RD-GR 52/2026 RDR FORTALEZA DO TABOCÃO TRAFO RETIRADO POTÊNCIA : 112,5KV TENSÃO : 34,5KV Nº ENERGISA (CITD) : 138563 Nº DE SÉRIE : 1510147 MARCA : ROMAGNOLE DATA FABRICAÇÃO : 03/2024 IMPEDANCIA : 3,87 POS. TAP : 02 TRAFO INSTALADO POTÊNCIA : 150KVA TENSÃO : 34,5KV Nº ENERGISA (CITD) : 135119 Nº DE SÉRIE : 489685 MARCA : ITAIPU DATA FABRICAÇÃO : 03/2023 IMPEDANCIA : 4,03 POS. TAP : 02 MEDIÇÃO 1: 11,57 MEDIÇÃO 2: 07,98 MEDIÇÃO 3: 06,51 COORDENADA: X: 785308 Y: 9006432 OBS: O TRAFO INFORMADO NA SS É O 5741943048, MAS QUAN
A43: ETO-RD-GR 00095/2026 | B43: jan | C43: Sem interrupção comprovada | D43: Sem interrupção | E43: EXPURGO | F43: QUEIMADO | G43: esteira 1.582 | H43: AUSENTE DA CRÍTICA | I43: 5700396048 | J43: ENC-MLGR03 000031/2026 | K43: 712600063 | L43: 2026-01-16 16:33 | M43: 2026-01-17 02:02 | N43: FORMS SUBST DE TRANSFORMADOR | O43: ETO-RD-GR | P43: FORTALEZA DO TABOCAO | Q43: QUEIMADO | R43: DESCARGA ATMOSFÉRICA | S43: 573184 | T43: 820202 | U43: sim | Z43: SIM | AA43: leitura caso a caso | AB43: Fora do indicador: o código não aparece na Crítica em papel nenhum — nem com defeito, nem interrompido, nem manobrado — nos sete meses do acervo; nem o teste do vizinho achou explicação. | AC43: Trafo: 5700396048 Avariado Potencia: 15 KVATensão: 34,5kPara raio: queimado Acesso: Camioneta Equipe: 009op02 (63)99983-3829Obs. trafo esta com tensão baixa em uma das buchas. | AD43: SUBTITUIÇÃO DE TRAFO 5700396048 FAZ. MASC. ESPERANÇA II RDR DE FORTALEZA DO TABOCÃO TRAFO RETIRADO POTÊNCIA : 15KVA TENSÃO : 34,5KV Nº ENERGISA (CITD) : 127938 Nº DE SÉRIE : 573184 MARCA : TRAEL DATA FABRICAÇÃO : 04/2021 IMPEDANCIA : 3,0 POS. TAP : 02 TRAFO INSTALADO POTÊNCIA : 15KVA TENSÃO : 34,5KV Nº ENERGISA (CITD) : 149216 Nº DE SÉRIE : 820202 MARCA : TRAEL DATA FABRICAÇÃO : 11/2025 IMPEDANCIA : 3,0 POS. TAP : 03 MEDIÇÃO 1: 17,45 MEDIÇÃO 2: 11,57 MEDIÇÃO 3: 10,73 COORD. X: 786636 Y: 9005551
A44: ETO-RD-GR 00140/2026 | B44: jan | C44: Sem interrupção comprovada | D44: Sem interrupção | E44: EXPURGO | F44: QUEIMADO | G44: esteira 1.582 | H44: AUSENTE DA CRÍTICA | I44: 5700922009 | J44: ETO-RD-GR 000231/2026 | K44: 712600101 | L44: 2026-01-28 20:04 | M44: 2026-01-31 08:29 | N44: FORMS SUBST DE TRANSFORMADOR | O44: ETO-RD-GR | P44: GUARAI | Q44: QUEIMADO | R44: DESCARGA ATMOSFÉRICA | U44: não | Z44: SIM | AA44: leitura caso a caso | AB44: Fora do indicador: o ativo não existe na base de interrupção. Sem registro de interrupção não há evento a medir. | AC44: TR-5700922009 Queimadopara raios queiamado potência 10kvatensão 34,5kvacesso livreequipe 009op01 tel-63984566867 | AD44: TR-5700922009 Queimado para raios queiamado potência 10kva tensão 34,5kv acesso livre equipe 009op01 tel-63984566867
A45: ETO-RD-GU 00066/2026 | B45: jan | C45: Sem interrupção comprovada | D45: Sem interrupção | E45: EXPURGO | F45: QUEIMADO | G45: esteira 1.582 | H45: AUSENTE DA CRÍTICA | I45: 5710535094 | J45: DBM-MLDB05 000013/2026 | K45: 412600114 | L45: 2026-01-13 20:52 | M45: 2026-01-15 16:00 | N45: FORMS SUBST DE TRANSFORMADOR | O45: ETO-RD-GU | P45: PEIXE | Q45: QUEIMADO | R45: DESCARGA ATMOSFÉRICA | S45: 225341 | U45: não | Z45: SIM | AA45: leitura caso a caso | AB45: Fora do indicador: a Crítica nunca registrou defeito aberto neste transformador — em data nenhuma dos sete meses. O código aparece na base, mas só como interrompido ou manobrado, que é o que acontece com quem fica sem energia por defeito de outro equipamento. | AC45: transformador e para raio queimado | AD45: SUBSTITUIÇÃO DE TRANSFORMADOR NA RDR DE PEIXE INT: 20264079688074 SS: ETO-RD-GU 66/2026 ESPECIFICAÇÕES DO TRANSFORMADOR TRANSFORMADOR INSTALADO: 15 KVA TRANSFORMADOR RETIRADO: 5 KVA MEDIÇÕES LOGO APÓS A TROCA VAN: 209 OBS:SUBSTITUIÇÃO DE TRANSFORMADOR AUTORIZADA PELO DIONE.
A46: ETO-RD-GU 00073/2026 | B46: jan | C46: Sem interrupção comprovada | D46: Sem interrupção | E46: EXPURGO | F46: QUEIMADO | G46: esteira 1.582 | H46: AUSENTE DA CRÍTICA | I46: 5701108076 | J46: DBM-MLDB03 000008/2026 | K46: 412600116 | L46: 2026-01-14 16:27 | M46: 2026-01-16 12:01 | N46: FORMS SUBST DE TRANSFORMADOR | O46: ETO-RD-GU | P46: CARIRI DO TOCANTINS | Q46: QUEIMADO | R46: DESCARGA ATMOSFÉRICA | S46: 20674 | U46: não | Z46: não | AA46: leitura caso a caso | AB46: Fora do indicador: o ativo não existe na base de interrupção. Sem registro de interrupção não há evento a medir. | AC46: transformador e para raio queimado | AD46: SUBSTITUIÇÃO DE TRANSFORMADOR NA RDR DE DUERE INT: 20264080370563 SS: ETO-RD-GU 73/2026 ESPECIFICAÇÕES DO TRANSFORMADOR TRANSFORMADOR INSTALADO: 15 KVA TRANSFORMADOR RETIRADO: 05 KVA MEDIÇÕES LOGO APÓS A TROCA VAN: 202 VBN: 202 OBS:SUBSTITUIÇÃO DE TRANSFORMADOR AUTORIZADA PELO DIONE.
A47: DG-RD-PO 00179/2026 | B47: fev | C47: Sem interrupção comprovada | D47: Sem interrupção | E47: EXPURGO | F47: QUEIMADO | G47: esteira 1.582 | H47: AUSENTE DA CRÍTICA | I47: 5710046096 | J47: DG-MLPO01 000039/2026 | K47: 312500671 | L47: 2026-02-12 10:28 | M47: 2026-02-12 10:44 | N47: FORMS SUBST DE TRANSFORMADOR | O47: DG-RD-PO | P47: PINDORAMA DO TOCANTINS | Q47: QUEIMADO | R47: DESCARGA ATMOSFÉRICA | S47: 1463815 | T47: 1219870 | U47: sim | Z47: SIM | AA47: leitura caso a caso | AB47: Fora do indicador: o ativo não existe na base de interrupção. Sem registro de interrupção não há evento a medir. | AC47: SEGUE SS PARA SUBSTITUIR TRAFO QEUIMADO NA RDR DE PINDORAMAOBS: NOTA CRIADA PARA SUBST. A SS 800/2025 QUE FOI ABERTA NO TRAFO ERRADO | AD47: medido_ emergencial_ substituição de trafo queimado rdr pindorama obs: OS CRIADA PARA SUBSTITUIR MLPO0190/2025 OBRA 0312500671 TRAFO ERRADO
A48: DG-RD-PO 00180/2026 | B48: fev | C48: Sem interrupção comprovada | D48: Sem interrupção | E48: EXPURGO | F48: QUEIMADO | G48: esteira 1.582 | H48: AUSENTE DA CRÍTICA | I48: 5710046096 | J48: DG-MPDG01 000049/2026 | K48: 312500675 | L48: 2026-02-12 10:44 | M48: 2026-02-12 11:05 | N48: FORMS SUBST DE TRANSFORMADOR | O48: DG-RD-PO | P48: PINDORAMA DO TOCANTINS | Q48: GARANTIA DE TRAFO | R48: DESCARGA ATMOSFÉRICA | S48: 1219870 | T48: 586782 | U48: sim | Z48: não | AA48: leitura caso a caso | AB48: Fora do indicador: o ativo não existe na base de interrupção. Sem registro de interrupção não há evento a medir. | AC48: SEGUE SS PARA SUBSTITUIR TRAFO QUEIMADO OBS: NOTA CRIADA PARA SUBST. SS 814/2025 ABERTA NO TRAFO ERRADO | AD48: medido_ emergencial_ substituição de trafo queimado rdr pindorama obs: OS SUBSITUINDO OS MPDG01 210-2025 OBRA 0312500675 TRAFO ERRADO
A49: DOLP-RD-PA 00303/2026 | B49: fev | C49: Sem interrupção comprovada | D49: Sem interrupção | E49: EXPURGO | F49: AVARIADO | G49: esteira 1.582 | H49: AUSENTE DA CRÍTICA | I49: 5722285006 | J49: DLP-MPPA01 000076/2026 | K49: 112600434 | L49: 2026-02-28 08:04 | M49: 2026-03-23 09:00 | N49: FORMS SUBST DE TRANSFORMADOR | O49: DOLP-RD-PA | P49: TOCANTINIA | Q49: QUEIMADO | R49: VAZAMENTO DE ÓLEO | S49: 562169031 | T49: 586768 | U49: sim | Z49: SIM | AA49: leitura caso a caso | AB49: Fora do indicador: o ativo não existe na base de interrupção. Sem registro de interrupção não há evento a medir. | AC49: trafo 5722285006 vazaMENTO DE Óleo acesso livre potencia 30 kva tensão 34,5 para-raio queimado obs: leva porta fusivel para fecha o trafo | AD49: MEDIDO_ trafo 5722285006 vazaMENTO DE Óleo acesso livre potencia 30 kva tensão 34,5 para-raio queimado obs: leva porta fusivel para fecha o trafo DADOS ATENDIMENTO EQUIPE DOLP-MPPA01 ENCARREGADO - IBANEZ RODRIGUES SS DOLP-RD-PA 303/2026 DATA ATENDIMENTO 03/03/2026 CUMPRIR COM TODOS OS PROCEDIMENTOS DE SEGURANÇA *********** Parecer do COCM - ordem de serviço baixada sistemicamente, empreiteira estará fazendo as baixa de material e lançamento de mão de obra.
A50: ENC-RD-PS 00177/2026 | B50: fev | C50: Sem interrupção comprovada | D50: Sem interrupção | E50: EXPURGO | F50: QUEIMADO | G50: esteira 1.582 | H50: AUSENTE DA CRÍTICA | I50: 5701299084 | J50: ENC-LMPS04 000027/2026 | K50: 212600157 | L50: 2026-02-02 14:50 | M50: 2026-02-03 19:00 | N50: FORMS SUBST DE TRANSFORMADOR | O50: ENC-RD-PS | P50: DIVINOPOLIS DO TOCANTINS | Q50: QUEIMADO | R50: DESCARGA ATMOSFÉRICA | S50: 111028 | T50: 811235 | U50: sim | V50: PARA-RAIOS | W50: PARA-RAIOS CURTO-CIRCUITADO | Z50: SIM | AA50: leitura caso a caso | AB50: Fora do indicador: a Crítica nunca registrou defeito aberto neste transformador — em data nenhuma dos sete meses. O código aparece na base, mas só como interrompido ou manobrado, que é o que acontece com quem fica sem energia por defeito de outro equipamento. | AC50: Segue ss para tratativa com equipe de manutençao o quanto antessubstituir trafo 5701299084 | AD50: SS ENC-RD-PS 177/2026 trafo 5701299084 TRAFO RETIRADO POTÊNCIA : 10KVA TENSÃO : 34.5KV Nº ENERGISA (CITD) : ILEGIVEL Nº DE SÉRIE : 111028 MARCA : VIJAI DATA FABRICAÇÃO : 02/2011 IMPEDANCIA : 2.90 POS. TAP : 03 TRAFO INSTALADO' POTÊNCIA : 15KVA TENSÃO : 34.5KV Nº ENERGISA (CITD) : 149145 Nº DE SÉRIE : 811235 MARCA : TRAEL DATA FABRICAÇÃO : AGO/2025 IMPEDANCIA : 3.0 POS. TAP : 03
A51: ENC-RD-PS 00246/2026 | B51: fev | C51: Sem interrupção comprovada | D51: Sem interrupção | E51: EXPURGO | F51: QUEIMADO | G51: esteira 1.582 | H51: AUSENTE DA CRÍTICA | I51: 5720337055 | J51: ENC-LMPS04 000039/2026 | K51: 212600217 | L51: 2026-02-17 15:45 | M51: 2026-02-18 16:00 | N51: FORMS SUBST DE TRANSFORMADOR | O51: ENC-RD-PS | P51: ARAGUACEMA | Q51: QUEIMADO | R51: DESCARGA ATMOSFÉRICA | S51: 367926 | T51: 572129 | U51: sim | V51: MEIO AMBIENTE | W51: DESCARGA ATMOSFERICA | X51: TRANSFORMADOR | Y51: QUEIMADO POR DESCARGA ATMOSFERICA | Z51: SIM | AA51: leitura caso a caso | AB51: Fora do indicador: o dono mandou mover para ausente da base de interrupções. Conferido na Crítica crua: o código 5720337055 nunca teve defeito aberto nele em data nenhuma dos sete meses — aparece uma vez, e só como manobrado. O caso entrava pelo TMAE, não pela Crítica: era um F0, atendimento no código do trafo sem ocorrência que o sustentasse. | AC51: TR 572033705515KVAPARA RAIO DANIFIFCADO 34500CAMINHONETE EQUIPE 055OP01 | AD51: SS ENC-RD-PS 246/2026 TR 5720337055 TRAFO RETIRADO POTÊNCIA : 15KVA TENSÃO : 34.5KV Nº ENERGISA (CITD) : ILEGIVEL Nº DE SÉRIE : 367926 MARCA : TOSHIBA DATA FABRICAÇÃO : 06/1999 IMPEDANCIA : 3.0 POS. TAP : 03 TRAFO INSTALADO' POTÊNCIA : 15KVA TENSÃO : 34.5KV Nº ENERGISA (CITD) : 148868 Nº DE SÉRIE : 572129 MARCA : TRAEL DATA FABRICAÇÃO : 2025 IMPEDANCIA : 3.07 POS. TAP : 03
A52: ENC-RD-PS 00259/2026 | B52: fev | C52: Sem interrupção comprovada | D52: Sem interrupção | E52: EXPURGO | F52: QUEIMADO | G52: esteira 1.582 | H52: AUSENTE DA CRÍTICA | I52: 5700191054 | J52: ENC-LMPS01 000074/2026 | K52: 212600238 | L52: 2026-02-20 13:46 | M52: 2026-02-22 07:41 | N52: FORMS SUBST DE TRANSFORMADOR | O52: ENC-RD-PS | P52: PUGMIL | Q52: QUEIMADO | R52: ABALROADO | S52: C241333 | U52: não | V52: POSTE DE AT | W52: ABALROADO | X52: POSTE DE AT | Y52: ABALROADO | Z52: não | AA52: leitura caso a caso | AB52: Fora do indicador: o ativo não existe na base de interrupção. Sem registro de interrupção não há evento a medir. | AC52: substituir poste ID 47042587 10/300 estrutura do TR 5700191054 15KVA 19,9KV ACESSO BOM fotos anexadas na OS 20264131749370 | AD52: SS ENC-RD-PS 259/2026 TR 5700191054 TRAFO RETIRADO POTÊNCIA : 15KVA TENSÃO : 34.5KV Nº ENERGISA (CITD) : 137853 Nº DE SÉRIE : C 241333 MARCA : ITAM DATA FABRICAÇÃO : 09/2023 IMPEDANCIA : 3.0 POS. TAP : 03 TRAFO INSTALADO' POTÊNCIA : 15KVA TENSÃO : 34.5KV Nº ENERGISA (CITD) : 147906 Nº DE SÉRIE : C299631 MARCA : ITAM DATA FABRICAÇÃO : 01/2026 IMPEDANCIA : 3.02 POS. TAP : 03
A53: ETO-RD-AG 00164/2026 | B53: fev | C53: Sem interrupção comprovada | D53: Sem interrupção | E53: EXPURGO | F53: QUEIMADO | G53: esteira 1.582 | H53: AUSENTE DA CRÍTICA | I53: 5700032103 | J53: ENC-MPAG02 000017/2026 | K53: 662600087 | L53: 2026-02-07 19:18 | M53: 2026-02-08 01:55 | N53: FORMS SUBST DE TRANSFORMADOR | O53: ETO-RD-AG | P53: SAO MIGUEL DO TOCANTINS | Q53: QUEIMADO | R53: DESCARGA ATMOSFÉRICA | S53: 990387 | T53: 20084012 | U53: sim | Z53: SIM | AA53: leitura caso a caso | AB53: Fora do indicador: a Crítica nunca registrou defeito aberto neste transformador — em data nenhuma dos sete meses. O código aparece na base, mas só como interrompido ou manobrado, que é o que acontece com quem fica sem energia por defeito de outro equipamento. | AC53: trafo queimado | AD53: trafo queimado TRAFO RETIRADO POTÊNCIA; 112,5KVA 34,5KV DATA DE FAB; 01/2015 - REFORMA; 09/2025 MARCA; ROMAGNOLE - TRAEL-PA Nº CITD; 132844 Nº SÉRIE; 990387 IMPEDÂNCIA; 4,12 POS. TAP; 3 TRAFO INSTALADO POTÊNCIA; 112,5KVA 34,5KV DATA DE FAB; 09/2024 MARCA; TAMURA Nº CITD; 143798 Nº SÉRIE; 20084012 IMPEDÂNCIA; 3,86 POS. TAP; 2º MEDIÇÃO; 5,92 / 5,94 / 06,39
A54: ETO-RD-AR 00207/2026 | B54: fev | C54: Sem interrupção comprovada | D54: Sem interrupção | E54: EXPURGO | F54: QUEIMADO | G54: esteira 1.582 | H54: AUSENTE DA CRÍTICA | I54: 5366985025 | J54: ENC-MLAR05 000089/2026 | K54: 612600141 | L54: 2026-02-02 13:43 | M54: 2026-02-02 18:00 | N54: FORMS SUBST DE TRANSFORMADOR | O54: ETO-RD-AR | P54: ARAPOEMA | Q54: QUEIMADO | R54: DESCARGA ATMOSFÉRICA | S54: C 287221 | T54: 820280 | U54: sim | Z54: SIM | AA54: leitura caso a caso | AB54: Fora do indicador: o ativo não existe na base de interrupção. Sem registro de interrupção não há evento a medir. | AC54: Boa noite,Favor enviar manutenção para subsitutir trafo 5366985025 | AD54: ETO-RD-AR 207/2026 TR: 5366985025 TRAFO RETIRADO POTÊNCIA : 15KVA TENSÃO : 34,5KV Nº ENERGISA (CITD) : 148084 Nº DE SÉRIE : C287221 MARCA : ITAM DATA FABRICAÇÃO : 08/2025 IMPEDANCIA : 3,13 POS. TAP : 03 TRAFO INSTALADO POTÊNCIA : 15KVA TENSÃO : 34,5KV Nº ENERGISA (CITD) : 149294 Nº DE SÉRIE : 820280 MARCA : TRAEL DATA FABRICAÇÃO : 11/2025 IMPEDANCIA : 3,0 POS. TAP : 03
A55: ETO-RD-AR 00243/2026 | B55: fev | C55: Sem interrupção comprovada | D55: Sem interrupção | E55: EXPURGO | F55: AVARIADO | G55: esteira 1.582 | H55: AUSENTE DA CRÍTICA | I55: 5701262019 | J55: ENC-MLAR05 000091/2026 | K55: 612600149 | L55: 2026-02-04 18:47 | M55: 2026-02-04 18:05 | N55: FORMS SUBST DE TRANSFORMADOR | O55: ETO-RD-AR | P55: FILADELFIA | Q55: AVARIADO | R55: VAZAMENTO DE ÓLEO | S55: 175731 | T55: 820283 | U55: sim | Z55: não | AA55: leitura caso a caso | AB55: Fora do indicador: o ativo não existe na base de interrupção. Sem registro de interrupção não há evento a medir. | AC55: Trafo 5701262019 avariado 15kvaTensão: 19.9Acesso livre | AD55: ETO-RD-AR 243/2026 TR: 5701262019 TRAFO RETIRADO POTÊNCIA : 5KVA TENSÃO : 34,5KV Nº ENERGISA (CITD) : ILEGIVEL Nº DE SÉRIE : 175731 MARCA : VIJAI DATA FABRICAÇÃO : 08/2010 IMPEDANCIA : 3,14 POS. TAP : 03 TRAFO INSTALADO POTÊNCIA : 15KVA TENSÃO : 34,5KV Nº ENERGISA (CITD) : 149297 Nº DE SÉRIE : 820283 MARCA : TRAEL DATA FABRICAÇÃO : 11/2025 IMPEDANCIA : 3,0 POS. TAP : 02
A56: ETO-RD-AR 00315/2026 | B56: fev | C56: Sem interrupção comprovada | D56: Sem interrupção | E56: EXPURGO | F56: AVARIADO | G56: esteira 1.582 | H56: AUSENTE DA CRÍTICA | I56: 5702058004 | J56: ENC-MLAR05 000118/2026 | K56: 612600195 | L56: 2026-02-15 23:00 | M56: 2026-02-16 13:49 | N56: AVISO DE ANOMALIA | O56: ETO-RD-AR | P56: ARAGUAINA | Q56: AVARIADO | R56: VAZAMENTO DE ÓLEO | S56: 182492 | T56: 138720 | U56: sim | V56: CONEXAO | W56: CONEXAO DANIFICADA RAMAL COM RD | Z56: não | AA56: leitura caso a caso | AB56: Fora do indicador: a Crítica nunca registrou defeito aberto neste transformador — em data nenhuma dos sete meses. O código aparece na base, mas só como interrompido ou manobrado, que é o que acontece com quem fica sem energia por defeito de outro equipamento. | AC56: trafo faltanto fase interno secundaria 5702058004 e com vazamento de oleopot 30kvatensao 34,5kvacesso caminhonetefazenda sao paulo GRANJA | AD56: ETO-RD-AR 315/2026 TRAFO RETIRADO POTÊNCIA : 30 KVA TENSÃO : 13.8 KV Nº ENERGISA (CITD) : P 12806 Nº DE SÉRIE : 182492 MARCA : ABB DATA FABRICAÇÃO : 11/01 IMPEDANCIA : 3,87 POS. TAP : 03 TRAFO INSTALADO POTÊNCIA : 30 KVA TENSÃO : 13.8 KV Nº ENERGISA (CITD) : 149607 Nº DE SÉRIE : 138720 MARCA : CPFL DATA FABRICAÇÃO : 2008 IMPEDANCIA : 3,67 POS. TAP : 04
A57: ETO-RD-GR 00174/2026 | B57: fev | C57: Sem interrupção comprovada | D57: Sem interrupção | E57: EXPURGO | F57: QUEIMADO | G57: esteira 1.582 | H57: AUSENTE DA CRÍTICA | I57: 5747088104 | J57: ETO-RD-GR 000258/2026 | K57: 712600133 | L57: 2026-02-03 13:24 | M57: 2026-02-06 08:20 | N57: FORMS SUBST DE TRANSFORMADOR | O57: ETO-RD-GR | P57: BOM JESUS DO TOCANTINS | Q57: QUEIMADO | R57: DESCARGA ATMOSFÉRICA | U57: não | Z57: SIM | AA57: leitura caso a caso | AB57: Fora do indicador: o ativo não existe na base de interrupção. Sem registro de interrupção não há evento a medir. | AC57: trafo queimado 5747088104 - 15KVA - 34,5KV - Acesso caminhonete - para raio queimadofazenda conquista - cliente Jose Reis Amario da Silva tel. 9.92521087 rdr Bom Jesus do Tocantins | AD57: trafo queimado 5747088104 - 15KVA - 34,5KV - Acesso caminhonete - para raio queimado fazenda conquista - cliente Jose Reis Amario da Silva tel. 9.92521087 rdr Bom Jesus do Tocantins
A58: ETO-RD-GR 00189/2026 | B58: fev | C58: Sem interrupção comprovada | D58: Sem interrupção | E58: EXPURGO | F58: QUEIMADO | G58: esteira 1.582 | H58: AUSENTE DA CRÍTICA | I58: 5700424154 | J58: ETO-RD-GR 000256/2026 | K58: 712600129 | L58: 2026-02-04 18:05 | M58: 2026-02-05 15:30 | N58: FORMS SUBST DE TRANSFORMADOR | O58: ETO-RD-GR | P58: JUARINA | Q58: QUEIMADO | R58: DESCARGA ATMOSFÉRICA | S58: 457208 | U58: não | Z58: SIM | AA58: leitura caso a caso | AB58: Fora do indicador: o ativo não existe na base de interrupção. Sem registro de interrupção não há evento a medir. | AC58: TR-5700424154 Queimadopara raios queiamdo potência 10kvatensão 34,5kvacesso livreequipe 154op01 tel-63992674347 | AD58: TROCA DE TRAFO QUEIMADO 5700424154 ETO-RD-GR 189/2026 CHÁC. DOIS IRMÃOS - JUARINA 0154 TRAFO RETIRADO POTÊNCIA : 10KVA TENSÃO : 19.9KV Nº ENERGISA (CITD) : 19290 Nº DE SÉRIE : 457208 MARCA : ITB DATA FABRICAÇÃO : 03/2007 IMPEDANCIA : 2.91 POS. TAP : 01 TRAFO INSTALADO POTÊNCIA : 15KVA TENSÃO : 19.9KV Nº ENERGISA (CITD) : 149744 Nº DE SÉRIE : C 290305 MARCA : ITAM DATA FABRICAÇÃO : 10/2025 IMPEDANCIA : 3.10 POS. TAP : 03 MEDIÇÃO 1: 00.71 MEDIÇÃO 2: 00.48 MEDIÇÃO 3: 00.17 COORDENADA X: 708576 Y: 9101849
A59: ETO-RD-GR 00233/2026 | B59: fev | C59: Sem interrupção comprovada | D59: Sem interrupção | E59: EXPURGO | F59: QUEIMADO | G59: esteira 1.582 | H59: AUSENTE DA CRÍTICA | I59: 5700569227 | J59: ETO-RD-GR 000306/2026 | K59: 712600148 | L59: 2026-02-15 13:28 | M59: 2026-02-17 08:23 | N59: FORMS SUBST DE TRANSFORMADOR | O59: ETO-RD-GR | P59: RECURSOLANDIA | Q59: QUEIMADO | R59: DESCARGA ATMOSFÉRICA | U59: não | Z59: SIM | AA59: leitura caso a caso | AB59: Fora do indicador: o ativo não existe na base de interrupção. Sem registro de interrupção não há evento a medir. | AC59: TRAFO 5745261227 SAI COM RDU DO TRAFO 5700013227 E FICA A FRENTE DO TRAFO 5700569227 QUEIMADO PARA RAIO TAMBÉM DE 15 KVA NA NA REDE 19,9 KV ACESSO BOM PARA CAMIONETE FOI FEITO TESTE AVAZIO COSTATADO QUEIMADO COM VAZAMENTO DE ÓLEO | AD59: TRAFO 5745261227 SAI COM RDU DO TRAFO 5700013227 E FICA A FRENTE DO TRAFO 5700569227 QUEIMADO PARA RAIO TAMBÉM DE 15 KVA NA NA REDE 19,9 KV ACESSO BOM PARA CAMIONETE FOI FEITO TESTE AVAZIO COSTATADO QUEIMADO COM VAZAMENTO DE ÓLEO
A60: ETO-RD-GR 00259/2026 | B60: fev | C60: Sem interrupção comprovada | D60: Sem interrupção | E60: EXPURGO | F60: QUEIMADO | G60: esteira 1.582 | H60: AUSENTE DA CRÍTICA | I60: 5710023113 | J60: ETO-RD-GR 000353/2026 | K60: 712600176 | L60: 2026-02-21 13:09 | M60: 2026-02-24 10:44 | N60: FORMS SUBST DE TRANSFORMADOR | O60: ETO-RD-GR | P60: COUTO MAGALHAES | Q60: QUEIMADO | R60: DESCARGA ATMOSFÉRICA | U60: não | Z60: SIM | AA60: leitura caso a caso | AB60: Fora do indicador: o ativo não existe na base de interrupção. Sem registro de interrupção não há evento a medir. | AC60: trafo queimado 5710023113 - 15KVA - 34,5KV acesso caminhonete para raio queimado necessario refazer aterramento IND ASSENTAMEN P.A. UNIAO, 0 - CHA JANDAIAuc 562509263991206181 -RDR COUTO MAGALHAES | AD60: trafo queimado 5710023113 - 15KVA - 34,5KV acesso caminhonete para raio queimado necessario refazer aterramento IND ASSENTAMEN P.A. UNIAO, 0 - CHA JANDAIA uc 5625092 63991206181 -RDR COUTO MAGALHAES
A61: ETO-RD-GR 00292/2026 | B61: fev | C61: Sem interrupção comprovada | D61: Sem interrupção | E61: EXPURGO | F61: QUEIMADO | G61: esteira 1.582 | H61: AUSENTE DA CRÍTICA | I61: 5710447023 | J61: ENC-MLGR03 000084/2026 | K61: 712600196 | L61: 2026-02-26 19:07 | M61: 2026-02-28 03:11 | N61: FORMS SUBST DE TRANSFORMADOR | O61: ETO-RD-GR | P61: COLINAS DO TOCANTINS | Q61: QUEIMADO | R61: DESCARGA ATMOSFÉRICA | S61: 69687 | T61: 1024143 | U61: sim | Z61: SIM | AA61: leitura caso a caso | AB61: Fora do indicador: o ativo não existe na base de interrupção. Sem registro de interrupção não há evento a medir. | AC61: Boa noite,Favor enviar manutenção para substituir trafo queimado 5710447023 | AD61: TROCA DE TRAFO QUEIMADO 5710447023 ETO-RD-GR 292/2026 CHÁC. VITÓRIA - COLINAS 0023 TRAFO RETIRADO POTÊNCIA : 10KVA TENSÃO : 7.9KV Nº ENERGISA (CITD) : ILEGIVEL Nº DE SÉRIE : 69687 MARCA : TRAEL DATA FABRICAÇÃO : 11/2005 IMPEDANCIA : 2.58 POS. TAP : TRAFO INSTALADO POTÊNCIA : 15KVA TENSÃO : 7.9KV Nº ENERGISA (CITD) : 148731 Nº DE SÉRIE : 1024143 MARCA : ITB - TRAEL DATA FABRICAÇÃO : 06/2016 - 11/2025 IMPEDANCIA : 2.46 POS. TAP : 03 MEDIÇÃO 1: 17.45 MEDIÇÃO 2: 12.76 MEDIÇÃO 3: 10.73 COORDENADA X: 779218 Y: 9111665
A62: ETO-RD-GR 00295/2026 | B62: fev | C62: Sem interrupção comprovada | D62: Sem interrupção | E62: EXPURGO | F62: QUEIMADO | G62: esteira 1.582 | H62: AUSENTE DA CRÍTICA | I62: 5710173023 | J62: ENC-MLGR03 000082/2026 | K62: 712600194 | L62: 2026-02-27 15:07 | M62: 2026-02-28 16:52 | N62: FORMS SUBST DE TRANSFORMADOR | O62: ETO-RD-GR | P62: COLINAS DO TOCANTINS | Q62: QUEIMADO | R62: BUCHA DANIFICADA | S62: 182622 | T62: 133927 | U62: sim | Z62: SIM | AA62: leitura caso a caso | AB62: Fora do indicador: a Crítica nunca registrou defeito aberto neste transformador — em data nenhuma dos sete meses. O código aparece na base, mas só como interrompido ou manobrado, que é o que acontece com quem fica sem energia por defeito de outro equipamento. | AC62: Boa tarde,Favor enviar manutenção para subsitutir trafo com bucha secundaria com defeito 5710173023Obs: Necessario substituir cruzeta deterioradaEstrutura: N3 | AD62: TROCA DE TRAFO QUEIMADO 5710173023 ETO-RD-GR 295/2026 FAZ. MARAJÁ DA SERRA - COLINAS 0023 TRAFO RETIRADO POTÊNCIA : 30KVA TENSÃO : 13.8KV Nº ENERGISA (CITD) : ILEGIVEL Nº DE SÉRIE : 182622 MARCA : ABB DATA FABRICAÇÃO : 11/2001 IMPEDANCIA : 3.57 POS. TAP : 01 TRAFO INSTALADO POTÊNCIA : 30KVA TENSÃO : 13.8KV Nº ENERGISA (CITD) : 138478 Nº DE SÉRIE : 133927 MARCA : TRAEL - TRAEL DATA FABRICAÇÃO : 07/2008 - 02/2024 IMPEDANCIA : 3.74 POS. TAP : 02 MEDIÇÃO 1: 09.57 MEDIÇÃO 2: 08.24 MEDIÇÃO 3: 08.08 COORDENADA X: 763074 Y: 9115556
A63: ETO-RD-GU 00218/2026 | B63: fev | C63: Sem interrupção comprovada | D63: Sem interrupção | E63: EXPURGO | F63: QUEIMADO | G63: esteira 1.582 | H63: AUSENTE DA CRÍTICA | I63: 5710863003 | J63: DBM-MLDB04 000059/2026 | K63: 412600221 | L63: 2026-02-16 19:10 | M63: 2026-02-23 08:10 | N63: FORMS SUBST DE TRANSFORMADOR | O63: ETO-RD-GU | P63: GURUPI | Q63: QUEIMADO | R63: DESCARGA ATMOSFÉRICA | S63: 670034 | U63: não | V63: MEIO AMBIENTE | W63: DESCARGA ATMOSFERICA | Z63: SIM | AA63: leitura caso a caso | AB63: Fora do indicador: a Crítica nunca registrou defeito aberto neste transformador — em data nenhuma dos sete meses. O código aparece na base, mas só como interrompido ou manobrado, que é o que acontece com quem fica sem energia por defeito de outro equipamento. | AC63: TRAFO 5710863003 QUEIMADO EM CAMPO DE 15 KVA ACESSO PARA CAMIONETE PARA RAIO QUEIMADO | AD63: SUBSTITUIÇÃO DE TRANSFORMADOR NA RDR DE GURUPI INT: S/N SS: ETO-RD-GU 218/2026 ESPECIFICAÇÕES DO TRANSFORMADOR TRANSFORMADOR INSTALADO: 15KVA TRANSFORMADOR RETIRADO: 15KVA MEDIÇÕES LOGO APÓS A TROCA VAN: 205.7 VBN: 206.4 VAB: 411 OBS:SUBSTITUIÇÃO DE TRANSFORMADOR AUTORIZADA PELO DIONE.
A64: DG-RD-PO 00233/2026 | B64: mar | C64: Sem interrupção comprovada | D64: Sem interrupção | E64: EXPURGO | F64: QUEIMADO | G64: esteira 1.582 | H64: AUSENTE DA CRÍTICA | I64: 5702646001 | J64: DG-MPDG01 000054/2026 | K64: 312600177 | L64: 2026-03-03 08:09 | M64: 2026-03-03 08:45 | N64: AVISO DE ANOMALIA | O64: DG-RD-PO | P64: PORTO NACIONAL | Q64: QUEIMADO | S64: 2695 | T64: 1597377 | U64: sim | Z64: não | AA64: leitura caso a caso | AB64: Fora do indicador: o ativo não existe na base de interrupção. Sem registro de interrupção não há evento a medir. | AC64: segue nota trafo queimado de 45kVA paraio bom | AD64: medido_ emergencial_ substituição de trafo queimado rdu porto obs: cobrando sobre aviso pedrini 21 a 23/02
A65: DG-RD-PO 00243/2026 | B65: mar | C65: Sem interrupção comprovada | D65: Sem interrupção | E65: EXPURGO | F65: QUEIMADO | G65: esteira 1.582 | H65: AUSENTE DA CRÍTICA | I65: 5710079256 | J65: DG-MLPO02 000052/2026 | K65: 312600197 | L65: 2026-03-05 19:31 | M65: 2026-03-08 11:24 | N65: FORMS SUBST DE TRANSFORMADOR | O65: DG-RD-PO | P65: MATEIROS | Q65: QUEIMADO | R65: DESCARGA ATMOSFÉRICA | S65: 332336 | T65: 463560 | U65: sim | Z65: SIM | AA65: leitura caso a caso | AB65: Fora do indicador: o ativo não existe na base de interrupção. Sem registro de interrupção não há evento a medir. | AC65: TR 5710079256 queimado | AD65: medido_ emergencial_ substituição de trafo queimado rdr mateiros
A66: DOLP-RD-PA 00382/2026 | B66: mar | C66: Sem interrupção comprovada | D66: Sem interrupção | E66: EXPURGO | F66: QUEIMADO | G66: esteira 1.582 | H66: AUSENTE DA CRÍTICA | I66: 5763161196 | J66: DLP-MLPA01 000099/2026 | K66: 112600358 | L66: 2026-03-24 14:14 | M66: 2026-03-23 18:20 | N66: FORMS SUBST DE TRANSFORMADOR | O66: DOLP-RD-PA | P66: LAGOA DO TOCANTINS | Q66: QUEIMADO | R66: DESCARGA ATMOSFÉRICA | S66: 474885 | T66: 1403743 | U66: sim | V66: CAUSA NAO IDENTIFICADA | W66: CAUSA NAO IDENTIFICADA - ESPECIFICAR | Z66: SIM | AA66: leitura caso a caso | AB66: Fora do indicador: a Crítica nunca registrou defeito aberto neste transformador — em data nenhuma dos sete meses. O código aparece na base, mas só como interrompido ou manobrado, que é o que acontece com quem fica sem energia por defeito de outro equipamento. | AC66: SEGUE SS DE TRAFO 5763161196 QUEIMADO NA RDR DE LAGOA DO TOCANTINS. PARA AS DEVIDAS TRATATIVAS COM EQUIPE DE MANUTENÇÃOOBS: LEVAR JOGO DE CHAVE FUSIVEL PARA INSTALAR NA MESMA ESTRUTURA DE TRAFO | AD66: MEDIDO_ EMERGENCIAL_ SEGUE SS DE TRAFO 5763161196 QUEIMADO NA RDR DE LAGOA DO TOCANTINS. PARA AS DEVIDAS TRATATIVAS COM EQUIPE DE MANUTENÇÃO OBS: LEVAR JOGO DE CHAVE FUSIVEL PARA INSTALAR NA MESMA ESTRUTURA DE TRAFO DADOS ATENDIMENTO N° DOCUMENTO SS: DOLP-RD-PA 000382/2026 N° DOCUMENTO OS: DLP-MLPA01 000099/2026 TIPO DA INTERVENÇÃO: MANUTENÇÃO TIPO DO SERVIÇO: SUBSTITUIÇÃO DE TRANSFORMADOR, MELHORIA DE MALHA DE ATERRAMENTO E SUBSTITUIÇÃO DE CHAVE FUSIVEL POTENCIA: 15KVA - CLASSE DE TENSÃO: 34,5KV DATA PROGRAMADA DA ATIVIDADE: 23/03/2026 À 24/03/2026 HORARIO PREVISTO D
A67: ENC-RD-PS 00358/2026 | B67: mar | C67: Sem interrupção comprovada | D67: Sem interrupção | E67: EXPURGO | F67: QUEIMADO | G67: esteira 1.582 | H67: AUSENTE DA CRÍTICA | I67: 5700460055 | J67: ENC-LMPS04 000054/2026 | K67: 212600327 | L67: 2026-03-17 18:55 | M67: 2026-03-18 18:02 | N67: FORMS SUBST DE TRANSFORMADOR | O67: ENC-RD-PS | P67: ARAGUACEMA | Q67: QUEIMADO | R67: DESCARGA ATMOSFÉRICA | S67: C299635 | T67: 828125 | U67: sim | Z67: SIM | AA67: leitura caso a caso | AB67: Fora do indicador: o ativo não existe na base de interrupção. Sem registro de interrupção não há evento a medir. | AC67: TR 5763273055 15KVAPARA RAIO DANIFICADO ACESSO LIVRE PARA CAMINHONETE 055OP01 ESTEVE NO LOCAL TRAFO NAO AXISTE NO SISTEMA (ERRO CADASTRO) FICA PROX AO TR 5700460055MAIS INFORMAÇOES ENTRA EM CONTATO COM EQUIPE 055OP01 | AD67: SS ENC-RD-PS 358/2026 TR 5763273055 TRAFO NAO AXISTE NO SISTEMA (ERRO CADASTRO) FICA PROX AO TR 5700460055 TRAFO RETIRADO POTÊNCIA : 15KVA TENSÃO : 34.5KV Nº ENERGISA (CITD) : 147908 Nº DE SÉRIE : C299635 MARCA : ITAM DATA FABRICAÇÃO : 01/206 IMPEDANCIA : 2.92 POS. TAP : 03 TRAFO INSTALADO' POTÊNCIA : 15KVA TENSÃO : 34.5KV Nº ENERGISA (CITD) : 150402 Nº DE SÉRIE : 828125 MARCA : TRAEL DATA FABRICAÇÃO : 02/2026 IMPEDANCIA : 3.0 POS. TAP : 03
A68: ENC-RD-PS 00361/2026 | B68: mar | C68: Sem interrupção comprovada | D68: Sem interrupção | E68: EXPURGO | F68: QUEIMADO | G68: esteira 1.582 | H68: AUSENTE DA CRÍTICA | I68: 5701007008 | J68: ENC-LMPS03 000066/2026 | K68: 212600341 | L68: 2026-03-19 10:47 | M68: 2026-03-19 17:44 | N68: FORMS SUBST DE TRANSFORMADOR | O68: ENC-RD-PS | P68: MIRANORTE | Q68: QUEIMADO | R68: DESCARGA ATMOSFÉRICA | S68: 388932 | T68: 827738 | U68: sim | Z68: SIM | AA68: leitura caso a caso | AB68: Fora do indicador: o ativo não existe na base de interrupção. Sem registro de interrupção não há evento a medir. | AC68: OS:20264186004963Segue SS de TR queimado UC 9222677 e 3635120 TR não cadastrado 15KVA/7.9KV e para-raios queimados.Acesso livre.Localização: https://www.google.com/maps/search/?api=1&query=-9.534713,-48.600728 SS aberta no TR 5701007008 porém o que está queimado é outro.FAZENDA BOA SORTE63984910222 E 992859555LUZENI NERES DE OLIVEIRA SOUSA008OP01 63 99222-7417 | AD68: SS ENC-RD-PS 361/2026 TRAFO: 5701007008 TRAFO RETIRADO POTÊNCIA : 15KVA TENSÃO : 13.8KV Nº ENERGISA (CITD) : ILEGIVEL Nº DE SÉRIE : 388932 MARCA : TRAEL DATA FABRICAÇÃO : 06/2016 IMPEDANCIA : 2.41 POS. TAP : 01 TRAFO INSTALADO' POTÊNCIA : 15KVA TENSÃO : 13.8KV Nº ENERGISA (CITD) : 150015 Nº DE SÉRIE : 827738 MARCA : TRAEL DATA FABRICAÇÃO : 02/2026 IMPEDANCIA : 2.5 POS. TAP : 03
A69: ETO-RD-AG 00249/2026 | B69: mar | C69: Sem interrupção comprovada | D69: Sem interrupção | E69: EXPURGO | F69: QUEIMADO | G69: esteira 1.582 | H69: AUSENTE DA CRÍTICA | I69: 5700696045 | J69: ENC-MLAG01 000060/2026 | K69: 662600154 | L69: 2026-03-03 12:18 | M69: 2026-03-04 18:23 | N69: FORMS SUBST DE TRANSFORMADOR | O69: ETO-RD-AG | P69: AUGUSTINOPOLIS | Q69: QUEIMADO | R69: DESCARGA ATMOSFÉRICA | S69: 566197014 | T69: 183077 | U69: sim | V69: MEIO AMBIENTE | W69: DESCARGA ATMOSFERICA | Z69: SIM | AA69: leitura caso a caso | AB69: Fora do indicador: a Crítica nunca registrou defeito aberto neste transformador — em data nenhuma dos sete meses. O código aparece na base, mas só como interrompido ou manobrado, que é o que acontece com quem fica sem energia por defeito de outro equipamento. | AC69: TROCA DE TRAFO 5700696045 QUEIMADO DE 30KVA DA 34.5 PARA RAIOS QUEIMADO. ACESSO BOMTROCAR JOGO DE CHAVESUBSTITUIR OS GLV'SLEVAR ROLDANA DA BT. | AD69: TROCA DE TRAFO 5700696045 QUEIMADO DE 30KVA DA 34.5 PARA RAIOS QUEIMADO. ACESSO BOM TROCAR JOGO DE CHAVE SUBSTITUIR OS GLV'S LEVAR ROLDANA DA BT. TRAFO Nº 5700696045 TRAFO RETIRADO POTÊNCIA; 30KVA 34,5KV DATA DE FAB; 07/99 REF.; 11/2017 MARCA; SIEMENS - TRAEL Nº CITD; 108243 Nº SÉRIE; 566197014 POS. DO TAP; 2 IMPEDÂNCIA; 13,26 / 13,04 / 12,97 TRAFO INSTALADO POTÊNCIA; 30KVA 34,5KV DATA DE FAB; 12/01 REF.; 04/2024 MARCA; ABB - TRAEL PA Nº CITD; 138765 Nº SÉRIE; 183077 POS. DO TAP; 2 IMPEDÂNCIA;4,17 MEDIÇÃO; 13,26 / 13,04 /12,97 OBS; SUBST JOGO DE 03X CHAV
A70: ETO-RD-AR 00415/2026 | B70: mar | C70: Sem interrupção comprovada | D70: Sem interrupção | E70: EXPURGO | F70: AVARIADO | G70: esteira 1.582 | H70: AUSENTE DA CRÍTICA | I70: 5700402060 | J70: ENC-MLAR01 000124/2026 | K70: 612600249 | L70: 2026-03-03 20:22 | M70: 2026-03-04 15:25 | N70: FORMS SUBST DE TRANSFORMADOR | O70: ETO-RD-AR | P70: NOVA OLINDA | Q70: AVARIADO | R70: VAZAMENTO DE ÓLEO | S70: 177002 | T70: 249961 | U70: sim | Z70: não | AA70: leitura caso a caso | AB70: Fora do indicador: o ativo não existe na base de interrupção. Sem registro de interrupção não há evento a medir. | AC70: TR-5700402060 vazando oleo para raios bompotência 10kvatensão 13,8kvacesso livreequipe 060op0102 tel-63992173964 | AD70: ETO-RD-AR 415/2026 TRAFO 5700402060 TRAFO RETIRADO POTÊNCIA : 10 KVA TENSÃO : 13.8 KV Nº ENERGISA (CITD) : 37130 Nº DE SÉRIE : 177002 MARCA : TRAEL DATA FABRICAÇÃO : 01/2010 IMPEDANCIA : 2,59 POS. TAP : 03 TRAFO INSTALADO POTÊNCIA : 15 KVA TENSÃO : 13.8 KVA Nº ENERGISA (CITD) : 148823 Nº DE SÉRIE : 249961 MARCA : ITB DATA FABRICAÇÃO : 11/2025 IMPEDANCIA : 2,49 POS. TAP : 05
A71: ETO-RD-AR 00434/2026 | B71: mar | C71: Sem interrupção comprovada | D71: Sem interrupção | E71: EXPURGO | F71: QUEIMADO | G71: esteira 1.582 | H71: AUSENTE DA CRÍTICA | I71: 5710028040 | J71: ENC-MLAR01 000130/2026 | K71: 612600266 | L71: 2026-03-06 22:17 | M71: 2026-03-07 16:30 | N71: FORMS SUBST DE TRANSFORMADOR | O71: ETO-RD-AR | P71: ARAGOMINAS | Q71: QUEIMADO | R71: DESCARGA ATMOSFÉRICA | S71: 388798 | T71: 974078 | U71: sim | V71: MEIO AMBIENTE | W71: DESCARGA ATMOSFERICA | Z71: SIM | AA71: leitura caso a caso | AB71: Fora do indicador: a Crítica nunca registrou defeito aberto neste transformador — em data nenhuma dos sete meses. O código aparece na base, mas só como interrompido ou manobrado, que é o que acontece com quem fica sem energia por defeito de outro equipamento. | AC71: Trafo 5710028040 Queimado Potencia:15 KVATensão: 13,8 KVPara raio: Queimado Acesso: CamionetaEquipe: 040op36 (63)992870450 | AD71: ETO-RD-AR 434/2026 TRAFO 5710028040 TRAFO RETIRADO POTÊNCIA :15 KVA TENSÃO : 13.8 KV Nº ENERGISA (CITD) : 05100990 Nº DE SÉRIE : 388798 MARCA : TRAEL DATA FABRICAÇÃO : 06/2016 IMPEDANCIA : 2,4 POS. TAP : 04 TRAFO INSTALADO POTÊNCIA : 15 KVA TENSÃO : 13.8 KV Nº ENERGISA (CITD) : 148906 Nº DE SÉRIE : 974078 MARCA : ITB DATA FABRICAÇÃO : 2015 IMPEDANCIA : 2,38 POS. TAP : 05
A72: ETO-RD-AR 00437/2026 | B72: mar | C72: Sem interrupção comprovada | D72: Sem interrupção | E72: EXPURGO | F72: QUEIMADO | G72: esteira 1.582 | H72: AUSENTE DA CRÍTICA | I72: 5701771022 | J72: ENC-MLAR03 000007/2026 | K72: 612600271 | L72: 2026-03-07 13:00 | M72: 2026-03-08 13:40 | N72: FORMS SUBST DE TRANSFORMADOR | O72: ETO-RD-AR | P72: BABACULANDIA | Q72: QUEIMADO | R72: DESCARGA ATMOSFÉRICA | S72: 1611007 | T72: 827838 | U72: sim | Z72: SIM | AA72: leitura caso a caso | AB72: Fora do indicador: o ativo não existe na base de interrupção. Sem registro de interrupção não há evento a medir. | AC72: Trafo 5701771022 queimado 15kvaTensão: 34.5Acesso; somente para caminhonteEquipe: 004op27Endereço: Chacara Bela Vista | AD72: ETO-RD-AR 437/2026 TRAFO 5701771022 TRAFO RETIRADO POTÊNCIA : 15 KVA TENSÃO : 34.5 KV Nº ENERGISA (CITD) : 142471 Nº DE SÉRIE : 1611007 MARCA : ITB DATA FABRICAÇÃO : 05/2024 IMPEDANCIA : 2,88 POS. TAP : 05 TRAFO INSTALADO POTÊNCIA : 15 KVA TENSÃO : 34.5 KV Nº ENERGISA (CITD) : 150115 Nº DE SÉRIE : 827838 MARCA : TRAEL DATA FABRICAÇÃO : 02/2026 IMPEDANCIA : 3,0 POS. TAP : 03
A73: ETO-RD-AR 00440/2026 | B73: mar | C73: Sem interrupção comprovada | D73: Sem interrupção | E73: EXPURGO | F73: AVARIADO | G73: esteira 1.582 | H73: AUSENTE DA CRÍTICA | I73: 5701182022 | J73: ENC-MLAR01 000057/2026 | K73: 612600272 | L73: 2026-03-08 11:28 | M73: 2026-03-07 18:00 | N73: AVISO DE ANOMALIA | O73: ETO-RD-AR | P73: BABACULANDIA | Q73: POSTE | R73: DETERIORADA | S73: 172842 | T73: 827803 | U73: sim | Z73: não | AA73: leitura caso a caso | AB73: Fora do indicador: o ativo não existe na base de interrupção. Sem registro de interrupção não há evento a medir. | AC73: Bom dia Segue SSSenhores envia equipe na RDR de Babaçulândia para trocar poste e Trafo Trafo: 5701182022Poste: 10/200ID: 55662476Acesso: Para caminhão e caminhoneteEndereço: Chácara Cantinho Pov. FarturãoOBS: Trocar poste e Trafo. | AD73: ETO-RD-AR 440/2026 TRAFO 5701182022 TRAFO RETIRADO POTÊNCIA : 5 KVA TENSÃO : 34.5 KV Nº ENERGISA (CITD) : ILEGIVEL Nº DE SÉRIE : 172842 MARCA : VIJAI DATA FABRICAÇÃO : 08/2010 IMPEDANCIA : 3,11 POS. TAP : 05 TRAFO INSTALADO POTÊNCIA : 15 KVA TENSÃO : 34.5 KV Nº ENERGISA (CITD) : 150080 Nº DE SÉRIE : 827803 MARCA : TRAEL DATA FABRICAÇÃO : 02/2026 IMPEDANCIA : 3,0 POS. TAP : 05 DEVIDO A EROSAO FOI DANIFICADO O TRAFO TENDO QUE SUBTITUIR AVARIADO E O POSTE
A74: ETO-RD-AR 00468/2026 | B74: mar | C74: Sem interrupção comprovada | D74: Sem interrupção | E74: EXPURGO | F74: QUEIMADO | G74: esteira 1.582 | H74: AUSENTE DA CRÍTICA | I74: 5301889004 | J74: ENC-MLAR01 000136/2026 | K74: 612600312 | L74: 2026-03-12 19:30 | M74: 2026-03-13 15:30 | N74: FORMS SUBST DE TRANSFORMADOR | O74: ETO-RD-AR | P74: ARAGUAINA | Q74: QUEIMADO | R74: BUCHA DANIFICADA | S74: 141362 | T74: 826192 | U74: sim | Z74: não | AA74: leitura caso a caso | AB74: Fora do indicador: o dono reviu a própria decisão: “se estiver fora daquelas janelas … deverão ser excluídos”. Ele havia mandado incluir por ler queima com SIGCO incorreto; conferido na Crítica crua, o código 5301889004 não aparece em papel nenhum nos sete meses — nem com defeito, nem interrompido, nem manobrado. Nem o 5701889004 que a OS escreve, nem o 570188904 que a SS escreve. Sem registro de interrupção não há evento a medir. | AC74: Trafo 570188904 queimado 15kvaAcesso: Somente caminhonetePara-raio; Queimado Equipe: 004op26 | AD74: ETO-RD-AR 468/2026 TRAFO 5701889004 TRAFO RETIRADO POTÊNCIA : 15 KVA TENSÃO : 13.8 KV Nº ENERGISA (CITD) : 7658 Nº DE SÉRIE : 141362 MARCA : ITB DATA FABRICAÇÃO : 07/9 IMPEDANCIA : 2,43 POS. TAP : 03 TRAFO INSTALADO POTÊNCIA : 15 KVA TENSÃO : 13.8 KV Nº ENERGISA (CITD) : 149974 Nº DE SÉRIE : 826192 MARCA : TRAEL DATA FABRICAÇÃO : 01/2026 IMPEDANCIA : 2,5 POS. TAP : 05
A75: ETO-RD-AR 00504/2026 | B75: mar | C75: Sem interrupção comprovada | D75: Sem interrupção | E75: EXPURGO | F75: QUEIMADO | G75: esteira 1.582 | H75: AUSENTE DA CRÍTICA | I75: 5752570159 | J75: ENC-MLAR05 000157/2026 | K75: 612600330 | L75: 2026-03-17 20:04 | M75: 2026-03-18 21:24 | N75: FORMS SUBST DE TRANSFORMADOR | O75: ETO-RD-AR | P75: MURICILANDIA | Q75: QUEIMADO | R75: DESCARGA ATMOSFÉRICA | S75: 1298121 | T75: 586769 | U75: sim | V75: CAUSA NAO IDENTIFICADA | W75: CAUSA NAO IDENTIFICADA - ESPECIFICAR | Z75: SIM | AA75: leitura caso a caso | AB75: Fora do indicador: a Crítica nunca registrou defeito aberto neste transformador — em data nenhuma dos sete meses. O código aparece na base, mas só como interrompido ou manobrado, que é o que acontece com quem fica sem energia por defeito de outro equipamento. | AC75: 5752570159 30kva 34.5kv e para raioacesso livre | AD75: ETO-RD-AR 504/2026 TRAFO 5752570159 TRAFO RETIRADO POTÊNCIA : 30 KVA TENSÃO : 34.4 KV Nº ENERGISA (CITD) : 129196 Nº DE SÉRIE : 1298121 MARCA : ROMAGNOLE DATA FABRICAÇÃO : 06/2024 IMPEDANCIA : 3,69 POS. TAP : 4 TRAFO INSTALADO POTÊNCIA : 30 KVA TENSÃO : 34.5 KV Nº ENERGISA (CITD) : 147732 Nº DE SÉRIE : 586769 MARCA : ITAIPU DATA FABRICAÇÃO : 07/2025 IMPEDANCIA : 3,96 POS. TAP : 04 OBS: LANÇADO DISPONIBILIDADE REFERENTE AO DESLOCAMENTO DA SS ETO-RD-AG 224/2026 PARA FAZER MELHORIA,PORÉM NÃO FOI PRECISO DEVIDO NÃO TER TRAFO NO LOCAL.
A76: ETO-RD-AR 00555/2026 | B76: mar | C76: Sem interrupção comprovada | D76: Sem interrupção | E76: EXPURGO | F76: QUEIMADO | G76: esteira 1.582 | H76: AUSENTE DA CRÍTICA | I76: 5702259004 | J76: ETO-RD-AR 000876/2026 | K76: 612600355 | L76: 2026-03-25 19:39 | M76: 2026-03-26 17:28 | N76: FORMS SUBST DE TRANSFORMADOR | O76: ETO-RD-AR | P76: ARAGUAINA | Q76: QUEIMADO | R76: NÃO IDENTIFICADO | U76: não | Z76: SIM | AA76: leitura caso a caso | AB76: Fora do indicador: a Crítica nunca registrou defeito aberto neste transformador — em data nenhuma dos sete meses. O código aparece na base, mas só como interrompido ou manobrado, que é o que acontece com quem fica sem energia por defeito de outro equipamento. | AC76: trafo queimado 5702259004 queimado 15 kv 19,9 kva para raio Bom acesso bom.fazenda Santa Tereza - UC 3165559-0 cliente: Persio de Freitas Vilela. RDR Arapoema | AD76: trafo queimado 5702259004 queimado 15 kv 19,9 kva para raio Bom acesso bom. fazenda Santa Tereza - UC 3165559-0 cliente: Persio de Freitas Vilela. RDR Arapoema
A77: ETO-RD-AR 00557/2026 | B77: mar | C77: Sem interrupção comprovada | D77: Sem interrupção | E77: EXPURGO | F77: QUEIMADO | G77: esteira 1.582 | H77: AUSENTE DA CRÍTICA | I77: 5710138077 | J77: ENC-MLAR02 000072/2026 | K77: 612600344 | L77: 2026-03-26 08:51 | M77: 2026-03-27 18:00 | N77: FORMS SUBST DE TRANSFORMADOR | O77: ETO-RD-AR | P77: GOIATINS | Q77: AVARIADO | R77: SOBRECARGA | S77: 69463 | U77: não | Z77: SIM | AA77: leitura caso a caso | AB77: Fora do indicador: o ativo não existe na base de interrupção. Sem registro de interrupção não há evento a medir. | AC77: TR-5710138077 o mesmo não esta entregando a tensão adequadapara queimadopotência 10kvatensão 13,8kvacesso livreequipe 265op0 tel-63992212789 | AD77: ETO-RD-AR 557/2026 TRAFO 5710138077 TRAFO RETIRADO POTÊNCIA : 10 KVA TENSÃO : 13.8 KV Nº ENERGISA (CITD) : ILEGIVEL Nº DE SÉRIE :69463 MARCA : TRAEL DATA FABRICAÇÃO : 11/2005 IMPEDANCIA : 2,57 POS. TAP : 03 TRAFO INSTALADO POTÊNCIA : 15 KVA TENSÃO : 13.8 KV Nº ENERGISA (CITD) : 149841 Nº DE SÉRIE : C292465 MARCA : ITAM DATA FABRICAÇÃO : 10/2025 IMPEDANCIA : 2,75 POS. TAP : 05 OBS: LANÇADO UMA HORA DE DISPONIBILIDADE REFERENTE AO SERVIÇO DA SS 569/2026 PARA SEGURAR POSTE.
A78: ETO-RD-AR 00582/2026 | B78: mar | C78: Sem interrupção comprovada | D78: Sem interrupção | E78: EXPURGO | F78: QUEIMADO | G78: esteira 1.582 | H78: AUSENTE DA CRÍTICA | I78: 5710015080 | J78: ENC-MLAR03 000042/2026 | K78: 612600374 | L78: 2026-03-31 20:03 | M78: 2026-04-02 14:50 | N78: FORMS SUBST DE TRANSFORMADOR | O78: ETO-RD-AR | P78: DARCINOPOLIS | Q78: QUEIMADO | R78: SOBRECARGA | S78: 533216 | T78: 828055 | U78: sim | Z78: SIM | AA78: leitura caso a caso | AB78: Fora do indicador: o ativo não existe na base de interrupção. Sem registro de interrupção não há evento a medir. | AC78: Trafo: 5710015080 QueimadoPotência: 15 KVARede: 34.5Pararaio: 34.5Acesso: só pra veículo traçadoSubstituir o mesmo pois está com a bucha primária quebrado por descarga atmosférica | AD78: ETO-RD-AR 582/2026 TRAFO 5710015080 TRAFO RETIRADO POTÊNCIA : 15 KVA TENSÃO : 3465 KV Nº ENERGISA (CITD) : 6123420 Nº DE SÉRIE : 533216 MARCA : TRAEL DATA FABRICAÇÃO : 03/2020 IMPEDANCIA : 3,0 POS. TAP : 05 TRAFO INSTALADO POTÊNCIA : 15 KVA TENSÃO : 34.5 KV Nº ENERGISA (CITD) : 150332 Nº DE SÉRIE : 828055 MARCA : TRAEL DATA FABRICAÇÃO : 02/2026 IMPEDANCIA : 3,0 POS. TAP : 05
