Workbook
Name DadosExternos_2: 'BASE GERAL'!$A$1:$AJ$1582

Sheet Exportar Planilha (2)
A1: NUMERO_SS | B1: NUMERO_OS | C1: NUM_OBRA | D1: Coluna1 | E1: TASKDESCRIPTION | F1: ORIGEM_SS | G1: DEFEITO_SS | H1: ORIGEM | I1: DEFEITO | J1: ESQUEMA | K1: ANO | L1: ALIMENTADOR | M1: NUM_TRAFO | N1: NUM_PROJETO_SIGCO | O1: CRITICIDADE_SS | P1: SITUACAO_SS | Q1: DATA_ABERTURA_SS | R1: DATA_TERMINO_SS | S1: DATA_LIMITE_SS | T1: DESCICAO_DO_ATIVO | U1: LOCALIDADE | V1: SOLICITANTE | W1: RURA_URBANO | X1: TIPOSS | Y1: DESCRIPTION | Z1: POTENCIA_INST | AA1: POTENCIA_RET | AB1: POT_RET | AC1: DATA_ATUALIZACAO
A2: ETO-RD-AR 00011/2026 | B2: ENC-MLAR01 000016/2026 | C2: 612600024 | E2: ETO-RD-AR 11/2026_x000D_ TRAFO RETIRADO_x000D_ POTÊNCIA : 5 KVA_x000D_ TENSÃO : 34.5 KV_x000D_ Nº ENERGISA (CITD) : ILEGIVEL_x000D_ Nº DE SÉRIE : 125062_x000D_ MARCA : VIJAI_x000D_ DATA FABRICAÇÃO : 08/2008_x000D_ IMPEDANCIA : 2,85_x000D_ POS. TAP : 05_x000D_ _x000D_ TRAFO INSTALADO_x000D_ POTÊNCIA : 15 KVA_x000D_ TENSÃO : 34.5 KV_x000D_ Nº ENERGISA (CITD) : 110729_x000D_ Nº DE SÉRIE : 455521_x000D_ MARCA : TRAEL_x000D_ DATA FABRICAÇÃO : 2016_x000D_ IMPEDANCIA : 3,04_x000D_ POS. TAP : 05_x000D_ | F2: QUEIMADO | G2: DESCARGA ATMOSFÉRICA | H2: QUEIMADO | I2: NÃO IDENTIFICADO | J2: MC - SUBSTITUIÇÃO DE TRANSFORMADOR | K2: 2026 | L2: LD03010004 | M2: 5700876040 | N2: 8385 | O2: EMERGENCIAL | P2: SS ATENDIDA | Q2: 46025.77 | R2: 46026.583 | S2: 46028.77 | T2: BLOCO TRANSFORMADOR DE DISTRIBUIÇÃO | U2: ARAGOMINAS | V2: GUILHERME BORGES DE OLIVEIRA | W2: RURAL | X2: FORMS SUBST DE TRANSFORMADOR | Y2: 5700876040 10 kva 34.5kv e para raioacesso livre | Z2: 15 | AA2: 5 | AB2: 10KVA | AC2: 46225.761
A3: ETO-RD-GU 00314/2026 | B3: DBM-MLDB06 000046/2026 | C3: 412600319 | E3: SUBSTITUIÇÃO DE TRANSFORMADOR NA RDR DE PARANA_x000D_ _x000D_ INT: 20264171148086_x000D_ _x000D_ SS: ETO-RD-GU 314/2026_x000D_ _x000D_ ESPECIFICAÇÕES DO TRANSFORMADOR_x000D_ _x000D_ TRANSFORMADOR INSTALADO: 15 KVA_x000D_ _x000D_ TRANSFORMADOR RETIRADO: 15 KVA_x000D_ _x000D_ MEDIÇÕES_x000D_ _x000D_ LOGO APÓS A TROCA _x000D_ _x000D_ VAN: 218_x000D_ _x000D_ OBS:SUBSTITUIÇÃO DE TRANSFORMADOR AUTORIZADA PELO DIONE._x000D_ | F3: QUEIMADO | G3: DESCARGA ATMOSFÉRICA | H3: QUEIMADO | I3: DESCARGA ATMOSFÉRICA | J3: MC - SUBSTITUIÇÃO DE TRANSFORMADOR | K3: 2026 | L3: LD01066094 | M3: 5700866021 | N3: 8812 | O3: EMERGENCIAL | P3: SS ATENDIDA | Q3: 46091.577 | R3: 46092.754 | S3: 46094.577 | T3: BLOCO TRANSFORMADOR DE DISTRIBUIÇÃO | U3: PARANA | V3: JURANDY GOMES DE OLIVEIRA | W3: RURAL | X3: FORMS SUBST DE TRANSFORMADOR | Y3: Trafo 5700866021 queimado em campo de 15 kva tensão 19.9 kv acesso camionete para raio queimado,rdr de paranã | Z3: 15 | AA3: 15 | AB3: 15 | AC3: 46225.761
A4: ETO-RD-GR 00085/2026 | B4: ENC-MLGR03 000035/2026 | C4: 712600065 | E4: SUBSTITUIÇÃO DE TRAFO 5700632104, ETO-RD-GR 85/2026, FAZ. CHUPE RDR DE SANTA MARIA _x000D_ _x000D_ TRAFO RETIRADO_x000D_ POTÊNCIA : 15KVA _x000D_ TENSÃO : 34,5KV_x000D_ Nº ENERGISA (CITD) : 108759_x000D_ Nº DE SÉRIE : 442904_x000D_ MARCA : TRAEL_x000D_ DATA FABRICAÇÃO : 09/2017_x000D_ IMPEDANCIA : 3,06_x000D_ POS. TAP : 03_x000D_ _x000D_ TRAFO INSTALADO_x000D_ POTÊNCIA : 15KVA_x000D_ TENSÃO : 34,5KV_x000D_ Nº ENERGISA (CITD) : 149266_x000D_ Nº DE SÉRIE : 820252_x000D_ MARCA : TRAEL_x000D_ DATA FABRICAÇÃO : 11/2025_x000D_ IMPEDANCIA : 3,0_x000D_ POS. TAP : 3_x000D_ _x000D_ MEDIÇÃO 1: 00,18_x000D_ MEDIÇÃO 2: 00,08_x000D_ MEDIÇÃO 3: 00,07_x000D_ _x000D_ COORD._x000D_ X: 855817_x000D_ Y: 9019527 | F4: QUEIMADO | G4: DESCARGA ATMOSFÉRICA | H4: QUEIMADO | I4: DESCARGA ATMOSFÉRICA | J4: MC - SUBSTITUIÇÃO DE TRANSFORMADOR | K4: 2026 | L4: LD01065015 | M4: 5700632104 | N4: 8812 | O4: PROGRAMAVEL | P4: SS ATENDIDA | Q4: 46038.504 | R4: 46038.875 | S4: 46438.504 | T4: BLOCO TRANSFORMADOR DE DISTRIBUIÇÃO | U4: SANTA MARIA DO TOCANTINS | V4: VALERIA DE JESUS BORGES CARVAL | W4: RURAL | X4: FORMS SUBST DE TRANSFORMADOR | Y4: TRAFO QUEIMADO 5700632104 - 15KVA 19,9KV ACESSO LIVRE PARA RAIO QUEIMADO IND FAZENDA CHUPE - CLIENTE LENIEL FONSECA LOPES - UC 10074720 - TEL. 63984232073RDR SANTA MARIA | Z4: 15 | AA4: 15 | AB4: 15KVA | AC4: 46225.761
A5: ETO-RD-GU 00404/2026 | B5: DBM-MLDB05 000078/2026 | C5: 412600346 | E5: SUBSTITUIÇÃO DE TRANSFORMADOR NA RDR DE PEIXE_x000D_ _x000D_ INT: 20264210037659_x000D_ _x000D_ SS: ETO-RD-GU 404/2026_x000D_ _x000D_ ESPECIFICAÇÕES DO TRANSFORMADOR_x000D_ _x000D_ TRANSFORMADOR INSTALADO: 15KVA_x000D_ _x000D_ TRANSFORMADOR RETIRADO: 15KVA_x000D_ _x000D_ MEDIÇÕES_x000D_ _x000D_ LOGO APÓS A TROCA _x000D_ _x000D_ VAN: 220.8_x000D_ _x000D_ VBN: 220.8_x000D_ _x000D_ OBS:SUBSTITUIÇÃO DE TRANSFORMADOR AUTORIZADA PELO DIONE._x000D_ _x000D_ _x000D_ | F5: QUEIMADO | G5: NÃO IDENTIFICADO | H5: QUEIMADO | I5: NÃO IDENTIFICADO | J5: MC - SUBSTITUIÇÃO DE TRANSFORMADOR | K5: 2026 | L5: LD02072001 | M5: 5700924094 | N5: 8812 | O5: EMERGENCIAL | P5: SS ATENDIDA | Q5: 46110.794 | R5: 46112.36 | S5: 46113.794 | T5: BLOCO TRANSFORMADOR DE DISTRIBUIÇÃO | U5: PEIXE | V5: Wilmar Lucas Rodrigues Noleto | W5: RURAL | X5: FORMS SUBST DE TRANSFORMADOR | Y5: SEGUE SS DE TRAFO QUEIMADO NA RDR DE PEIXE, TRAFO DE 15KVA NA REDE DE 19.9KV, ACESSO LIVRE E PARA RAIOS QUEIMADO. | Z5: 15 | AA5: 15 | AB5: 15KVA | AC5: 46225.761
A6: ETO-RD-GU 00141/2026 | B6: DBM-MLDB03 000026/2026 | C6: 412600152 | E6: SUBSTITUIÇÃO DE TRANSFORMADOR NA RDR DE PEIXE_x000D_ _x000D_ INT: 20264106374261_x000D_ _x000D_ SS: ETO-RD-GU 141/2026_x000D_ _x000D_ ESPECIFICAÇÕES DO TRANSFORMADOR_x000D_ _x000D_ TRANSFORMADOR INSTALADO: 15 KVA_x000D_ _x000D_ TRANSFORMADOR RETIRADO: 05 KVA _x000D_ _x000D_ _x000D_ OBS:SUBSTITUIÇÃO DE TRANSFORMADOR AUTORIZADA PELO DIONE._x000D_ | F6: QUEIMADO | G6: DESCARGA ATMOSFÉRICA | H6: QUEIMADO | I6: DESCARGA ATMOSFÉRICA | J6: MC - SUBSTITUIÇÃO DE TRANSFORMADOR | K6: 2026 | L6: LD01066094 | M6: 5701125094 | N6: 8385 | O6: EMERGENCIAL | P6: SS ATENDIDA | Q6: 46051.638 | R6: 46052.995 | S6: 46054.638 | T6: BLOCO TRANSFORMADOR DE DISTRIBUIÇÃO | U6: PEIXE | V6: JURANDY GOMES DE OLIVEIRA | W6: RURAL | X6: FORMS SUBST DE TRANSFORMADOR | Y6: trafo 5701125094 de 15 kva queimado acesso livre rdr de peixe tensão 19.9 para raio queimado | Z6: 15 | AA6: 5 | AB6: 10 | AC6: 46225.761
A7: ETO-RD-AR 00414/2026 | B7: ENC-MLAR01 000123/2026 | C7: 612600256 | E7: ETO-RD-AR 414/2026_x000D_ TRAFO RETIRADO_x000D_ POTÊNCIA : 5 KVA_x000D_ TENSÃO : 34.5 KV_x000D_ Nº ENERGISA (CITD) : 35539_x000D_ Nº DE SÉRIE : 612733_x000D_ MARCA : ITB_x000D_ DATA FABRICAÇÃO : 08/2009_x000D_ IMPEDANCIA : 3,04_x000D_ POS. TAP : 05_x000D_ _x000D_ TRAFO INSTALADO_x000D_ POTÊNCIA : 15 KVA_x000D_ TENSÃO : 34.5 KV_x000D_ Nº ENERGISA (CITD) : 150083_x000D_ Nº DE SÉRIE : 827806_x000D_ MARCA : TRAEL_x000D_ DATA FABRICAÇÃO : 02/2026_x000D_ IMPEDANCIA : 3,0_x000D_ POS. TAP : 05_x000D_ | F7: QUEIMADO | G7: NÃO IDENTIFICADO | H7: QUEIMADO | I7: DESCARGA ATMOSFÉRICA | J7: MC - SUBSTITUIÇÃO DE TRANSFORMADOR | K7: 2026 | L7: LD02010004 | M7: 5700498080 | N7: 8812 | O7: EMERGENCIAL | P7: SS ATENDIDA | Q7: 46084.617 | R7: 46084.972 | S7: 46087.617 | T7: BLOCO TRANSFORMADOR DE DISTRIBUIÇÃO | U7: DARCINOPOLIS | V7: LEANDRO BISPO DE BARROS | W7: RURAL | X7: FORMS SUBST DE TRANSFORMADOR | Y7: trafo 5700498080 queimado 5 KVA acesso livre equipe 016op02 992153859 | Z7: 15 | AA7: 15 | AB7: 5kva | AC7: 46225.761
A8: DOLP-RD-PA 00374/2026 | B8: DLP-MPPA01 000088/2026 | C8: 112600369 | E8: MEDIDO__x000D_ _x000D_ EMERGENCIAL__x000D_ _x000D_ segue ss de 01 trafo de 45 kvar da rede de 34.500kv queimado para ser subistituido pela equipe de manutencão acesso livre clientes penalizado 01 equipe que fez o atendimento 092op01 cel, 63991002294/992607968 acesso livre favor agilizar o atendimento_x000D_ _x000D_ DADOS DO ATENDIMENTO:_x000D_ _x000D_ EQUIPE: 833017 - DLP-MPPA02_x000D_ ENCARREGADO: JULIO IGNACIO_x000D_ DATA: 23/03/2026 | F8: QUEIMADO | G8: NÃO IDENTIFICADO | H8: QUEIMADO | I8: NÃO IDENTIFICADO | J8: MC - SUBSTITUIÇÃO DE TRANSFORMADOR | K8: 2026 | L8: LD01059122 | M8: 5730634070 | N8: 8812 | O8: EMERGENCIAL | P8: SS ATENDIDA | Q8: 46103.837 | R8: 46104.75 | S8: 46106.837 | T8: BLOCO TRANSFORMADOR DE DISTRIBUIÇÃO | U8: RIO SONO | V8: JOAO PAULO VASCONCELOS MARINHO | W8: RURAL | X8: FORMS SUBST DE TRANSFORMADOR | Y8: segue ss de 01 trafo de 45 kvar da rede de 34.500kv queimado para ser subistituido pela equipe de manutencão acesso livre clientes penalizado 01 equipe que fez o atendimento 092op01 cel, 63991002294/992607968 acesso livre favor agilizar o atendimento | Z8: 45 | AA8: 45 | AB8: 45 kvar | AC8: 46225.761
A9: ETO-RD-AR 00207/2026 | B9: ENC-MLAR05 000089/2026 | C9: 612600141 | E9: ETO-RD-AR 207/2026_x000D_ TR: 5366985025_x000D_ _x000D_ TRAFO RETIRADO_x000D_ POTÊNCIA : 15KVA_x000D_ TENSÃO : 34,5KV_x000D_ Nº ENERGISA (CITD) : 148084_x000D_ Nº DE SÉRIE : C287221_x000D_ MARCA : ITAM_x000D_ DATA FABRICAÇÃO : 08/2025_x000D_ IMPEDANCIA : 3,13_x000D_ POS. TAP : 03_x000D_ _x000D_ TRAFO INSTALADO_x000D_ POTÊNCIA : 15KVA_x000D_ TENSÃO : 34,5KV_x000D_ Nº ENERGISA (CITD) : 149294_x000D_ Nº DE SÉRIE : 820280_x000D_ MARCA : TRAEL_x000D_ DATA FABRICAÇÃO : 11/2025_x000D_ IMPEDANCIA : 3,0_x000D_ POS. TAP : 03_x000D_ | F9: QUEIMADO | G9: DESCARGA ATMOSFÉRICA | H9: QUEIMADO | I9: DESCARGA ATMOSFÉRICA | J9: MC - SUBSTITUIÇÃO DE TRANSFORMADOR | K9: 2026 | L9: LD02010153 | M9: 5366985025 | N9: 8812 | O9: EMERGENCIAL | P9: SS ATENDIDA | Q9: 46055.572 | R9: 46055.75 | S9: 46058.572 | T9: BLOCO TRANSFORMADOR DE DISTRIBUIÇÃO | U9: ARAPOEMA | V9: MAIKOM DOUGLAS DA SILVA | W9: RURAL | X9: FORMS SUBST DE TRANSFORMADOR | Y9: Boa noite,Favor enviar manutenção para subsitutir trafo 5366985025 | Z9: 15 | AA9: 15 | AB9: 15 | AC9: 46225.761
A10: DOLP-RD-PA 00429/2026 | B10: DLP-CTPA00 000064/2026 | C10: 112600384 | E10: MEDIDO__x000D_ _x000D_ 01. Baixado para consumo de material_x000D_ _x000D_ Transformador com vazamento de oleo grande proporção 5764409122 feito divisão de circuito recente com 5700354122, potencia 112kva, tensão 13.8, acesso livre a caminhao, para raio bom._x000D_ _x000D_ DADOS DO ATENDIMENTO:_x000D_ DOLP-RD-PA 429/2026_x000D_ EQUIPE: 833019 - DOLP-CT-PA 07_x000D_ ENCARREGADO: REGINALDO DE OLIVEIRA_x000D_ DATA: 08/04/2026 | F10: AVARIADO | G10: VAZAMENTO DE ÓLEO | H10: AVARIADO | I10: VAZAMENTO DE ÓLEO | J10: MC - SUBSTITUIÇÃO DE TRANSFORMADOR | K10: 2026 | L10: AL03059122 | M10: 5700354122 | N10: 25962 | O10: EMERGENCIAL | P10: SS ATENDIDA | Q10: 46120.616 | R10: 46120.75 | S10: 46123.616 | T10: TRANSFORMADOR DE DISTRIBUIÇÃO ENERGISA 13.8Kv | U10: PALMAS | V10: HELDER SILVA CARVALHO | W10: URBANO | X10: FORMS SUBST DE TRANSFORMADOR | Y10: Transformador com vazamento de oleo grande proporção 5764409122 feito divisão de circuito recente com 5700354122, potencia 112kva, tensão 13.8, acesso livre a caminhao, para raio bom. | Z10: 10 | AA10: 10 | AB10: 112,5 | AC10: 46225.761
A11: ETO-RD-GU 00105/2026 | B11: DBM-MLDB05 000017/2026 | C11: 412600144 | E11: SUBSTITUIÇÃO DE TRANSFORMADOR NA RDR DE ARAGUAÇU_x000D_ _x000D_ INT: S/N_x000D_ _x000D_ SS: ETO-RD-GU 105/2026_x000D_ _x000D_ ESPECIFICAÇÕES DO TRANSFORMADOR_x000D_ _x000D_ TRANSFORMADOR INSTALADO: 15KVA_x000D_ _x000D_ TRANSFORMADOR RETIRADO: 15KVA_x000D_ _x000D_ MEDIÇÕES_x000D_ _x000D_ LOGO APÓS A TROCA _x000D_ _x000D_ VAN: 210.3_x000D_ _x000D_ VBN: 210.3_x000D_ _x000D_ VAB: 419_x000D_ _x000D_ OBS:SUBSTITUIÇÃO DE TRANSFORMADOR AUTORIZADA PELO DIONE._x000D_ _x000D_ | F11: QUEIMADO | G11: DESCARGA ATMOSFÉRICA | H11: QUEIMADO | I11: DESCARGA ATMOSFÉRICA | J11: MC - SUBSTITUIÇÃO DE TRANSFORMADOR | K11: 2026 | L11: LD01003036 | M11: 5710170032 | N11: 8812 | O11: EMERGENCIAL | P11: SS ATENDIDA | Q11: 46041.749 | R11: 46043.565 | S11: 46044.749 | T11: BLOCO TRANSFORMADOR DE DISTRIBUIÇÃO | U11: ARAGUACU | V11: JONATAN ALVES DE SOUZA | W11: RURAL | X11: FORMS SUBST DE TRANSFORMADOR | Y11: SEGUE SOLICITAÇÃO DE SERVIÇO PARA TROCA DE TRAFO QUEIMADO | Z11: 15 | AA11: 15 | AB11: 15KVA | AC11: 46225.761
A12: ETO-RD-AR 00613/2026 | B12: ENC-MLAR03 000041/2026 | C12: 612600369 | E12: ETO-RD-AR 613/2026_x000D_ TRAFO 5702072004_x000D_ TRAFO RETIRADO_x000D_ POTÊNCIA : 15 KVA_x000D_ TENSÃO : 13.8 KV_x000D_ Nº ENERGISA (CITD) : ILEGIVEL_x000D_ Nº DE SÉRIE : 141321_x000D_ MARCA : ITB_x000D_ DATA FABRICAÇÃO : 07/99_x000D_ IMPEDANCIA : 2,45_x000D_ POS. TAP : 05_x000D_ _x000D_ TRAFO INSTALADO_x000D_ POTÊNCIA : 15 KVA_x000D_ TENSÃO : 13.8 KV_x000D_ Nº ENERGISA (CITD) : 150022_x000D_ Nº DE SÉRIE : 827745_x000D_ MARCA : TRAEL_x000D_ DATA FABRICAÇÃO : 02/2026_x000D_ IMPEDANCIA : 2,5_x000D_ POS. TAP : 05_x000D_ | F12: QUEIMADO | G12: DESCARGA ATMOSFÉRICA | H12: QUEIMADO | I12: DESCARGA ATMOSFÉRICA | J12: MC - SUBSTITUIÇÃO DE TRANSFORMADOR | K12: 2026 | L12: AL04096004 | M12: 5702072004 | N12: 8812 | O12: EMERGENCIAL | P12: SS ATENDIDA | Q12: 46115.853 | R12: 46116.451 | S12: 46118.853 | T12: BLOCO TRANSFORMADOR DE DISTRIBUIÇÃO | U12: ARAGUAINA | V12: SIRDEIS ALVES MONTEIRO | W12: RURAL | X12: FORMS SUBST DE TRANSFORMADOR | Y12: trafo 5702072004 queimado | Z12: 15 | AA12: 15 | AB12: 15 kva | AC12: 46225.761
A13: ETO-RD-AR 00551/2026 | B13: ENC-MLAR01 000152/2026 | C13: 612600337 | E13: ETO-RD-AR 551/2026_x000D_ TRAFO 5700322060_x000D_ TRAFO RETIRADO_x000D_ POTÊNCIA : 15 KVA_x000D_ TENSÃO : 13.8 KV_x000D_ Nº ENERGISA (CITD) : P8322_x000D_ Nº DE SÉRIE : 178008_x000D_ MARCA : ABB_x000D_ DATA FABRICAÇÃO : 02/2001_x000D_ IMPEDANCIA : 2,36_x000D_ POS. TAP : 03_x000D_ _x000D_ TRAFO INSTALADO_x000D_ POTÊNCIA : 15 KVA_x000D_ TENSÃO : 13.8 KV_x000D_ Nº ENERGISA (CITD) : 149855_x000D_ Nº DE SÉRIE : C297819_x000D_ MARCA : ITAM_x000D_ DATA FABRICAÇÃO : 12/2025_x000D_ IMPEDANCIA : 2,61_x000D_ POS. TAP : 05_x000D_ | F13: QUEIMADO | G13: NÃO IDENTIFICADO | H13: QUEIMADO | I13: DESCARGA ATMOSFÉRICA | J13: MC - SUBSTITUIÇÃO DE TRANSFORMADOR | K13: 2026 | L13: AL01054060 | M13: 5700322060 | N13: 8812 | O13: EMERGENCIAL | P13: SS ATENDIDA | Q13: 46105.727 | R13: 46106.507 | S13: 46108.727 | T13: BLOCO TRANSFORMADOR DE DISTRIBUIÇÃO | U13: NOVA OLINDA | V13: Wilmar Lucas Rodrigues Noleto | W13: RURAL | X13: FORMS SUBST DE TRANSFORMADOR | Y13: SEGUE SS DE TRAFO QUEIMADO NA RDR DE NOVA OLINDA, TRAFO DE 15KVA NA REDE DE 7.8KV, PARA RAIO QUEIMADO E ACESSO LIVRE. | Z13: 15 | AA13: 15 | AB13: 15KVA | AC13: 46225.761
... A17: ETO-RD-GU 00042/2026 | B17: ETO-RD-GU 000114/2026 | C17: 412600082 | E17: SS: ETO-RD-GU 42/2026_x000D_ _x000D_ FOI FEITO COM EQUIPE PROPRIA ENERGISA_x000D_ _x000D_ FOI FEITO A SUBTITUIÇÃO DE TRANSFORMADOR DE 15KVA POR 15KVA | F17: QUEIMADO | G17: NÃO IDENTIFICADO | H17: QUEIMADO | I17: SOBRECARGA | J17: MC - SUBSTITUIÇÃO DE TRANSFORMADOR | K17: 2026 | L17: LD01066094 | M17: 5701136094 | N17: 8812 | O17: EMERGENCIAL | P17: SS ATENDIDA | Q17: 46032.857 | R17: 46033.526 | S17: 46035.857 | T17: BLOCO TRANSFORMADOR DE DISTRIBUIÇÃO | U17: PEIXE | V17: Wilmar Lucas Rodrigues Noleto | W17: RURAL | X17: FORMS SUBST DE TRANSFORMADOR | Y17: SEGUE SS DE TRAFO QUEIMADO NA RDR DE SAO VALERIO, TRAFO DE 15KVA NA REDE DE 19KV, ACESSO LIVRE PARA CAMINHONTE, PARA RAIO QUEIMADO. | Z17: 15 | AA17: 15 | AB17: 15KVA | AC17: 46225.761
A18: ETO-RD-AR 00522/2026 | B18: ETO-RD-AR 000767/2026 | C18: 612600331 | E18: TR 5700117063_x000D_ 15KVA_x000D_ QUEIMADO _x000D_ PARA RAIO NOVO _x000D_ ACESSO LIVRE_x000D_ _x000D_ _x000D_ 060OP01 ESTEVE NO LOCAL | F18: QUEIMADO | G18: DESCARGA ATMOSFÉRICA | H18: QUEIMADO | I18: DESCARGA ATMOSFÉRICA | J18: MC - FERRAGENS | K18: 2026 | L18: LD01054060 | M18: 5700117063 | N18: 8812 | O18: EMERGENCIAL | P18: SS ATENDIDA | Q18: 46100.669 | R18: 46101.755 | S18: 46103.669 | T18: BLOCO TRANSFORMADOR DE DISTRIBUIÇÃO | U18: PAU D'ARCO | V18: Felipe Batista Ferrreira | W18: RURAL | X18: FORMS SUBST DE TRANSFORMADOR | Y18: TR 570011706315KVAQUEIMADO PARA RAIO NOVO ACESSO LIVRE060OP01 ESTEVE NO LOCAL | AB18: 15KVA | AC18: 46225.761
A19: ETO-RD-GR 00034/2026 | B19: ENC-MLGR01 000016/2026 | C19: 712600042 | E19: SUBSTITUIÇÃO DE TRAFO 5700026195 ETO-RD-GR 34/2026 AST. P.A RIO VERMELHO RDR DE CENTENARIO _x000D_ _x000D_ TRAFO RETIRADO_x000D_ POTÊNCIA : 15KVA_x000D_ TENSÃO : 34,5KV_x000D_ Nº ENERGISA (CITD) : 127855_x000D_ Nº DE SÉRIE : 573101_x000D_ MARCA : TRAEL_x000D_ DATA FABRICAÇÃO : 04/2021_x000D_ IMPEDANCIA : 3,0_x000D_ POS. TAP : 03_x000D_ _x000D_ TRAFO INSTALADO_x000D_ POTÊNCIA : 15KVA_x000D_ TENSÃO : 34,5KV_x000D_ Nº ENERGISA (CITD) : 149670_x000D_ Nº DE SÉRIE : C290231_x000D_ MARCA : ITAM_x000D_ DATA FABRICAÇÃO : 09/2025_x000D_ IMPEDANCIA : 3,13_x000D_ POS. TAP : 03_x000D_ _x000D_ MEDIÇÃO 1: 21,20_x000D_ MEDIÇÃO 2: 17,45_x000D_ MEDIÇÃO 3: 12,76_x000D_ _x000D_ COORDENADA_x000D_ X: 893367_x000D_ Y: 9000689 | F19: QUEIMADO | G19: DESCARGA ATMOSFÉRICA | H19: QUEIMADO | I19: DESCARGA ATMOSFÉRICA | J19: MC - SUBSTITUIÇÃO DE TRANSFORMADOR | K19: 2026 | L19: LD01065015 | M19: 5700026195 | N19: 8812 | O19: EMERGENCIAL | P19: SS ATENDIDA | Q19: 46028.697 | R19: 46029.87 | S19: 46031.697 | T19: BLOCO TRANSFORMADOR DE DISTRIBUIÇÃO | U19: CENTENARIO | V19: STANLEY APARECIDO DO CARMO | W19: RURAL | X19: FORMS SUBST DE TRANSFORMADOR | Y19: Trafo: 5700026195 Queimado Potencia: 15 KVATensão: 34,5 KVPara raio: queimado Acesso: Camioneta Equipe: 227op01 (63)99247-2838/99928-1276 | Z19: 15 | AA19: 15 | AB19: 15 KVA | AC19: 46225.761
A20: ETO-RD-AG 00184/2026 | B20: ENC-MPAG02 000022/2026 | C20: 662600115 | E20: 5748172045 QUEIMADO _x000D_ POT. 45KVA_x000D_ 34,5KV_x000D_ PARA-RAIO BT E MT RUIM_x000D_ ACESSO BOM_x000D_ RDR SAMPAIO_x000D_ _x000D_ _x000D_ TRAFO Nº _x000D_ _x000D_ TRAFO RETIRADO_x000D_ _x000D_ POTÊNCIA; 45VKA 34,5KV_x000D_ POS. DO TAP; 2º_x000D_ DATA DE FAB; 02/2015 REFORMA; 05/2024_x000D_ MARCA; TRAEL - TRAEL PA_x000D_ Nº CITD; 113354_x000D_ Nº SÉRIE; 460414_x000D_ IMPEDÂNCIA; 3,72_x000D_ _x000D_ TRAFO INSTALADO _x000D_ _x000D_ POTÊNCIA; 45KVA 34,5KV_x000D_ POS. DO TAP; 2º _x000D_ DATA DE FAB; 01/2023 REFORMA 04/2025_x000D_ MARCA; ITAIPU / TRAEL PA_x000D_ Nº CITD; 134715_x000D_ Nº SÉRIE; 487471_x000D_ IMPEDÂNCIA; 4_x000D_ MEDIÇÃO; 5,43 / 5,44 / 5,99_x000D_ _x000D_ | F20: QUEIMADO | G20: DESCARGA ATMOSFÉRICA | H20: QUEIMADO | I20: DESCARGA ATMOSFÉRICA | J20: MC - SUBSTITUIÇÃO DE TRANSFORMADOR | K20: 2026 | L20: LD02014045 | M20: 5748172045 | N20: 8385 | O20: EMERGENCIAL | P20: SS ATENDIDA | Q20: 46066.724 | R20: 46066.949 | S20: 46069.724 | T20: BLOCO TRANSFORMADOR DE DISTRIBUIÇÃO | U20: SAMPAIO | V20: ARTHUR MAGALHAES DAS DORES | W20: RURAL | X20: AVISO DE ANOMALIA | Y20: 5748172045 QUEIMADO POT. 45KVA34,5KVPARA-RAIO BT E MT RUIMACESSO BOMRDR SAMPAIO | Z20: 45 | AA20: 45 | AC20: 46225.761
A21: DOLP-RD-PA 00246/2026 | B21: DLP-MLPA01 000058/2026 | C21: 112600239 | E21: MEDIDO__x000D_ _x000D_ EMERGENCIAL__x000D_ _x000D_ segue nota de trafo queimado, trafo 5712754122, trafo de 15kva, tensao 34500 / 440 V, acesso livre, para-raio danificado_x000D_ _x000D_ _x000D_ DADOS ATENDIMENTO_x000D_ _x000D_ EQUIPE: PALMA04M_x000D_ LIDER: JOSE RAIMUNDO LOPES DE SOUZA _x000D_ CONTATO: 63 9296-9610_x000D_ DOLP-RD-PA 000246/2026_x000D_ DATA ATENDIMENTO: 12/02/2026_x000D_ _x000D_ Atenção!_x000D_ Não intervenha na rede sem autorização do COI (Centro de Operações Integradas) | F21: QUEIMADO | G21: DESCARGA ATMOSFÉRICA | H21: QUEIMADO | I21: DESCARGA ATMOSFÉRICA | J21: MC - SUBSTITUIÇÃO DE TRANSFORMADOR | K21: 2026 | L21: LD02059122 | M21: 5712754122 | N21: 8812 | O21: EMERGENCIAL | P21: SS ATENDIDA | Q21: 46064.804 | R21: 46065.447 | S21: 46067.804 | T21: BLOCO TRANSFORMADOR DE DISTRIBUIÇÃO | U21: PALMAS | V21: MARCO ANTONIO LOURENCO CAMPOS | W21: RURAL | X21: FORMS SUBST DE TRANSFORMADOR | Y21: segue nota de trafo queimado, trafo 5712754122, trafo de 15kva, tensao 34500 / 440 V, acesso livre, para-raio danificado | Z21: 25 | AA21: 15 | AB21: 15kva | AC21: 46225.761
A22: DG-RD-PO 00159/2026 | B22: DG-MLPO01 000034/2026 | C22: 312600124 | E22: medido__x000D_ emergencial__x000D_ _x000D_ _x000D_ Trafo 5700799026 de 15kva e para-raio queimado, Tensão 19,9kv, Acesso para camionete 4x4, Local Rural de Ponte Alta, Faz. IND FAZENDA RESERVA, 0 - LPT -13290 FAZ. RESERVA_x000D_ | F22: QUEIMADO | G22: DESCARGA ATMOSFÉRICA | H22: QUEIMADO | I22: DESCARGA ATMOSFÉRICA | J22: MC - SUBSTITUIÇÃO DE TRANSFORMADOR | K22: 2026 | L22: LD03046026 | M22: 5700799026 | N22: 8812 | O22: EMERGENCIAL | P22: SS ATENDIDA | Q22: 46057.139 | R22: 46058.504 | S22: 46060.139 | T22: BLOCO TRANSFORMADOR DE DISTRIBUIÇÃO | U22: PONTE ALTA DO TOCANTINS | V22: SAMUEL PINTO GOMES | W22: RURAL | X22: FORMS SUBST DE TRANSFORMADOR | Y22: Trafo 5700799026 de 15kva e para-raio queimado, Tensão 19,9kv, Acesso para camionete 4x4, Local Rural de Ponte Alta, Faz. IND FAZENDA RESERVA, 0 - LPT -13290 FAZ. RESERVA | Z22: 15 | AA22: 5 | AB22: 15kva | AC22: 46225.761
A23: ETO-RD-AG 00315/2026 | B23: ETO-RD-AG 000273/2026 | C23: 662600206 | E23: TROCAR TRECHO DE REDE BT NO CIRCUITO DO TRAFO 5700383123._x000D_ _x000D_ ---->NOTA AC_x000D_ SUBST 02 VÃO DE REDE CABO 04AWG CA DE 60MT X02 DE CABO 04AWG CA POR CABO 04AWG CAA ENTRE OS PORTES ID-68454819 AO POSTE ID-68428603._x000D_ _x000D_ SUBST 01 VÃO DE REDE CABO 35mm MONOFASICO MULTIPLEXADO DE 45MT POR CABO 35mm BIFASICO MULTIPLEX ENTRE OS PORTES ID-68455048 AO POSTE ID-68428603._x000D_ _x000D_ _x000D_ INTERCALADO 01 POSTE 10/600 DT SI4 ENTRE OS PORTES ID-68428603 AO POSTE ID*-68455048. | F23: GARANTIA DE TRAFO | G23: VEGETAÇÃO | H23: GARANTIA DE TRAFO | I23: VEGETAÇÃO | J23: MC - CONEXÃO MT | K23: 2026 | L23: LD01084002 | M23: 5700373123 | N23: 8389 | O23: EMERGENCIAL | P23: SS ATENDIDA | Q23: 46101.378 | R23: 46101.583 | S23: 46104.378 | T23: TRANSFORMADOR DE DISTRIBUIÇÃO ENERGISA 19919Kv | U23: AGUIARNOPOLIS | V23: ADRIANO DE SOUSA GOMES | W23: RURAL | X23: SOLICITAÇÃO DE SERVIÇO | Y23: TROCAR TRECHO DE REDE BT NO CIRCUITO DO TRAFO 5700383123.50 METROS DE REDE COMPACTA (DP/10)80 METROS DE REDE CABO NU. (DU/35) | AC23: 46225.761
A24: DG-RD-PO 00189/2026 | B24: DG-MLPO01 000041/2026 | C24: 312600152 | E24: medido__x000D_ emergencial__x000D_ _x000D_ _x000D_ 5701005096 15kva e para queimado 19,9 acessol livre equipé 096op01 992607520_x000D_ | F24: QUEIMADO | G24: DESCARGA ATMOSFÉRICA | H24: QUEIMADO | I24: DESCARGA ATMOSFÉRICA | J24: MC - SUBSTITUIÇÃO DE TRANSFORMADOR | K24: 2026 | L24: LD03046026 | M24: 5701005096 | N24: 8812 | O24: EMERGENCIAL | P24: SS ATENDIDA | Q24: 46067.499 | R24: 46067.799 | S24: 46070.499 | T24: TRANSFORMADOR DE DISTRIBUIÇÃO ENERGISA 19.919Kv | U24: PINDORAMA DO TOCANTINS | V24: CLEONE PEREIRA DE SOUZA LIMA | W24: RURAL | X24: FORMS SUBST DE TRANSFORMADOR | Y24: 5701005096 15kva e para queimado 19,9 acessol livre equipé 096op01 992607520 | Z24: 15 | AA24: 5 | AB24: 15kva | AC24: 46225.761
A25: DG-RD-PO 00198/2026 | B25: DG-MLPO01 000048/2026 | C25: 312600158 | E25: medido__x000D_ emergencial__x000D_ _x000D_ _x000D_ INT: 20264128798303_x000D_ Segue SS de TR 5700905152 15KVA/19.9KV e para-raios queimados._x000D_ Acesso somente para caminhonete_x000D_ UC 10433800_x000D_ FAZENDA BOA VISTA_x000D_ 63992761180_x000D_ ADAILDA RIBEIRO RODRIGUES_x000D_ 152OP01 63 98413-9467_x000D_ | F25: QUEIMADO | G25: DESCARGA ATMOSFÉRICA | H25: QUEIMADO | I25: DESCARGA ATMOSFÉRICA | J25: MC - SUBSTITUIÇÃO DE TRANSFORMADOR | K25: 2026 | L25: LD02072001 | M25: 5700905152 | N25: 8812 | O25: EMERGENCIAL | P25: SS ATENDIDA | Q25: 46069.668 | R25: 46071.743 | S25: 46072.668 | T25: TRANSFORMADOR DE DISTRIBUIÇÃO ENERGISA 19.919Kv | U25: SANTA ROSA DO TOCANTINS | V25: JOSE MARIA ALVES MONTEL | W25: RURAL | X25: FORMS SUBST DE TRANSFORMADOR | Y25: INT: 20264128798303Segue SS de TR 5700905152 15KVA/19.9KV e para-raios queimados.Acesso somente para caminhoneteUC 10433800FAZENDA BOA VISTA63992761180ADAILDA RIBEIRO RODRIGUES152OP01 63 98413-9467 | Z25: 15 | AA25: 5 | AB25: 15 | AC25: 46225.761
A26: ETO-RD-DP 00128/2026 | B26: ETO-MLDP01 000057/2026 | C26: 512600085 | E26: Foi constatado Trafo 5726149027 15kva 19,9kv e para-raios Queimados | F26: QUEIMADO | G26: DESCARGA ATMOSFÉRICA | H26: QUEIMADO | I26: DESCARGA ATMOSFÉRICA | J26: MC - SUBSTITUIÇÃO DE TRANSFORMADOR | K26: 2026 | L26: LD01414027 | M26: 5726149027 | N26: 8812 | O26: EMERGENCIAL | P26: SS ATENDIDA | Q26: 46072.88 | R26: 46074.565 | S26: 46075.88 | T26: BLOCO TRANSFORMADOR DE DISTRIBUIÇÃO | U26: PONTE ALTA DO BOM JESUS | V26: GILMAR VIEIRA DE SOUSA | W26: RURAL | X26: FORMS SUBST DE TRANSFORMADOR | Y26: Foi constatado Trafo 5726149027 15kva 19,9kv e para-raios Queimados | Z26: 15 | AA26: 15 | AB26: 15kva | AC26: 46225.761
A27: ETO-RD-GU 00261/2026 | B27: DBM-MLDB04 000066/2026 | C27: 412600249 | E27: SUBSTITUIÇÃO DE TRANSFORMADOR NA RDR DE GURUPI_x000D_ _x000D_ INT: 20264133735727_x000D_ _x000D_ SS: ETO-RD-GU 261/2026_x000D_ _x000D_ ESPECIFICAÇÕES DO TRANSFORMADOR_x000D_ _x000D_ TRANSFORMADOR INSTALADO: 15KVA_x000D_ _x000D_ TRANSFORMADOR RETIRADO: 15KVA_x000D_ _x000D_ MEDIÇÕES_x000D_ _x000D_ LOGO APÓS A TROCA _x000D_ _x000D_ VAN: 221.3_x000D_ _x000D_ OBS:SUBSTITUIÇÃO DE TRANSFORMADOR AUTORIZADA PELO DIONE._x000D_ _x000D_ | F27: QUEIMADO | G27: DESCARGA ATMOSFÉRICA | H27: QUEIMADO | I27: DESCARGA ATMOSFÉRICA | J27: MC - SUBSTITUIÇÃO DE TRANSFORMADOR | K27: 2026 | L27: LD04040003 | M27: 5362153003 | N27: 8812 | O27: EMERGENCIAL | P27: SS ATENDIDA | Q27: 46076.711 | R27: 46078.446 | S27: 46079.711 | T27: BLOCO TRANSFORMADOR DE DISTRIBUIÇÃO | U27: GURUPI | V27: HELDER SILVA CARVALHO | W27: RURAL | X27: FORMS SUBST DE TRANSFORMADOR | Y27: Transformador queimado 5362153003, potencia 15kva, tensão 19.9, acesso livre a camionete , para raio queimado, causa descarga atmosférica, feito teste a vazio.telefone 63992666663 equipe 003op13 | Z27: 15 | AA27: 15 | AB27: 15 | AC27: 46225.761
A28: ETO-RD-AR 00198/2026 | B28: ENC-MLAR05 000069/2026 | C28: 612600130 | E28: ETO-RD-AR 198/2026_x000D_ TR: 5710365060_x000D_ N° CHAVE: 0310365060_x000D_ _x000D_ TRAFO RETIRADO_x000D_ POTÊNCIA : 15KVA_x000D_ TENSÃO : 13,8KV_x000D_ Nº ENERGISA (CITD) : 116756_x000D_ Nº DE SÉRIE : 473495_x000D_ MARCA : TRAEL_x000D_ DATA FABRICAÇÃO : 06/2018_x000D_ IMPEDANCIA : 2,62_x000D_ POS. TAP : 03_x000D_ _x000D_ TRAFO INSTALADO_x000D_ POTÊNCIA : 15KVA_x000D_ TENSÃO : 13,8KV_x000D_ Nº ENERGISA (CITD) : 148486_x000D_ Nº DE SÉRIE : C289650_x000D_ MARCA : ITAM_x000D_ DATA FABRICAÇÃO : 09/2025_x000D_ IMPEDANCIA : 2,54_x000D_ POS. TAP : 3_x000D_ | F28: QUEIMADO | G28: DESCARGA ATMOSFÉRICA | H28: QUEIMADO | I28: DESCARGA ATMOSFÉRICA | J28: MC - SUBSTITUIÇÃO DE TRANSFORMADOR | K28: 2026 | L28: AL01054060 | M28: 5710365060 | N28: 8812 | O28: EMERGENCIAL | P28: SS ATENDIDA | Q28: 46053.747 | R28: 46054.729 | S28: 46056.747 | T28: BLOCO TRANSFORMADOR DE DISTRIBUIÇÃO | U28: NOVA OLINDA | V28: MAIKOM DOUGLAS DA SILVA | W28: RURAL | X28: FORMS SUBST DE TRANSFORMADOR | Y28: Boa tarde,Favor enviar manutenção para subsituitr trafo queimado 5710365060 | Z28: 15 | AA28: 15 | AB28: 15 | AC28: 46225.761
A29: ETO-RD-GR 00387/2026 | B29: ENC-MLAR03 000028/2026 | C29: 712600276 | E29: TROCA DE TRAFO AVARIADO 5700018155 ETO-RD-GR 387/2026 ZONA RURAL - PALMEIRANTE 0155_x000D_ _x000D_ TRAFO RETIRADO_x000D_ POTÊNCIA : 25KVA_x000D_ TENSÃO : 19.9KV _x000D_ Nº ENERGISA (CITD) : ILEGIVEL_x000D_ Nº DE SÉRIE : 352737_x000D_ MARCA : TRAEL_x000D_ DATA FABRICAÇÃO : 10/2015_x000D_ IMPEDANCIA : 2.84_x000D_ POS. TAP : 03_x000D_ _x000D_ TRAFO INSTALADO_x000D_ POTÊNCIA : 15KVA_x000D_ TENSÃO : 19.9KV _x000D_ Nº ENERGISA (CITD) : 150227_x000D_ Nº DE SÉRIE : 827950_x000D_ MARCA : TRAEL_x000D_ DATA FABRICAÇÃO : 02/2026_x000D_ IMPEDANCIA : 3.0_x000D_ POS. TAP : 03_x000D_ _x000D_ MEDIÇÃO 1: 07.95_x000D_ MEDIÇÃO 2: 06.50_x000D_ MEDIÇÃO 3: 05.83_x000D_ _x000D_ COORDENADA_x000D_ X: 828148_x000D_ Y: 9148054_x000D_ _x000D_ _x000D_ _x000D_ SERVIÇO EM CONJUNTO COM A OS ENC-MLAR03 29/2026. | F29: AVARIADO | G29: VAZAMENTO DE ÓLEO | H29: AVARIADO | I29: VAZAMENTO DE ÓLEO | J29: MC - SUBSTITUIÇÃO DE TRANSFORMADOR | K29: 2026 | L29: LD02105019 | M29: 5700018155 | N29: 8812 | O29: EMERGENCIAL | P29: SS ATENDIDA | Q29: 46108.409 | R29: 46108.708 | S29: 46111.409 | T29: BLOCO TRANSFORMADOR DE DISTRIBUIÇÃO | U29: PALMEIRANTE | V29: VALERIA DE JESUS BORGES CARVAL | W29: RURAL | X29: FORMS SUBST DE TRANSFORMADOR | Y29: trafo 5700018155 com vazamento de óleo - 25KVA - 19,9KV - para raio queimado substituir poste 10/200 estrutura U1/S1 - danificado na base. RDU do Povoado Cicilândia RDR Palmeirante | Z29: 15 | AA29: 25 | AB29: 25KVA | AC29: 46225.761
A30: ETO-RD-GU 00239/2026 | B30: DBM-MPDB08 000051/2026 | C30: 412600226 | E30: SUBSTITUIÇÃO DE TRANSFORMADOR NA RDR DE ARAGUAÇU_x000D_ _x000D_ INT: 20264133090042_x000D_ _x000D_ SS: ETO-RD-GU 239/2026_x000D_ _x000D_ ESPECIFICAÇÕES DO TRANSFORMADOR_x000D_ _x000D_ TRANSFORMADOR INSTALADO: 75 KVA_x000D_ _x000D_ TRANSFORMADOR RETIRADO: 75 KVA_x000D_ _x000D_ MEDIÇÕES_x000D_ _x000D_ LOGO APÓS A TROCA _x000D_ _x000D_ VAN: 223_x000D_ _x000D_ VBN: 223_x000D_ _x000D_ OBS:SUBSTITUIÇÃO DE TRANSFORMADOR AUTORIZADA PELO DIONE._x000D_ | F30: QUEIMADO | G30: DESCARGA ATMOSFÉRICA | H30: QUEIMADO | I30: DESCARGA ATMOSFÉRICA | J30: MC - SUBSTITUIÇÃO DE TRANSFORMADOR | K30: 2026 | L30: LD01003036 | M30: 5764992032 | N30: 8812 | O30: EMERGENCIAL | P30: SS ATENDIDA | Q30: 46073.802 | R30: 46077.255 | S30: 46076.802 | T30: BLOCO TRANSFORMADOR DE DISTRIBUIÇÃO | U30: ARAGUACU | V30: JONATAN ALVES DE SOUZA | W30: RURAL | X30: FORMS SUBST DE TRANSFORMADOR | Y30: SEGUE SOLICITAÇÃO DE SERVIÇO PARA TROCA DE TRAFO QUEIMADO NA RDR DE ARAGUAÇU | Z30: 75 | AA30: 75 | AB30: 75KVA | AC30: 46225.761
A31: ETO-RD-AR 00456/2026 | B31: ETO-RD-AR 000572/2026 | C31: 612600315 | E31: TRAFO 5762725060 QUEIMADO TRIFASICO DE 75 KVA NA REDE 13.8 KV ACESSO BOM FEITO TESTE AVAZIO PARA RAIO BOM REDUE DE NOVA OLINDA | F31: QUEIMADO | G31: DESCARGA ATMOSFÉRICA | H31: QUEIMADO | I31: DESCARGA ATMOSFÉRICA | J31: MC - FERRAGENS | K31: 2026 | L31: AL02054060 | M31: 5762725060 | N31: 8812 | O31: EMERGENCIAL | P31: SS ATENDIDA | Q31: 46092.545 | R31: 46093.641 | S31: 46095.545 | T31: BLOCO TRANSFORMADOR DE DISTRIBUIÇÃO | U31: NOVA OLINDA | V31: PAULO SERGIO CAETANO FREIRE | W31: URBANO | X31: FORMS SUBST DE TRANSFORMADOR | Y31: TRAFO 5762725060 QUEIMADO TRIFASICO DE 75 KVA NA REDE 13.8 KV ACESSO BOM FEITO TESTE AVAZIO PARA RAIO BOM REDUE DE NOVA OLINDA | AB31: 75 KVA | AC31: 46225.761
A32: ETO-RD-GU 00427/2026 | B32: DBM-MLDB05 000083/2026 | C32: 412600351 | E32: SUBSTITUIÇÃO DE TRANSFORMADOR NA RDR DE SANDOLÂNDIA_x000D_ _x000D_ INT: 20264254458485_x000D_ _x000D_ SS: ETO-RD-GU 427/2026_x000D_ _x000D_ ESPECIFICAÇÕES DO TRANSFORMADOR_x000D_ _x000D_ TRANSFORMADOR INSTALADO: 15KVA_x000D_ _x000D_ TRANSFORMADOR RETIRADO: 15KVA_x000D_ _x000D_ MEDIÇÕES_x000D_ _x000D_ LOGO APÓS A TROCA _x000D_ _x000D_ VAN: 224.7_x000D_ _x000D_ OBS:SUBSTITUIÇÃO DE TRANSFORMADOR AUTORIZADA PELO DIONE._x000D_ _x000D_ _x000D_ | F32: QUEIMADO | G32: BUCHA DANIFICADA | H32: QUEIMADO | I32: BUCHA DANIFICADA | J32: MC - SUBSTITUIÇÃO DE TRANSFORMADOR | K32: 2026 | L32: LD01003036 | M32: 5700574107 | N32: 8812 | O32: EMERGENCIAL | P32: SS ATENDIDA | Q32: 46117.676 | R32: 46118.766 | S32: 46120.676 | T32: BLOCO TRANSFORMADOR DE DISTRIBUIÇÃO | U32: SANDOLANDIA | V32: JONATAN ALVES DE SOUZA | W32: RURAL | X32: FORMS SUBST DE TRANSFORMADOR | Y32: SEGUE SOLICITAÇÃO DE SERVIÇO PARA TROCA DE TRAFO QUEIMADO NA RDR DE SANDOLANDIA E COM MUITO VAZAMENTO DE OLEO BUCHA SECUNDARIA ESTOURADA | Z32: 15 | AA32: 15 | AB32: 15KVA | AC32: 46225.761
A33: ETO-RD-AR 00261/2026 | B33: ENC-MLAR05 000107/2026 | C33: 612600165 | E33: SS ETO-RD-AR 261/2026_x000D_ TRAFO 5700041030_x000D_ _x000D_ _x000D_ _x000D_ TRAFO RETIRADO_x000D_ POTÊNCIA : 30KVA_x000D_ TENSÃO : 13.8KV_x000D_ Nº ENERGISA (CITD) : 1337_x000D_ Nº DE SÉRIE : 3398_x000D_ MARCA : PCG_x000D_ DATA FABRICAÇÃO : 1976_x000D_ IMPEDANCIA : 3.45_x000D_ POS. TAP : 02_x000D_ _x000D_ TRAFO INSTALADO'_x000D_ POTÊNCIA : 30KVA_x000D_ TENSÃO : 13.8KV_x000D_ Nº ENERGISA (CITD) : 147756_x000D_ Nº DE SÉRIE : 586793_x000D_ MARCA : ITAIPU_x000D_ DATA FABRICAÇÃO : 07/2025_x000D_ IMPEDANCIA : 3.56_x000D_ POS. TAP : 02_x000D_ | F33: AVARIADO | G33: VAZAMENTO DE ÓLEO | H33: AVARIADO | I33: VAZAMENTO DE ÓLEO | J33: MC - SUBSTITUIÇÃO DE TRANSFORMADOR | K33: 2026 | L33: AL01087030 | M33: 5700041030 | N33: 25962 | O33: EMERGENCIAL | P33: SS ATENDIDA | Q33: 46060.44 | R33: 46061.681 | S33: 46063.44 | T33: BLOCO TRANSFORMADOR DE DISTRIBUIÇÃO | U33: XAMBIOA | V33: EZEQUIEL CAVALCANTE DOS SANTOS | W33: URBANO | X33: FORMS SUBST DE TRANSFORMADOR | Y33: Substitui trafo 5700041030 potencia 30kva tensão 13,8kv vazamento de óleo acesso livre. Equipe solicitou para reposicionar na chave do trafo para facilitar a abertura da mesma. | Z33: 30 | AA33: 30 | AB33: 30 | AC33: 46225.761
A34: ETO-RD-AR 00267/2026 | B34: ENC-MLAR01 000076/2026 | C34: 612600168 | E34: SS ETO-RD-AR 267/2026_x000D_ TRAFO: 5700416016_x000D_ _x000D_ _x000D_ _x000D_ TRAFO RETIRADO_x000D_ POTÊNCIA : 5KVA_x000D_ TENSÃO : 34.5KV_x000D_ Nº ENERGISA (CITD) : ILEGIVEL_x000D_ Nº DE SÉRIE : 480845_x000D_ MARCA : ITB_x000D_ DATA FABRICAÇÃO : AGO/2007_x000D_ IMPEDANCIA : 2.78_x000D_ POS. TAP : 02_x000D_ _x000D_ TRAFO INSTALADO'_x000D_ POTÊNCIA : 15KVA_x000D_ TENSÃO : 34.5KV_x000D_ Nº ENERGISA (CITD) : 149188_x000D_ Nº DE SÉRIE : 820174_x000D_ MARCA : TRAEL_x000D_ DATA FABRICAÇÃO : 11/2025_x000D_ IMPEDANCIA : 3.0_x000D_ POS. TAP : 03_x000D_ | F34: QUEIMADO | G34: NÃO IDENTIFICADO | H34: QUEIMADO | I34: DESCARGA ATMOSFÉRICA | J34: MC - SUBSTITUIÇÃO DE TRANSFORMADOR | K34: 2026 | L34: LD02010004 | M34: 5700416016 | N34: 8812 | O34: EMERGENCIAL | P34: SS ATENDIDA | Q34: 46061.405 | R34: 46062.712 | S34: 46064.405 | T34: BLOCO TRANSFORMADOR DE DISTRIBUIÇÃO | U34: WANDERLANDIA | V34: LEANDRO BISPO DE BARROS | W34: RURAL | X34: FORMS SUBST DE TRANSFORMADOR | Y34: trafo 5700416016 queimado pararaios danificados acesso livre | Z34: 15 | AA34: 5 | AB34: 5kva | AC34: 46225.761
A35: ETO-RD-AG 00361/2026 | B35: ETO-RD-AG 000319/2026 | C35: 662600216 | E35: PLANO DE MEDIDA - Realizar substituição do trafo 5700133123 de 10 kVA para 15 kVA | F35: SOBRECARGA PREVENTIVA | G35: SOBRECARGA | H35: SOBRECARGA PREVENTIVA | I35: SOBRECARGA | J35: MC - SUBSTITUIÇÃO DE TRANSFORMADOR | K35: 2026 | L35: LD01084002 | M35: 5700133123 | N35: 25983 | O35: EMERGENCIAL | P35: SS ATENDIDA | Q35: 46113.664 | R35: 46114.032 | S35: 46116.664 | T35: BLOCO TRANSFORMADOR DE DISTRIBUIÇÃO | U35: AGUIARNOPOLIS | V35: ADRIANO DE SOUSA GOMES | W35: RURAL | X35: AVISO DE ANOMALIA | Y35: TR 5700133123 QueimadoPotencia: 10 Kva tensão 34,5 kva, acesso para acaminhão | AB35: 10 kva | AC35: 46225.761
A36: ETO-RD-GU 00626/2026 | B36: DBM-MLDB05 000100/2026 | C36: 412600501 | E36: SEGUE SOLICITAÇÃO DE SERVIÇO PARA TROCA DE TRAFO QUEIMADO A RDR DE PARANÃ_x000D_ _x000D_ _x000D_ SUBSTITUIÇÃO DE TRANSFORMADOR NA RDR DE PARANÃ_x000D_ _x000D_ INT: 20264514579985_x000D_ _x000D_ SS: ETO-RD-GU 626/2026_x000D_ _x000D_ ESPECIFICAÇÕES DO TRANSFORMADOR_x000D_ _x000D_ TRANSFORMADOR INSTALADO: 15 KVA_x000D_ _x000D_ TRANSFORMADOR RETIRADO: 15 KVA_x000D_ _x000D_ MEDIÇÕES_x000D_ _x000D_ LOGO APÓS A TROCA _x000D_ _x000D_ VAN: 209_x000D_ _x000D_ _x000D_ OBS:SUBSTITUIÇÃO DE TRANSFORMADOR AUTORIZADA PELO DIONE._x000D_ | F36: QUEIMADO | G36: NÃO IDENTIFICADO | H36: QUEIMADO | I36: NÃO IDENTIFICADO | J36: MC - SUBSTITUIÇÃO DE TRANSFORMADOR | K36: 2026 | L36: LD01010021 | M36: 5743917021 | N36: 8812 | O36: EMERGENCIAL | P36: SS ATENDIDA | Q36: 46187.669 | R36: 46188.5 | S36: 46190.669 | T36: BLOCO TRANSFORMADOR DE DISTRIBUIÇÃO | U36: PARANA | V36: JONATAN ALVES DE SOUZA | W36: RURAL | X36: FORMS SUBST DE TRANSFORMADOR | Y36: SEGUE SOLICITAÇÃO DE SERVIÇO PARA TROCA DE TRAFO QUEIMADO A RDR DE PARANÃ | Z36: 15 | AA36: 15 | AB36: 15KVA | AC36: 46225.761
A37: DOLP-RD-PA 00303/2026 | B37: DLP-MPPA01 000076/2026 | C37: 112600434 | E37: MEDIDO__x000D_ trafo 5722285006 vazaMENTO DE Óleo _x000D_ acesso livre _x000D_ potencia 30 kva _x000D_ tensão 34,5 _x000D_ para-raio queimado _x000D_ _x000D_ obs: leva porta fusivel para fecha o trafo_x000D_ _x000D_ _x000D_ _x000D_ DADOS ATENDIMENTO_x000D_ EQUIPE DOLP-MPPA01_x000D_ ENCARREGADO - IBANEZ RODRIGUES_x000D_ _x000D_ SS DOLP-RD-PA 303/2026_x000D_ _x000D_ _x000D_ DATA ATENDIMENTO_x000D_ 03/03/2026_x000D_ _x000D_ _x000D_ _x000D_ CUMPRIR COM TODOS OS PROCEDIMENTOS DE SEGURANÇA_x000D_ _x000D_ _x000D_ _x000D_ *********** Parecer do COCM - ordem de serviço baixada sistemicamente, empreiteira estará fazendo as baixa de material e lançamento de mão de obra. | F37: QUEIMADO | G37: VAZAMENTO DE ÓLEO | H37: QUEIMADO | I37: VAZAMENTO DE ÓLEO | J37: MC - SUBSTITUIÇÃO DE TRANSFORMADOR | K37: 2026 | L37: LD03059122 | M37: 5722285006 | N37: 25962 | O37: EMERGENCIAL | P37: SS ATENDIDA | Q37: 46081.337 | R37: 46104.375 | S37: 46084.337 | T37: BLOCO TRANSFORMADOR DE DISTRIBUIÇÃO | U37: TOCANTINIA | V37: JORGE BOAZ FERREIRA SOUSA DA S | W37: RURAL | X37: FORMS SUBST DE TRANSFORMADOR | Y37: trafo 5722285006 vazaMENTO DE Óleo acesso livre potencia 30 kva tensão 34,5 para-raio queimado obs: leva porta fusivel para fecha o trafo | Z37: 30 | AA37: 30 | AB37: 30 KVA | AC37: 46225.761
A38: DOLP-RD-PA 00685/2026 | B38: DLP-MLPA03 000101/2026 | C38: 112600629 | E38: MEDIDO__x000D_ _x000D_ EMERGENCIAL__x000D_ _x000D_ ATIVO: 190.02545117_x000D_ LOCALIZAÇÃO: 190-13651952_x000D_ _x000D_ segue ss de 01 trafo 15 kva e 01 para raio da rede de 34.500kv queimado para ser subistituido pela equipe de manutencão acesso só caminhonete cliente penalizado 1 equipe que atendeu 151op01 cel, 63992044413/992447381 favor agilizar o atendimento chave de referencia. 5700318196_x000D_ _x000D_ DADOS ATENDIMENTO_x000D_ _x000D_ N° DOCUMENTO SS: DOLP-RD-PA 000685/2026_x000D_ N° DOCUMENTO OS: DLP-MLPA03 000000/2026_x000D_ _x000D_ TIPO DA INTERVENÇÃO: MANUTENÇÃO_x000D_ TIPO DO SERVIÇO: SUBSTITUIÇÃO DE TRANSFORMADOR E MELHORIA DE MALHA DE ATERRAMENTO_x000D_ DATA PROGRAMADA DA ATIVIDADE: 25/05/2026 A 30/05/2026_x000D_ HORARIO PREVISTO DA ATIVIDADE: 08:00 ÀS 18:00_x000D_ CIDADE: LAGOA DO TOCANTINS - ALIMENTADOR: LD02059122 - TRANSFORMADOR: 5700318196_x000D_ _x000D_ _x000D_ _x000D_ EQUIPE: DOLP-MLPA05_x000D_ CONTATO DA EQUIPE: 63 9296-7129_x000D_ COMPOSIÇÃO DA EQUIPE:_x000D_ 1 - EDUARDO DA SILVA SANTOS_x000D_ 2 - JOÃO CLAUDIO SACRAMENTO_x000D_ _x000D_ _x000D_ _x000D_ SUPERVISOR: PAULO VÍTOR LEMES GOMES CONTATO: 63 9 9296-6939_x000D_ FISCAL RESPONSAVEL: JOELSON SILVA DE SOUZA_x000D_ _x000D_ Atenção!_x000D_ _x000D_ A segurança é o nosso "Peso 10" e nenhuma urgência operacional justifica a exposição ao risco!_x000D_ _x000D_ * Utilize os equipamentos de proteção de acordo com a classe de tensão da rede._x000D_ * Reforçamos a obrigatoriedade sempre que for realizar manobra de ré, ou manobras que envolvam potenciais riscos existentes o apoio em terra de um dos parceiros da equipe._x000D_ * A velocidade deve ser compatível com a via e as condições climáticas no momento da direção._x000D_ * Toda intervenção deve seguir protocolos de segurança, não intervenha sem autorização do COI (Centro de Operações Integrado)._x000D_ _x000D_ _x000D_ Atenção Redobrada no Final do Turno!_x000D_ _x000D_ * Descanso é Regra: Os horários de refeição e descanso devem ser respeitados integralmente. Eles são o que garante a sua energia para a continuidade do trabalho._x000D_ * Saúde e Bem-estar: Mantenha a hidratação e use o protetor solar. O desgaste físico interfere diretamente na sua tomada de decisão._x000D_ * Manobras de Risco: Nunca realize manobras críticas ou de ré sem o apoio em solo de um parceiro. O olhar externo é sua maior proteção._x000D_ * Condições Climáticas: Em caso de chuvas fortes que diminuam a visibilidade, reduza a velocidade imediatamente. Se necessário, pare o veículo em local seguro até que as condições melhorem._x000D_ * Comunicação Aberta: Sinalize à supervisão qualquer condição anormal, inclusive questões de relacionamento com o parceiro. Unidade na equipe é segurança na rede._x000D_ * Que todos tenham um excelente e seguro retorno. Missão cumprida é missão com Zero Acidentes!_x000D_ _x000D_ Nós somos o que fazemos e fazemos o que acreditamos! | F38: QUEIMADO | G38: NÃO IDENTIFICADO | H38: QUEIMADO | I38: NÃO IDENTIFICADO | J38: MC - SUBSTITUIÇÃO DE TRANSFORMADOR | K38: 2026 | L38: LD02059122 | M38: 5700318196 | N38: 8812 | O38: EMERGENCIAL | P38: SS ATENDIDA | Q38: 46190.644 | R38: 46191.75 | S38: 46193.644 | T38: BLOCO TRANSFORMADOR DE DISTRIBUIÇÃO | U38: LAGOA DO TOCANTINS | V38: JOAO PAULO VASCONCELOS MARINHO | W38: RURAL | X38: FORMS SUBST DE TRANSFORMADOR | Y38: segue ss de 01 trafo 15 kva e 01 para raio da rede de 34.500kv queimado para ser subistituido pela equipe de manutencão acesso só caminhonete cliente penalizado 1 equipe que atendeu 151op01 cel, 63992044413/992447381 favor agilizar o atendimento chave de referencia. 5700318196 | Z38: 15 | AA38: 15 | AB38: 15 kvar rede de 34,500kv | AC38: 46225.761
A39: ETO-RD-GR 00720/2026 | B39: ENC-MPGR01 000147/2026 | C39: 712600460 | E39: INSTALAÇÃO DE POSTO DE TRANSFORMAÇÃO EM NOVA DIVISÃO DE CIRCUITO ETO-RD-GR 720/2026 ZONA URBANA - TUPIRATINS 0066_x000D_ _x000D_ TRAFO INSTALADO_x000D_ POTÊNCIA : 25KVA_x000D_ TENSÃO : 19.9KV _x000D_ Nº ENERGISA (CITD) : 151765_x000D_ Nº DE SÉRIE : Z 308332_x000D_ MARCA : ITAM_x000D_ DATA FABRICAÇÃO : 04/2026_x000D_ IMPEDANCIA : 2.78_x000D_ POS. TAP : 03_x000D_ _x000D_ MEDIÇÃO 1: 13.74_x000D_ MEDIÇÃO 2: 09.97_x000D_ MEDIÇÃO 3: 05.93_x000D_ _x000D_ COORDENADA_x000D_ X: 816827_x000D_ Y: 9072112_x000D_ | H39: SOBRECARGA PREVENTIVA | I39: SOBRECARGA | J39: MC - SUBSTITUIÇÃO DE TRANSFORMADOR | K39: 2026 | L39: LD03038009 | M39: 5720015066 | N39: 8389 | O39: EMERGENCIAL | P39: SS ATENDIDA | Q39: 46217.472 | R39: 46217.729 | S39: 46220.472 | T39: BLOCO TRANSFORMADOR DE DISTRIBUIÇÃO | U39: TUPIRATINS | V39: LEONARDO SANTOS DA SILVA | W39: RURAL | X39: AVISO DE ANOMALIA | Y39: Divisão de circuito emergencial do trafo 5720015066 | Z39: 25 | AA39: 5 | AC39: 46225.761
A40: ETO-RD-AG 00485/2026 | B40: ENC-MLAG01 000119/2026 | C40: 662600296 | E40: OS PARA SUBSTITUICAO DE TRAFO QUEIMADO_x000D_ _x000D_ _x000D_ TRAFO Nº 5700597119_x000D_ _x000D_ TRANSFORMAR RETIRADO_x000D_ _x000D_ POTÊNCIA; 05KVA 34,5KV_x000D_ DATA DE FAB; AGOSTO/2010_x000D_ MARCA; ITB_x000D_ Nº CITD; 40034_x000D_ Nº SÉRIE; 691095_x000D_ POS. DO TAP; 3º_x000D_ IMPEDÂNCIA; 3,15_x000D_ _x000D_ TRAFO INSTALADO _x000D_ _x000D_ _x000D_ POTÊNCIA; 15KVA 34,5KV_x000D_ DATA DE FAB; FEV/2026_x000D_ MARCA; TRAEL_x000D_ Nº CITD; 150329_x000D_ Nº SÉRIE; 828052_x000D_ POS. DO TAP; 3º_x000D_ IMPEDÂNCIA; 3,0_x000D_ MEDIÇÃO; 13,41 / 13,21 / 13,17 | F40: QUEIMADO | G40: DESCARGA ATMOSFÉRICA | H40: QUEIMADO | I40: DESCARGA ATMOSFÉRICA | J40: MC - SUBSTITUIÇÃO DE TRANSFORMADOR | K40: 2026 | L40: LD03005098 | M40: 5700597119 | N40: 8812 | O40: EMERGENCIAL | P40: SS ATENDIDA | Q40: 46149.569 | R40: 46151.404 | S40: 46152.569 | T40: BLOCO TRANSFORMADOR DE DISTRIBUIÇÃO | U40: SAO BENTO DO TOCANTINS | V40: GUILHERME BORGES DE OLIVEIRA | W40: RURAL | X40: FORMS SUBST DE TRANSFORMADOR | Y40: TRAFO 5700597119 15KVA 34.5KV E PARA RAIO QUEIMADOACESSO CAMINHONETELEVAR CARRINHO DE MÃO PARA CARREGAR TRAFO ATE O POSTE. | Z40: 15 | AA40: 5 | AB40: 15KVA | AC40: 46225.761
A41: ENC-RD-PS 00491/2026 | B41: ENC-LMPS03 000079/2026 | C41: 212600455 | E41: SS ENC-RD-PS 491/2026_x000D_ trafo 5700428086 _x000D_ _x000D_ _x000D_ TRAFO RETIRADO_x000D_ POTÊNCIA : 5KVA_x000D_ TENSÃO : 34.5KV_x000D_ Nº ENERGISA (CITD) : ILEGIVEL_x000D_ Nº DE SÉRIE : 128045_x000D_ MARCA : VIJAI_x000D_ DATA FABRICAÇÃO : 10/2008_x000D_ IMPEDANCIA : 3.08_x000D_ POS. TAP : 03_x000D_ _x000D_ TRAFO INSTALADO'_x000D_ POTÊNCIA : 25KVA_x000D_ TENSÃO : 34.5KV_x000D_ Nº ENERGISA (CITD) : 150443_x000D_ Nº DE SÉRIE : 828166_x000D_ MARCA : TRAEL_x000D_ DATA FABRICAÇÃO : 02/2026_x000D_ IMPEDANCIA : 3.0_x000D_ POS. TAP : 03_x000D_ _x000D_ | F41: QUEIMADO | G41: DESCARGA ATMOSFÉRICA | H41: QUEIMADO | I41: DESCARGA ATMOSFÉRICA | J41: MC - SUBSTITUIÇÃO DE TRANSFORMADOR | K41: 2026 | L41: LD03414149 | M41: 5700428086 | N41: 8812 | O41: EMERGENCIAL | P41: SS ATENDIDA | Q41: 46143.475 | R41: 46143.838 | S41: 46146.475 | T41: BLOCO TRANSFORMADOR DE DISTRIBUIÇÃO | U41: MARIANOPOLIS DO TOCANTINS | V41: THIAGO BORGES DE OLIVEIRA | W41: RURAL | X41: FORMS SUBST DE TRANSFORMADOR | Y41: Segue ss para tratativa com equipe de manutençao o quanto antessubstituir trafo 5700428086 queimado na rdr de marianopolis | Z41: 25 | AA41: 5 | AB41: 15 | AC41: 46225.761
A42: ETO-RD-GR 00718/2026 | B42: ENC-MLGR01 000162/2026 | C42: 712600466 | E42: TROCA DE TRAFO QUEIMADO 5700417087 ETO-RD-GR 718/2026 ZONA RURAL - GOIANORTE 0087_x000D_ _x000D_ TRAFO RETIRADO_x000D_ POTÊNCIA : 05KVA_x000D_ TENSÃO : 19.9KV _x000D_ Nº ENERGISA (CITD) : ILEGIVEL_x000D_ Nº DE SÉRIE : 172224_x000D_ MARCA : VIJAI_x000D_ DATA FABRICAÇÃO : 08/2010_x000D_ IMPEDANCIA : 3.14_x000D_ POS. TAP : 01_x000D_ _x000D_ TRAFO INSTALADO_x000D_ POTÊNCIA : 15KVA_x000D_ TENSÃO : 19.9KV _x000D_ Nº ENERGISA (CITD) : 149509_x000D_ Nº DE SÉRIE : 822944_x000D_ MARCA : TRAEL_x000D_ DATA FABRICAÇÃO : 03/2026_x000D_ IMPEDANCIA : 3.0_x000D_ POS. TAP : 03_x000D_ _x000D_ MEDIÇÃO 1: 00.39_x000D_ MEDIÇÃO 2: 00.20_x000D_ MEDIÇÃO 3: 00.14_x000D_ _x000D_ COORDENADA_x000D_ X: 733055_x000D_ Y: 9015992_x000D_ | F42: QUEIMADO | G42: SOBRECARGA | H42: QUEIMADO | I42: SOBRECARGA | J42: MC - SUBSTITUIÇÃO DE TRANSFORMADOR | K42: 2026 | L42: LD02022033 | M42: 5700417087 | N42: 8812 | O42: EMERGENCIAL | P42: SS ATENDIDA | Q42: 46217.39 | R42: 46217.833 | S42: 46220.39 | T42: BLOCO TRANSFORMADOR DE DISTRIBUIÇÃO | U42: BABACULANDIA | V42: CLEIBER DA SILVA | W42: RURAL | X42: FORMS SUBST DE TRANSFORMADOR | Y42: trafo 5700417087 e para raio queimado acesso livre | Z42: 15 | AA42: 5 | AB42: 15 | AC42: 46225.761
A43: ETO-RD-AR 00872/2026 | B43: ENC-MLAR01 000202/2026 | C43: 612600532 | E43: ETO-RD-AR 872/2026_x000D_ TRAFO 5710241016_x000D_ TRAFO RETIRADO_x000D_ POTÊNCIA : 10 KVA_x000D_ TENSÃO : 34.5 KV_x000D_ Nº ENERGISA (CITD) : ILEGIVEL_x000D_ Nº DE SÉRIE : 66567_x000D_ MARCA : TRAEL_x000D_ DATA FABRICAÇÃO : 10/2005_x000D_ IMPEDANCIA : 3,01_x000D_ POS. TAP : 03_x000D_ _x000D_ TRAFO INSTALADO_x000D_ POTÊNCIA : 15 KVA_x000D_ TENSÃO : 34.5 KV_x000D_ Nº ENERGISA (CITD) : 149646_x000D_ Nº DE SÉRIE : 469632_x000D_ MARCA : TRAEL_x000D_ DATA FABRICAÇÃO : 05/2018_x000D_ IMPEDANCIA : 2,89_x000D_ POS. TAP : 05_x000D_ | F43: QUEIMADO | G43: DESCARGA ATMOSFÉRICA | H43: QUEIMADO | I43: DESCARGA ATMOSFÉRICA | J43: MC - SUBSTITUIÇÃO DE TRANSFORMADOR | K43: 2026 | L43: LD01095030 | M43: 5710241016 | N43: 8812 | O43: EMERGENCIAL | P43: SS ATENDIDA | Q43: 46159.747 | R43: 46160.677 | S43: 46162.747 | T43: BLOCO TRANSFORMADOR DE DISTRIBUIÇÃO | U43: WANDERLANDIA | V43: STANLEY APARECIDO DO CARMO | W43: RURAL | X43: FORMS SUBST DE TRANSFORMADOR | Y43: Trafo 5710241016 Queimado Potencia: 10 KVATensão: 34,5 KVPara raio: Queimado Acesso: livreEquipe: 004op26 (63)99214-9597 | Z43: 15 | AA43: 10 | AB43: 10 KVA | AC43: 46225.761
A44: ETO-RD-AR 01038/2026 | B44: ENC-MLAR02 000133/2026 | C44: 612600650 | E44: ETO-RD-AR 1038/2026_x000D_ TRAFO 5710631004_x000D_ TRAFO RETIRADO_x000D_ POTÊNCIA : 15 KVA_x000D_ TENSÃO : 34.5 KV_x000D_ Nº ENERGISA (CITD) : 06123309_x000D_ Nº DE SÉRIE : 533099_x000D_ MARCA : TRAEL_x000D_ DATA FABRICAÇÃO : 03/2020_x000D_ IMPEDANCIA : 3,0_x000D_ POS. TAP : 05_x000D_ _x000D_ TRAFO INSTALADO_x000D_ POTÊNCIA : 15 KVA_x000D_ TENSÃO : 34.5 KVA_x000D_ Nº ENERGISA (CITD) : 150910_x000D_ Nº DE SÉRIE : C 303290_x000D_ MARCA : ITAM_x000D_ DATA FABRICAÇÃO : 02/2026_x000D_ IMPEDANCIA : 2,99_x000D_ POS. TAP : 05_x000D_ | F44: QUEIMADO | G44: NÃO IDENTIFICADO | H44: QUEIMADO | I44: SOBRECARGA | J44: MC - SUBSTITUIÇÃO DE TRANSFORMADOR | K44: 2026 | L44: LD05010004 | M44: 5710631004 | N44: 8812 | O44: EMERGENCIAL | P44: SS ATENDIDA | Q44: 46200.819 | R44: 46201.479 | S44: 46203.819 | T44: TRANSFORMADOR DE DISTRIBUIÇÃO ENERGISA 19919Kv | U44: ARAGUAINA | V44: ERLAN PEREIRA DE SOUSA | W44: RURAL | X44: FORMS SUBST DE TRANSFORMADOR | Y44: Trafo 5710631004 queimado 15kvaTensão: 34,5Acesso: Somente para caminhoneteEquipe: 004op22 | Z44: 15 | AA44: 15 | AB44: 15kva | AC44: 46225.761
A45: ETO-RD-GR 00517/2026 | B45: ENC-MLGR03 000191/2026 | C45: 712600354 | E45: TROCA DE TRAFO QUEIMADO 5710317009 ETO-RD-GR 517/2026 ZONA RURAL - GUARAI 0009_x000D_ _x000D_ TRAFO RETIRADO_x000D_ POTÊNCIA : 10KVA_x000D_ TENSÃO : 19.9KV _x000D_ Nº ENERGISA (CITD) : ILEGIVEL_x000D_ Nº DE SÉRIE : 359275_x000D_ MARCA : ITB_x000D_ DATA FABRICAÇÃO : 10/2005_x000D_ IMPEDANCIA : 2.88_x000D_ POS. TAP : 02_x000D_ _x000D_ TRAFO INSTALADO_x000D_ POTÊNCIA : 25KVA_x000D_ TENSÃO : 19.9KV _x000D_ Nº ENERGISA (CITD) : 148984_x000D_ Nº DE SÉRIE : 477447_x000D_ MARCA : ITAIPU - TRAEL_x000D_ DATA FABRICAÇÃO : 10/2022 - 02/2026_x000D_ IMPEDANCIA : 2.94_x000D_ POS. TAP : 03_x000D_ _x000D_ MEDIÇÃO 1: 19.73_x000D_ MEDIÇÃO 2: 18.08_x000D_ MEDIÇÃO 3: 17.78_x000D_ _x000D_ COORDENADA_x000D_ X: 777635_x000D_ Y: 9028021_x000D_ | F45: QUEIMADO | G45: NÃO IDENTIFICADO | H45: QUEIMADO | I45: NÃO IDENTIFICADO | J45: MC - SUBSTITUIÇÃO DE TRANSFORMADOR | K45: 2026 | L45: LD04038009 | M45: 5710317009 | N45: 8812 | O45: EMERGENCIAL | P45: SS ATENDIDA | Q45: 46151.728 | R45: 46152.485 | S45: 46154.728 | T45: BLOCO TRANSFORMADOR DE DISTRIBUIÇÃO | U45: GUARAI | V45: EVA RAIANE CASTELO BONFIM DA S | W45: RURAL | X45: FORMS SUBST DE TRANSFORMADOR | Y45: trafo queimado 10kva 19,9kv acesso caminhonete | Z45: 25 | AA45: 10 | AB45: 10kva | AC45: 46225.761
A46: ENC-RD-PS 00515/2026 | B46: ENC-LMPS01 000125/2026 | C46: 212600483 | E46: SS ENC-RD-PS 515/2026_x000D_ TR 5701548013 _x000D_ _x000D_ _x000D_ _x000D_ _x000D_ _x000D_ TRAFO RETIRADO_x000D_ POTÊNCIA : 30KVA_x000D_ TENSÃO : 34.5KV_x000D_ Nº ENERGISA (CITD) : 135269_x000D_ Nº DE SÉRIE : 566652014_x000D_ MARCA : SIEMENS_x000D_ DATA FABRICAÇÃO : 07/1999_x000D_ IMPEDANCIA : 4.00_x000D_ POS. TAP : 02_x000D_ _x000D_ TRAFO INSTALADO'_x000D_ POTÊNCIA : 30KVA_x000D_ TENSÃO : 34.5KV_x000D_ Nº ENERGISA (CITD) : 147707_x000D_ Nº DE SÉRIE : 586744_x000D_ MARCA : ITAIPU_x000D_ DATA FABRICAÇÃO : 07/2025_x000D_ IMPEDANCIA : 4.09_x000D_ POS. TAP : 02_x000D_ | F46: QUEIMADO | G46: NÃO IDENTIFICADO | H46: QUEIMADO | I46: NÃO IDENTIFICADO | J46: MC - SUBSTITUIÇÃO DE TRANSFORMADOR | K46: 2026 | L46: LD04062013 | M46: 5701548013 | N46: 8812 | O46: EMERGENCIAL | P46: SS ATENDIDA | Q46: 46158.729 | R46: 46159.656 | S46: 46161.729 | T46: BLOCO TRANSFORMADOR DE DISTRIBUIÇÃO | U46: PARAISO DO TOCANTINS | V46: JOSE MARIA ALVES MONTEL | W46: RURAL | X46: FORMS SUBST DE TRANSFORMADOR | Y46: INT: 20264403139176TR 5701548013 30KVA/34.5KV queimado, carcaça estourada.Acesso livre.Obs: Verificar possibilidade de instalar um de 45KVAUC 7634617LOTEAMENTO PARAISO, 0 - LOTE : 49- CHA. RAIO DE LUA63992390521PARAISO PET NUTRICAO ANIMAL LTDA ME013OP03 63 99242-2464 | Z46: 30 | AA46: 30 | AB46: 30 | AC46: 46225.761
A47: ETO-RD-GU 00464/2026 | B47: ETO-RD-GU 001200/2026 | C47: 412600402 | E47: SEGUE SOLICITAÇÃO PARA TROCA DE TRAFO QUEIMADO NA RDR DE SÃO SALVADOR_x000D_ | F47: QUEIMADO | G47: DESCARGA ATMOSFÉRICA | H47: QUEIMADO | I47: DESCARGA ATMOSFÉRICA | J47: MC - SUBSTITUIÇÃO DE TRANSFORMADOR | K47: 2026 | L47: LD02066094 | M47: 5700601200 | N47: 8385 | O47: EMERGENCIAL | P47: SS ATENDIDA | Q47: 46131.533 | R47: 46132.458 | S47: 46134.533 | T47: BLOCO TRANSFORMADOR DE DISTRIBUIÇÃO | U47: SAO SALVADOR DO TOCANTINS | V47: JONATAN ALVES DE SOUZA | W47: RURAL | X47: FORMS SUBST DE TRANSFORMADOR | Y47: SEGUE SOLICITAÇÃO PARA TROCA DE TRAFO QUEIMADO NA RDR DE SÃO SALVADOR | Z47: 15 | AA47: 15 | AB47: 5KVA | AC47: 46225.761
A48: ETO-RD-AG 00569/2026 | B48: ETO-RD-AG 000480/2026 | C48: 662600346 | E48: PLANO DE MEDIDA - REMANEJAR TRAFO DE 5KVA-34.KV POR TRAFO DE 15KVA-34.5KV - DIRECIONAR PARA O PROJETO 25983. | F48: SOBRECARGA PREVENTIVA | G48: NÃO IDENTIFICADO | H48: QUEIMADO | I48: SOBRECARGA | J48: MC - SUBSTITUIÇÃO DE TRANSFORMADOR | K48: 2026 | L48: LD03014045 | M48: 5700041132 | N48: 25983 | O48: EMERGENCIAL | P48: SS ATENDIDA | Q48: 46175.804 | R48: 46176.689 | S48: 46178.804 | T48: BLOCO TRANSFORMADOR DE DISTRIBUIÇÃO | U48: SAMPAIO | V48: DIONES COSTA SILVA | W48: RURAL | X48: AVISO DE ANOMALIA | Y48: SEGUE SS PARA SUBSTITUIR TRAFO 5700041132 QUEIMADO NA RDR DE SAMPAIO Instal.Transformadora [5700041132] Potência Nominal 5 kVATensão Nominal 34500 / 440 VEndereço IND CHACARA DEUS E GRANDE, 0Ponto Referência 63999745190 Ocorrência Técnica: - Energia vizinho: NAO - Dijuntor ligado: NAO - Risco acidente: NAO - - Gerado via URA - Tel: 63999745190 | AB48: 5 kVA_x000D_ | AC48: 46225.761
A49: ETO-RD-DP 00059/2026 | B49: ETO-MLDP01 000029/2026 | C49: 512600047 | E49: SUBSTITUIÇÃO DE TRANSFORMADOR NA RDR_x000D_ _x000D_ _x000D_ POSTO TRANFORMADOR:5720590072_x000D_ _x000D_ _x000D_ SS: 59/2026_x000D_ _x000D_ POT. TRANSFORMADOR RETIRADO: 15 KVA_x000D_ _x000D_ _x000D_ _x000D_ _x000D_ POT. TRANSFORMADOR INSTALADO: 15 KVA | F49: QUEIMADO | G49: BUCHA DANIFICADA | H49: QUEIMADO | J49: MC - SUBSTITUIÇÃO DE TRANSFORMADOR | K49: 2026 | L49: LD01010021 | M49: 5720590072 | N49: 8812 | O49: EMERGENCIAL | P49: SS ATENDIDA | Q49: 46041.638 | R49: 46042.657 | S49: 46044.638 | T49: BLOCO TRANSFORMADOR DE DISTRIBUIÇÃO | U49: CONCEICAO DO TOCANTINS | V49: IZAIAS SANTOS BRAGA JUNIOR | W49: RURAL | X49: FORMS SUBST DE TRANSFORMADOR | Y49: Conforme informações da equipe 072op01 segue SS para transformador queimado 5720590072 , defeito na bucha secundaria , 15KVA na 19.9 KV , pararaio queimado , acesso livre para camionete | Z49: 15 | AA49: 15 | AB49: 15 | AC49: 46225.761
A50: ETO-RD-GU 00345/2026 | B50: DBM-MPDB10 000047/2026 | C50: 412600357 | E50: SUBSTITUIÇÃO DE TRANSFORMADOR NA RDR DE SANDOLÂNDIA_x000D_ _x000D_ INT: 20264185938400_x000D_ _x000D_ SS: ETO-RD-GU 345/2026_x000D_ _x000D_ ESPECIFICAÇÕES DO TRANSFORMADOR_x000D_ _x000D_ TRANSFORMADOR INSTALADO: 15KVA_x000D_ _x000D_ TRANSFORMADOR RETIRADO: 05KVA_x000D_ _x000D_ MEDIÇÕES_x000D_ _x000D_ LOGO APÓS A TROCA _x000D_ _x000D_ VAN: 212_x000D_ _x000D_ VBN: 213_x000D_ _x000D_ VAB: 434_x000D_ _x000D_ OBS:SUBSTITUIÇÃO DE TRANSFORMADOR AUTORIZADA PELO DIONE._x000D_ _x000D_ _x000D_ _x000D_ | F50: QUEIMADO | G50: DESCARGA ATMOSFÉRICA | H50: QUEIMADO | I50: DESCARGA ATMOSFÉRICA | J50: MC - SUBSTITUIÇÃO DE TRANSFORMADOR | K50: 2026 | L50: LD02036052 | M50: 5700901107 | N50: 8385 | O50: EMERGENCIAL | P50: SS ATENDIDA | Q50: 46099.777 | R50: 46105.637 | S50: 46102.777 | T50: BLOCO TRANSFORMADOR DE DISTRIBUIÇÃO | U50: SANDOLANDIA | V50: CARLOS ALBERTO COUTINHO DE MOR | W50: RURAL | X50: FORMS SUBST DE TRANSFORMADOR | Y50: segue ss para substituiçao de tranformador queimado asseço para caminhonete | Z50: 15 | AB50: 05 kva | AC50: 46225.761
A51: ENC-RD-PS 00409/2026 | B51: ENC-MPPS01 000092/2026 | C51: 212600366 | E51: SS ENC-RD-PS 409/2026_x000D_ trafo 5700188046_x000D_ _x000D_ _x000D_ _x000D_ TRAFO RETIRADO_x000D_ POTÊNCIA : 30KVA_x000D_ TENSÃO : 34.5KV_x000D_ Nº ENERGISA (CITD) : 134706_x000D_ Nº DE SÉRIE : 136158_x000D_ MARCA : TRAEL_x000D_ DATA FABRICAÇÃO : 08/08_x000D_ IMPEDANCIA : 4.15_x000D_ POS. TAP : 02_x000D_ _x000D_ TRAFO INSTALADO'_x000D_ POTÊNCIA : 30KVA_x000D_ TENSÃO : 34.5KV_x000D_ Nº ENERGISA (CITD) : 147710_x000D_ Nº DE SÉRIE : 586747_x000D_ MARCA : ITAIPU_x000D_ DATA FABRICAÇÃO : 07/2025_x000D_ IMPEDANCIA : 4.04_x000D_ POS. TAP : 02_x000D_ _x000D_ | F51: QUEIMADO | G51: DESCARGA ATMOSFÉRICA | H51: QUEIMADO | I51: DESCARGA ATMOSFÉRICA | J51: MC - SUBSTITUIÇÃO DE TRANSFORMADOR | K51: 2026 | L51: LD01056046 | M51: 5700188046 | N51: 8812 | O51: EMERGENCIAL | P51: SS ATENDIDA | Q51: 46108.415 | R51: 46110.689 | S51: 46111.415 | T51: BLOCO TRANSFORMADOR DE DISTRIBUIÇÃO | U51: NOVA ROSALANDIA | V51: THIAGO BORGES DE OLIVEIRA | W51: RURAL | X51: FORMS SUBST DE TRANSFORMADOR | Y51: Segue ss para tratativa com equipe de manutençao o quanto antessubstituir trafo queimado na rdr de nova rosalandiatrafo 5700188046 | Z51: 30 | AA51: 30 | AB51: 30 | AC51: 46225.761
A52: ENC-RD-PS 00096/2026 | B52: ENC-LMPS01 000023/2026 | C52: 212600083 | E52: SS ENC-RD-PS 96/2026_x000D_ TR 5710120055_x000D_ _x000D_ _x000D_ _x000D_ _x000D_ TRAFO RETIRADO_x000D_ POTÊNCIA : 45KVA_x000D_ TENSÃO : 34.5KV_x000D_ Nº ENERGISA (CITD) : ILEGIVEL_x000D_ Nº DE SÉRIE : 563083023_x000D_ MARCA : SIEMENS_x000D_ DATA FABRICAÇÃO : 01/1999_x000D_ IMPEDANCIA : 4.13_x000D_ POS. TAP : 02_x000D_ _x000D_ TRAFO INSTALADO'_x000D_ POTÊNCIA : 45KVA_x000D_ TENSÃO : 34.5KV_x000D_ Nº ENERGISA (CITD) : 145390_x000D_ Nº DE SÉRIE : 118446_x000D_ MARCA : ENGERNORTE_x000D_ DATA FABRICAÇÃO : 2007_x000D_ IMPEDANCIA : 4.17_x000D_ POS. TAP : 02_x000D_ | F52: QUEIMADO | G52: DESCARGA ATMOSFÉRICA | H52: QUEIMADO | I52: DESCARGA ATMOSFÉRICA | J52: MC - SUBSTITUIÇÃO DE TRANSFORMADOR | K52: 2026 | L52: LD01434149 | M52: 5710120055 | N52: 8812 | O52: EMERGENCIAL | P52: SS ATENDIDA | Q52: 46040.418 | R52: 46041.692 | S52: 46043.418 | T52: BLOCO TRANSFORMADOR DE DISTRIBUIÇÃO | U52: ARAGUACEMA | V52: Felipe Batista Ferrreira | W52: RURAL | X52: FORMS SUBST DE TRANSFORMADOR | Y52: TR QUEIMADO 571012005545KVAT 34500PARA RAIO DANIFICADO ACESSO PARA CAMINHAO 055OP01 2UC PENALIZADAS | Z52: 45 | AA52: 45 | AB52: 34,5 | AC52: 46225.761
A53: DOLP-RD-PA 00054/2026 | B53: DLP-MLPA01 000008/2026 | C53: 112600120 | E53: MEDIDO__x000D_ _x000D_ EMERGENCIAL__x000D_ _x000D_ segue ss de trafo queimado na RDR de tocantinia, trafo 5710162006, tensao 34500 / 440 V, trafo de 25KVA, acesso livre, aldeia funil. obs sao dois trafo na mesma estrutura._x000D_ _x000D_ DADOS ATENDIMENTO_x000D_ EQUIPE PALM04M_x000D_ LIDER - JOSÉ RAIMUNDO_x000D_ CONTATO - (63) 99296-9610_x000D_ SS DOLP-RD-PA 0054/2026_x000D_ DATA ATENDIMENTO: 14/01/2026_x000D_ _x000D_ _x000D_ _x000D_ | F53: QUEIMADO | G53: DESCARGA ATMOSFÉRICA | H53: QUEIMADO | I53: DESCARGA ATMOSFÉRICA | J53: MC - SUBSTITUIÇÃO DE TRANSFORMADOR | K53: 2026 | L53: LD05050008 | M53: 5710162006 | N53: 8812 | O53: EMERGENCIAL | P53: SS ATENDIDA | Q53: 46035.646 | R53: 46027.833 | S53: 46038.646 | T53: BLOCO TRANSFORMADOR DE DISTRIBUIÇÃO | U53: TOCANTINIA | V53: MARCO ANTONIO LOURENCO CAMPOS | W53: RURAL | X53: FORMS SUBST DE TRANSFORMADOR | Y53: segue ss de trafo queimado na RDR de tocantinia, trafo 5710162006, tensao 34500 / 440 V, trafo de 25KVA, acesso livre, aldeia funil. obs sao dois trafo na mesma estrutura. | Z53: 15 | AA53: 15 | AB53: 25kva | AC53: 46225.761
A54: DG-RD-PO 00106/2026 | B54: DG-MLPO02 000028/2026 | C54: 312600090 | E54: medido__x000D_ emergencial__x000D_ _x000D_ _x000D_ substituição de trafo queimado rdr ponte alta_x000D_ | F54: QUEIMADO | G54: DESCARGA ATMOSFÉRICA | J54: MC - SUBSTITUIÇÃO DE TRANSFORMADOR | K54: 2026 | L54: LD03046026 | M54: 5728738026 | N54: 8812 | O54: EMERGENCIAL | P54: SS ATENDIDA | Q54: 46047.429 | R54: 46049.446 | S54: 46050.429 | T54: BLOCO TRANSFORMADOR DE DISTRIBUIÇÃO | U54: PONTE ALTA DO TOCANTINS | V54: JANES FERREIRA DA SILVA | W54: RURAL | X54: FORMS SUBST DE TRANSFORMADOR | Y54: tr 5728738026 queimado segue SS para substituiçaõ | Z54: 15 | AA54: 15 | AB54: 10 | AC54: 46225.761
A55: ETO-RD-GU 00078/2026 | B55: DBM-MLDB06 000011/2026 | C55: 412600097 | E55: SUBSTITUIÇÃO DE TRANSFORMADOR NA RDR DE PEIXE_x000D_ _x000D_ SS: ETO-RD-GU 78/2026_x000D_ _x000D_ ESPECIFICAÇÕES DO TRANSFORMADOR_x000D_ _x000D_ TRANSFORMADOR INSTALADO: 15 KVA_x000D_ _x000D_ TRANSFORMADOR RETIRADO: 15 KVA_x000D_ _x000D_ MEDIÇÕES_x000D_ _x000D_ LOGO APÓS A TROCA _x000D_ _x000D_ VAN: 215_x000D_ _x000D_ VBN: 214_x000D_ _x000D_ OBS:SUBSTITUIÇÃO DE TRANSFORMADOR AUTORIZADA PELO DIONE._x000D_ _x000D_ | F55: QUEIMADO | G55: NÃO IDENTIFICADO | J55: MC - SUBSTITUIÇÃO DE TRANSFORMADOR | K55: 2026 | L55: LD01066094 | M55: 5701362094 | N55: 8812 | O55: EMERGENCIAL | P55: SS ATENDIDA | Q55: 46037.735 | R55: 46037.967 | S55: 46040.735 | T55: BLOCO TRANSFORMADOR DE DISTRIBUIÇÃO | U55: PEIXE | V55: Wilmar Lucas Rodrigues Noleto | W55: RURAL | X55: FORMS SUBST DE TRANSFORMADOR | Y55: SEGUE SS DE TRAFO QUEIMADO NA RDR DE PEIXE, TRAFO DE 15KVA REDE DE 19.9KV, PARA RAIO QUEIMADO E ACESSO LIVRE, TRAFO NA COMPENSAÇÃO T0-R$2515,00 ---- T10-3255,00 | Z55: 15 | AA55: 15 | AB55: 15kva | AC55: 46225.761
A56: DG-RD-PO 00116/2026 | B56: DG-MLPO01 000024/2026 | C56: 312600095 | E56: medido__x000D_ emergencial__x000D_ _x000D_ _x000D_ substituição de trafo furtado rdr ipueiras _x000D_ | F56: FURTADO | G56: FURTADO | J56: MC - SUBSTITUIÇÃO DE TRANSFORMADOR | K56: 2026 | L56: LD02072001 | M56: 5710067250 | O56: EMERGENCIAL | P56: SS ATENDIDA | Q56: 46049.781 | R56: 46050.696 | S56: 46052.781 | T56: TRANSFORMADOR DE DISTRIBUIÇÃO ENERGISA 19.919Kv | U56: IPUEIRAS | V56: JOSE MARIA ALVES MONTEL | W56: RURAL | X56: FORMS SUBST DE TRANSFORMADOR | Y56: INT: 20264101055791Segue SS de TR 5710067250 15KVA/19.9KV e para-raios possivelmente furtado.Acesso livre para caminhonete.UC 8832714CHACARA SAO JOAO BATISTA63992193439CLEUSA DOS SANTOS001OP18 63 99295-3666 | Z56: 15 | AA56: 15 | AB56: 15 | AC56: 46225.761
A57: ETO-RD-GR 00100/2026 | B57: ENC-MLGR03 000036/2026 | C57: 712600066 | E57: TROCA DE TRAFO QUEIMADO 5710172009 ETO-RD-GR 100/2026 FAZ. ALEGRIA E PROGRESSO - GUARAI 0009_x000D_ _x000D_ TRAFO RETIRADO_x000D_ POTÊNCIA : 15KVA_x000D_ TENSÃO : 19.9KV _x000D_ Nº ENERGISA (CITD) : CITD06017756_x000D_ Nº DE SÉRIE : 976234_x000D_ MARCA : ITB_x000D_ DATA FABRICAÇÃO : 10/2015_x000D_ IMPEDANCIA : 3.10_x000D_ POS. TAP : 03_x000D_ _x000D_ TRAFO INSTALADO_x000D_ POTÊNCIA : 15KVA_x000D_ TENSÃO : 19.9KV _x000D_ Nº ENERGISA (CITD) : 149283_x000D_ Nº DE SÉRIE : 820269_x000D_ MARCA : TRAEL_x000D_ DATA FABRICAÇÃO : 11/2025_x000D_ IMPEDANCIA : 3.0_x000D_ POS. TAP : 03_x000D_ _x000D_ MEDIÇÃO 1: 00.14_x000D_ MEDIÇÃO 2: 00.11_x000D_ MEDIÇÃO 3: 00.09_x000D_ _x000D_ COORDENADA_x000D_ X: 762558_x000D_ Y: 9028062_x000D_ | F57: QUEIMADO | G57: DESCARGA ATMOSFÉRICA | H57: QUEIMADO | I57: DESCARGA ATMOSFÉRICA | J57: MC - SUBSTITUIÇÃO DE TRANSFORMADOR | K57: 2026 | L57: LD04038009 | M57: 5710172009 | N57: 8812 | O57: EMERGENCIAL | P57: SS ATENDIDA | Q57: 46039.745 | R57: 46039.975 | S57: 46042.745 | T57: BLOCO TRANSFORMADOR DE DISTRIBUIÇÃO | U57: GUARAI | V57: STANLEY APARECIDO DO CARMO | W57: RURAL | X57: FORMS SUBST DE TRANSFORMADOR | Y57: Trafo: 5710172009 QueimadoPotencia: 15 KVATensão: 34,5 KVPara raio: NovoAcesso: Camioneta Equipe: 009op03 (63)99256-7506 | Z57: 15 | AA57: 15 | AB57: 15 KVA | AC57: 46225.761
A58: ENC-RD-PS 00038/2026 | B58: ENC-MPPS01 000009/2026 | C58: 212600070 | E58: SS ENC-RD-PS 38/2026_x000D_ TRAFO: 5710592085_x000D_ _x000D_ _x000D_ _x000D_ TRAFO RETIRADO_x000D_ POTÊNCIA : 10KVA_x000D_ TENSÃO : 34.5KV_x000D_ Nº ENERGISA (CITD) : ILEGIVEL_x000D_ Nº DE SÉRIE : 78086_x000D_ MARCA : TRAEL_x000D_ DATA FABRICAÇÃO : MA/2005_x000D_ IMPEDANCIA : 2.92_x000D_ POS. TAP : 02_x000D_ _x000D_ TRAFO INSTALADO'_x000D_ POTÊNCIA : 15KVA_x000D_ TENSÃO : 34.5KV_x000D_ Nº ENERGISA (CITD) : 149776_x000D_ Nº DE SÉRIE : 290337_x000D_ MARCA : ITAM_x000D_ DATA FABRICAÇÃO : 10/2025_x000D_ IMPEDANCIA : 3.25_x000D_ POS. TAP : 03_x000D_ | F58: QUEIMADO | G58: NÃO IDENTIFICADO | H58: QUEIMADO | I58: NÃO IDENTIFICADO | J58: MC - SUBSTITUIÇÃO DE TRANSFORMADOR | K58: 2026 | L58: LD03062013 | M58: 5710592085 | N58: 8812 | O58: EMERGENCIAL | P58: SS ATENDIDA | Q58: 46032.759 | R58: 46034.081 | S58: 46035.759 | T58: BLOCO TRANSFORMADOR DE DISTRIBUIÇÃO | U58: MONTE SANTO DO TOCANTINS | V58: JOAO PAULO VASCONCELOS MARINHO | W58: RURAL | X58: FORMS SUBST DE TRANSFORMADOR | Y58: segue ss de 01 trafo de 10 kvar e 01 para raio da rede de 34.500kv queimado e 01 poste de 10/300 da estrutura do trafo para ser subistituido devido o poste ser muito fino e não suporta o trafo de 15 kvar se for instalar um de 15 acesso bom equipe que atendeu 013op04 cel, 63991022334/984921228 cliente penalizado 01 favor agilizar o atendimento | Z58: 15 | AA58: 10 | AB58: 10 kvar | AC58: 46225.761
A59: ENC-RD-PS 00037/2026 | B59: ENC-LMPS03 000009/2026 | C59: 212600062 | E59: SS ENC-RD-PS 37/2026_x000D_ TRAFO:5700758084_x000D_ _x000D_ _x000D_ _x000D_ TRAFO RETIRADO_x000D_ POTÊNCIA : 15KVA_x000D_ TENSÃO : 34.5KV_x000D_ Nº ENERGISA (CITD) : 128994_x000D_ Nº DE SÉRIE : 442976_x000D_ MARCA : TRAEL_x000D_ DATA FABRICAÇÃO : 09/2017_x000D_ IMPEDANCIA : 2.97_x000D_ POS. TAP : 03_x000D_ _x000D_ TRAFO INSTALADO'_x000D_ POTÊNCIA : 15KVA_x000D_ TENSÃO : 34.5KV_x000D_ Nº ENERGISA (CITD) : 149801_x000D_ Nº DE SÉRIE : 290394_x000D_ MARCA : ITAM_x000D_ DATA FABRICAÇÃO : 10/2025_x000D_ IMPEDANCIA : 3.10_x000D_ POS. TAP : 03_x000D_ | F59: QUEIMADO | G59: NÃO IDENTIFICADO | H59: QUEIMADO | I59: NÃO IDENTIFICADO | J59: MC - SUBSTITUIÇÃO DE TRANSFORMADOR | K59: 2026 | L59: LD03414149 | M59: 5700758084 | N59: 8812 | O59: EMERGENCIAL | P59: SS ATENDIDA | Q59: 46032.733 | R59: 46034.999 | S59: 46035.733 | T59: BLOCO TRANSFORMADOR DE DISTRIBUIÇÃO | U59: DIVINOPOLIS DO TOCANTINS | V59: JOAO PAULO VASCONCELOS MARINHO | W59: RURAL | X59: FORMS SUBST DE TRANSFORMADOR | Y59: segue ss de 01 trafo de 15 kvar e 01 para raio queimado da rede de 34,500kv para ser subistitruido pela equipé de manutencão acesso bom equipe que atendeu 084op02 cel, 63984097354/992357310/984623208 cliente penalizado 01 | Z59: 15 | AA59: 15 | AB59: 15 kvar | AC59: 46225.761
A60: ETO-RD-GR 00178/2026 | B60: ETO-RD-GR 000253/2026 | C60: 712600132 | E60: TR-5700315153Queimado_x000D_ para raios bom_x000D_ potência 15kva_x000D_ tensão 34,5kv_x000D_ acesso livre_x000D_ equipe 153op01 tel-63984324652 | F60: QUEIMADO | G60: DESCARGA ATMOSFÉRICA | H60: QUEIMADO | I60: DESCARGA ATMOSFÉRICA | J60: MC - SUBSTITUIÇÃO DE TRANSFORMADOR | K60: 2026 | L60: LD01010153 | M60: 5700315153 | N60: 8812 | O60: EMERGENCIAL | P60: SS ATENDIDA | Q60: 46056.773 | R60: 46057.904 | S60: 46059.773 | T60: BLOCO TRANSFORMADOR DE DISTRIBUIÇÃO | U60: BERNARDO SAYAO | V60: ROBSON FERNANDO LAUERMANN RICO | W60: RURAL | X60: FORMS SUBST DE TRANSFORMADOR | Y60: TR-5700315153Queimadopara raios bompotência 15kvatensão 34,5kvacesso livreequipe 153op01 tel-63984324652 | AB60: 15 | AC60: 46225.761
A61: ETO-RD-AR 00243/2026 | B61: ENC-MLAR05 000091/2026 | C61: 612600149 | E61: ETO-RD-AR 243/2026_x000D_ TR: 5701262019_x000D_ _x000D_ TRAFO RETIRADO_x000D_ POTÊNCIA : 5KVA_x000D_ TENSÃO : 34,5KV_x000D_ Nº ENERGISA (CITD) : ILEGIVEL _x000D_ Nº DE SÉRIE : 175731_x000D_ MARCA : VIJAI_x000D_ DATA FABRICAÇÃO : 08/2010_x000D_ IMPEDANCIA : 3,14_x000D_ POS. TAP : 03_x000D_ _x000D_ TRAFO INSTALADO_x000D_ POTÊNCIA : 15KVA_x000D_ TENSÃO : 34,5KV_x000D_ Nº ENERGISA (CITD) : 149297_x000D_ Nº DE SÉRIE : 820283_x000D_ MARCA : TRAEL_x000D_ DATA FABRICAÇÃO : 11/2025_x000D_ IMPEDANCIA : 3,0_x000D_ POS. TAP : 02_x000D_ | F61: AVARIADO | G61: VAZAMENTO DE ÓLEO | H61: QUEIMADO | I61: VAZAMENTO DE ÓLEO | J61: MC - SUBSTITUIÇÃO DE TRANSFORMADOR | K61: 2026 | L61: LD01105019 | M61: 5701262019 | N61: 8805 | O61: EMERGENCIAL | P61: SS ATENDIDA | Q61: 46057.783 | R61: 46057.753 | S61: 46060.783 | T61: TRANSFORMADOR DE DISTRIBUIÇÃO ENERGISA 19.919Kv | U61: FILADELFIA | V61: ERLAN PEREIRA DE SOUSA | W61: RURAL | X61: FORMS SUBST DE TRANSFORMADOR | Y61: Trafo 5701262019 avariado 15kvaTensão: 19.9Acesso livre | Z61: 15 | AA61: 5 | AB61: 15kva | AC61: 46225.761
A62: DOLP-RD-PA 00285/2026 | B62: DLP-MLPA03 000012/2026 | C62: 112600416 | E62: MEDIDO__x000D_ _x000D_ EMERGENCIAL__x000D_ _x000D_ _x000D_ Trafo 5710549001 de 15kva e para-raio queimado, Tensão 7,9kv, Acesso para camionete 4x4, Local rural de Luzimangues, Chac. Solar das Mangabeiras SN Irrigante. _x000D_ _x000D_ _x000D_ _x000D_ DADOS ATENDIMENTO_x000D_ _x000D_ N° DOCUMENTO SS: DOLP-RD-PA 000285/2026_x000D_ N° DOCUMENTO OS: DLP-MLPA03 000012/2026_x000D_ _x000D_ TIPO DA INTERVENÇÃO: MANUTENÇÃO_x000D_ TIPO DO SERVIÇO: SUBSTITUIÇÃO DE TRANSFORMADOR E MELHORIA DE MALHA DE ATERRAMENTO_x000D_ DATA PROGRAMADA DA ATIVIDADE: 23/02/2026_x000D_ HORARIO PREVISTO DA ATIVIDADE: 08:00 ÀS 18:00_x000D_ CIDADE: LUZIMANGUES ALIMENTADOR: AL03101271_x000D_ _x000D_ EQUIPE: DOLP-MLPA04_x000D_ CONTATO DA EQUIPE: 63 9295-4214_x000D_ COMPOSIÇÃO DA EQUIPE: _x000D_ 1 - ELTON SILVA DE JESUS_x000D_ 2 - ROMARIO PEREIRA DOS SANTOS_x000D_ _x000D_ SUPERVISOR: PAULO VÍTOR LEMES GOMES_x000D_ CONTATO: 63 9 9296-6939_x000D_ FISCAL RESPONSAVÉL: JAILTON GOMES VIEIRAS_x000D_ CONTATO: 63 8415-6027_x000D_ _x000D_ Atenção!_x000D_ Não intervenha na rede sem autorização do COI (Centro de Operações Integradas) | F62: QUEIMADO | G62: DESCARGA ATMOSFÉRICA | H62: QUEIMADO | I62: DESCARGA ATMOSFÉRICA | J62: MC - SUBSTITUIÇÃO DE TRANSFORMADOR | K62: 2026 | L62: AL03101271 | M62: 5710549001 | N62: 8812 | O62: EMERGENCIAL | P62: SS ATENDIDA | Q62: 46076.03 | R62: 46076.681 | S62: 46079.03 | T62: BLOCO TRANSFORMADOR DE DISTRIBUIÇÃO | U62: PORTO NACIONAL | V62: SAMUEL PINTO GOMES | W62: RURAL | X62: FORMS SUBST DE TRANSFORMADOR | Y62: Trafo 5710549001 de 15kva e para-raio queimado, Tensão 7,9kv, Acesso para camionete 4x4, Local rural de Luzimangues, Chac. Solar das Mangabeiras SN Irrigante. | Z62: 15 | AA62: 15 | AB62: 15kva | AC62: 46225.761
A63: ETO-RD-GU 00117/2026 | B63: DBM-MPDB10 000016/2026 | C63: 412600147 | E63: SUBSTITUIÇÃO DE TRANSFORMADOR NA RDR DE SANDOLÂNDIA_x000D_ _x000D_ INT: 20264094905080_x000D_ _x000D_ SS: ETO-RD-GU 117/2026_x000D_ _x000D_ ESPECIFICAÇÕES DO TRANSFORMADOR_x000D_ _x000D_ TRANSFORMADOR INSTALADO: 112,5KVA_x000D_ _x000D_ TRANSFORMADOR RETIRADO: 75KVA_x000D_ _x000D_ MEDIÇÕES_x000D_ _x000D_ LOGO APÓS A TROCA _x000D_ _x000D_ VAN: 238_x000D_ _x000D_ VBN: 239_x000D_ _x000D_ VCN: 237_x000D_ _x000D_ VAB: 411_x000D_ _x000D_ VBC: 416_x000D_ _x000D_ VCA: 415_x000D_ _x000D_ OBS:SUBSTITUIÇÃO DE TRANSFORMADOR AUTORIZADA PELO DIONE._x000D_ _x000D_ OBS:EM CAMPO JÁ EXISTE SEGUNDA DESCIDA_x000D_ _x000D_ | F63: QUEIMADO | G63: DESCARGA ATMOSFÉRICA | H63: QUEIMADO | I63: DESCARGA ATMOSFÉRICA | J63: MC - SUBSTITUIÇÃO DE TRANSFORMADOR | K63: 2026 | L63: LD02036052 | M63: 5720057107 | N63: 8385 | O63: EMERGENCIAL | P63: SS ATENDIDA | Q63: 46045.626 | R63: 46048.94 | S63: 46048.626 | T63: BLOCO TRANSFORMADOR DE DISTRIBUIÇÃO | U63: SANDOLANDIA | V63: JONATAN ALVES DE SOUZA | W63: RURAL | X63: FORMS SUBST DE TRANSFORMADOR | Y63: SEGUE SOLICITAÇÃO DE SERVIÇO PARA TROCA DE TRAFO TRIFASICO NA RDR DE SANDOLANDIA CLIENTE COM AUTO POTENCIAL DE COMPESAÇÃO | Z63: 1125 | AA63: 75 | AB63: 75KVA | AC63: 46225.761
A64: ETO-RD-GR 00048/2026 | B64: ENC-MLGR01 000017/2026 | C64: 712600043 | E64: SUBSTITUIÇÃO DE TRAFO 5728543227 ETO-RD-GR 48/2026 FAZ. GAMELEIRA RDR DE RECURSOLANDIA _x000D_ _x000D_ TRAFO RETIRADO_x000D_ POTÊNCIA : 15KVA_x000D_ TENSÃO : 34,5KV_x000D_ Nº ENERGISA (CITD) : 06107734_x000D_ Nº DE SÉRIE : 441859_x000D_ MARCA : TRAEL_x000D_ DATA FABRICAÇÃO : 08/2017_x000D_ IMPEDANCIA : S/N_x000D_ POS. TAP : 01_x000D_ _x000D_ TRAFO INSTALADO_x000D_ POTÊNCIA : 15KVA_x000D_ TENSÃO : 34,5KV_x000D_ Nº ENERGISA (CITD) : 149699_x000D_ Nº DE SÉRIE : C290239_x000D_ MARCA : ITAM_x000D_ DATA FABRICAÇÃO : 09/2025_x000D_ IMPEDANCIA : 3,19_x000D_ POS. TAP : 03_x000D_ _x000D_ MEDIÇÃO 1: 18,68_x000D_ MEDIÇÃO 2: 17,26_x000D_ MEDIÇÃO 3: 16,07_x000D_ _x000D_ COORDENADA_x000D_ X: 915587 _x000D_ Y: 9054180_x000D_ | F64: QUEIMADO | G64: DESCARGA ATMOSFÉRICA | H64: QUEIMADO | I64: DESCARGA ATMOSFÉRICA | J64: MC - SUBSTITUIÇÃO DE TRANSFORMADOR | K64: 2026 | L64: LD01065015 | M64: 5728543227 | N64: 8812 | O64: EMERGENCIAL | P64: SS ATENDIDA | Q64: 46030.753 | R64: 46031.69 | S64: 46033.753 | T64: BLOCO TRANSFORMADOR DE DISTRIBUIÇÃO | U64: RECURSOLANDIA | V64: STANLEY APARECIDO DO CARMO | W64: RURAL | X64: FORMS SUBST DE TRANSFORMADOR | Y64: Trafo: 5728543227 Queimado Potencia: 15 KVATensão: 34,5KVPara raio: queimado Acesso: Camioneta Equipe: 22op01 (63)99247-2838 | Z64: 15 | AA64: 15 | AB64: 15 KVA | AC64: 46225.761
A65: ETO-RD-GR 00436/2026 | B65: ENC-MPGR01 000076/2026 | C65: 712600306 | E65: TROCA DE TRAFO QUEIMADO 5700008111 ETO-RD-GR 436/2026 ZONA URBANA - PEQUIZEIRO 0111_x000D_ _x000D_ TRAFO RETIRADO_x000D_ POTÊNCIA : 112.5KVA_x000D_ TENSÃO : 34.5KV _x000D_ Nº ENERGISA (CITD) : 124830_x000D_ Nº DE SÉRIE : 1.233.962_x000D_ MARCA : ROMAGNOLE_x000D_ DATA FABRICAÇÃO : 06/2020_x000D_ IMPEDANCIA : 3.95_x000D_ POS. TAP : 02_x000D_ _x000D_ TRAFO INSTALADO_x000D_ POTÊNCIA : 112.5KVA_x000D_ TENSÃO : 34.5KV _x000D_ Nº ENERGISA (CITD) : 141917_x000D_ Nº DE SÉRIE : 1603829_x000D_ MARCA : ITB - TRAEL_x000D_ DATA FABRICAÇÃO : 01/2025 - 02/2026_x000D_ IMPEDANCIA : 3.80_x000D_ POS. TAP : 02_x000D_ _x000D_ MEDIÇÃO 1: 13.91_x000D_ MEDIÇÃO 2: 12.64_x000D_ MEDIÇÃO 3: 11.56_x000D_ _x000D_ COORDENADA_x000D_ X: 727229_x000D_ Y: 9049688_x000D_ | F65: QUEIMADO | G65: DESCARGA ATMOSFÉRICA | H65: QUEIMADO | I65: DESCARGA ATMOSFÉRICA | J65: MC - SUBSTITUIÇÃO DE TRANSFORMADOR | K65: 2026 | L65: LD02022033 | M65: 5700008111 | N65: 8812 | O65: EMERGENCIAL | P65: SS ATENDIDA | Q65: 46128.399 | R65: 46128.667 | S65: 46131.399 | T65: BLOCO TRANSFORMADOR DE DISTRIBUIÇÃO | U65: PEQUIZEIRO | V65: SIRDEIS ALVES MONTEIRO | W65: URBANO | X65: FORMS SUBST DE TRANSFORMADOR | Y65: trafo 5700008111 queimado em campo 112,5 kva na 34,5 kv acesso bom | Z65: 1125 | AA65: 1125 | AB65: 112,5kva | AC65: 46225.761
A66: ETO-RD-GR 00363/2026 | B66: ENC-MLGR03 000128/2026 | C66: 712600250 | E66: TROCA DE TRAFO QUEIMADO 5700639018 ETO-RD-GR 363/2026 FAZ. ALTO ALEGRE - BOM JESUS 0018_x000D_ _x000D_ TRAFO RETIRADO_x000D_ POTÊNCIA : 05KVA_x000D_ TENSÃO : 19.9KV _x000D_ Nº ENERGISA (CITD) : ILEGIVEL_x000D_ Nº DE SÉRIE : 199057_x000D_ MARCA : VIJAI_x000D_ DATA FABRICAÇÃO : 09/2011_x000D_ IMPEDANCIA : 2.95_x000D_ POS. TAP : 03_x000D_ _x000D_ TRAFO INSTALADO_x000D_ POTÊNCIA : 15KVA_x000D_ TENSÃO : 19.9KV _x000D_ Nº ENERGISA (CITD) : 150195_x000D_ Nº DE SÉRIE : 827918_x000D_ MARCA : TRAEL_x000D_ DATA FABRICAÇÃO : 02/2026_x000D_ IMPEDANCIA : 3.0_x000D_ POS. TAP : 03_x000D_ _x000D_ MEDIÇÃO 1: 16.83_x000D_ MEDIÇÃO 2: 14.36_x000D_ MEDIÇÃO 3: 13.65_x000D_ _x000D_ COORDENADA_x000D_ X: 862348_x000D_ Y: 8996186_x000D_ | F66: QUEIMADO | G66: DESCARGA ATMOSFÉRICA | H66: QUEIMADO | I66: DESCARGA ATMOSFÉRICA | J66: MC - SUBSTITUIÇÃO DE TRANSFORMADOR | K66: 2026 | L66: LD02424015 | M66: 5700639018 | N66: 8812 | O66: EMERGENCIAL | P66: SS ATENDIDA | Q66: 46102.507 | R66: 46103.683 | S66: 46105.507 | T66: BLOCO TRANSFORMADOR DE DISTRIBUIÇÃO | U66: BOM JESUS DO TOCANTINS | V66: SIRDEIS ALVES MONTEIRO | W66: RURAL | X66: FORMS SUBST DE TRANSFORMADOR | Y66: Trafo queimado 5700639018 - 10KVA 34,5kv acesso caminhonete ate uns 20mt próximo do Trafo para raio queimado | Z66: 15 | AA66: 5 | AB66: 15 kva | AC66: 46225.761
A67: ETO-RD-GU 00116/2026 | B67: DBM-MLDB06 000018/2026 | C67: 412600132 | E67: SUBSTITUIÇÃO DE TRANSFORMADOR NA RDR DE ARAGUAÇU_x000D_ _x000D_ INT: 20264090285512_x000D_ _x000D_ SS: ETO-RD-GU 115/2026_x000D_ _x000D_ ESPECIFICAÇÕES DO TRANSFORMADOR_x000D_ _x000D_ TRANSFORMADOR INSTALADO: 15 KVA_x000D_ _x000D_ TRANSFORMADOR RETIRADO: 15 KVA_x000D_ _x000D_ MEDIÇÕES_x000D_ _x000D_ LOGO APÓS A TROCA _x000D_ _x000D_ VAN: 217_x000D_ _x000D_ VBN: 215_x000D_ _x000D_ OBS:SUBSTITUIÇÃO DE TRANSFORMADOR AUTORIZADA PELO DIONE._x000D_ | F67: QUEIMADO | G67: DESCARGA ATMOSFÉRICA | J67: MC - SUBSTITUIÇÃO DE TRANSFORMADOR | K67: 2026 | L67: LD01066094 | M67: 5710017148 | N67: 8812 | O67: EMERGENCIAL | P67: SS ATENDIDA | Q67: 46045.47 | R67: 46045.472 | S67: 46048.47 | T67: BLOCO TRANSFORMADOR DE DISTRIBUIÇÃO | U67: SAO VALERIO | V67: GERALDO JOSE DE FARIA | W67: RURAL | X67: FORMS SUBST DE TRANSFORMADOR | Y67: trafo queimado 5710017148 de 15kva da 19.9 para raios queimado. acesso livre. 01 cliente penalizado. | Z67: 15 | AA67: 15 | AB67: 15 | AC67: 46225.761
A68: ETO-RD-GR 00366/2026 | B68: ETO-RD-GR 000628/2026 | C68: 712600254 | E68: trafo 5700121011 queimado 15 kv 13,8 kva para raio queimado acesso bom | F68: QUEIMADO | G68: DESCARGA ATMOSFÉRICA | H68: QUEIMADO | I68: DESCARGA ATMOSFÉRICA | J68: MC - SUBSTITUIÇÃO DE TRANSFORMADOR | K68: 2026 | L68: AL01065015 | M68: 5700121011 | N68: 8812 | O68: EMERGENCIAL | P68: SS ATENDIDA | Q68: 46103.657 | R68: 46104.598 | S68: 46106.657 | T68: BLOCO TRANSFORMADOR DE DISTRIBUIÇÃO | U68: TUPIRAMA | V68: SIRDEIS ALVES MONTEIRO | W68: RURAL | X68: FORMS SUBST DE TRANSFORMADOR | Y68: trafo 5700121011 queimado 15 kv 13,8 kva para raio queimado acesso bom | AB68: 15 kva | AC68: 46225.761
A69: DG-RD-PO 00289/2026 | B69: DG-MLPO02 000055/2026 | C69: 312600223 | E69: medido__x000D_ emergencial__x000D_ _x000D_ _x000D_ substituição de trafo queimado rdr monte do carmo_x000D_ | F69: QUEIMADO | G69: DESCARGA ATMOSFÉRICA | J69: MC - SUBSTITUIÇÃO DE TRANSFORMADOR | K69: 2026 | L69: LD01051035 | M69: 5700780035 | N69: 8812 | O69: EMERGENCIAL | P69: SS ATENDIDA | Q69: 46105.317 | R69: 46106.565 | S69: 46108.317 | T69: BLOCO TRANSFORMADOR DE DISTRIBUIÇÃO | U69: MONTE DO CARMO | V69: HERIK BUARQUE DOS SANTOS | W69: RURAL | X69: FORMS SUBST DE TRANSFORMADOR | Y69: TRAFO 5700780035 QUEIMADO DE 15KVA NA 19,9 E PARA RAIO TAMBEM QUEIMADO.Endereço: IND CHACARA BALUARTE, 0ACESSO TEM QUE PASSAR UM CORREGO A PE E ANDAR MAIS 300 METROS ATE O TRAFO. OU SEJA NAO TEM ACESSO COM VEICULO SOMENTE A PE, MAIS IMFORMACOES ENTRA EM CONTATO COM A EQUIPE. | Z69: 15 | AA69: 5 | AB69: 15 KVA | AC69: 46225.761
A70: ETO-RD-DP 00088/2026 | B70: ETO-MLDP01 000040/2026 | C70: 512600062 | E70: Conforme informações da equipe 028op04 segue SS do transformador 5700295116 queimado 15KVA - 19.9 . | F70: QUEIMADO | G70: NÃO IDENTIFICADO | H70: QUEIMADO | I70: NÃO IDENTIFICADO | J70: MC - SUBSTITUIÇÃO DE TRANSFORMADOR | K70: 2026 | L70: LD02072001 | M70: 5700295116 | N70: 8812 | O70: EMERGENCIAL | P70: SS ATENDIDA | Q70: 46055.797 | R70: 46057.5 | S70: 46058.797 | T70: BLOCO TRANSFORMADOR DE DISTRIBUIÇÃO | U70: CHAPADA DA NATIVIDADE | V70: IZAIAS SANTOS BRAGA JUNIOR | W70: RURAL | X70: FORMS SUBST DE TRANSFORMADOR | Y70: Conforme informações da equipe 028op04 segue SS do transformador 5700295116 queimado 15KVA - 19.9 . | Z70: 15 | AA70: 15 | AB70: 15 | AC70: 46225.761
A71: ETO-RD-AR 00504/2026 | B71: ENC-MLAR05 000157/2026 | C71: 612600330 | E71: ETO-RD-AR 504/2026_x000D_ TRAFO 5752570159_x000D_ TRAFO RETIRADO_x000D_ POTÊNCIA : 30 KVA_x000D_ TENSÃO : 34.4 KV_x000D_ Nº ENERGISA (CITD) : 129196_x000D_ Nº DE SÉRIE : 1298121_x000D_ MARCA : ROMAGNOLE_x000D_ DATA FABRICAÇÃO : 06/2024_x000D_ IMPEDANCIA : 3,69_x000D_ POS. TAP : 4_x000D_ _x000D_ TRAFO INSTALADO_x000D_ POTÊNCIA : 30 KVA_x000D_ TENSÃO : 34.5 KV_x000D_ Nº ENERGISA (CITD) : 147732_x000D_ Nº DE SÉRIE : 586769_x000D_ MARCA : ITAIPU_x000D_ DATA FABRICAÇÃO : 07/2025_x000D_ IMPEDANCIA : 3,96_x000D_ POS. TAP : 04_x000D_ _x000D_ OBS: LANÇADO DISPONIBILIDADE REFERENTE AO DESLOCAMENTO DA SS ETO-RD-AG 224/2026 PARA FAZER MELHORIA,PORÉM NÃO FOI PRECISO DEVIDO NÃO TER TRAFO NO LOCAL. | F71: QUEIMADO | G71: DESCARGA ATMOSFÉRICA | H71: QUEIMADO | I71: DESCARGA ATMOSFÉRICA | J71: MC - SUBSTITUIÇÃO DE TRANSFORMADOR | K71: 2026 | L71: LD03010004 | M71: 5752570159 | N71: 8812 | O71: EMERGENCIAL | P71: SS ATENDIDA | Q71: 46098.837 | R71: 46099.892 | S71: 46101.837 | T71: BLOCO TRANSFORMADOR DE DISTRIBUIÇÃO | U71: MURICILANDIA | V71: GUILHERME BORGES DE OLIVEIRA | W71: RURAL | X71: FORMS SUBST DE TRANSFORMADOR | Y71: 5752570159 30kva 34.5kv e para raioacesso livre | Z71: 30 | AA71: 30 | AB71: 30KVA | AC71: 46225.761
A72: ETO-RD-GR 00322/2026 | B72: ETO-RD-GR 000584/2026 | C72: 712600229 | E72: trafo queimado 5710108154 - 15KVA 34,5KV + para raio queimado acesso livre _x000D_ IND FAZENDA NOVA PROVIDENCIA - cliente WERTHER PEREIRA DIAS FILHO - uc 5795206 telefone 63984117042_x000D_ _x000D_ RDR JUARINA | F72: QUEIMADO | G72: DESCARGA ATMOSFÉRICA | H72: QUEIMADO | I72: DESCARGA ATMOSFÉRICA | J72: MC - SUBSTITUIÇÃO DE TRANSFORMADOR | K72: 2026 | L72: LD01010153 | M72: 5710108154 | N72: 8812 | O72: EMERGENCIAL | P72: SS ATENDIDA | Q72: 46090.734 | R72: 46092.343 | S72: 46093.734 | T72: BLOCO TRANSFORMADOR DE DISTRIBUIÇÃO | U72: JUARINA | V72: VALERIA DE JESUS BORGES CARVAL | W72: RURAL | X72: FORMS SUBST DE TRANSFORMADOR | Y72: trafo queimado 5710108154 - 15KVA 34,5KV + para raio queimado acesso livre IND FAZENDA NOVA PROVIDENCIA - cliente WERTHER PEREIRA DIAS FILHO - uc 5795206 telefone 63984117042RDR JUARINA | AB72: 15KVA | AC72: 46225.761
A73: ETO-RD-GR 00155/2026 | B73: ENC-MLGR01 000037/2026 | C73: 712600107 | E73: TROCA DE TRAFO QUEIMADO 5710378023 ETO-RD-GR 155/2026 FAZ. BOA SORTE - COLINAS 0023_x000D_ _x000D_ TRAFO RETIRADO_x000D_ POTÊNCIA : 15KVA_x000D_ TENSÃO : 7.9KV _x000D_ Nº ENERGISA (CITD) : ILEGIVEL_x000D_ Nº DE SÉRIE : 372728_x000D_ MARCA : TOSHIBA_x000D_ DATA FABRICAÇÃO : 02/2000 - ????_x000D_ IMPEDANCIA : 2.5_x000D_ POS. TAP : 01_x000D_ _x000D_ TRAFO INSTALADO_x000D_ POTÊNCIA : 25KVA_x000D_ TENSÃO : 7.9KV _x000D_ Nº ENERGISA (CITD) : 144288_x000D_ Nº DE SÉRIE : Z 267045_x000D_ MARCA : ITAM_x000D_ DATA FABRICAÇÃO : 12/2024_x000D_ IMPEDANCIA : 2.67_x000D_ POS. TAP : 03_x000D_ _x000D_ MEDIÇÃO 1: 23.26_x000D_ MEDIÇÃO 2: 16.94_x000D_ MEDIÇÃO 3: 12.91_x000D_ _x000D_ COORDENADA_x000D_ X: 768268_x000D_ Y: 9104245_x000D_ | F73: QUEIMADO | G73: DESCARGA ATMOSFÉRICA | H73: QUEIMADO | I73: DESCARGA ATMOSFÉRICA | J73: MC - SUBSTITUIÇÃO DE TRANSFORMADOR | K73: 2026 | L73: AL05020023 | M73: 5710378023 | N73: 8812 | O73: EMERGENCIAL | P73: SS ATENDIDA | Q73: 46053.506 | R73: 46054.509 | S73: 46056.506 | T73: BLOCO TRANSFORMADOR DE DISTRIBUIÇÃO | U73: COLINAS DO TOCANTINS | V73: ROBSON FERNANDO LAUERMANN RICO | W73: RURAL | X73: FORMS SUBST DE TRANSFORMADOR | Y73: TR-5710378023 Queimadopara raios queimadopotência 15kvatensão 13,8kvacesso livreequipe 023op04 tel-63984508644 | Z73: 25 | AA73: 15 | AB73: 15 | AC73: 46225.761
A74: ETO-RD-GU 00335/2026 | B74: ETO-RD-GU 000736/2026 | C74: 412600301 | E74: SS: ETO-RD-GU 335-2026_x000D_ _x000D_ LOCALIDADE: DUERE_x000D_ _x000D_ EQUIPE: ENERGISA_x000D_ _x000D_ FOI FEITO A TROCA DO TRANSFORMADOR DE 5KVA PARA 15KVA | F74: QUEIMADO | G74: NÃO IDENTIFICADO | H74: QUEIMADO | I74: SOBRECARGA | J74: MC - SUBSTITUIÇÃO DE TRANSFORMADOR | K74: 2026 | L74: LD02040003 | M74: 5710342076 | N74: 8385 | O74: EMERGENCIAL | P74: SS ATENDIDA | Q74: 46098.402 | R74: 46098.562 | S74: 46101.402 | T74: BLOCO TRANSFORMADOR DE DISTRIBUIÇÃO | U74: DUERE | V74: Wilmar Lucas Rodrigues Noleto | W74: RURAL | X74: FORMS SUBST DE TRANSFORMADOR | Y74: SEGUE SS DE TRAFO QUEIMADO NA RDR DE DUERÉ, TRAFO DE 5KVA NA REDE DE 19.9KV, PARA RAIOS QUEIMADO E ACESSO LIVRE. | Z74: 15 | AA74: 5 | AB74: 5KVA | AC74: 46225.761
A75: DG-RD-PO 00191/2026 | B75: DG-MLPO01 000044/2026 | C75: 312600153 | E75: medido__x000D_ emergencial__x000D_ _x000D_ _x000D_ Segue SS para substituiçao de TR queimado_x000D_ | F75: QUEIMADO | G75: ABALROADO | H75: QUEIMADO | I75: ABALROADO | J75: MC - SUBSTITUIÇÃO DE TRANSFORMADOR | K75: 2026 | L75: LD02059122 | M75: 5700498026 | N75: 8385 | O75: EMERGENCIAL | P75: SS ATENDIDA | Q75: 46067.783 | R75: 46068.757 | S75: 46070.783 | T75: BLOCO TRANSFORMADOR DE DISTRIBUIÇÃO | U75: PONTE ALTA DO TOCANTINS | V75: JANES FERREIRA DA SILVA | W75: RURAL | X75: FORMS SUBST DE TRANSFORMADOR | Y75: Segue SS para substituiçao de TR queimado | Z75: 15 | AA75: 15 | AB75: 15 kva | AC75: 46225.761
A76: ENC-RD-PS 00314/2026 | B76: ENC-MPPS01 000061/2026 | C76: 212600291 | E76: SS ENC-RD-PS 314/2026_x000D_ TR 5700019014_x000D_ _x000D_ _x000D_ TRAFO RETIRADO_x000D_ POTÊNCIA : 30KVA_x000D_ TENSÃO : 13.8KV_x000D_ Nº ENERGISA (CITD) : ILEGIVEL_x000D_ Nº DE SÉRIE : 182260_x000D_ MARCA : ABB_x000D_ DATA FABRICAÇÃO : 11/01_x000D_ IMPEDANCIA : 3.62_x000D_ POS. TAP : 01_x000D_ _x000D_ TRAFO INSTALADO'_x000D_ POTÊNCIA : 30KVA_x000D_ TENSÃO : 13.8KV_x000D_ Nº ENERGISA (CITD) : 135439_x000D_ Nº DE SÉRIE : 182550_x000D_ MARCA : ABB_x000D_ DATA FABRICAÇÃO : 11/01_x000D_ IMPEDANCIA : 3.50_x000D_ POS. TAP : 02_x000D_ _x000D_ _x000D_ | F76: FURTADO | G76: FURTADO | H76: FURTADO | I76: FURTADO | J76: MC - SUBSTITUIÇÃO DE TRANSFORMADOR | K76: 2026 | L76: AL01068014 | M76: 5700019014 | N76: 61993 | O76: EMERGENCIAL | P76: SS ATENDIDA | Q76: 46088.677 | R76: 46090.691 | S76: 46091.677 | T76: BLOCO TRANSFORMADOR DE DISTRIBUIÇÃO | U76: PIUM | V76: Felipe Batista Ferrreira | W76: RURAL | X76: FORMS SUBST DE TRANSFORMADOR | Y76: TR 570001901430KVATRAFO FURTADO ACESSO LIVRE CAMINHAO TENSAO 13800PARA RAIO DANIFICADO 014OP02 SERGIO | Z76: 30 | AA76: 30 | AB76: 13,8 | AC76: 46225.761
A77: ETO-RD-GR 00066/2026 | B77: ENC-MLGR02 000007/2026 | C77: 712600057 | E77: SUBSTITUIÇÃO DE UM TRAFO 5710060104 ETO-RD-GR 66/2026 FAZ. REGIÃO DO SONIN RDR DE SANTA MARIA _x000D_ _x000D_ TRAFO RETIRADO_x000D_ POTÊNCIA : 15KV_x000D_ TENSÃO : 34,5KV_x000D_ Nº ENERGISA (CITD) : 117193_x000D_ Nº DE SÉRIE : 476879_x000D_ MARCA : TRAEL_x000D_ DATA FABRICAÇÃO : 07/2018_x000D_ IMPEDANCIA : 2,92_x000D_ POS. TAP : 03_x000D_ _x000D_ TRAFO INSTALADO_x000D_ POTÊNCIA : 15KVA_x000D_ TENSÃO : 34,5KV_x000D_ Nº ENERGISA (CITD) : 149690_x000D_ Nº DE SÉRIE : C290251_x000D_ MARCA : ITAM _x000D_ DATA FABRICAÇÃO : 09/2025_x000D_ IMPEDANCIA : 3,05_x000D_ POS. TAP : 03_x000D_ _x000D_ MEDIÇÃO 1: 00,42_x000D_ MEDIÇÃO 2: 00,19 _x000D_ MEDIÇÃO 3: 00,06_x000D_ _x000D_ COORDENADA _x000D_ X: 857002 _x000D_ Y: 9017443 | F77: QUEIMADO | G77: DESCARGA ATMOSFÉRICA | H77: QUEIMADO | I77: DESCARGA ATMOSFÉRICA | J77: MC - SUBSTITUIÇÃO DE TRANSFORMADOR | K77: 2026 | L77: LD01065015 | M77: 5710060104 | N77: 8812 | O77: EMERGENCIAL | P77: SS ATENDIDA | Q77: 46034.768 | R77: 46035.514 | S77: 46037.768 | T77: BLOCO TRANSFORMADOR DE DISTRIBUIÇÃO | U77: SANTA MARIA DO TOCANTINS | V77: PAULO SERGIO CAETANO FREIRE | W77: RURAL | X77: FORMS SUBST DE TRANSFORMADOR | Y77: TRAFO 5710060104 QUEIMADO PARA RAIO TAMBÉM DE 15 KVA NA NA REDE 19,9 KV ACESSO BOM NÃO FOI FEITO TESTE AVAZIO MUITO GRANDE DE ÓLEO | Z77: 15 | AA77: 15 | AB77: 15 KVA | AC77: 46225.761
A78: ETO-RD-AG 00311/2026 | B78: ENC-MPAG02 000039/2026 | C78: 662600187 | E78: Enviar equipe da manutenção para substituir transformador queimado mais para raio, acesso normal_x000D_ _x000D_ TRAFO Nº 5710071065_x000D_ _x000D_ TRAFO RETIRADO _x000D_ _x000D_ POTÊNCIA; 15KVA 13.8KV_x000D_ DATA DE FAB; MARÇO/2019_x000D_ MARCA; TRAEL_x000D_ Nº CITD; 119229_x000D_ Nº SÉRIE; 497071_x000D_ IMPEDÂNCIA; 2,53_x000D_ _x000D_ TRAFO INSTALADO _x000D_ _x000D_ POTÊNCIA; 15KVA 13.8KV_x000D_ DATA DE FAB; 24/01/2026_x000D_ MARCA; ITAM_x000D_ Nº CITD; 150636_x000D_ Nº SÉRIE; C.299685_x000D_ IMPEDÂNCIA; 2,39_x000D_ MEDIÇÃO; 20,40 / 20,50 / 20,46_x000D_ _x000D_ | F78: QUEIMADO | G78: DESCARGA ATMOSFÉRICA | H78: QUEIMADO | I78: DESCARGA ATMOSFÉRICA | J78: MC - SUBSTITUIÇÃO DE TRANSFORMADOR | K78: 2026 | L78: AL01016065 | M78: 5710071065 | N78: 8812 | O78: EMERGENCIAL | P78: SS ATENDIDA | Q78: 46100.657 | R78: 46100.928 | S78: 46103.657 | T78: BLOCO TRANSFORMADOR DE DISTRIBUIÇÃO | U78: AXIXA DO TOCANTINS | V78: DELIO NUNES OSCAR | W78: RURAL | X78: FORMS SUBST DE TRANSFORMADOR | Y78: Enviar equipe da manutenção para substituir transformador queimado mais para raio, acesso normal | Z78: 15 | AA78: 15 | AB78: 15 | AC78: 46225.761
A79: DOLP-RD-PA 00130/2026 | B79: DLP-MPPA01 000044/2026 | C79: 112600147 | E79: MEDIDO__x000D_ _x000D_ EMERGENCIAL__x000D_ _x000D_ _x000D_ Segue SS para equipe de manutenção deslocar para executar emenda de cabo rompido no circuito do transformador 5751511059 _x000D_ RDU de Taquaralto_x000D_ _x000D_ Substituído vão de cabo do poste ID: 387290 ATÉ O ID:36056955 | F79: POSTE | G79: VEGETAÇÃO | H79: POSTE | I79: VEGETAÇÃO | J79: MC - POSTES | K79: 2026 | L79: AL03099059 | M79: 5751511059 | O79: EMERGENCIAL | P79: SS ATENDIDA | Q79: 46048.975 | R79: 46048.206 | S79: 46051.975 | T79: TRANSFORMADOR DE DISTRIBUIÇÃO ENERGISA 13.8Kv | U79: PALMAS | V79: Glauk Henrique Miranda Cardoso | W79: URBANO | X79: AVISO DE ANOMALIA | Y79: Segue SS para equipe de manutenção deslocar para executar emenda de cabo rompido no circuito do transformador 5751511059 RDU de Taquaralto | AC79: 46225.761
A80: DG-RD-PO 00051/2026 | B80: DG-MLPO02 000014/2026 | C80: 312600047 | E80: medido__x000D_ emergencial__x000D_ _x000D_ susbtituição de trafo queimado rdr porto _x000D_ | F80: QUEIMADO | G80: VAZAMENTO DE ÓLEO | J80: MC - SUBSTITUIÇÃO DE TRANSFORMADOR | K80: 2026 | L80: AL01057189 | M80: 5721219001 | N80: 8812 | O80: EMERGENCIAL | P80: SS ATENDIDA | Q80: 46035.831 | R80: 46036.758 | S80: 46038.831 | T80: BLOCO TRANSFORMADOR DE DISTRIBUIÇÃO | U80: PORTO NACIONAL | V80: ANDERSON FAZAN SOARES | W80: RURAL | X80: FORMS SUBST DE TRANSFORMADOR | Y80: TR 5721219001TR 15 KVAREDE: 13.8 KVPARA RAIO QUEIMADO ACESSO LIVRE MARIA FRANCISCA BORGES DE CASTROUC: 8/3200701-5 | Z80: 25 | AA80: 10 | AB80: 15 KVA | AC80: 46225.761
A81: ENC-RD-PS 00179/2026 | B81: ENC-LMPS03 000034/2026 | C81: 212600161 | E81: SS ENC-RD-PS 179/2026_x000D_ trafo 5710011013 _x000D_ _x000D_ _x000D_ TRAFO RETIRADO_x000D_ POTÊNCIA : 5KVA_x000D_ TENSÃO : 34.5KV_x000D_ Nº ENERGISA (CITD) : 007192_x000D_ Nº DE SÉRIE : 178967_x000D_ MARCA : VIJAI_x000D_ DATA FABRICAÇÃO : 09/2010_x000D_ IMPEDANCIA : 3.11_x000D_ POS. TAP : 03_x000D_ _x000D_ TRAFO INSTALADO'_x000D_ POTÊNCIA : 15KVA_x000D_ TENSÃO : 34.5KV_x000D_ Nº ENERGISA (CITD) : 114647_x000D_ Nº DE SÉRIE : 469918_x000D_ MARCA : TRAEL_x000D_ DATA FABRICAÇÃO : 2018_x000D_ IMPEDANCIA : 3.16_x000D_ POS. TAP : 03_x000D_ | F81: QUEIMADO | G81: DESCARGA ATMOSFÉRICA | H81: QUEIMADO | I81: DESCARGA ATMOSFÉRICA | J81: MC - SUBSTITUIÇÃO DE TRANSFORMADOR | K81: 2026 | L81: LD03062013 | M81: 5710011013 | N81: 8812 | O81: EMERGENCIAL | P81: SS ATENDIDA | Q81: 46055.654 | R81: 46057.965 | S81: 46058.654 | T81: BLOCO TRANSFORMADOR DE DISTRIBUIÇÃO | U81: PARAISO DO TOCANTINS | V81: THIAGO BORGES DE OLIVEIRA | W81: RURAL | X81: FORMS SUBST DE TRANSFORMADOR | Y81: Segue ss para tratativa com equipe de manutençao o quanto antes substituir trafo 5710011013 na rdr de paraiso | Z81: 15 | AA81: 5 | AB81: 15 | AC81: 46225.761
A82: ETO-RD-GU 00248/2026 | B82: DBM-MLDB03 000046/2026 | C82: 412600232 | E82: SUBSTITUIÇÃO DE TRANSFORMADOR NA RDR DE ARAGUAÇU_x000D_ _x000D_ INT: 20264133423658_x000D_ _x000D_ SS: ETO-RD-GU 248/2026_x000D_ _x000D_ ESPECIFICAÇÕES DO TRANSFORMADOR_x000D_ _x000D_ TRANSFORMADOR INSTALADO: 15 KVA_x000D_ _x000D_ TRANSFORMADOR RETIRADO: 15 KVA_x000D_ _x000D_ MEDIÇÕES_x000D_ _x000D_ LOGO APÓS A TROCA _x000D_ _x000D_ VAN: 206_x000D_ _x000D_ OBS:SUBSTITUIÇÃO DE TRANSFORMADOR AUTORIZADA PELO DIONE._x000D_ | F82: QUEIMADO | G82: DESCARGA ATMOSFÉRICA | H82: QUEIMADO | I82: DESCARGA ATMOSFÉRICA | J82: MC - SUBSTITUIÇÃO DE TRANSFORMADOR | K82: 2026 | L82: LD01010021 | M82: 5356618021 | N82: 8812 | O82: EMERGENCIAL | P82: SS ATENDIDA | Q82: 46076.659 | R82: 46077.773 | S82: 46079.659 | T82: BLOCO TRANSFORMADOR DE DISTRIBUIÇÃO | U82: PARANA | V82: HELDER SILVA CARVALHO | W82: RURAL | X82: FORMS SUBST DE TRANSFORMADOR | Y82: Transformador queimado 5356618021, tensão 19.9, potencia 15kva, para raio queimado, acesso caminhão e camionete, causa descarga atmosférica, feito teste a vazio não aceitou.IND FAZENDA ESPIRITO SANTO, equipe 021op01 telefone 63991010212, cliente 63984875148 | Z82: 15 | AA82: 15 | AB82: 15kva | AC82: 46225.761
A83: ETO-RD-AR 00709/2026 | B83: ENC-MLAR05 000196/2026 | C83: 612600430 | E83: ETO-RD-AR 709/2026_x000D_ TRAFO 5710154053_x000D_ TRAFO RETIRADO_x000D_ POTÊNCIA :10 KVA_x000D_ TENSÃO : 34.5 KV_x000D_ Nº ENERGISA (CITD) : 9540_x000D_ Nº DE SÉRIE : 359351_x000D_ MARCA : ITB_x000D_ DATA FABRICAÇÃO : 10/2005_x000D_ IMPEDANCIA : 2,82_x000D_ POS. TAP : 03_x000D_ _x000D_ TRAFO INSTALADO_x000D_ POTÊNCIA : 15 KVA_x000D_ TENSÃO : 34.5 KV_x000D_ Nº ENERGISA (CITD) : 150364_x000D_ Nº DE SÉRIE : 828087_x000D_ MARCA : TRAEL_x000D_ DATA FABRICAÇÃO : 02/2026_x000D_ IMPEDANCIA : 3,0_x000D_ POS. TAP : 05_x000D_ _x000D_ MEDIÇÃO 1: 7.09_x000D_ MEDIÇÃO 2: 6.77_x000D_ MEDIÇÃO 3: 6.41_x000D_ | F83: AVARIADO | G83: VAZAMENTO DE ÓLEO | H83: AVARIADO | I83: SOBRECARGA | J83: MC - SUBSTITUIÇÃO DE TRANSFORMADOR | K83: 2026 | L83: LD02010004 | M83: 5710154053 | N83: 25962 | O83: EMERGENCIAL | P83: SS ATENDIDA | Q83: 46132.734 | R83: 46134.503 | S83: 46135.734 | T83: BLOCO TRANSFORMADOR DE DISTRIBUIÇÃO | U83: PIRAQUE | V83: ADRIANO DE SOUSA GOMES | W83: RURAL | X83: FORMS SUBST DE TRANSFORMADOR | Y83: VAZAMENTO DE ÓLEOTrafo 5710154053Rdr de Piraquê10kva34.5kvAcesso livre | Z83: 15 | AA83: 10 | AB83: 10KVA | AC83: 46225.761
A84: ETO-RD-GR 00283/2026 | B84: ETO-RD-GR 000381/2026 | C84: 712600183 | E84: Trafo: 5747077064 queimado _x000D_ Potencia: 25 KVA_x000D_ Tensão: 34,5 KV_x000D_ Para raio: queimado _x000D_ Acesso: livre _x000D_ Equipe: 023op01 (63)99987-1478 | F84: QUEIMADO | G84: DESCARGA ATMOSFÉRICA | H84: QUEIMADO | I84: DESCARGA ATMOSFÉRICA | J84: MC - SUBSTITUIÇÃO DE TRANSFORMADOR | K84: 2026 | L84: LD02020023 | M84: 5747077064 | N84: 8812 | O84: EMERGENCIAL | P84: SS ATENDIDA | Q84: 46078.586 | R84: 46079.654 | S84: 46081.586 | T84: BLOCO TRANSFORMADOR DE DISTRIBUIÇÃO | U84: BRASILANDIA DO TOCANTINS | V84: STANLEY APARECIDO DO CARMO | W84: RURAL | X84: FORMS SUBST DE TRANSFORMADOR | Y84: Trafo: 5747077064 queimado Potencia: 25 KVATensão: 34,5 KVPara raio: queimado Acesso: livre Equipe: 023op01 (63)99987-1478 | AB84: 25 KVA | AC84: 46225.761
A85: ETO-RD-AR 00268/2026 | B85: ENC-MLAR01 000077/2026 | C85: 612600167 | E85: SS ETO-RD-AR 268/2026_x000D_ TRAFO 5700382016_x000D_ _x000D_ _x000D_ _x000D_ TRAFO RETIRADO_x000D_ POTÊNCIA : 15KVA_x000D_ TENSÃO : 34.5KV_x000D_ Nº ENERGISA (CITD) : 145435_x000D_ Nº DE SÉRIE : 179561_x000D_ MARCA : TRAEL_x000D_ DATA FABRICAÇÃO : 02/2002_x000D_ IMPEDANCIA : 2.98_x000D_ POS. TAP : 03_x000D_ _x000D_ TRAFO INSTALADO'_x000D_ POTÊNCIA : 15KVA_x000D_ TENSÃO : 34.5KV_x000D_ Nº ENERGISA (CITD) : 149197_x000D_ Nº DE SÉRIE : 820183_x000D_ MARCA : TRAEL_x000D_ DATA FABRICAÇÃO : NOV/2025_x000D_ IMPEDANCIA : 3.0_x000D_ POS. TAP : 03_x000D_ | F85: QUEIMADO | G85: DESCARGA ATMOSFÉRICA | H85: QUEIMADO | I85: DESCARGA ATMOSFÉRICA | J85: MC - SUBSTITUIÇÃO DE TRANSFORMADOR | K85: 2026 | L85: LD01095030 | M85: 5700382016 | N85: 8812 | O85: EMERGENCIAL | P85: SS ATENDIDA | Q85: 46061.473 | R85: 46062.774 | S85: 46064.473 | T85: BLOCO TRANSFORMADOR DE DISTRIBUIÇÃO | U85: WANDERLANDIA | V85: LEANDRO BISPO DE BARROS | W85: RURAL | X85: FORMS SUBST DE TRANSFORMADOR | Y85: trafo queimado, caiu uma descarga no mesmo pararaio queimado | Z85: 15 | AA85: 15 | AB85: 15kva | AC85: 46225.761
A86: ETO-RD-DP 00094/2026 | B86: ETO-MLDP01 000045/2026 | C86: 512600072 | E86: Conforme informações da equipe 005OP01 , segeu SS de transformador 5700486005 queimado , 10KVA na 19.9KV | F86: QUEIMADO | G86: DESCARGA ATMOSFÉRICA | H86: QUEIMADO | I86: DESCARGA ATMOSFÉRICA | J86: MC - SUBSTITUIÇÃO DE TRANSFORMADOR | K86: 2026 | L86: LD01110005 | M86: 5700486005 | N86: 8812 | O86: EMERGENCIAL | P86: SS ATENDIDA | Q86: 46057.551 | R86: 46058.729 | S86: 46060.551 | T86: TRANSFORMADOR DE DISTRIBUIÇÃO ENERGISA 19.919Kv | U86: ARRAIAS | V86: IZAIAS SANTOS BRAGA JUNIOR | W86: RURAL | X86: FORMS SUBST DE TRANSFORMADOR | Y86: Conforme informações da equipe 005OP01 , segeu SS de transformador 5700486005 queimado , 10KVA na 19.9KV | Z86: 15 | AA86: 10 | AB86: 10 | AC86: 46225.761
A87: ETO-RD-DP 00114/2026 | B87: ETO-RD-DP 000177/2026 | C87: 512600073 | E87: SUBSTITUIÇÃO DE TRANSFORMADOR NA RDR_x000D_ _x000D_ POSTO TRANFORMADOR: 5710140028 _x000D_ _x000D_ SS: ETO-RD-DP 114/2026_x000D_ _x000D_ _x000D_ POT. TRANSFORMADOR RETIRADO: 15 KVA_x000D_ _x000D_ _x000D_ _x000D_ _x000D_ POT. TRANSFORMADOR INSTALADO: 15 KVA | F87: QUEIMADO | G87: NÃO IDENTIFICADO | H87: QUEIMADO | I87: NÃO IDENTIFICADO | J87: MC - SUBSTITUIÇÃO DE TRANSFORMADOR | K87: 2026 | L87: LD04002091 | M87: 5710140028 | N87: 8812 | O87: EMERGENCIAL | P87: SS ATENDIDA | Q87: 46060.643 | R87: 46061.604 | S87: 46063.643 | T87: TRANSFORMADOR DE DISTRIBUIÇÃO ENERGISA 34.5Kv | U87: NATIVIDADE | V87: IZAIAS SANTOS BRAGA JUNIOR | W87: RURAL | X87: FORMS SUBST DE TRANSFORMADOR | Y87: Segue SS do transformador 5710140028 queimado ,15KVA na 19.9 KV | Z87: 15 | AA87: 15 | AB87: 15 | AC87: 46225.761
A88: ETO-RD-AG 00104/2026 | B88: ETO-RD-AG 000073/2026 | C88: 662600065 | E88: transformador furtado 5700150156 potencia 5kva tensão 19.9kv acesso livre leva chave fusivel a mesma foi furtada eleva cabo para junper e glv leva para-raio_x000D_ equipe: 6399616867_x000D_ SS -ETO-RD-AG 00104/2026_x000D_ _x000D_ _x000D_ TRAFO INSTALADO_x000D_ _x000D_ POTÊNCIA; 15KVA 34,5KV_x000D_ DATA DE FAB; OUT/2025_x000D_ MARCA; TRAEL_x000D_ Nº CITD; 149112_x000D_ Nº SÉRIE; 799461_x000D_ IMPEDEÂNCIA; 3,0_x000D_ MEDIÇÃO; 5,61 / 7,60 / 6,65 | F88: FURTADO | G88: FURTADO | H88: FURTADO | I88: FURTADO | J88: MC - SUBSTITUIÇÃO DE TRANSFORMADOR | K88: 2026 | L88: LD03005098 | M88: 5700150156 | N88: 61993 | O88: EMERGENCIAL | P88: SS ATENDIDA | Q88: 46049.554 | R88: 46050.016 | S88: 46052.554 | T88: BLOCO TRANSFORMADOR DE DISTRIBUIÇÃO | U88: CACHOEIRINHA | V88: EZEQUIEL CAVALCANTE DOS SANTOS | W88: RURAL | X88: FORMS SUBST DE TRANSFORMADOR | Y88: transformador furtado 5700150156 potencia 5kva tensão 19.9kv acesso livre leva chave fusivel a mesma foi furtada eleva cabo para junper e glv leva para-raioequipe: 6399616867 | Z88: 15 | AB88: 5kva | AC88: 46225.761
A89: DG-RD-PO 00303/2026 | B89: DG-MLPO01 000066/2026 | C89: 312600234 | E89: medido__x000D_ emergencial__x000D_ _x000D_ _x000D_ substituição de trafo queimado rdr porto_x000D_ | F89: QUEIMADO | G89: NÃO IDENTIFICADO | J89: MC - SUBSTITUIÇÃO DE TRANSFORMADOR | K89: 2026 | L89: LD01072001 | M89: 5710210001 | N89: 8812 | O89: EMERGENCIAL | P89: SS ATENDIDA | Q89: 46114.459 | R89: 46114.717 | S89: 46117.459 | T89: BLOCO TRANSFORMADOR DE DISTRIBUIÇÃO | U89: PORTO NACIONAL | V89: HERBSON DE AMORIM GOMES | W89: RURAL | X89: FORMS SUBST DE TRANSFORMADOR | Y89: TRAFO 5710210001 E PARA RAIO QUEIMADO POTENCI: 45KVA 34500ACESSO: LIVRE | Z89: 45 | AA89: 45 | AB89: 45KVA | AC89: 46225.761
A90: DG-RD-PO 00311/2026 | B90: DG-MLPO02 000058/2026 | C90: 312600246 | E90: medido__x000D_ emergencial__x000D_ _x000D_ _x000D_ substituição de trafo queimado rdr santa rosa_x000D_ | F90: QUEIMADO | G90: DESCARGA ATMOSFÉRICA | J90: MC - SUBSTITUIÇÃO DE TRANSFORMADOR | K90: 2026 | L90: AL01026041 | M90: 5710213110 | N90: 8812 | O90: EMERGENCIAL | P90: SS ATENDIDA | Q90: 46119.766 | R90: 46120.686 | S90: 46122.766 | T90: BLOCO TRANSFORMADOR DE DISTRIBUIÇÃO | U90: SANTA RITA DO TOCANTINS | V90: Leonardo Oliveira Bezerra Mato | W90: RURAL | X90: FORMS SUBST DE TRANSFORMADOR | Y90: Segue SS de trafo 5710213110 queimado para devidas trativas com equipé de manutenção.Potencia 15 kvaTensão 13,8 kv aceso livre para raio queimado | Z90: 15 | AA90: 15 | AB90: 15 KVA | AC90: 46225.761
A91: DG-RD-PO 00378/2026 | B91: DG-MLPO02 000071/2026 | C91: 312600308 | E91: medido__x000D_ emergencial__x000D_ _x000D_ substituição de trafo queimado rdr pindorama_x000D_ | F91: QUEIMADO | G91: DESCARGA ATMOSFÉRICA | J91: MC - SUBSTITUIÇÃO DE TRANSFORMADOR | K91: 2026 | L91: LD03046026 | M91: 5700698096 | N91: 8812 | O91: EMERGENCIAL | P91: SS ATENDIDA | Q91: 46156.485 | R91: 46157.683 | S91: 46159.485 | T91: BLOCO TRANSFORMADOR DE DISTRIBUIÇÃO | U91: PINDORAMA DO TOCANTINS | V91: JANES FERREIRA DA SILVA | W91: RURAL | X91: FORMS SUBST DE TRANSFORMADOR | Y91: segue SS para susbtituição de TR queimado 5700698096 | Z91: 15 | AA91: 5 | AB91: 15 kva | AC91: 46225.761
A92: ETO-RD-AG 00589/2026 | B92: ENC-MPAG02 000094/2026 | C92: 662600371 | E92: TRAFO 5700301068 QUEIMADO DE 15KVA DA 19.9. PARA RAIOS QUEMADO. ACESSO BOM. 19 CLIENTES PENALIZADO._x000D_ _x000D_ TRAFO Nº 5700301068_x000D_ _x000D_ TRAOF RETIRADO_x000D_ _x000D_ POTÊNCIA; 15KVA 34,5KV_x000D_ DATA DE FAB; 06/1999_x000D_ MARCA; TOSHIBA_x000D_ Nº CITD; N/A_x000D_ Nº SÉRIE; 368215_x000D_ POS. DO TAP; 1º_x000D_ IMPEDÂNCIA; 3,0_x000D_ _x000D_ TRAFO INSTALADO _x000D_ _x000D_ POTÊNCIA; 25KVA 34,5KV_x000D_ DATA DE FAB; 23/02/2026_x000D_ MARCA; ITAM_x000D_ Nº CITD; 151002_x000D_ Nº SÉRIE; Z.303122_x000D_ POS. DO TAP; 3º_x000D_ IMPEDÂNCIA; 2,75_x000D_ MEDIÇÃO; 14,77 / 14,56/ 14,46 | F92: QUEIMADO | G92: VAZAMENTO DE ÓLEO | H92: QUEIMADO | I92: VAZAMENTO DE ÓLEO | J92: MC - SUBSTITUIÇÃO DE TRANSFORMADOR | K92: 2026 | L92: LD02109039 | M92: 5700301068 | N92: 8812 | O92: EMERGENCIAL | P92: SS ATENDIDA | Q92: 46185.731 | R92: 46186.008 | S92: 46188.731 | T92: BLOCO TRANSFORMADOR DE DISTRIBUIÇÃO | U92: BURITI DO TOCANTINS | V92: GERALDO JOSE DE FARIA | W92: RURAL | X92: FORMS SUBST DE TRANSFORMADOR | Y92: TRAFO 5700301068 QUEIMADO DE 15KVA DA 19.9. PARA RAIOS QUEMADO. ACESSO BOM. 19 CLIENTES PENALIZADO. | Z92: 25 | AA92: 15 | AB92: 15 | AC92: 46225.761
A93: ETO-RD-AG 00419/2026 | B93: ENC-MPAG01 000164/2026 | C93: 662600279 | E93: Troca de poste de BT , Rede de BT cabo nu. Fica na Rua mariquina marinho, circuito do trafo. 5700010081.Após entrar na Rua fica a quarta estrutura lado esquerdo. Situação da estrutura critica_x000D_ _x000D_ obs. Solicitação equipe 81OP01, fone 63985124414._x000D_ _x000D_ _x000D_ --->NOTA AC_x000D_ SUBST 01 POSTE 09/150 S1 POR UM POSTE 10/150 S1 ID-67116962._x000D_ ( POSTE ANTES ID-67117077 - POSTE DEPOIS ID-67116957 ). | F93: AVARIADO | G93: ABALROADO | H93: AVARIADO | J93: MC - POSTES | K93: 2026 | L93: AL01043081 | M93: 5700010081 | N93: 20497 | O93: URGENTE | P93: SS ATENDIDA | Q93: 46132.73 | R93: 46139.674 | S93: 46139.73 | T93: BLOCO TRANSFORMADOR DE DISTRIBUIÇÃO | U93: ITAGUATINS | V93: GERALDO JOSE DE FARIA | W93: URBANO | X93: AVISO DE ANOMALIA | Y93: Troca de poste de BT , Rede de BT cabo nu. Fica na Rua mariquina marinho, circuito do trafo. 5700010081.Após entrar na Rua fica a quarta estrutura lado esquerdo. Situação da estrutura criticaobs. Solicitação equipe 81OP01, fone 63985124414. | AC93: 46225.761
A94: ENC-RD-PS 00509/2026 | B94: ENC-LMPS03 000083/2026 | C94: 212600478 | E94: SS ENC-RD-PS 509/2026_x000D_ TR 5710276149_x000D_ _x000D_ _x000D_ _x000D_ TRAFO RETIRADO_x000D_ POTÊNCIA : 15KVA_x000D_ TENSÃO : 34.5KV_x000D_ Nº ENERGISA (CITD) : ILEGIVEL_x000D_ Nº DE SÉRIE : 296216_x000D_ MARCA : ITB_x000D_ DATA FABRICAÇÃO : 11/2004_x000D_ IMPEDANCIA : 3.09_x000D_ POS. TAP : 02_x000D_ _x000D_ TRAFO INSTALADO'_x000D_ POTÊNCIA : 15KVA_x000D_ TENSÃO : 34.5KV _x000D_ Nº ENERGISA (CITD) : 150761_x000D_ Nº DE SÉRIE : 799421_x000D_ MARCA : TRAEL_x000D_ DATA FABRICAÇÃO : 10/2025_x000D_ IMPEDANCIA : 3.0_x000D_ POS. TAP : 03_x000D_ | F94: QUEIMADO | G94: NÃO IDENTIFICADO | H94: QUEIMADO | I94: NÃO IDENTIFICADO | J94: MC - SUBSTITUIÇÃO DE TRANSFORMADOR | K94: 2026 | L94: LD03414149 | M94: 5710276149 | N94: 8812 | O94: EMERGENCIAL | P94: SS ATENDIDA | Q94: 46154.766 | R94: 46156.735 | S94: 46157.766 | T94: BLOCO TRANSFORMADOR DE DISTRIBUIÇÃO | U94: CASEARA | V94: Felipe Batista Ferrreira | W94: RURAL | X94: FORMS SUBST DE TRANSFORMADOR | Y94: TR 571027614915KVAPARA RAIO QUEIMADO ACESSO PARA CAMINHONETE TENSAO 34,5149PO02 | Z94: 15 | AA94: 15 | AB94: 15KVA | AC94: 46225.761
A95: ETO-RD-GR 00563/2026 | B95: ENC-MLGR01 000146/2026 | C95: 712600379 | E95: TROCA DE TRAFO QUEIMADO 5710064087 ETO-RD-GR 563/2026 ZONA RURAL - GOIANORTE 0087_x000D_ _x000D_ TRAFO RETIRADO_x000D_ POTÊNCIA : 15KVA_x000D_ TENSÃO : 19.9KV _x000D_ Nº ENERGISA (CITD) : CITD06114311_x000D_ Nº DE SÉRIE : 469582_x000D_ MARCA : TRAEL_x000D_ DATA FABRICAÇÃO : 05/2018_x000D_ IMPEDANCIA : 2.98_x000D_ POS. TAP : 01_x000D_ _x000D_ TRAFO INSTALADO_x000D_ POTÊNCIA : 15KVA_x000D_ TENSÃO : 19.9KV _x000D_ Nº ENERGISA (CITD) : 151701_x000D_ Nº DE SÉRIE : C 308270_x000D_ MARCA : ITAM_x000D_ DATA FABRICAÇÃO : 04/2026_x000D_ IMPEDANCIA : 3.19_x000D_ POS. TAP : 03_x000D_ _x000D_ MEDIÇÃO 1: 19.75_x000D_ MEDIÇÃO 2: 16.03_x000D_ MEDIÇÃO 3: 12.12_x000D_ _x000D_ COORDENADA_x000D_ X: 727477_x000D_ Y: 9020328_x000D_ | F95: QUEIMADO | G95: DESCARGA ATMOSFÉRICA | H95: QUEIMADO | I95: DESCARGA ATMOSFÉRICA | J95: MC - SUBSTITUIÇÃO DE TRANSFORMADOR | K95: 2026 | L95: LD02022033 | M95: 5710064087 | N95: 8812 | O95: EMERGENCIAL | P95: SS ATENDIDA | Q95: 46169.39 | R95: 46170.501 | S95: 46172.39 | T95: BLOCO TRANSFORMADOR DE DISTRIBUIÇÃO | U95: GOIANORTE | V95: CLEIBER DA SILVA | W95: RURAL | X95: FORMS SUBST DE TRANSFORMADOR | Y95: trafo 5710064087 queimado acesso livre equipe 087op01 | Z95: 15 | AA95: 15 | AB95: 15 | AC95: 46225.761
A96: DG-RD-PO 00449/2026 | B96: DG-MPDG01 000114/2026 | C96: 312600359 | E96: medido__x000D_ emergencial__x000D_ _x000D_ _x000D_ substituiçaõ de trafo furtado rdr ipueiras_x000D_ | F96: FURTADO | G96: FURTADO | J96: MC - SUBSTITUIÇÃO DE TRANSFORMADOR | K96: 2026 | L96: LD02072001 | M96: 5700396250 | N96: 61993 | O96: EMERGENCIAL | P96: SS ATENDIDA | Q96: 46209.759 | R96: 46210.833 | S96: 46212.759 | T96: TRANSFORMADOR SEM BAIXA TENSAO 19919V | U96: IPUEIRAS | V96: JORGE BOAZ FERREIRA SOUSA DA S | X96: FORMS SUBST DE TRANSFORMADOR | Y96: Segue SS para atendimento com equipe de manutenção , instalar trafo 5700396250 FURTADO na RDR de impueiras , tensão 34,5 , acesso livre , . para-raio furtado , potencia 15 kva | Z96: 15 | AA96: 15 | AB96: 15 KVA | AC96: 46225.761
A97: ENC-RD-PS 00016/2026 | B97: ENC-LMPS04 000003/2026 | C97: 212600054 | E97: SS ENC-RD-PS 16/2026_x000D_ TRAFO 5710042046 _x000D_ _x000D_ _x000D_ _x000D_ _x000D_ _x000D_ _x000D_ TRAFO RETIRADO_x000D_ POTÊNCIA : 15KVA_x000D_ TENSÃO : 34.5KV_x000D_ Nº ENERGISA (CITD) : 06897_x000D_ Nº DE SÉRIE : 373581_x000D_ MARCA : TOSHIBA_x000D_ DATA FABRICAÇÃO : 03/2000_x000D_ IMPEDANCIA : 3_x000D_ POS. TAP : 01_x000D_ _x000D_ TRAFO INSTALADO'_x000D_ POTÊNCIA : 25KVA_x000D_ TENSÃO : 34.5KV_x000D_ Nº ENERGISA (CITD) : 144379_x000D_ Nº DE SÉRIE : Z260738_x000D_ MARCA : ITAM_x000D_ DATA FABRICAÇÃO : 12/2024_x000D_ IMPEDANCIA : 3.17_x000D_ POS. TAP : 03_x000D_ | F97: FURTADO | G97: VANDALISMO | H97: FURTADO | I97: VANDALISMO | J97: MC - SUBSTITUIÇÃO DE TRANSFORMADOR | K97: 2026 | L97: LD01056046 | M97: 5710042046 | N97: 61993 | O97: EMERGENCIAL | P97: SS ATENDIDA | Q97: 46027.616 | R97: 46029.743 | S97: 46030.616 | T97: BLOCO TRANSFORMADOR DE DISTRIBUIÇÃO | U97: OLIVEIRA DE FATIMA | V97: HERBSON DE AMORIM GOMES | W97: RURAL | X97: FORMS SUBST DE TRANSFORMADOR | Y97: SS PARA TRAFO 5710042046 FUTADO POTENCIA: 15KVAACESSO: LIVRE | Z97: 25 | AA97: 15 | AB97: 15KVA | AC97: 46225.761
A98: ETO-RD-DP 00162/2026 | B98: ETO-MLDP02 000069/2026 | C98: 512600088 | E98: Esquema de Serviço para Apoio a Obra de Construção. | F98: SOBRECARGA PREVENTIVA | G98: NÃO IDENTIFICADO | H98: QUEIMADO | I98: DESCARGA ATMOSFÉRICA | J98: MC - SUBSTITUIÇÃO DE TRANSFORMADOR | K98: 2026 | L98: LD04002091 | M98: 5710072028 | N98: 8385 | O98: EMERGENCIAL | P98: SS ATENDIDA | Q98: 46081.571 | R98: 46082.562 | S98: 46084.571 | T98: BLOCO TRANSFORMADOR DE DISTRIBUIÇÃO | U98: NATIVIDADE | V98: DIONES COSTA SILVA | W98: RURAL | X98: FORMS SUBST DE TRANSFORMADOR | Y98: SEGUE SS PARA SUBSTITUIR TRAFO DEVIDO REICIDENCIA (O MESMO ESTA DESARMENDO TODOS OS DIAS GERANDO INSATISFAÇÃO DO CLIENTE SEGUNDO A EQUIPE 028OP01 SOLICITANTE DA SUBSTITUIÇÃO) | Z98: 15 | AA98: 15 | AB98: 15 kVA_x000D_ | AC98: 46225.761
A99: DOLP-RD-PA 00070/2026 | B99: DLP-MLPA01 000010/2026 | C99: 112600276 | E99: MEDIDO__x000D_ _x000D_ EMERGENCIAL__x000D_ _x000D_ segue nota de trafo queimado, trafo 5710112006, trafo de 15kva, tensao 34500 / 440 V, para raio danificado, acesso livre, rural de tocantinia proximo_x000D_ a palminha_x000D_ _x000D_ _x000D_ DADOS ATENDIMENTO_x000D_ EQUIPE PALM05M_x000D_ LIDER - ALVARO MELO_x000D_ CONTATO - (63) 99295-6812_x000D_ SS DOLP-RD-PA 070/2026_x000D_ DATA ATENDIMENTO: 15/01/2026_x000D_ _x000D_ | F99: QUEIMADO | G99: DESCARGA ATMOSFÉRICA | H99: QUEIMADO | I99: DESCARGA ATMOSFÉRICA | J99: MC - SUBSTITUIÇÃO DE TRANSFORMADOR | K99: 2026 | L99: LD03059122 | M99: 5710112006 | N99: 8812 | O99: EMERGENCIAL | P99: SS ATENDIDA | Q99: 46036.911 | R99: 46037.684 | S99: 46039.911 | T99: BLOCO TRANSFORMADOR DE DISTRIBUIÇÃO | U99: TOCANTINIA | V99: MARCO ANTONIO LOURENCO CAMPOS | W99: RURAL | X99: FORMS SUBST DE TRANSFORMADOR | Y99: segue nota de trafo queimado, trafo 5710112006, trafo de 15kva, tensao 34500 / 440 V, para raio danificado, acesso livre, rural de tocantinia proximo a palminha | Z99: 15 | AA99: 15 | AB99: 15KVA | AC99: 46225.761
A100: ETO-RD-GU 00342/2026 | B100: DBM-MLDB06 000048/2026 | C100: 412600321 | E100: SUBSTITUIÇÃO DE TRANSFORMADOR NA RDR DE SÃO VALERIO_x000D_ _x000D_ INT: 20264182450013_x000D_ _x000D_ SS: ETO-RD-GU 342/2026_x000D_ _x000D_ ESPECIFICAÇÕES DO TRANSFORMADOR_x000D_ _x000D_ TRANSFORMADOR INSTALADO: 15 KVA_x000D_ _x000D_ TRANSFORMADOR RETIRADO: 15 KVA_x000D_ _x000D_ MEDIÇÕES_x000D_ _x000D_ LOGO APÓS A TROCA _x000D_ _x000D_ VAN: 216_x000D_ _x000D_ VBN: 216_x000D_ _x000D_ OBS:SUBSTITUIÇÃO DE TRANSFORMADOR AUTORIZADA PELO DIONE._x000D_ | F100: QUEIMADO | G100: NÃO IDENTIFICADO | H100: QUEIMADO | I100: NÃO IDENTIFICADO | J100: MC - SUBSTITUIÇÃO DE TRANSFORMADOR | K100: 2026 | L100: LD01066094 | M100: 5300800148 | N100: 8812 | O100: EMERGENCIAL | P100: SS ATENDIDA | Q100: 46099.459 | R100: 46103.295 | S100: 46102.459 | T100: BLOCO TRANSFORMADOR DE DISTRIBUIÇÃO | U100: SAO VALERIO | V100: Wilmar Lucas Rodrigues Noleto | W100: RURAL | X100: FORMS SUBST DE TRANSFORMADOR | Y100: SEGUE SS DE TRAFO QUEIMADO NA RDR DE SAO VALERIO, TRAFO DE 15KVA REDE 19.9KV E PARA RAIOS QUEIMADO, ACESSO LIVRE | Z100: 15 | AA100: 15 | AB100: 15KVA | AC100: 46225.761
A101: ETO-RD-GU 00379/2026 | B101: DBM-MLDB04 000082/2026 | C101: 412600321 | E101: TRAFO 5701027021 COM VAZAMENTO DE OLEO BUCHA SENCUNDARIA DO TRAFO ACESSO CAMIONETE DE 15 KVA TENSÃO 19.9 KV PARA RAIO QUEIMADO ._x000D_ TRAFO REINCIDENTE EM ABERTURA EM CAMPO_x000D_ _x000D_ _x000D_ COLAGEM DE TRANSFORMADOR NA RDR DE PARANÃ_x000D_ _x000D_ INT: S/N_x000D_ _x000D_ SS: ETO-RD-GU 379/2026_x000D_ _x000D_ COMPLEMENTO: 190-13678275 | F101: AVARIADO | G101: VAZAMENTO DE ÓLEO | H101: AVARIADO | I101: VAZAMENTO DE ÓLEO | J101: MC - OBJETO ESTRANHO | K101: 2026 | L101: LD01066094 | M101: 5701027021 | N101: 8812 | O101: EMERGENCIAL | P101: SS ATENDIDA | Q101: 46104.852 | R101: 46105.5 | S101: 46107.852 | T101: BLOCO TRANSFORMADOR DE DISTRIBUIÇÃO | U101: PARANA | V101: JURANDY GOMES DE OLIVEIRA | W101: RURAL | X101: SOLICITAÇÃO DE SERVIÇO | Y101: TRAFO 5701027021 COM VAZAMENTO DE OLEO BUCHA SENCUNDARIA DO TRAFO ACESSO CAMIONETE DE 15 KVA TENSÃO 19.9 KV PARA RAIO QUEIMADO .TRAFO REINCIDENTE EM ABERTURA EM CAMPO | Z101: 15 | AB101: 15 | AC101: 46225.761
A102: ETO-RD-GR 00063/2026 | B102: ENC-MLGR03 000021/2026 | C102: 712600050 | E102: SUBSTITUIÇÃO DE TRAFO 5720187009 ETO-RD-GR 63/2026 GUARAI _x000D_ _x000D_ TRAFO RETIRADO_x000D_ POTÊNCIA : 15KVA_x000D_ TENSÃO : 13,8KV_x000D_ Nº ENERGISA (CITD) : 128656_x000D_ Nº DE SÉRIE : 577013_x000D_ MARCA : TRAEL_x000D_ DATA FABRICAÇÃO : 05/2021_x000D_ IMPEDANCIA : 2,5_x000D_ POS. TAP : 04_x000D_ _x000D_ TRAFO INSTALADO_x000D_ POTÊNCIA : 15KVA_x000D_ TENSÃO : 13,8KV_x000D_ Nº ENERGISA (CITD) : 148444_x000D_ Nº DE SÉRIE : C289608_x000D_ MARCA : ITAM_x000D_ DATA FABRICAÇÃO : 09/2025_x000D_ IMPEDANCIA : 2,49_x000D_ POS. TAP : 03_x000D_ _x000D_ MEDIÇÃO 1: 00,36_x000D_ MEDIÇÃO 2: 00,30_x000D_ MEDIÇÃO 3: 00,11_x000D_ _x000D_ COORDENADA _x000D_ X: 776636 _x000D_ Y: 9020277 | F102: QUEIMADO | G102: DESCARGA ATMOSFÉRICA | H102: QUEIMADO | I102: DESCARGA ATMOSFÉRICA | J102: MC - SUBSTITUIÇÃO DE TRANSFORMADOR | K102: 2026 | L102: AL03037009 | M102: 5720187009 | N102: 8812 | O102: EMERGENCIAL | P102: SS ATENDIDA | Q102: 46034.514 | R102: 46034.816 | S102: 46037.514 | T102: BLOCO TRANSFORMADOR DE DISTRIBUIÇÃO | U102: GUARAI | V102: STANLEY APARECIDO DO CARMO | W102: RURAL | X102: FORMS SUBST DE TRANSFORMADOR | Y102: Trafo: 5720187009 Queimado Potencia: 15 KVATensão: 13,8 KVPara raio: queimado Acesso: Livre Equipe: 009op08 (63)99942-6789 | Z102: 15 | AA102: 15 | AB102: 15 KVA | AC102: 46225.761
A103: ETO-RD-GR 00376/2026 | B103: ENC-MLGR03 000134/2026 | C103: 712600264 | E103: TROCA DE TRAFO QUEIMADO 5710034155 ETO-RD-GR 376/2026 FAZ. NOVA ESPERANÇA - PALMEIRANTE 0155_x000D_ _x000D_ TRAFO RETIRADO_x000D_ POTÊNCIA : 30KVA_x000D_ TENSÃO : 34.5KV _x000D_ Nº ENERGISA (CITD) : 121046_x000D_ Nº DE SÉRIE : 395709_x000D_ MARCA : TRAEL - POTENCIAL_x000D_ DATA FABRICAÇÃO : 07/2016 - 10/2019_x000D_ IMPEDANCIA : 3.78_x000D_ POS. TAP : 02_x000D_ _x000D_ TRAFO INSTALADO_x000D_ POTÊNCIA : 30KVA_x000D_ TENSÃO : 34.5KV _x000D_ Nº ENERGISA (CITD) : 135559_x000D_ Nº DE SÉRIE : 1463806_x000D_ MARCA : ROMAGNOLE - CPFL_x000D_ DATA FABRICAÇÃO : 2023 - 02/2026_x000D_ IMPEDANCIA : 3.95_x000D_ POS. TAP : 02_x000D_ _x000D_ MEDIÇÃO 1: 16.19_x000D_ MEDIÇÃO 2: 15.80_x000D_ MEDIÇÃO 3: 14.33_x000D_ _x000D_ COORDENADA_x000D_ X: 837046_x000D_ Y: 9141642_x000D_ | F103: QUEIMADO | G103: NÃO IDENTIFICADO | H103: QUEIMADO | I103: NÃO IDENTIFICADO | J103: MC - SUBSTITUIÇÃO DE TRANSFORMADOR | K103: 2026 | L103: LD02105019 | M103: 5710034155 | N103: 8812 | O103: EMERGENCIAL | P103: SS ATENDIDA | Q103: 46105.42 | R103: 46106.406 | S103: 46108.42 | T103: BLOCO TRANSFORMADOR DE DISTRIBUIÇÃO | U103: PALMEIRANTE | V103: Wilmar Lucas Rodrigues Noleto | W103: RURAL | X103: FORMS SUBST DE TRANSFORMADOR | Y103: SEGUE SS DE TRAFO DE 30KVA QUEIMADO, NA REDE DE 34,5KV, PARA RAIO BT E MT QUEIMADO, ACESSO LIVRE PARA MANUNTENÇÃO. | Z103: 30 | AA103: 30 | AB103: 30KVA | AC103: 46225.761
...

Sheet COLETA
C1: EMPRESA | D1: Coluna1 | E1: REGIONAL | F1: POLO | G1: LOCALIDADE | H1: LOCAL | I1: ALIMENTADOR | J1: NÚMERO OPERATIVO | K1: MATHEUS | L1: Nº DA OCORRÊNCIA | M1: CONCAT | N1: DATA OC | O1: CAUSA | P1: DESC_CAUSA | Q1: SITUAÇÃO | R1: NS RETIRADO | S1: N_TOMBAMENTO_RETIRADO | T1: FABRICANTE | U1: DATA_FABRICAÇÃO | V1: FASES | W1: CLASSE DE TENSÃO | X1: POTÊNCIA RETIRADA | Y1: REFORMADO | Z1: REFORMADORA | AA1: DATA REFORMA | AB1: NS INSTALADO | AC1: N_TOMBAMENTO_INSTALADO | AD1: POTENCIA INSTALADA | AE1: OS (SGM) | AF1: COD. EQUIPE SUBSTITUIÇÃO | AG1: NÚMERO OBRA | AH1: QTDE OCORRÊNCIAS ANTES DA QUEIMA (12M) | AI1: EXISTE GD? | AJ1: CARREGAMENTO % | AK1: Carregamento GD | AL1: Reclamações
A2: =_xlfn.CONCAT(Table1[[#This Row],[NÚMERO OPERATIVO]],TRIM(Table1[[#This Row],[OS (SGM)]])) -> 5700469083DLP-MLPA01 000007/2026 | C2: ETO | D2: 5700469083DLP-MLPA01 000007/2026 | E2: CENTRO | F2: PALMAS | G2: APARECIDA DO RIO NEGRO | H2: RURAL | I2: LD01059122 | J2: 5700469083 | K2: =_xlfn.XLOOKUP(Table1[[#This Row],[NÚMERO OPERATIVO]],#REF!,#REF!) -> #REF! | L2: 20264078451012 | M2: =_xlfn.CONCAT(Table1[[#This Row],[NÚMERO OPERATIVO]],Table1[[#This Row],[DATA OC]]) -> 570046908346034,7742708333 | N2: 46034.774 | O2: QUEIMADO | P2: DESCARGA ATMOSFÉRICA | Q2: QUEIMADO | R2: 177594 | S2: ILGIVEL | T2: VIJAI | U2: 01/09/2010 10:36:50 | V2: 1F | W2: 34.5 | X2: 5 | Y2: NÃO É REFORMADO | Z2: NÃO É REFORMADO | AA2: 17/01/2026 | AB2: 271379 | AC2: 145190 | AD2: 25 | AE2: DLP-MLPA01 000007/2026 | AF2: DOLP-RD-PA | AG2: 112600121 | AH2: 1
A3: =_xlfn.CONCAT(Table1[[#This Row],[NÚMERO OPERATIVO]],Table1[[#This Row],[OS (SGM)]]) -> 5700482083DLP-MLPA01 000013/2026 | C3: ETO | D3: 5700482083DLP-MLPA01 000013/2026 | E3: CENTRO | F3: PALMAS | G3: APARECIDA DO RIO NEGRO | H3: RURAL | I3: LD01059122 | J3: 5700482083 | K3: =_xlfn.XLOOKUP(Table1[[#This Row],[NÚMERO OPERATIVO]],#REF!,#REF!) -> #REF! | L3: 20264085646931 | M3: =_xlfn.CONCAT(Table1[[#This Row],[NÚMERO OPERATIVO]],Table1[[#This Row],[DATA OC]]) -> 570048208346039,7143981481 | N3: 46039.714 | O3: QUEIMADO | P3: NÃO IDENTIFICADO | Q3: QUEIMADO | R3: 236340 | S3: ILEGIVEL | T3: ITB | U3: 01/11/2004 17:18:24 | V3: 1F | W3: 34.5 | X3: 15 | Y3: NÃO É REFORMADO | Z3: NÃO É REFORMADO | AA3: 19/01/2026 | AB3: 435312 | AC3: 126789 | AD3: 15 | AE3: DLP-MLPA01 000013/2026 | AF3: DOLP-RD-PA | AG3: 112600225 | AH3: 1
A4: =_xlfn.CONCAT(Table1[[#This Row],[NÚMERO OPERATIVO]],Table1[[#This Row],[OS (SGM)]]) -> 5727558083DLP-MLPA02 000014/2026 | C4: ETO | D4: 5727558083DLP-MLPA02 000014/2026 | E4: CENTRO | F4: PALMAS | G4: APARECIDA DO RIO NEGRO | H4: RURAL | I4: LD01059122 | J4: 5727558083 | K4: =_xlfn.XLOOKUP(Table1[[#This Row],[NÚMERO OPERATIVO]],#REF!,#REF!) -> #REF! | L4: 20264113074466 | M4: =_xlfn.CONCAT(Table1[[#This Row],[NÚMERO OPERATIVO]],Table1[[#This Row],[DATA OC]]) -> 572755808346053,5055324074 | N4: 46053.506 | O4: QUEIMADO | P4: NÃO IDENTIFICADO | Q4: QUEIMADO | R4: 474656 | S4: 117141 | T4: TRAEL | U4: 01/07/2018 09:08:30 | V4: 1F | W4: 34.5 | X4: 15 | Y4: NÃO É REFORMADO | Z4: NÃO É REFORMADO | AA4: 04/02/2026 | AB4: 290333 | AC4: 149772 | AD4: 15 | AE4: DLP-MLPA02 000014/2026 | AF4: DOLP-RD-PA | AG4: 112600180 | AH4: 1
A5: =_xlfn.CONCAT(Table1[[#This Row],[NÚMERO OPERATIVO]],Table1[[#This Row],[OS (SGM)]]) -> 5700770083DLP-MLPA02 000001/2026 | C5: ETO | D5: 5700770083DLP-MLPA02 000001/2026 | E5: CENTRO | F5: PALMAS | G5: APARECIDA DO RIO NEGRO | H5: RURAL | I5: LD02059122 | J5: 5700770083 | K5: =_xlfn.XLOOKUP(Table1[[#This Row],[NÚMERO OPERATIVO]],#REF!,#REF!) -> #REF! | L5: 20264062932834 | M5: =_xlfn.CONCAT(Table1[[#This Row],[NÚMERO OPERATIVO]],Table1[[#This Row],[DATA OC]]) -> 570077008346026,7250115741 | N5: 46026.725 | O5: QUEIMADO | P5: DESCARGA ATMOSFÉRICA | Q5: QUEIMADO | R5: 1600355 | S5: 141651 | T5: ITB | U5: 01/04/2024 09:43:30 | V5: 1F | W5: 34.5 | X5: 15 | Y5: NÃO É REFORMADO | Z5: CPFL | AA5: 09/01/2026 | AB5: 1014506 | AC5: 134574 | AD5: 15 | AE5: DLP-MLPA02 000001/2026 | AF5: DOLP-RD-PA | AG5: 112600061 | AH5: 1
A6: =_xlfn.CONCAT(Table1[[#This Row],[NÚMERO OPERATIVO]],Table1[[#This Row],[OS (SGM)]]) -> 5700307083DLP-MLPA03 000004/2026 | C6: ETO | D6: 5700307083DLP-MLPA03 000004/2026 | E6: CENTRO | F6: PALMAS | G6: APARECIDA DO RIO NEGRO | H6: RURAL | I6: LD03059122 | J6: 5700307083 | K6: =_xlfn.XLOOKUP(Table1[[#This Row],[NÚMERO OPERATIVO]],#REF!,#REF!) -> #REF! | L6: 20264097382713 | M6: =_xlfn.CONCAT(Table1[[#This Row],[NÚMERO OPERATIVO]],Table1[[#This Row],[DATA OC]]) -> 570030708346047,8396990741 | N6: 46047.84 | O6: QUEIMADO | P6: VAZAMENTO DE ÓLEO | Q6: QUEIMADO | R6: 497936 | S6: 13706 | T6: INCONTRAZA | U6: 01/11/2007 09:39:35 | V6: 1F | W6: 34.5 | X6: 5 | Y6: NÃO É REFORMADO | Z6: NÃO É REFORMADO | AA6: 30/01/2026 | AB6: 1615822 | AC6: 146300 | AD6: 15 | AE6: DLP-MLPA03 000004/2026 | AF6: DOLP-RD-PA | AG6: 112600148 | AH6: 1
A7: =_xlfn.CONCAT(Table1[[#This Row],[NÚMERO OPERATIVO]],Table1[[#This Row],[OS (SGM)]]) -> 5700298253DLP-MLPA01 000038/2026 | C7: ETO | D7: 5700298253DLP-MLPA01 000038/2026 | E7: CENTRO | F7: PALMAS | G7: CHAPADA DE AREIA | H7: RURAL | I7: LD03062013 | J7: 5700298253 | K7: =_xlfn.XLOOKUP(Table1[[#This Row],[NÚMERO OPERATIVO]],#REF!,#REF!) -> #REF! | L7: 20264117076029 | M7: =_xlfn.CONCAT(Table1[[#This Row],[NÚMERO OPERATIVO]],Table1[[#This Row],[DATA OC]]) -> 570029825346057,3625462963 | N7: 46057.363 | O7: QUEIMADO | P7: DESCARGA ATMOSFÉRICA | Q7: QUEIMADO | R7: 128152 | S7: 0 | T7: VIJAI | U7: 01/01/2018 09:18:17 | V7: 1F | W7: 34.5 | X7: 5 | Y7: NÃO É REFORMADO | Z7: NÃO É REFORMADO | AA7: 06/02/2026 | AB7: 1600373 | AC7: 141669 | AD7: 15 | AE7: DLP-MLPA01 000038/2026 | AF7: DOLP-RD-PA | AG7: 112600266 | AH7: 1
A8: =_xlfn.CONCAT(Table1[[#This Row],[NÚMERO OPERATIVO]],Table1[[#This Row],[OS (SGM)]]) -> 5700221196DLP-MLPA01 000054/2026 | C8: ETO | D8: 5700221196DLP-MLPA01 000054/2026 | E8: CENTRO | F8: PALMAS | G8: LAGOA DO TOCANTINS | H8: RURAL | I8: LD02059122 | J8: 5700221196 | K8: =_xlfn.XLOOKUP(Table1[[#This Row],[NÚMERO OPERATIVO]],#REF!,#REF!) -> #REF! | L8: 20264121766011 | M8: =_xlfn.CONCAT(Table1[[#This Row],[NÚMERO OPERATIVO]],Table1[[#This Row],[DATA OC]]) -> 570022119646063,0092708333 | N8: 46063.009 | O8: QUEIMADO | P8: DESCARGA ATMOSFÉRICA | Q8: QUEIMADO | R8: 78606 | S8: 0 | T8: TRAEL | U8: 01/03/2006 10:14:18 | V8: 1F | W8: 34.5 | X8: 10 | Y8: NÃO É REFORMADO | AA8: 23/02/2026 | AB8: 297839 | AC8: 149875 | AD8: 15 | AE8: DLP-MLPA01 000054/2026 | AF8: DOLP-RD-PA | AG8: 112600185 | AH8: 1
A9: =_xlfn.CONCAT(Table1[[#This Row],[NÚMERO OPERATIVO]],Table1[[#This Row],[OS (SGM)]]) -> 5700227196DLP-MLPA01 000002/2026 | C9: ETO | D9: 5700227196DLP-MLPA01 000002/2026 | E9: CENTRO | F9: PALMAS | G9: LAGOA DO TOCANTINS | H9: RURAL | I9: LD02059122 | J9: 5700227196 | K9: =_xlfn.XLOOKUP(Table1[[#This Row],[NÚMERO OPERATIVO]],#REF!,#REF!) -> #REF! | L9: 20264062695982 | M9: =_xlfn.CONCAT(Table1[[#This Row],[NÚMERO OPERATIVO]],Table1[[#This Row],[DATA OC]]) -> 570022719646024,8898958333 | N9: 46024.89 | O9: QUEIMADO | P9: NÃO IDENTIFICADO | Q9: QUEIMADO | R9: 0 | S9: 0 | T9: ABB | U9: 10/02/2026 10:25:09 | V9: 1F | W9: 34.5 | X9: 10 | Y9: CPFL | Z9: CPFL | AA9: 03/02/2026 | AB9: 0 | AC9: 0 | AD9: 15 | AE9: DLP-MLPA01 000002/2026 | AF9: DOLP-RD-PA | AG9: 112600274 | AH9: 1
A10: =_xlfn.CONCAT(Table1[[#This Row],[NÚMERO OPERATIVO]],Table1[[#This Row],[OS (SGM)]]) -> 5700602196DLP-MLPA01 000039/2026 | C10: ETO | D10: 5700602196DLP-MLPA01 000039/2026 | E10: CENTRO | F10: PALMAS | G10: LAGOA DO TOCANTINS | H10: RURAL | I10: LD02059122 | J10: 5700602196 | K10: =_xlfn.XLOOKUP(Table1[[#This Row],[NÚMERO OPERATIVO]],#REF!,#REF!) -> #REF! | L10: 20264117004593 | M10: =_xlfn.CONCAT(Table1[[#This Row],[NÚMERO OPERATIVO]],Table1[[#This Row],[DATA OC]]) -> 570060219646056,7008796296 | N10: 46056.701 | O10: QUEIMADO | P10: NÃO IDENTIFICADO | Q10: QUEIMADO | R10: 202491 | S10: 0 | T10: VIJAI | U10: 01/11/2011 09:51:00 | V10: 1F | W10: 34.5 | X10: 5 | Y10: NÃO É REFORMADO | Z10: CPFL | AB10: 345311 | AC10: 109946 | AD10: 15 | AE10: DLP-MLPA01 000039/2026 | AF10: DOLP-RD-PA | AG10: 112600182 | AH10: 1
A11: =_xlfn.CONCAT(Table1[[#This Row],[NÚMERO OPERATIVO]],Table1[[#This Row],[OS (SGM)]]) -> 5710106196DLP-MLPA02 000009/2026 | C11: ETO | D11: 5710106196DLP-MLPA02 000009/2026 | E11: CENTRO | F11: PALMAS | G11: LAGOA DO TOCANTINS | H11: RURAL | I11: LD02059122 | J11: 5710106196 | K11: =_xlfn.XLOOKUP(Table1[[#This Row],[NÚMERO OPERATIVO]],#REF!,#REF!) -> #REF! | L11: 20264096615371 | M11: =_xlfn.CONCAT(Table1[[#This Row],[NÚMERO OPERATIVO]],Table1[[#This Row],[DATA OC]]) -> 571010619646046,4916666667 | N11: 46046.492 | O11: QUEIMADO | P11: NÃO IDENTIFICADO | Q11: QUEIMADO | R11: 459968 | S11: ILEGÍVEL | T11: ITB | U11: 11/02/2007 16:17:09 | V11: 1F | W11: 34.5 | X11: 5 | Y11: INTEL | Z11: NÃO É REFORMADO | AA11: 11/02/2009 | AB11: C290389 | AC11: 149796 | AD11: 15 | AE11: DLP-MLPA02 000009/2026 | AF11: DOLP-RD-PA | AG11: 112600198 | AH11: 1
A12: =_xlfn.CONCAT(Table1[[#This Row],[NÚMERO OPERATIVO]],Table1[[#This Row],[OS (SGM)]]) -> 5736153196DLP-MLPA03 000011/2026 | C12: ETO | D12: 5736153196DLP-MLPA03 000011/2026 | E12: CENTRO | F12: PALMAS | G12: LAGOA DO TOCANTINS | H12: RURAL | I12: LD02059122 | J12: 5736153196 | K12: =_xlfn.XLOOKUP(Table1[[#This Row],[NÚMERO OPERATIVO]],#REF!,#REF!) -> #REF! | L12: 20264113143399 | M12: =_xlfn.CONCAT(Table1[[#This Row],[NÚMERO OPERATIVO]],Table1[[#This Row],[DATA OC]]) -> 573615319646053,7020717593 | N12: 46053.702 | O12: QUEIMADO | P12: DESCARGA ATMOSFÉRICA | Q12: QUEIMADO | R12: 0 | S12: 0 | T12: ABB | U12: 10/02/2026 10:06:19 | V12: 1F | W12: 13.8 | X12: 10 | Y12: CPFL | Z12: CPFL | AA12: 10/02/2026 | AB12: 0 | AC12: 0 | AD12: 15 | AE12: DLP-MLPA03 000011/2026 | AF12: DOLP-RD-PA | AG12: 112600282 | AH12: 1
A13: =_xlfn.CONCAT(Table1[[#This Row],[NÚMERO OPERATIVO]],Table1[[#This Row],[OS (SGM)]]) -> 5737864196DLP-MLPA01 000056/2026 | C13: ETO | D13: 5737864196DLP-MLPA01 000056/2026 | E13: CENTRO | F13: PALMAS | G13: LAGOA DO TOCANTINS | H13: RURAL | I13: LD02059122 | J13: 5737864196 | K13: =_xlfn.XLOOKUP(Table1[[#This Row],[NÚMERO OPERATIVO]],#REF!,#REF!) -> #REF! | L13: 20264123796101 | M13: =_xlfn.CONCAT(Table1[[#This Row],[NÚMERO OPERATIVO]],Table1[[#This Row],[DATA OC]]) -> 573786419646064,5174189815 | N13: 46064.517 | O13: QUEIMADO | P13: NÃO IDENTIFICADO | Q13: QUEIMADO | R13: 459007 | S13: 112556 | T13: TRAEL | U13: 01/02/2026 18:25:01 | V13: 1F | W13: 34.5 | X13: 15 | Y13: NÃO É REFORMADO | Z13: NÃO É REFORMADO | AA13: 04/03/2026 | AB13: 799471 | AC13: 149122 | AD13: 15 | AE13: DLP-MLPA01 000056/2026 | AF13: DOLP-RD-PA | AG13: 112600260 | AH13: 1
A14: =_xlfn.CONCAT(Table1[[#This Row],[NÚMERO OPERATIVO]],Table1[[#This Row],[OS (SGM)]]) -> 5753804196DLP-MPPA01 000004/2026 | C14: ETO | D14: 5753804196DLP-MPPA01 000004/2026 | E14: CENTRO | F14: PALMAS | G14: LAGOA DO TOCANTINS | H14: RURAL | I14: LD02059122 | J14: 5753804196 | K14: =_xlfn.XLOOKUP(Table1[[#This Row],[NÚMERO OPERATIVO]],#REF!,#REF!) -> #REF! | L14: 20264064897583 | M14: =_xlfn.CONCAT(Table1[[#This Row],[NÚMERO OPERATIVO]],Table1[[#This Row],[DATA OC]]) -> 575380419646026,6832291667 | N14: 46026.683 | O14: QUEIMADO | P14: DESCARGA ATMOSFÉRICA | Q14: QUEIMADO | R14: 692910 | S14: 012811 | T14: TRAEL | U14: 01/08/2024 07:48:54 | V14: 3F | W14: 34.5 | X14: 45 | Y14: NÃO É REFORMADO | Z14: NÃO É REFORMADO | AA14: 09/01/2026 | AB14: 1616966 | AC14: 146094 | AD14: 45 | AE14: DLP-MPPA01 000004/2026 | AF14: DOLP-RD-PA | AG14: 112600057 | AH14: 1
A15: =_xlfn.CONCAT(Table1[[#This Row],[NÚMERO OPERATIVO]],Table1[[#This Row],[OS (SGM)]]) -> 5700628010DLP-MLPA01 000060/2026 | C15: ETO | D15: 5700628010DLP-MLPA01 000060/2026 | E15: CENTRO | F15: PALMAS | G15: LAJEADO | H15: RURAL | I15: LD03059122 | J15: 5700628010 | K15: =_xlfn.XLOOKUP(Table1[[#This Row],[NÚMERO OPERATIVO]],#REF!,#REF!) -> #REF! | L15: será aberta em campo | M15: =_xlfn.CONCAT(Table1[[#This Row],[NÚMERO OPERATIVO]],Table1[[#This Row],[DATA OC]]) -> 570062801046065,8999652778 | N15: 46065.9 | O15: QUEIMADO | P15: NÃO IDENTIFICADO | Q15: QUEIMADO | V15: 1F | W15: 34.5 | X15: 15 | AD15: 15 | AE15: DLP-MLPA01 000060/2026 | AF15: DOLP-RD-PA | AG15: 112600272 | AH15: 1
A16: =_xlfn.CONCAT(Table1[[#This Row],[NÚMERO OPERATIVO]],Table1[[#This Row],[OS (SGM)]]) -> 5700671010DLP-MLPA01 000001/2026 | C16: ETO | D16: 5700671010DLP-MLPA01 000001/2026 | E16: CENTRO | F16: PALMAS | G16: LAJEADO | H16: RURAL | I16: LD03059122 | J16: 5700671010 | K16: =_xlfn.XLOOKUP(Table1[[#This Row],[NÚMERO OPERATIVO]],#REF!,#REF!) -> #REF! | L16: 20264060599303 | M16: =_xlfn.CONCAT(Table1[[#This Row],[NÚMERO OPERATIVO]],Table1[[#This Row],[DATA OC]]) -> 570067101046023,5344907407 | N16: 46023.534 | O16: QUEIMADO | P16: DESCARGA ATMOSFÉRICA | Q16: QUEIMADO | R16: 533284 | S16: 123494 | T16: TRAEL | U16: 01/03/2020 09:03:39 | V16: 1F | W16: 34.5 | X16: 150 | Y16: NÃO É REFORMADO | Z16: CPFL | AA16: 12/01/2026 | AB16: 474621 | AC16: 117106 | AD16: 15 | AE16: DLP-MLPA01 000001/2026 | AF16: DOLP-RD-PA | AG16: 112600085 | AH16: 1
A17: =_xlfn.CONCAT(Table1[[#This Row],[NÚMERO OPERATIVO]],Table1[[#This Row],[OS (SGM)]]) -> 5710080010DLP-CTPA01 000012/2026 | C17: ETO | D17: 5710080010DLP-CTPA01 000012/2026 | E17: CENTRO | F17: PALMAS | G17: LAJEADO | H17: RURAL | I17: LD03059122 | J17: 5710080010 | K17: =_xlfn.XLOOKUP(Table1[[#This Row],[NÚMERO OPERATIVO]],#REF!,#REF!) -> #REF! | L17: 20264089194957 | M17: =_xlfn.CONCAT(Table1[[#This Row],[NÚMERO OPERATIVO]],Table1[[#This Row],[DATA OC]]) -> 571008001046042,6536226852 | N17: 46042.654 | O17: QUEIMADO | P17: NÃO IDENTIFICADO | Q17: QUEIMADO | R17: 426107 | S17: 129558 | T17: TRAEL | U17: 30/01/2023 09:13:49 | V17: 3F | W17: 34.5 | X17: 75 | Y17: NÃO É REFORMADO | Z17: NÃO É REFORMADO | AA17: 30/01/2026 | AB17: 1644184 | AC17: 148393 | AD17: 75 | AE17: DLP-CTPA01 000012/2026 | AF17: DOLP-RD-PA | AG17: 112600250 | AH17: 1
A18: =_xlfn.CONCAT(Table1[[#This Row],[NÚMERO OPERATIVO]],Table1[[#This Row],[OS (SGM)]]) -> 5710110010DLP-MLPA01 000034/2026 | C18: ETO | D18: 5710110010DLP-MLPA01 000034/2026 | E18: CENTRO | F18: PALMAS | G18: LAJEADO | H18: RURAL | I18: LD03059122 | J18: 5710110010 | K18: =_xlfn.XLOOKUP(Table1[[#This Row],[NÚMERO OPERATIVO]],#REF!,#REF!) -> #REF! | L18: 20264114899867 | M18: =_xlfn.CONCAT(Table1[[#This Row],[NÚMERO OPERATIVO]],Table1[[#This Row],[DATA OC]]) -> 571011001046056,6232638889 | N18: 46056.623 | O18: QUEIMADO | P18: NÃO IDENTIFICADO | Q18: QUEIMADO | R18: 179804 | S18: 1011815 | T18: ABB | U18: 06/02/2026 09:22:28 | V18: 1F | W18: 34.5 | X18: 15 | Y18: CPFL | Z18: NÃO É REFORMADO | AA18: 06/02/2026 | AB18: 1622898 | AC18: 143199 | AD18: 15 | AE18: DLP-MLPA01 000034/2026 | AF18: DOLP-RD-PA | AG18: 112600238 | AH18: 1
A19: =_xlfn.CONCAT(Table1[[#This Row],[NÚMERO OPERATIVO]],Table1[[#This Row],[OS (SGM)]]) -> 5710321010DLP-MLPA01 000059/2026 | C19: ETO | D19: 5710321010DLP-MLPA01 000059/2026 | E19: CENTRO | F19: PALMAS | G19: LAJEADO | H19: RURAL | I19: LD03059122 | J19: 5710321010 | K19: =_xlfn.XLOOKUP(Table1[[#This Row],[NÚMERO OPERATIVO]],#REF!,#REF!) -> #REF! | L19: 20264123973016 | M19: =_xlfn.CONCAT(Table1[[#This Row],[NÚMERO OPERATIVO]],Table1[[#This Row],[DATA OC]]) -> 571032101046064,7447569444 | N19: 46064.745 | O19: QUEIMADO | P19: DESCARGA ATMOSFÉRICA | Q19: QUEIMADO | R19: 928991 | S19: 01454 | T19: ITB | U19: 01/01/2015 17:26:23 | V19: 1F | W19: 34.5 | X19: 10 | Y19: NÃO É REFORMADO | Z19: NÃO É REFORMADO | AA19: 05/03/2026 | AB19: 498289 | AC19: 119474 | AD19: 15 | AE19: DLP-MLPA01 000059/2026 | AF19: DOLP-RD-PA | AG19: 112600269 | AH19: 1
A20: =_xlfn.CONCAT(Table1[[#This Row],[NÚMERO OPERATIVO]],Table1[[#This Row],[OS (SGM)]]) -> 5700367010DLP-MLPA02 000016/2026 | C20: ETO | D20: 5700367010DLP-MLPA02 000016/2026 | E20: CENTRO | F20: PALMAS | G20: LAJEADO | H20: RURAL | I20: LD05050008 | J20: 5700367010 | K20: =_xlfn.XLOOKUP(Table1[[#This Row],[NÚMERO OPERATIVO]],#REF!,#REF!) -> #REF! | L20: 20264129319509 | M20: =_xlfn.CONCAT(Table1[[#This Row],[NÚMERO OPERATIVO]],Table1[[#This Row],[DATA OC]]) -> 570036701046070,8066666667 | N20: 46070.807 | O20: QUEIMADO | P20: DESCARGA ATMOSFÉRICA | Q20: QUEIMADO | R20: 457930 | S20: 20023 | T20: ITB | U20: 05/03/2024 10:54:51 | V20: 1F | W20: 34.5 | X20: 10 | Y20: TRAEL | Z20: NÃO É REFORMADO | AA20: 05/03/2026 | AB20: 296112 | AC20: 148796 | AD20: 15 | AE20: DLP-MLPA02 000016/2026 | AF20: DOLP-RD-PA | AG20: 112600417 | AH20: 1
A21: =_xlfn.CONCAT(Table1[[#This Row],[NÚMERO OPERATIVO]],Table1[[#This Row],[OS (SGM)]]) -> 5700095082DLP-MLPA01 000051/2026 | C21: ETO | D21: 5700095082DLP-MLPA01 000051/2026 | E21: CENTRO | F21: PALMAS | G21: LIZARDA | H21: RURAL | I21: LD02065015 | J21: 5700095082 | K21: =_xlfn.XLOOKUP(Table1[[#This Row],[NÚMERO OPERATIVO]],#REF!,#REF!) -> #REF! | L21: será aberta em campo | M21: =_xlfn.CONCAT(Table1[[#This Row],[NÚMERO OPERATIVO]],Table1[[#This Row],[DATA OC]]) -> 570009508246062,4116319444 | N21: 46062.412 | O21: QUEIMADO | P21: DESCARGA ATMOSFÉRICA | Q21: QUEIMADO | R21: 233720 | S21: 136235 | T21: ITAIPU | U21: 01/04/2024 09:18:47 | V21: 1F | W21: 34.5 | X21: 15 | Y21: NÃO É REFORMADO | Z21: NÃO É REFORMADO | AA21: 12/02/2026 | AB21: 297841 | AC21: 149877 | AD21: 15 | AE21: DLP-MLPA01 000051/2026 | AF21: DOLP-RD-PA | AG21: 112600186 | AH21: 1
A22: =_xlfn.CONCAT(Table1[[#This Row],[NÚMERO OPERATIVO]],Table1[[#This Row],[OS (SGM)]]) -> 5737313082DLP-MLPA01 000017/2026 | C22: ETO | D22: 5737313082DLP-MLPA01 000017/2026 | E22: CENTRO | F22: PALMAS | G22: LIZARDA | H22: RURAL | I22: LD02065015 | J22: 5737313082 | K22: =_xlfn.XLOOKUP(Table1[[#This Row],[NÚMERO OPERATIVO]],#REF!,#REF!) -> #REF! | L22: 20264088293417 | M22: =_xlfn.CONCAT(Table1[[#This Row],[NÚMERO OPERATIVO]],Table1[[#This Row],[DATA OC]]) -> 573731308246041,6654282407 | N22: 46041.665 | O22: QUEIMADO | P22: NÃO IDENTIFICADO | Q22: QUEIMADO | R22: 458699 | S22: 111775 | T22: TRAEL | U22: 01/02/2018 08:16:47 | V22: 1F | W22: 34.5 | X22: 15 | Y22: NÃO É REFORMADO | Z22: NÃO É REFORMADO | AA22: 30/01/2026 | AB22: 799486 | AC22: 149137 | AD22: 15 | AE22: DLP-MLPA01 000017/2026 | AF22: DOLP-RD-PA | AG22: 112600134 | AH22: 1
A23: =_xlfn.CONCAT(Table1[[#This Row],[NÚMERO OPERATIVO]],Table1[[#This Row],[OS (SGM)]]) -> 5744418082DLP-CTPA00 000013/2026 | C23: ETO | D23: 5744418082DLP-CTPA00 000013/2026 | E23: CENTRO | F23: PALMAS | G23: LIZARDA | H23: RURAL | I23: LD02065015 | J23: 5744418082 | K23: =_xlfn.XLOOKUP(Table1[[#This Row],[NÚMERO OPERATIVO]],#REF!,#REF!) -> #REF! | L23: 20264088376128 | M23: =_xlfn.CONCAT(Table1[[#This Row],[NÚMERO OPERATIVO]],Table1[[#This Row],[DATA OC]]) -> 574441808246042,5600115741 | N23: 46042.56 | O23: AVARIADO | P23: DESCARGA ATMOSFÉRICA | Q23: AVARIADO | R23: 463594 | S23: 113643 | T23: TRAEL | U23: 01/10/2023 14:58:24 | V23: 3F | W23: 34.5 | X23: 30 | Y23: NÃO É REFORMADO | Z23: NÃO É REFORMADO | AA23: 09/02/2026 | AB23: 644451 | AC23: 142691 | AD23: 45 | AE23: DLP-CTPA00 000013/2026 | AF23: DOLP-RD-PA | AG23: 112600256 | AH23: 1
A24: =_xlfn.CONCAT(Table1[[#This Row],[NÚMERO OPERATIVO]],Table1[[#This Row],[OS (SGM)]]) -> 5744418082DLP-MLPA01 000035/2026 | C24: ETO | D24: 5744418082DLP-MLPA01 000035/2026 | E24: CENTRO | F24: PALMAS | G24: LIZARDA | H24: RURAL | I24: LD02065015 | J24: 5744418082 | K24: =_xlfn.XLOOKUP(Table1[[#This Row],[NÚMERO OPERATIVO]],#REF!,#REF!) -> #REF! | L24: 20264116126348 | M24: =_xlfn.CONCAT(Table1[[#This Row],[NÚMERO OPERATIVO]],Table1[[#This Row],[DATA OC]]) -> 574441808246056,5503703704 | N24: 46056.55 | O24: QUEIMADO | P24: NÃO IDENTIFICADO | Q24: QUEIMADO | R24: 644451 | S24: 142691 | T24: TRAEL | U24: 01/08/2022 10:16:37 | V24: 3F | W24: 34.5 | X24: 45 | Y24: CPFL | Z24: NÃO É REFORMADO | AA24: 01/09/2024 | AB24: 16542 | AC24: 109972 | AD24: 45 | AE24: DLP-MLPA01 000035/2026 | AF24: DOLP-RD-PA | AG24: 112600256 | AH24: 1
A25: =_xlfn.CONCAT(Table1[[#This Row],[NÚMERO OPERATIVO]],Table1[[#This Row],[OS (SGM)]]) -> 5744418082DLP-MLPA01 000076/2026 | C25: ETO | D25: 5744418082DLP-MLPA01 000076/2026 | E25: CENTRO | F25: PALMAS | G25: LIZARDA | H25: RURAL | I25: LD02065015 | J25: 5744418082 | K25: =_xlfn.XLOOKUP(Table1[[#This Row],[NÚMERO OPERATIVO]],#REF!,#REF!) -> #REF! | L25: será aberta em campo | M25: =_xlfn.CONCAT(Table1[[#This Row],[NÚMERO OPERATIVO]],Table1[[#This Row],[DATA OC]]) -> 574441808246074,8994907407 | N25: 46074.899 | O25: QUEIMADO | P25: VAZAMENTO DE ÓLEO | Q25: QUEIMADO | V25: 3F | W25: 34.5 | X25: 30 | AD25: 45 | AE25: DLP-MLPA01 000076/2026 | AF25: DOLP-RD-PA | AG25: 112600256 | AH25: 1
A26: =_xlfn.CONCAT(Table1[[#This Row],[NÚMERO OPERATIVO]],Table1[[#This Row],[OS (SGM)]]) -> 5745888082DLP-MLPA01 000004/2026 | C26: ETO | D26: 5745888082DLP-MLPA01 000004/2026 | E26: CENTRO | F26: PALMAS | G26: LIZARDA | H26: RURAL | I26: LD02065015 | J26: 5745888082 | K26: =_xlfn.XLOOKUP(Table1[[#This Row],[NÚMERO OPERATIVO]],#REF!,#REF!) -> #REF! | L26: 20264069727774 | M26: =_xlfn.CONCAT(Table1[[#This Row],[NÚMERO OPERATIVO]],Table1[[#This Row],[DATA OC]]) -> 574588808246030,9067592593 | N26: 46030.907 | O26: QUEIMADO | P26: DESCARGA ATMOSFÉRICA | Q26: QUEIMADO | R26: 1289363 | S26: 127129 | T26: ROMAGNOLE | U26: 01/05/2025 08:55:58 | V26: 3F | W26: 34.5 | X26: 30 | Y26: NÃO É REFORMADO | Z26: NÃO É REFORMADO | AA26: 16/01/2026 | AB26: 1442136 | AC26: 132281 | AD26: 30 | AE26: DLP-MLPA01 000004/2026 | AF26: DOLP-RD-PA | AG26: 112600116 | AH26: 1
A27: =_xlfn.CONCAT(Table1[[#This Row],[NÚMERO OPERATIVO]],Table1[[#This Row],[OS (SGM)]]) -> 5745888082DLP-MPPA01 000034/2026 | C27: ETO | D27: 5745888082DLP-MPPA01 000034/2026 | E27: CENTRO | F27: PALMAS | G27: LIZARDA | H27: RURAL | I27: LD02065015 | J27: 5745888082 | K27: =_xlfn.XLOOKUP(Table1[[#This Row],[NÚMERO OPERATIVO]],#REF!,#REF!) -> #REF! | L27: 20264088317130 | M27: =_xlfn.CONCAT(Table1[[#This Row],[NÚMERO OPERATIVO]],Table1[[#This Row],[DATA OC]]) -> 574588808246041,6858217593 | N27: 46041.686 | O27: QUEIMADO | P27: NÃO IDENTIFICADO | Q27: QUEIMADO | R27: 1442136 | S27: 132281 | T27: TRAEL | U27: 01/04/2025 07:10:49 | V27: 3F | W27: 34.5 | X27: 30 | Y27: NÃO É REFORMADO | Z27: NÃO É REFORMADO | AA27: 30/01/2026 | AB27: 1616964 | AC27: 146092 | AD27: 45 | AE27: DLP-MPPA01 000034/2026 | AF27: DOLP-RD-PA | AH27: 1
A28: =_xlfn.CONCAT(Table1[[#This Row],[NÚMERO OPERATIVO]],Table1[[#This Row],[OS (SGM)]]) -> 5702917122DLP-MLPA01 000053/2026 | C28: ETO | D28: 5702917122DLP-MLPA01 000053/2026 | E28: CENTRO | F28: PALMAS | G28: MONTE DO CARMO | H28: RURAL | I28: LD02059122 | J28: 5702917122 | K28: =_xlfn.XLOOKUP(Table1[[#This Row],[NÚMERO OPERATIVO]],#REF!,#REF!) -> #REF! | L28: 20264121668411 | M28: =_xlfn.CONCAT(Table1[[#This Row],[NÚMERO OPERATIVO]],Table1[[#This Row],[DATA OC]]) -> 570291712246062,7940509259 | N28: 46062.794 | O28: QUEIMADO | P28: DESCARGA ATMOSFÉRICA | Q28: QUEIMADO | R28: 457959 | S28: 200170 | T28: ITB | U28: 04/03/2007 15:01:26 | V28: 1F | W28: 34.5 | X28: 10 | Y28: NÃO É REFORMADO | Z28: NÃO É REFORMADO | AB28: 1289670 | AC28: 149122 | AD28: 15 | AE28: DLP-MLPA01 000053/2026 | AF28: DOLP-RD-PA | AG28: 112600261 | AH28: 1
A29: =_xlfn.CONCAT(Table1[[#This Row],[NÚMERO OPERATIVO]],Table1[[#This Row],[OS (SGM)]]) -> 5705116122DLP-MLPA01 000012/2026 | C29: ETO | D29: 5705116122DLP-MLPA01 000012/2026 | E29: CENTRO | F29: PALMAS | G29: MONTE DO CARMO | H29: RURAL | I29: LD02059122 | J29: 5705116122 | K29: =_xlfn.XLOOKUP(Table1[[#This Row],[NÚMERO OPERATIVO]],#REF!,#REF!) -> #REF! | L29: 20264084970808 | M29: =_xlfn.CONCAT(Table1[[#This Row],[NÚMERO OPERATIVO]],Table1[[#This Row],[DATA OC]]) -> 570511612246039,2322106482 | N29: 46039.232 | O29: QUEIMADO | P29: DESCARGA ATMOSFÉRICA | Q29: QUEIMADO | R29: 185196 | S29: ILEGIVEL | T29: VIJAI | U29: 01/02/2011 17:01:28 | V29: 1F | W29: 34.5 | X29: 5 | Y29: NÃO É REFORMADO | Z29: NÃO É REFORMADO | AA29: 19/01/2026 | AB29: 315512 | AC29: 127587 | AD29: 15 | AE29: DLP-MLPA01 000012/2026 | AF29: DOLP-RD-PA | AG29: 112600249 | AH29: 1
A30: =_xlfn.CONCAT(Table1[[#This Row],[NÚMERO OPERATIVO]],Table1[[#This Row],[OS (SGM)]]) -> 5700449092DLP-MLPA01 000014/2026 | C30: ETO | D30: 5700449092DLP-MLPA01 000014/2026 | E30: CENTRO | F30: PALMAS | G30: NOVO ACORDO | H30: RURAL | I30: LD01059122 | J30: 5700449092 | K30: =_xlfn.XLOOKUP(Table1[[#This Row],[NÚMERO OPERATIVO]],#REF!,#REF!) -> #REF! | L30: 20264086106673 | M30: =_xlfn.CONCAT(Table1[[#This Row],[NÚMERO OPERATIVO]],Table1[[#This Row],[DATA OC]]) -> 570044909246040,8920949074 | N30: 46040.892 | O30: QUEIMADO | P30: NÃO IDENTIFICADO | Q30: QUEIMADO | R30: 90517 | S30: 0122979 | T30: ITB | U30: 01/06/2014 06:33:01 | V30: 1F | W30: 34.5 | X30: 15 | Y30: NÃO É REFORMADO | Z30: NÃO É REFORMADO | AA30: 21/01/2026 | AB30: 271343 | AC30: 145154 | AD30: 25 | AE30: DLP-MLPA01 000014/2026 | AF30: DOLP-RD-PA | AG30: 112600154 | AH30: 1
A31: =_xlfn.CONCAT(Table1[[#This Row],[NÚMERO OPERATIVO]],Table1[[#This Row],[OS (SGM)]]) -> 5700203092DLP-MLPA03 000018/2026 | C31: ETO | D31: 5700203092DLP-MLPA03 000018/2026 | E31: CENTRO | F31: PALMAS | G31: NOVO ACORDO | H31: RURAL | I31: LD03046026 | J31: 5700203092 | K31: =_xlfn.XLOOKUP(Table1[[#This Row],[NÚMERO OPERATIVO]],#REF!,#REF!) -> #REF! | L31: 20264138741538 | M31: =_xlfn.CONCAT(Table1[[#This Row],[NÚMERO OPERATIVO]],Table1[[#This Row],[DATA OC]]) -> 570020309246079,3477314815 | N31: 46079.348 | O31: QUEIMADO | P31: DESCARGA ATMOSFÉRICA | Q31: QUEIMADO | V31: 1F | W31: 13.8 | X31: 15 | AD31: 15 | AE31: DLP-MLPA03 000018/2026 | AF31: DOLP-RD-PA | AG31: 112600333 | AH31: 1
A32: =_xlfn.CONCAT(Table1[[#This Row],[NÚMERO OPERATIVO]],Table1[[#This Row],[OS (SGM)]]) -> 5727565092DLP-MLPA02 000012/2026 | C32: ETO | D32: 5727565092DLP-MLPA02 000012/2026 | E32: CENTRO | F32: PALMAS | G32: NOVO ACORDO | H32: RURAL | I32: LD03046026 | J32: 5727565092 | K32: =_xlfn.XLOOKUP(Table1[[#This Row],[NÚMERO OPERATIVO]],#REF!,#REF!) -> #REF! | L32: 20264112017715 | M32: =_xlfn.CONCAT(Table1[[#This Row],[NÚMERO OPERATIVO]],Table1[[#This Row],[DATA OC]]) -> 572756509246052,8841550926 | N32: 46052.884 | O32: QUEIMADO | P32: DESCARGA ATMOSFÉRICA | Q32: QUEIMADO | R32: 442002 | S32: 06107877 | T32: TRAEL | U32: 01/08/2017 09:45:22 | V32: 1F | W32: 34.5 | X32: 15 | Y32: NÃO É REFORMADO | Z32: NÃO É REFORMADO | AB32: 1615844 | AC32: 146322 | AD32: 15 | AE32: DLP-MLPA02 000012/2026 | AF32: DOLP-RD-PA | AG32: 112600173 | AH32: 1
A33: =_xlfn.CONCAT(Table1[[#This Row],[NÚMERO OPERATIVO]],Table1[[#This Row],[OS (SGM)]]) -> 5719041100DLP-MLPA01 000068/2026 | C33: ETO | D33: 5719041100DLP-MLPA01 000068/2026 | E33: CENTRO | F33: PALMAS | G33: PALMAS | H33: RURAL | I33: AL01081100 | J33: 5719041100 | K33: =_xlfn.XLOOKUP(Table1[[#This Row],[NÚMERO OPERATIVO]],#REF!,#REF!) -> #REF! | L33: 20264128552514 | M33: =_xlfn.CONCAT(Table1[[#This Row],[NÚMERO OPERATIVO]],Table1[[#This Row],[DATA OC]]) -> 571904110046069,3856828704 | N33: 46069.386 | O33: QUEIMADO | P33: VAZAMENTO DE ÓLEO | Q33: QUEIMADO | V33: 1F | W33: 13.8 | X33: 25 | AD33: 25 | AE33: DLP-MLPA01 000068/2026 | AF33: DOLP-RD-PA | AG33: 112600403 | AH33: 1
A34: =_xlfn.CONCAT(Table1[[#This Row],[NÚMERO OPERATIVO]],Table1[[#This Row],[OS (SGM)]]) -> 5705910122DLP-MPPA01 000020/2026 | C34: ETO | D34: 5705910122DLP-MPPA01 000020/2026 | E34: CENTRO | F34: PALMAS | G34: PALMAS | H34: RURAL | I34: AL01099059 | J34: 5705910122 | K34: =_xlfn.XLOOKUP(Table1[[#This Row],[NÚMERO OPERATIVO]],#REF!,#REF!) -> #REF! | L34: 20264070154331 | M34: =_xlfn.CONCAT(Table1[[#This Row],[NÚMERO OPERATIVO]],Table1[[#This Row],[DATA OC]]) -> 570591012246031,6149768519 | N34: 46031.615 | O34: QUEIMADO | P34: NÃO IDENTIFICADO | Q34: QUEIMADO | R34: 228039 | S34: 134940 | T34: ITAIPU | U34: 01/02/2023 09:12:22 | V34: 1F | W34: 13.8 | X34: 25 | Y34: NÃO É REFORMADO | Z34: NÃO É REFORMADO | AA34: 16/01/2026 | AB34: 525755 | AC34: 122542 | AD34: 25 | AE34: DLP-MPPA01 000020/2026 | AF34: DOLP-RD-PA | AG34: 112600115 | AH34: 1
A35: =_xlfn.CONCAT(Table1[[#This Row],[NÚMERO OPERATIVO]],Table1[[#This Row],[OS (SGM)]]) -> 5712697122DLP-MLPA01 000022/2026 | C35: ETO | D35: 5712697122DLP-MLPA01 000022/2026 | E35: CENTRO | F35: PALMAS | G35: PALMAS | H35: RURAL | I35: LD01059122 | J35: 5712697122 | K35: =_xlfn.XLOOKUP(Table1[[#This Row],[NÚMERO OPERATIVO]],#REF!,#REF!) -> #REF! | L35: 05 20264097373561 | M35: =_xlfn.CONCAT(Table1[[#This Row],[NÚMERO OPERATIVO]],Table1[[#This Row],[DATA OC]]) -> 571269712246047,8660648148 | N35: 46047.866 | O35: QUEIMADO | P35: DESCARGA ATMOSFÉRICA | Q35: QUEIMADO | R35: 615231 | S35: 131064 | T35: TRAEL | U35: 01/04/2022 17:56:04 | V35: 1F | W35: 13.8 | X35: 15 | Y35: NÃO É REFORMADO | Z35: NÃO É REFORMADO | AA35: 29/01/2026 | AB35: 1615843 | AC35: 146321 | AD35: 15 | AE35: DLP-MLPA01 000022/2026 | AF35: DOLP-RD-PA | AG35: 112600145 | AH35: 1
A36: =_xlfn.CONCAT(Table1[[#This Row],[NÚMERO OPERATIVO]],Table1[[#This Row],[OS (SGM)]]) -> 5702935122DLP-MPPA01 000054/2026 | C36: ETO | D36: 5702935122DLP-MPPA01 000054/2026 | E36: CENTRO | F36: PALMAS | G36: PALMAS | H36: RURAL | I36: LD01100001 | J36: 5702935122 | K36: =_xlfn.XLOOKUP(Table1[[#This Row],[NÚMERO OPERATIVO]],#REF!,#REF!) -> #REF! | L36: 20264106617264 | M36: =_xlfn.CONCAT(Table1[[#This Row],[NÚMERO OPERATIVO]],Table1[[#This Row],[DATA OC]]) -> 570293512246051,8863888889 | N36: 46051.886 | O36: QUEIMADO | P36: NÃO IDENTIFICADO | Q36: QUEIMADO | R36: 182896 | S36: ILEGÍVEL | T36: INTEL | U36: 06/02/2026 09:33:12 | V36: 3F | W36: 34.5 | X36: 30 | Y36: NÃO É REFORMADO | Z36: NÃO É REFORMADO | AA36: 16/02/2026 | AB36: 1603822 | AC36: 141910 | AD36: 15 | AE36: DLP-MPPA01 000054/2026 | AF36: DOLP-RD-PA | AG36: 112600223 | AH36: 1
A37: =_xlfn.CONCAT(Table1[[#This Row],[NÚMERO OPERATIVO]],Table1[[#This Row],[OS (SGM)]]) -> 5703014122DLP-MLPA01 000052/2026 | C37: ETO | D37: 5703014122DLP-MLPA01 000052/2026 | E37: CENTRO | F37: PALMAS | G37: PALMAS | H37: RURAL | I37: LD01100001 | J37: 5703014122 | K37: =_xlfn.XLOOKUP(Table1[[#This Row],[NÚMERO OPERATIVO]],#REF!,#REF!) -> #REF! | L37: 20264118321656 | M37: =_xlfn.CONCAT(Table1[[#This Row],[NÚMERO OPERATIVO]],Table1[[#This Row],[DATA OC]]) -> 570301412246058,4309722222 | N37: 46058.431 | O37: QUEIMADO | P37: DESCARGA ATMOSFÉRICA | Q37: QUEIMADO | V37: 1F | W37: 34.5 | X37: 5 | AD37: 15 | AE37: DLP-MLPA01 000052/2026 | AF37: DOLP-RD-PA | AG37: 112600332 | AH37: 1
A38: =_xlfn.CONCAT(Table1[[#This Row],[NÚMERO OPERATIVO]],Table1[[#This Row],[OS (SGM)]]) -> 5211917122DLP-MLPA01 000064/2026 | C38: ETO | D38: 5211917122DLP-MLPA01 000064/2026 | E38: CENTRO | F38: PALMAS | G38: PALMAS | H38: RURAL | I38: LD02059122 | J38: 5211917122 | K38: =_xlfn.XLOOKUP(Table1[[#This Row],[NÚMERO OPERATIVO]],#REF!,#REF!) -> #REF! | L38: 20264127916456 | M38: =_xlfn.CONCAT(Table1[[#This Row],[NÚMERO OPERATIVO]],Table1[[#This Row],[DATA OC]]) -> 521191712246067,7774884259 | N38: 46067.777 | O38: QUEIMADO | P38: NÃO IDENTIFICADO | Q38: QUEIMADO | R38: 550845 | S38: 125885 | T38: TRAEL | U38: 01/06/2020 10:07:49 | V38: 1F | W38: 34.5 | X38: 15 | Y38: NÃO É REFORMADO | Z38: NÃO É REFORMADO | AA38: 05/03/2026 | AB38: 482499 | AC38: 118265 | AD38: 15 | AE38: DLP-MLPA01 000064/2026 | AF38: DOLP-RD-PA | AG38: 112600262 | AH38: 1
A39: =_xlfn.CONCAT(Table1[[#This Row],[NÚMERO OPERATIVO]],Table1[[#This Row],[OS (SGM)]]) -> 5700101100DLP-MLPA01 000072/2026 | C39: ETO | D39: 5700101100DLP-MLPA01 000072/2026 | E39: CENTRO | F39: PALMAS | G39: PALMAS | H39: RURAL | I39: LD02059122 | J39: 5700101100 | K39: =_xlfn.XLOOKUP(Table1[[#This Row],[NÚMERO OPERATIVO]],#REF!,#REF!) -> #REF! | L39: 20264130932361 | M39: =_xlfn.CONCAT(Table1[[#This Row],[NÚMERO OPERATIVO]],Table1[[#This Row],[DATA OC]]) -> 570010110046071,7866087963 | N39: 46071.787 | O39: QUEIMADO | P39: DESCARGA ATMOSFÉRICA | Q39: QUEIMADO | R39: 928991 | S39: 01454 | T39: ITB | U39: 01/01/2015 17:09:48 | V39: 1F | W39: 34.5 | X39: 10 | Y39: NÃO É REFORMADO | Z39: NÃO É REFORMADO | AA39: 05/03/2026 | AB39: 498289 | AC39: 119474 | AD39: 15 | AE39: DLP-MLPA01 000072/2026 | AF39: DOLP-RD-PA | AG39: 112600267 | AH39: 1
A40: =_xlfn.CONCAT(Table1[[#This Row],[NÚMERO OPERATIVO]],Table1[[#This Row],[OS (SGM)]]) -> 5700109100DLP-CTPA00 000001/2026 | C40: ETO | D40: 5700109100DLP-CTPA00 000001/2026 | E40: CENTRO | F40: PALMAS | G40: PALMAS | H40: RURAL | I40: LD02059122 | J40: 5700109100 | K40: =_xlfn.XLOOKUP(Table1[[#This Row],[NÚMERO OPERATIVO]],#REF!,#REF!) -> #REF! | L40: 20264066776703 | M40: =_xlfn.CONCAT(Table1[[#This Row],[NÚMERO OPERATIVO]],Table1[[#This Row],[DATA OC]]) -> 570010910046027,5527199074 | N40: 46027.553 | O40: QUEIMADO | P40: DESCARGA ATMOSFÉRICA | Q40: QUEIMADO | R40: 395727 | S40: 103028 | T40: TRAEL | U40: 01/07/2018 10:35:55 | V40: 3F | W40: 34.5 | X40: 30 | Y40: TRAEL | Z40: TRAEL | AA40: 01/04/2018 | AB40: 480412 | AC40: 113252 | AD40: 45 | AE40: DLP-CTPA00 000001/2026 | AF40: DOLP-RD-PA | AG40: 112600170 | AH40: 1
A41: =_xlfn.CONCAT(Table1[[#This Row],[NÚMERO OPERATIVO]],Table1[[#This Row],[OS (SGM)]]) -> 5703012059DLP-MLPA01 000062/2026 | C41: ETO | D41: 5703012059DLP-MLPA01 000062/2026 | E41: CENTRO | F41: PALMAS | G41: PALMAS | H41: RURAL | I41: LD02059122 | J41: 5703012059 | K41: =_xlfn.XLOOKUP(Table1[[#This Row],[NÚMERO OPERATIVO]],#REF!,#REF!) -> #REF! | L41: 20264126831105 | M41: =_xlfn.CONCAT(Table1[[#This Row],[NÚMERO OPERATIVO]],Table1[[#This Row],[DATA OC]]) -> 570301205946066,7540162037 | N41: 46066.754 | O41: QUEIMADO | P41: NÃO IDENTIFICADO | Q41: QUEIMADO | R41: 459021 | S41: 112570 | T41: TRAEL | U41: 16/02/2018 17:05:11 | V41: 1F | W41: 34.5 | X41: 15 | Y41: NÃO É REFORMADO | Z41: NÃO É REFORMADO | AA41: 16/02/2026 | AB41: 297834 | AC41: 149870 | AD41: 15 | AE41: DLP-MLPA01 000062/2026 | AF41: DOLP-RD-PA | AG41: 112600240 | AH41: 1
A42: =_xlfn.CONCAT(Table1[[#This Row],[NÚMERO OPERATIVO]],Table1[[#This Row],[OS (SGM)]]) -> 5703525122DLP-MLPA01 000005/2026 | C42: ETO | D42: 5703525122DLP-MLPA01 000005/2026 | E42: CENTRO | F42: PALMAS | G42: PALMAS | H42: RURAL | I42: LD02059122 | J42: 5703525122 | K42: =_xlfn.XLOOKUP(Table1[[#This Row],[NÚMERO OPERATIVO]],#REF!,#REF!) -> #REF! | L42: 20264070736909 | M42: =_xlfn.CONCAT(Table1[[#This Row],[NÚMERO OPERATIVO]],Table1[[#This Row],[DATA OC]]) -> 570352512246032,2379513889 | N42: 46032.238 | O42: QUEIMADO | P42: DESCARGA ATMOSFÉRICA | Q42: QUEIMADO | R42: 896349 | S42: 121244 | T42: ABB | U42: 10/02/2026 10:20:27 | V42: 1F | W42: 34.5 | X42: 15 | Y42: CPFL | Z42: CPFL | AA42: 10/02/2026 | AB42: 1615834 | AC42: 146312 | AD42: 15 | AE42: DLP-MLPA01 000005/2026 | AF42: DOLP-RD-PA | AG42: 112600275 | AH42: 1
A43: =_xlfn.CONCAT(Table1[[#This Row],[NÚMERO OPERATIVO]],Table1[[#This Row],[OS (SGM)]]) -> 5705022122DLP-MLPA02 000004/2026 | C43: ETO | D43: 5705022122DLP-MLPA02 000004/2026 | E43: CENTRO | F43: PALMAS | G43: PALMAS | H43: RURAL | I43: LD02059122 | J43: 5705022122 | K43: =_xlfn.XLOOKUP(Table1[[#This Row],[NÚMERO OPERATIVO]],#REF!,#REF!) -> #REF! | L43: 20264079599541 | M43: =_xlfn.CONCAT(Table1[[#This Row],[NÚMERO OPERATIVO]],Table1[[#This Row],[DATA OC]]) -> 570502212246035,7875810185 | N43: 46035.788 | O43: QUEIMADO | P43: DESCARGA ATMOSFÉRICA | Q43: QUEIMADO | R43: 0 | S43: 0 | T43: ABB | U43: 19/01/2026 10:36:11 | V43: 1F | W43: 34.5 | X43: 10 | Y43: CPFL | Z43: CPFL | AB43: 0 | AC43: 0 | AD43: 15 | AE43: DLP-MLPA02 000004/2026 | AF43: DOLP-RD-PA | AG43: 112600224 | AH43: 1
A44: =_xlfn.CONCAT(Table1[[#This Row],[NÚMERO OPERATIVO]],Table1[[#This Row],[OS (SGM)]]) -> 5710061122DLP-MPPA01 000033/2026 | C44: ETO | D44: 5710061122DLP-MPPA01 000033/2026 | E44: CENTRO | F44: PALMAS | G44: PALMAS | H44: RURAL | I44: LD02059122 | J44: 5710061122 | K44: =_xlfn.XLOOKUP(Table1[[#This Row],[NÚMERO OPERATIVO]],#REF!,#REF!) -> #REF! | L44: 20264086104706 | M44: =_xlfn.CONCAT(Table1[[#This Row],[NÚMERO OPERATIVO]],Table1[[#This Row],[DATA OC]]) -> 571006112246041,5346643518 | N44: 46041.535 | O44: QUEIMADO | P44: NÃO IDENTIFICADO | Q44: QUEIMADO | R44: 371794 | S44: 121222 | T44: TRAEL | U44: 01/12/1999 07:35:06 | V44: 1F | W44: 34.5 | X44: 15 | Y44: NÃO É REFORMADO | Z44: NÃO É REFORMADO | AA44: 21/01/2026 | AB44: 271327 | AC44: 145138 | AD44: 25 | AE44: DLP-MPPA01 000033/2026 | AF44: DOLP-RD-PA | AG44: 112600133 | AH44: 1
A45: =_xlfn.CONCAT(Table1[[#This Row],[NÚMERO OPERATIVO]],Table1[[#This Row],[OS (SGM)]]) -> 5710565122DLP-MLPA01 000071/2026 | C45: ETO | D45: 5710565122DLP-MLPA01 000071/2026 | E45: CENTRO | F45: PALMAS | G45: PALMAS | H45: RURAL | I45: LD02059122 | J45: 5710565122 | K45: =_xlfn.XLOOKUP(Table1[[#This Row],[NÚMERO OPERATIVO]],#REF!,#REF!) -> #REF! | L45: 20264130146887 | M45: =_xlfn.CONCAT(Table1[[#This Row],[NÚMERO OPERATIVO]],Table1[[#This Row],[DATA OC]]) -> 571056512246071,6366550926 | N45: 46071.637 | O45: QUEIMADO | P45: DESCARGA ATMOSFÉRICA | Q45: QUEIMADO | R45: 481700 | S45: 24324 | T45: ITAIPU | U45: 05/03/2026 13:13:38 | V45: 1F | W45: 34.5 | X45: 10 | Y45: NÃO É REFORMADO | Z45: NÃO É REFORMADO | AA45: 05/03/2026 | AB45: 254185 | AC45: 142974 | AD45: 25 | AE45: DLP-MLPA01 000071/2026 | AF45: DOLP-RD-PA | AG45: 112600265 | AH45: 1
A46: =_xlfn.CONCAT(Table1[[#This Row],[NÚMERO OPERATIVO]],Table1[[#This Row],[OS (SGM)]]) -> 5711864122DLP-MLPA01 000025/2026 | C46: ETO | D46: 5711864122DLP-MLPA01 000025/2026 | E46: CENTRO | F46: PALMAS | G46: PALMAS | H46: RURAL | I46: LD02059122 | J46: 5711864122 | K46: =_xlfn.XLOOKUP(Table1[[#This Row],[NÚMERO OPERATIVO]],#REF!,#REF!) -> #REF! | L46: 20264100806292 | M46: =_xlfn.CONCAT(Table1[[#This Row],[NÚMERO OPERATIVO]],Table1[[#This Row],[DATA OC]]) -> 571186412246049,8711921296 | N46: 46049.871 | O46: QUEIMADO | P46: DESCARGA ATMOSFÉRICA | Q46: QUEIMADO | R46: 393912 | S46: ILEGIVEL | T46: MACZ | U46: 01/04/2006 09:52:04 | V46: 1F | W46: 34.5 | X46: 10 | Y46: NÃO É REFORMADO | Z46: NÃO É REFORMADO | AA46: 31/01/2026 | AB46: 290261 | AC46: 149700 | AD46: 15 | AE46: DLP-MLPA01 000025/2026 | AF46: DOLP-RD-PA | AG46: 112600251 | AH46: 1
A47: =_xlfn.CONCAT(Table1[[#This Row],[NÚMERO OPERATIVO]],Table1[[#This Row],[OS (SGM)]]) -> 5711933122DLP-MLPA01 000021/2026 | C47: ETO | D47: 5711933122DLP-MLPA01 000021/2026 | E47: CENTRO | F47: PALMAS | G47: PALMAS | H47: RURAL | I47: LD02059122 | J47: 5711933122 | K47: =_xlfn.XLOOKUP(Table1[[#This Row],[NÚMERO OPERATIVO]],#REF!,#REF!) -> #REF! | L47: 20264095769617 | M47: =_xlfn.CONCAT(Table1[[#This Row],[NÚMERO OPERATIVO]],Table1[[#This Row],[DATA OC]]) -> 571193312246047,5244328704 | N47: 46047.524 | O47: QUEIMADO | P47: NÃO IDENTIFICADO | Q47: QUEIMADO | R47: 181042 | S47: ILEGIVEL | T47: ABB | U47: 01/09/2007 08:34:47 | V47: 1F | W47: 34.5 | X47: 15 | Y47: NÃO É REFORMADO | Z47: NÃO É REFORMADO | AA47: 30/01/2026 | AB47: 799443 | AC47: 149094 | AD47: 15 | AE47: DLP-MLPA01 000021/2026 | AF47: DOLP-RD-PA | AG47: 112600144 | AH47: 1
A48: =_xlfn.CONCAT(Table1[[#This Row],[NÚMERO OPERATIVO]],Table1[[#This Row],[OS (SGM)]]) -> 5712197122DLP-MLPA02 000017/2026 | C48: ETO | D48: 5712197122DLP-MLPA02 000017/2026 | E48: CENTRO | F48: PALMAS | G48: PALMAS | H48: RURAL | I48: LD02059122 | J48: 5712197122 | K48: =_xlfn.XLOOKUP(Table1[[#This Row],[NÚMERO OPERATIVO]],#REF!,#REF!) -> #REF! | L48: 20264130105217 | M48: =_xlfn.CONCAT(Table1[[#This Row],[NÚMERO OPERATIVO]],Table1[[#This Row],[DATA OC]]) -> 571219712246071,5652777778 | N48: 46071.565 | O48: QUEIMADO | P48: DESCARGA ATMOSFÉRICA | Q48: QUEIMADO | R48: 371905 | S48: 00044415 | T48: TOSHIBA | U48: 01/04/2013 11:36:05 | V48: 1F | W48: 34.5 | X48: 15 | Y48: NÃO É REFORMADO | Z48: NÃO É REFORMADO | AB48: 178608 | AC48: 0 | AD48: 15 | AE48: DLP-MLPA02 000017/2026 | AF48: DOLP-RD-PA | AG48: 112600407 | AH48: 1
A49: =_xlfn.CONCAT(Table1[[#This Row],[NÚMERO OPERATIVO]],Table1[[#This Row],[OS (SGM)]]) -> 5712275122DLP-MLPA01 000070/2026 | C49: ETO | D49: 5712275122DLP-MLPA01 000070/2026 | E49: CENTRO | F49: PALMAS | G49: PALMAS | H49: RURAL | I49: LD02059122 | J49: 5712275122 | K49: =_xlfn.XLOOKUP(Table1[[#This Row],[NÚMERO OPERATIVO]],#REF!,#REF!) -> #REF! | L49: 20264129197593 | M49: =_xlfn.CONCAT(Table1[[#This Row],[NÚMERO OPERATIVO]],Table1[[#This Row],[DATA OC]]) -> 571227512246070,514375 | N49: 46070.514 | O49: QUEIMADO | P49: NÃO IDENTIFICADO | Q49: QUEIMADO | R49: 80759 | S49: 0 | T49: TRAEL | U49: 06/03/2010 10:02:47 | V49: 1F | W49: 34.5 | X49: 10 | Y49: NÃO É REFORMADO | Z49: NÃO É REFORMADO | AB49: 468084 | AC49: 115062 | AD49: 15 | AE49: DLP-MLPA01 000070/2026 | AF49: DOLP-RD-PA | AG49: 112600402 | AH49: 1
A50: =_xlfn.CONCAT(Table1[[#This Row],[NÚMERO OPERATIVO]],Table1[[#This Row],[OS (SGM)]]) -> 5712754122DLP-MLPA01 000058/2026 | C50: ETO | D50: 5712754122DLP-MLPA01 000058/2026 | E50: CENTRO | F50: PALMAS | G50: PALMAS | H50: RURAL | I50: LD02059122 | J50: 5712754122 | K50: =_xlfn.XLOOKUP(Table1[[#This Row],[NÚMERO OPERATIVO]],#REF!,#REF!) -> #REF! | L50: 20264123995988 | M50: =_xlfn.CONCAT(Table1[[#This Row],[NÚMERO OPERATIVO]],Table1[[#This Row],[DATA OC]]) -> 571275412246064,8042824074 | N50: 46064.804 | O50: QUEIMADO | P50: DESCARGA ATMOSFÉRICA | Q50: QUEIMADO | R50: 443048 | S50: 120865 | T50: TRAEL | U50: 01/09/2011 16:13:18 | V50: 1F | W50: 34.5 | X50: 15 | Y50: NÃO É REFORMADO | Z50: NÃO É REFORMADO | AA50: 19/02/2026 | AB50: 250326 | AC50: 141092 | AD50: 25 | AE50: DLP-MLPA01 000058/2026 | AF50: DOLP-RD-PA | AG50: 112600239 | AH50: 1
A51: =_xlfn.CONCAT(Table1[[#This Row],[NÚMERO OPERATIVO]],Table1[[#This Row],[OS (SGM)]]) -> 5712754122DLP-MLPA01 000067/2026 | C51: ETO | D51: 5712754122DLP-MLPA01 000067/2026 | E51: CENTRO | F51: PALMAS | G51: PALMAS | H51: RURAL | I51: LD02059122 | J51: 5712754122 | K51: =_xlfn.XLOOKUP(Table1[[#This Row],[NÚMERO OPERATIVO]],#REF!,#REF!) -> #REF! | L51: 20264128532536 | M51: =_xlfn.CONCAT(Table1[[#This Row],[NÚMERO OPERATIVO]],Table1[[#This Row],[DATA OC]]) -> 571275412246069,4438078704 | N51: 46069.444 | O51: QUEIMADO | P51: DESCARGA ATMOSFÉRICA | Q51: QUEIMADO | R51: 250326 | S51: 146092 | T51: TRAEL | U51: 05/03/2025 10:38:07 | V51: 1F | W51: 34.5 | X51: 25 | Y51: NÃO É REFORMADO | Z51: NÃO É REFORMADO | AA51: 05/03/2026 | AB51: 289718 | AC51: 148578 | AD51: 25 | AE51: DLP-MLPA01 000067/2026 | AF51: DOLP-RD-PA | AG51: 112600414 | AH51: 1
A52: =_xlfn.CONCAT(Table1[[#This Row],[NÚMERO OPERATIVO]],Table1[[#This Row],[OS (SGM)]]) -> 5735803122DLP-MLPA02 000011/2026 | C52: ETO | D52: 5735803122DLP-MLPA02 000011/2026 | E52: CENTRO | F52: PALMAS | G52: PALMAS | H52: RURAL | I52: LD02059122 | J52: 5735803122 | K52: =_xlfn.XLOOKUP(Table1[[#This Row],[NÚMERO OPERATIVO]],#REF!,#REF!) -> #REF! | L52: 20264111909605 | M52: =_xlfn.CONCAT(Table1[[#This Row],[NÚMERO OPERATIVO]],Table1[[#This Row],[DATA OC]]) -> 573580312246052,7641087963 | N52: 46052.764 | O52: QUEIMADO | P52: DESCARGA ATMOSFÉRICA | Q52: QUEIMADO | R52: 473548 | S52: 126677 | T52: TRAEL | U52: 01/08/2018 10:09:33 | V52: 1F | W52: 34.5 | X52: 15 | Y52: POTENCIAL | Z52: NÃO É REFORMADO | AA52: 01/06/2021 | AB52: 290106 | AC52: 149813 | AD52: 15 | AE52: DLP-MLPA02 000011/2026 | AF52: DOLP-RD-PA | AG52: 112600169 | AH52: 1
A53: =_xlfn.CONCAT(Table1[[#This Row],[NÚMERO OPERATIVO]],Table1[[#This Row],[OS (SGM)]]) -> 5703466122DLP-MLPA02 000002/2026 | C53: ETO | D53: 5703466122DLP-MLPA02 000002/2026 | E53: CENTRO | F53: PALMAS | G53: PALMAS | H53: RURAL | I53: LD03059122 | J53: 5703466122 | K53: =_xlfn.XLOOKUP(Table1[[#This Row],[NÚMERO OPERATIVO]],#REF!,#REF!) -> #REF! | L53: 20264067304419 | M53: =_xlfn.CONCAT(Table1[[#This Row],[NÚMERO OPERATIVO]],Table1[[#This Row],[DATA OC]]) -> 570346612246028,6636226852 | N53: 46028.664 | O53: QUEIMADO | P53: DESCARGA ATMOSFÉRICA | Q53: QUEIMADO | R53: 1615818 | S53: 146296 | T53: ROMAGNOLE | U53: 01/04/2025 16:14:49 | V53: 1F | W53: 34.5 | X53: 15 | Y53: NÃO É REFORMADO | Z53: NÃO É REFORMADO | AA53: 15/01/2026 | AB53: 1615853 | AC53: 146296 | AD53: 15 | AE53: DLP-MLPA02 000002/2026 | AF53: DOLP-RD-PA | AG53: 112600101 | AH53: 1
A54: =_xlfn.CONCAT(Table1[[#This Row],[NÚMERO OPERATIVO]],Table1[[#This Row],[OS (SGM)]]) -> 5710444122DLP-MPPA01 000051/2026 | C54: ETO | D54: 5710444122DLP-MPPA01 000051/2026 | E54: CENTRO | F54: PALMAS | G54: PALMAS | H54: RURAL | I54: LD03059122 | J54: 5710444122 | K54: =_xlfn.XLOOKUP(Table1[[#This Row],[NÚMERO OPERATIVO]],#REF!,#REF!) -> #REF! | L54: 20264106162701 | M54: =_xlfn.CONCAT(Table1[[#This Row],[NÚMERO OPERATIVO]],Table1[[#This Row],[DATA OC]]) -> 571044412246051,4555902778 | N54: 46051.456 | O54: QUEIMADO | P54: DESCARGA ATMOSFÉRICA | Q54: QUEIMADO | R54: - | S54: - | T54: INTEL | U54: 01/04/2010 09:09:31 | V54: 1F | W54: 34.5 | X54: 10 | Y54: NÃO É REFORMADO | Z54: NÃO É REFORMADO | AA54: 31/01/2026 | AB54: 290335 | AC54: - | AD54: 15 | AE54: DLP-MPPA01 000051/2026 | AF54: DOLP-RD-PA | AG54: 112600253 | AH54: 1
A55: =_xlfn.CONCAT(Table1[[#This Row],[NÚMERO OPERATIVO]],Table1[[#This Row],[OS (SGM)]]) -> 5757168122DLP-CTPA01 000018/2026 | C55: ETO | D55: 5757168122DLP-CTPA01 000018/2026 | E55: CENTRO | F55: PALMAS | G55: PALMAS | H55: RURAL | I55: LD03059122 | J55: 5757168122 | K55: =_xlfn.XLOOKUP(Table1[[#This Row],[NÚMERO OPERATIVO]],#REF!,#REF!) -> #REF! | L55: 20264123842425 | M55: =_xlfn.CONCAT(Table1[[#This Row],[NÚMERO OPERATIVO]],Table1[[#This Row],[DATA OC]]) -> 575716812246064,5262731481 | N55: 46064.526 | O55: QUEIMADO | P55: DESCARGA ATMOSFÉRICA | Q55: QUEIMADO | V55: 3F | W55: 34.5 | X55: 75 | AD55: 75 | AE55: DLP-CTPA01 000018/2026 | AF55: DOLP-RD-PA | AG55: 112600429 | AH55: 1
A56: =_xlfn.CONCAT(Table1[[#This Row],[NÚMERO OPERATIVO]],Table1[[#This Row],[OS (SGM)]]) -> 5723384122DLP-MLPA01 000027/2026 | C56: ETO | D56: 5723384122DLP-MLPA01 000027/2026 | E56: CENTRO | F56: PALMAS | G56: PALMAS | H56: URBANO | I56: AL01099059 | J56: 5723384122 | K56: =_xlfn.XLOOKUP(Table1[[#This Row],[NÚMERO OPERATIVO]],#REF!,#REF!) -> #REF! | L56: 20264100789602 | M56: =_xlfn.CONCAT(Table1[[#This Row],[NÚMERO OPERATIVO]],Table1[[#This Row],[DATA OC]]) -> 572338412246049,6788888889 | N56: 46049.679 | O56: AVARIADO | P56: SOBRECARGA | Q56: AVARIADO | R56: 364589 | S56: ILEGIVEL | T56: TRAEL | U56: 01/10/2015 09:33:03 | V56: 1F | W56: 13.8 | X56: 15 | Y56: NÃO É REFORMADO | Z56: NÃO É REFORMADO | AA56: 31/01/2026 | AB56: 253978 | AC56: 142021 | AD56: 25 | AE56: DLP-MLPA01 000027/2026 | AF56: DOLP-RD-PA | AG56: 112600252 | AH56: 1
A57: =_xlfn.CONCAT(Table1[[#This Row],[NÚMERO OPERATIVO]],Table1[[#This Row],[OS (SGM)]]) -> 5711359122DLP-CTPA00 000014/2026 | C57: ETO | D57: 5711359122DLP-CTPA00 000014/2026 | E57: CENTRO | F57: PALMAS | G57: PALMAS | H57: URBANO | I57: AL03060122 | J57: 5711359122 | K57: =_xlfn.XLOOKUP(Table1[[#This Row],[NÚMERO OPERATIVO]],#REF!,#REF!) -> #REF! | L57: 20264090076216 | M57: =_xlfn.CONCAT(Table1[[#This Row],[NÚMERO OPERATIVO]],Table1[[#This Row],[DATA OC]]) -> 571135912246043,4741550926 | N57: 46043.474 | O57: AVARIADO | P57: VAZAMENTO DE ÓLEO | Q57: AVARIADO | R57: 124519 | S57: ILEGIVEL | T57: ITB | U57: 30/01/1999 08:54:43 | V57: 3F | W57: 13.8 | X57: 75 | Y57: NÃO É REFORMADO | Z57: NÃO É REFORMADO | AA57: 30/01/2026 | AB57: 305072 | AC57: 148832 | AD57: 112.5 | AE57: DLP-CTPA00 000014/2026 | AF57: DOLP-RD-PA | AG57: 112600135 | AH57: 1
A58: =_xlfn.CONCAT(Table1[[#This Row],[NÚMERO OPERATIVO]],Table1[[#This Row],[OS (SGM)]]) -> 5762443122DLP-MPPA01 000019/2026 | C58: ETO | D58: 5762443122DLP-MPPA01 000019/2026 | E58: CENTRO | F58: PALMAS | G58: PALMAS | H58: URBANO | I58: AL03097122 | J58: 5762443122 | K58: =_xlfn.XLOOKUP(Table1[[#This Row],[NÚMERO OPERATIVO]],#REF!,#REF!) -> #REF! | L58: 20264070092688 | M58: =_xlfn.CONCAT(Table1[[#This Row],[NÚMERO OPERATIVO]],Table1[[#This Row],[DATA OC]]) -> 576244312246031,3584259259 | N58: 46031.358 | O58: QUEIMADO | P58: NÃO IDENTIFICADO | Q58: QUEIMADO | R58: 1587786 | S58: 144006 | T58: ROMAGNOLE | U58: 01/11/2024 09:27:13 | V58: 3F | W58: 13.8 | X58: 75 | Y58: NÃO É REFORMADO | Z58: NÃO É REFORMADO | AA58: 16/01/2026 | AB58: 582453 | AC58: 147425 | AD58: 75 | AE58: DLP-MPPA01 000019/2026 | AF58: DOLP-RD-PA | AG58: 112600114 | AH58: 1
A59: =_xlfn.CONCAT(Table1[[#This Row],[NÚMERO OPERATIVO]],Table1[[#This Row],[OS (SGM)]]) -> 5704495122DLP-MPPA01 000049/2026 | C59: ETO | D59: 5704495122DLP-MPPA01 000049/2026 | E59: CENTRO | F59: PALMAS | G59: PALMAS | H59: URBANO | I59: AL04059122 | J59: 5704495122 | K59: =_xlfn.XLOOKUP(Table1[[#This Row],[NÚMERO OPERATIVO]],#REF!,#REF!) -> #REF! | L59: SERA GERADO NA HORA | M59: =_xlfn.CONCAT(Table1[[#This Row],[NÚMERO OPERATIVO]],Table1[[#This Row],[DATA OC]]) -> 570449512246049,5760185185 | N59: 46049.576 | O59: AVARIADO | P59: VAZAMENTO DE ÓLEO | Q59: AVARIADO | R59: 175547 | S59: 36909 | T59: TRAEL | U59: 31/01/2010 09:19:22 | V59: 3F | W59: 13.8 | X59: 75 | Y59: NÃO É REFORMADO | Z59: NÃO É REFORMADO | AA59: 31/01/2026 | AB59: 1648849 | AC59: 148970 | AD59: 75 | AE59: DLP-MPPA01 000049/2026 | AF59: DOLP-RD-PA | AG59: 112600280 | AH59: 1
A60: =_xlfn.CONCAT(Table1[[#This Row],[NÚMERO OPERATIVO]],Table1[[#This Row],[OS (SGM)]]) -> 5735643059DLP-MPPA01 000061/2026 | C60: ETO | D60: 5735643059DLP-MPPA01 000061/2026 | E60: CENTRO | F60: PALMAS | G60: PALMAS | H60: URBANO | I60: AL06099059 | J60: 5735643059 | K60: =_xlfn.XLOOKUP(Table1[[#This Row],[NÚMERO OPERATIVO]],#REF!,#REF!) -> #REF! | L60: 20264119055883 | M60: =_xlfn.CONCAT(Table1[[#This Row],[NÚMERO OPERATIVO]],Table1[[#This Row],[DATA OC]]) -> 573564305946059,2889814815 | N60: 46059.289 | O60: QUEIMADO | P60: BUCHA DANIFICADA | Q60: QUEIMADO | R60: 457520 | S60: 1101 | T60: TRAEL | U60: 01/02/2016 10:00:13 | V60: 3F | W60: 13.8 | X60: 75 | Y60: NÃO É REFORMADO | Z60: NÃO É REFORMADO | AB60: 1648839 | AC60: 148960 | AD60: 75 | AE60: DLP-MPPA01 000061/2026 | AF60: DOLP-RD-PA | AG60: 112600409 | AH60: 1
A61: =_xlfn.CONCAT(Table1[[#This Row],[NÚMERO OPERATIVO]],Table1[[#This Row],[OS (SGM)]]) -> 5700707122DLP-MPPA01 000066/2026 | C61: ETO | D61: 5700707122DLP-MPPA01 000066/2026 | E61: CENTRO | F61: PALMAS | G61: PALMAS | H61: URBANO | I61: AL07097122 | J61: 5700707122 | K61: =_xlfn.XLOOKUP(Table1[[#This Row],[NÚMERO OPERATIVO]],#REF!,#REF!) -> #REF! | L61: Vai abrir na hora da atividade | M61: =_xlfn.CONCAT(Table1[[#This Row],[NÚMERO OPERATIVO]],Table1[[#This Row],[DATA OC]]) -> 570070712246065,6394560185 | N61: 46065.639 | O61: AVARIADO | P61: VAZAMENTO DE ÓLEO | Q61: AVARIADO | R61: 102297 | S61: 10776 | T61: INTEL | U61: 01/11/1998 09:02:43 | V61: 3F | W61: 13.8 | X61: 75 | Y61: NÃO É REFORMADO | Z61: NÃO É REFORMADO | AB61: 1647129 | AC61: 148954 | AD61: 75 | AE61: DLP-MPPA01 000066/2026 | AF61: DOLP-RD-PA | AG61: 112600408 | AH61: 1
A62: =_xlfn.CONCAT(Table1[[#This Row],[NÚMERO OPERATIVO]],Table1[[#This Row],[OS (SGM)]]) -> 5700725122DLP-MPPA01 000027/2026 | C62: ETO | D62: 5700725122DLP-MPPA01 000027/2026 | E62: CENTRO | F62: PALMAS | G62: PALMAS | H62: URBANO | I62: AL07097122 | J62: 5700725122 | K62: =_xlfn.XLOOKUP(Table1[[#This Row],[NÚMERO OPERATIVO]],#REF!,#REF!) -> #REF! | L62: 20264079656968 | M62: =_xlfn.CONCAT(Table1[[#This Row],[NÚMERO OPERATIVO]],Table1[[#This Row],[DATA OC]]) -> 570072512246036,0304282407 | N62: 46036.03 | O62: QUEIMADO | P62: DESCARGA ATMOSFÉRICA | Q62: QUEIMADO | R62: 0 | S62: 2 | T62: ABB | U62: 19/01/2026 10:16:34 | V62: 3F | W62: 13.8 | X62: 10 | Y62: CPFL | Z62: CPFL | AA62: 19/01/2026 | AB62: 144002 | AC62: 1587782 | AD62: 15 | AE62: DLP-MPPA01 000027/2026 | AF62: DOLP-RD-PA | AG62: 112600152 | AH62: 1
A63: =_xlfn.CONCAT(Table1[[#This Row],[NÚMERO OPERATIVO]],Table1[[#This Row],[OS (SGM)]]) -> 5700935122ETO-RD-PA 000103/2026 | C63: ETO | D63: 5700935122ETO-RD-PA 000103/2026 | E63: CENTRO | F63: PALMAS | G63: PALMAS | H63: URBANO | I63: AL09059122 | J63: 5700935122 | K63: =_xlfn.XLOOKUP(Table1[[#This Row],[NÚMERO OPERATIVO]],#REF!,#REF!) -> #REF! | L63: SERA GERADO NA HORA | M63: =_xlfn.CONCAT(Table1[[#This Row],[NÚMERO OPERATIVO]],Table1[[#This Row],[DATA OC]]) -> 570093512246029,3116435185 | N63: 46029.312 | O63: AVARIADO | P63: VAZAMENTO DE ÓLEO | Q63: AVARIADO | V63: 3F | W63: 13.8 | X63: 75 | AD63: 75 | AE63: ETO-RD-PA 000103/2026 | AF63: ETO-RD-PA | AH63: 1
A64: =_xlfn.CONCAT(Table1[[#This Row],[NÚMERO OPERATIVO]],Table1[[#This Row],[OS (SGM)]]) -> 5710049096DLP-CTPA00 000034/2026 | C64: ETO | D64: 5710049096DLP-CTPA00 000034/2026 | E64: CENTRO | F64: PALMAS | G64: PINDORAMA DO TOCANTINS | H64: RURAL | I64: LD03046026 | J64: 5710049096 | K64: =_xlfn.XLOOKUP(Table1[[#This Row],[NÚMERO OPERATIVO]],#REF!,#REF!) -> #REF! | L64: 20264113461254 | M64: =_xlfn.CONCAT(Table1[[#This Row],[NÚMERO OPERATIVO]],Table1[[#This Row],[DATA OC]]) -> 571004909646056,3560416667 | N64: 46056.356 | O64: QUEIMADO | P64: DESCARGA ATMOSFÉRICA | Q64: QUEIMADO | R64: 1234038 | S64: 124872 | T64: ROMAGNOLE | U64: 01/08/2020 13:37:04 | V64: 3F | W64: 34.5 | X64: 45 | Y64: CPFL | Z64: CPFL | AB64: 113303 | AC64: 338021 | AD64: 45 | AE64: DLP-CTPA00 000034/2026 | AF64: DOLP-RD-PA | AG64: 112600400 | AH64: 1
A65: =_xlfn.CONCAT(Table1[[#This Row],[NÚMERO OPERATIVO]],Table1[[#This Row],[OS (SGM)]]) -> 5755307026DLP-MLPA01 000032/2026 | C65: ETO | D65: 5755307026DLP-MLPA01 000032/2026 | E65: CENTRO | F65: PALMAS | G65: PONTE ALTA DO TOCANTINS | H65: RURAL | I65: LD06002091 | J65: 5755307026 | K65: =_xlfn.XLOOKUP(Table1[[#This Row],[NÚMERO OPERATIVO]],#REF!,#REF!) -> #REF! | L65: . | M65: =_xlfn.CONCAT(Table1[[#This Row],[NÚMERO OPERATIVO]],Table1[[#This Row],[DATA OC]]) -> 575530702646056,3554861111 | N65: 46056.355 | O65: QUEIMADO | P65: DESCARGA ATMOSFÉRICA | Q65: QUEIMADO | R65: 1026962 | S65: 102642 | T65: ITB | U65: 01/12/2021 15:08:33 | V65: 1F | W65: 34.5 | X65: 15 | Y65: CPFL | Z65: NÃO É REFORMADO | AA65: 28/12/2024 | AB65: 287170 | AC65: 0 | AD65: 15 | AE65: DLP-MLPA01 000032/2026 | AF65: DOLP-RD-PA | AG65: 112600258 | AH65: 1
A66: =_xlfn.CONCAT(Table1[[#This Row],[NÚMERO OPERATIVO]],Table1[[#This Row],[OS (SGM)]]) -> 5704333001DLP-MPPA01 000058/2026 | C66: ETO | D66: 5704333001DLP-MPPA01 000058/2026 | E66: CENTRO | F66: PALMAS | G66: PORTO NACIONAL | H66: RURAL | I66: AL01102271 | J66: 5704333001 | K66: =_xlfn.XLOOKUP(Table1[[#This Row],[NÚMERO OPERATIVO]],#REF!,#REF!) -> #REF! | L66: 20264117081462 | M66: =_xlfn.CONCAT(Table1[[#This Row],[NÚMERO OPERATIVO]],Table1[[#This Row],[DATA OC]]) -> 570433300146056,7823726852 | N66: 46056.782 | O66: QUEIMADO | P66: DESCARGA ATMOSFÉRICA | Q66: QUEIMADO | R66: 107482 | S66: 21938 | T66: TRAEL | U66: 01/04/2007 09:37:16 | V66: 1F | W66: 13.8 | X66: 15 | Y66: NÃO É REFORMADO | Z66: CPFL | AB66: 181888 | AC66: 139719 | AD66: 15 | AE66: DLP-MPPA01 000058/2026 | AF66: DOLP-RD-PA | AG66: 112600175 | AH66: 1
A67: =_xlfn.CONCAT(Table1[[#This Row],[NÚMERO OPERATIVO]],Table1[[#This Row],[OS (SGM)]]) -> 5703917001DLP-MLPA02 000006/2026 | C67: ETO | D67: 5703917001DLP-MLPA02 000006/2026 | E67: CENTRO | F67: PALMAS | G67: PORTO NACIONAL | H67: RURAL | I67: AL02101271 | J67: 5703917001 | K67: =_xlfn.XLOOKUP(Table1[[#This Row],[NÚMERO OPERATIVO]],#REF!,#REF!) -> #REF! | L67: 20264085562410 | M67: =_xlfn.CONCAT(Table1[[#This Row],[NÚMERO OPERATIVO]],Table1[[#This Row],[DATA OC]]) -> 570391700146039,9114351852 | N67: 46039.911 | O67: QUEIMADO | P67: DESCARGA ATMOSFÉRICA | Q67: QUEIMADO | R67: 195862 | S67: 195862 | T67: VIJAI | U67: 01/12/2011 05:36:57 | V67: 1F | W67: 13.8 | X67: 15 | Y67: NÃO É REFORMADO | Z67: CPFL | AA67: 21/01/2026 | AB67: 181726 | AC67: 143444 | AD67: 15 | AE67: DLP-MLPA02 000006/2026 | AF67: DOLP-RD-PA | AG67: 112600153 | AH67: 1
A68: =_xlfn.CONCAT(Table1[[#This Row],[NÚMERO OPERATIVO]],Table1[[#This Row],[OS (SGM)]]) -> 5758057001DLP-MLPA01 000050/2026 | C68: ETO | D68: 5758057001DLP-MLPA01 000050/2026 | E68: CENTRO | F68: PALMAS | G68: PORTO NACIONAL | H68: RURAL | I68: AL02101271 | J68: 5758057001 | K68: =_xlfn.XLOOKUP(Table1[[#This Row],[NÚMERO OPERATIVO]],#REF!,#REF!) -> #REF! | L68: 20264120218160 | M68: =_xlfn.CONCAT(Table1[[#This Row],[NÚMERO OPERATIVO]],Table1[[#This Row],[DATA OC]]) -> 575805700146061,5841319444 | N68: 46061.584 | O68: QUEIMADO | P68: DESCARGA ATMOSFÉRICA | Q68: QUEIMADO | V68: 1F | W68: 13.8 | X68: 25 | AD68: 25 | AE68: DLP-MLPA01 000050/2026 | AF68: DOLP-RD-PA | AG68: 112600432 | AH68: 1
A69: =_xlfn.CONCAT(Table1[[#This Row],[NÚMERO OPERATIVO]],Table1[[#This Row],[OS (SGM)]]) -> 5710549001DLP-MLPA03 000012/2026 | C69: ETO | D69: 5710549001DLP-MLPA03 000012/2026 | E69: CENTRO | F69: PALMAS | G69: PORTO NACIONAL | H69: RURAL | I69: AL03101271 | J69: 5710549001 | K69: =_xlfn.XLOOKUP(Table1[[#This Row],[NÚMERO OPERATIVO]],#REF!,#REF!) -> #REF! | L69: 20264133624843 | M69: =_xlfn.CONCAT(Table1[[#This Row],[NÚMERO OPERATIVO]],Table1[[#This Row],[DATA OC]]) -> 571054900146076,0298611111 | N69: 46076.03 | O69: QUEIMADO | P69: DESCARGA ATMOSFÉRICA | Q69: QUEIMADO | R69: 177877 | S69: ILEGIVEL | T69: INTEL | U69: 05/03/2026 13:57:50 | V69: 1F | W69: 13.8 | X69: 15 | Y69: NÃO É REFORMADO | Z69: NÃO É REFORMADO | AA69: 05/03/2026 | AB69: 820322 | AC69: 149334 | AD69: 15 | AE69: DLP-MLPA03 000012/2026 | AF69: DOLP-RD-PA | AG69: 112600416 | AH69: 1
A70: =_xlfn.CONCAT(Table1[[#This Row],[NÚMERO OPERATIVO]],Table1[[#This Row],[OS (SGM)]]) -> 5704986122DLP-MLPA01 000063/2026 | C70: ETO | D70: 5704986122DLP-MLPA01 000063/2026 | E70: CENTRO | F70: PALMAS | G70: PORTO NACIONAL | H70: RURAL | I70: LD01100001 | J70: 5704986122 | K70: =_xlfn.XLOOKUP(Table1[[#This Row],[NÚMERO OPERATIVO]],#REF!,#REF!) -> #REF! | L70: 20264127815561 | M70: =_xlfn.CONCAT(Table1[[#This Row],[NÚMERO OPERATIVO]],Table1[[#This Row],[DATA OC]]) -> 570498612246067,7258449074 | N70: 46067.726 | O70: QUEIMADO | P70: NÃO IDENTIFICADO | Q70: QUEIMADO | R70: 126934 | S70: N/A | T70: VIJAI | U70: 01/06/2008 10:46:12 | V70: 1F | W70: 34.5 | X70: 5 | Y70: NÃO É REFORMADO | Z70: TRAEL | AB70: 178211 | AC70: 148686 | AD70: 15 | AE70: DLP-MLPA01 000063/2026 | AF70: DOLP-RD-PA | AG70: 112600404 | AH70: 1
A71: =_xlfn.CONCAT(Table1[[#This Row],[NÚMERO OPERATIVO]],Table1[[#This Row],[OS (SGM)]]) -> 5710675001DLP-MLPA01 000019/2026 | C71: ETO | D71: 5710675001DLP-MLPA01 000019/2026 | E71: CENTRO | F71: PALMAS | G71: PORTO NACIONAL | H71: RURAL | I71: LD01100001 | J71: 5710675001 | K71: =_xlfn.XLOOKUP(Table1[[#This Row],[NÚMERO OPERATIVO]],#REF!,#REF!) -> #REF! | L71: 20264089329312 | M71: =_xlfn.CONCAT(Table1[[#This Row],[NÚMERO OPERATIVO]],Table1[[#This Row],[DATA OC]]) -> 571067500146042,9929398148 | N71: 46042.993 | O71: QUEIMADO | P71: DESCARGA ATMOSFÉRICA | Q71: QUEIMADO | R71: 332309 | S71: 129319 | T71: TRAEL | U71: 01/03/2016 17:30:33 | V71: 3F | W71: 34.5 | X71: 30 | Y71: NÃO É REFORMADO | AA71: 29/01/2026 | AB71: 56215007 | AC71: 139114 | AD71: 30 | AE71: DLP-MLPA01 000019/2026 | AF71: DOLP-RD-PA | AG71: 112600155 | AH71: 1
A72: =_xlfn.CONCAT(Table1[[#This Row],[NÚMERO OPERATIVO]],Table1[[#This Row],[OS (SGM)]]) -> 5724423271DLP-MPPA01 000047/2026 | C72: ETO | D72: 5724423271DLP-MPPA01 000047/2026 | E72: CENTRO | F72: PALMAS | G72: PORTO NACIONAL | H72: URBANO | I72: AL03101271 | J72: 5724423271 | K72: =_xlfn.XLOOKUP(Table1[[#This Row],[NÚMERO OPERATIVO]],#REF!,#REF!) -> #REF! | L72: 20264101009297 | M72: =_xlfn.CONCAT(Table1[[#This Row],[NÚMERO OPERATIVO]],Table1[[#This Row],[DATA OC]]) -> 572442327146049,8766666667 | N72: 46049.877 | O72: QUEIMADO | P72: DESCARGA ATMOSFÉRICA | Q72: QUEIMADO | R72: 4652 | S72: 24491 | T72: TRAEL | U72: 01/06/2016 09:42:34 | V72: 3F | W72: 13.8 | X72: 45 | Y72: NÃO É REFORMADO | Z72: NÃO É REFORMADO | AA72: 31/01/2026 | AB72: 1630184 | AC72: 147276 | AD72: 75 | AE72: DLP-MPPA01 000047/2026 | AF72: DOLP-RD-PA | AG72: 112600420 | AH72: 1
A73: =_xlfn.CONCAT(Table1[[#This Row],[NÚMERO OPERATIVO]],Table1[[#This Row],[OS (SGM)]]) -> 5754615001DLP-CTPA00 000026/2026 | C73: ETO | D73: 5754615001DLP-CTPA00 000026/2026 | E73: CENTRO | F73: PALMAS | G73: PORTO NACIONAL | H73: URBANO | I73: AL06072001 | J73: 5754615001 | K73: =_xlfn.XLOOKUP(Table1[[#This Row],[NÚMERO OPERATIVO]],#REF!,#REF!) -> #REF! | L73: 20264112017863 | M73: =_xlfn.CONCAT(Table1[[#This Row],[NÚMERO OPERATIVO]],Table1[[#This Row],[DATA OC]]) -> 575461500146052,9749768519 | N73: 46052.975 | O73: QUEIMADO | P73: DESCARGA ATMOSFÉRICA | Q73: QUEIMADO | R73: 0 | S73: 0 | T73: ABB | U73: 06/02/2026 09:42:14 | V73: 3F | W73: 13.8 | X73: 10 | Y73: CPFL | Z73: CPFL | AA73: 06/02/2026 | AB73: 0 | AC73: 0 | AD73: 15 | AE73: DLP-CTPA00 000026/2026 | AF73: DOLP-RD-PA | AG73: 112600412 | AH73: 1
A74: =_xlfn.CONCAT(Table1[[#This Row],[NÚMERO OPERATIVO]],Table1[[#This Row],[OS (SGM)]]) -> 5700987070DLP-MLPA01 000031/2026 | C74: ETO | D74: 5700987070DLP-MLPA01 000031/2026 | E74: CENTRO | F74: PALMAS | G74: RIO SONO | H74: RURAL | I74: LD01059122 | J74: 5700987070 | K74: =_xlfn.XLOOKUP(Table1[[#This Row],[NÚMERO OPERATIVO]],#REF!,#REF!) -> #REF! | L74: 20264115195388 | M74: =_xlfn.CONCAT(Table1[[#This Row],[NÚMERO OPERATIVO]],Table1[[#This Row],[DATA OC]]) -> 570098707046055,7621990741 | N74: 46055.762 | O74: QUEIMADO | P74: NÃO IDENTIFICADO | Q74: QUEIMADO | R74: 432108 | S74: 138512 | T74: TRAEL | U74: 01/07/2017 09:08:18 | V74: 1F | W74: 13.8 | X74: 15 | Y74: NÃO É REFORMADO | Z74: NÃO É REFORMADO | AB74: 1600523 | AC74: 141819 | AD74: 15 | AE74: DLP-MLPA01 000031/2026 | AF74: DOLP-RD-PA | AG74: 112600237 | AH74: 1
A75: =_xlfn.CONCAT(Table1[[#This Row],[NÚMERO OPERATIVO]],Table1[[#This Row],[OS (SGM)]]) -> 5701020070DLP-CTPA00 000029/2026 | C75: ETO | D75: 5701020070DLP-CTPA00 000029/2026 | E75: CENTRO | F75: PALMAS | G75: RIO SONO | H75: RURAL | I75: LD01059122 | J75: 5701020070 | K75: =_xlfn.XLOOKUP(Table1[[#This Row],[NÚMERO OPERATIVO]],#REF!,#REF!) -> #REF! | L75: 20264117780778 | M75: =_xlfn.CONCAT(Table1[[#This Row],[NÚMERO OPERATIVO]],Table1[[#This Row],[DATA OC]]) -> 570102007046057,757349537 | N75: 46057.757 | O75: QUEIMADO | P75: NÃO IDENTIFICADO | Q75: QUEIMADO | R75: 976547 | S75: 120935 | T75: ABB | U75: 08/12/2021 11:59:05 | V75: 1F | W75: 13.8 | X75: 15 | Y75: CPFL | Z75: NÃO É REFORMADO | AA75: 08/12/2021 | AB75: 1575025 | AC75: 139127 | AD75: 25 | AE75: DLP-CTPA00 000029/2026 | AF75: DOLP-RD-PA | AG75: 112600259 | AH75: 1
A76: =_xlfn.CONCAT(Table1[[#This Row],[NÚMERO OPERATIVO]],Table1[[#This Row],[OS (SGM)]]) -> 5727478070DLP-MPPA01 000018/2026 | C76: ETO | D76: 5727478070DLP-MPPA01 000018/2026 | E76: CENTRO | F76: PALMAS | G76: RIO SONO | H76: RURAL | I76: LD01059122 | J76: 5727478070 | K76: =_xlfn.XLOOKUP(Table1[[#This Row],[NÚMERO OPERATIVO]],#REF!,#REF!) -> #REF! | L76: 20264069776275 | M76: =_xlfn.CONCAT(Table1[[#This Row],[NÚMERO OPERATIVO]],Table1[[#This Row],[DATA OC]]) -> 572747807046030,9197800926 | N76: 46030.92 | O76: QUEIMADO | P76: NÃO IDENTIFICADO | Q76: QUEIMADO | R76: 881805 | S76: 110838 | T76: TRAEL | U76: 01/07/2018 15:30:01 | V76: 3F | W76: 34.5 | X76: 30 | Y76: NÃO É REFORMADO | Z76: NÃO É REFORMADO | AA76: 15/01/2026 | AB76: 1616971 | AC76: 146099 | AD76: 45 | AE76: DLP-MPPA01 000018/2026 | AF76: DOLP-RD-PA | AG76: 112600103 | AH76: 1
A77: =_xlfn.CONCAT(Table1[[#This Row],[NÚMERO OPERATIVO]],Table1[[#This Row],[OS (SGM)]]) -> 5750063070DLP-MLPA01 000037/2026 | C77: ETO | D77: 5750063070DLP-MLPA01 000037/2026 | E77: CENTRO | F77: PALMAS | G77: RIO SONO | H77: RURAL | I77: LD01059122 | J77: 5750063070 | K77: =_xlfn.XLOOKUP(Table1[[#This Row],[NÚMERO OPERATIVO]],#REF!,#REF!) -> #REF! | L77: 20264117689404 | M77: =_xlfn.CONCAT(Table1[[#This Row],[NÚMERO OPERATIVO]],Table1[[#This Row],[DATA OC]]) -> 575006307046057,4490509259 | N77: 46057.449 | O77: QUEIMADO | P77: NÃO IDENTIFICADO | Q77: QUEIMADO | R77: 183338 | S77: 129306 | T77: TRAEL | U77: 06/02/2026 09:14:49 | V77: 3F | W77: 34.5 | X77: 30 | Y77: INTEL | Z77: NÃO É REFORMADO | AA77: 06/02/2026 | AB77: 183338 | AC77: 140204 | AD77: 30 | AE77: DLP-MLPA01 000037/2026 | AF77: DOLP-RD-PA | AG77: 112600306 | AH77: 1
A78: =_xlfn.CONCAT(Table1[[#This Row],[NÚMERO OPERATIVO]],Table1[[#This Row],[OS (SGM)]]) -> 5700269070DLP-MLPA01 000003/2026 | C78: ETO | D78: 5700269070DLP-MLPA01 000003/2026 | E78: CENTRO | F78: PALMAS | G78: RIO SONO | H78: RURAL | I78: LD02065015 | J78: 5700269070 | K78: =_xlfn.XLOOKUP(Table1[[#This Row],[NÚMERO OPERATIVO]],#REF!,#REF!) -> #REF! | L78: 20264064477470 | M78: =_xlfn.CONCAT(Table1[[#This Row],[NÚMERO OPERATIVO]],Table1[[#This Row],[DATA OC]]) -> 570026907046025,7566666667 | N78: 46025.757 | O78: QUEIMADO | P78: DESCARGA ATMOSFÉRICA | Q78: QUEIMADO | R78: 437885 | S78: 107963 | T78: TRAEL | U78: 01/08/2017 08:27:41 | V78: 1F | W78: 34.5 | X78: 15 | Y78: NÃO É REFORMADO | Z78: NÃO É REFORMADO | AA78: 28/02/2026 | AB78: 1615862 | AC78: 146340 | AD78: 15 | AE78: DLP-MLPA01 000003/2026 | AF78: DOLP-RD-PA | AH78: 1
A79: =_xlfn.CONCAT(Table1[[#This Row],[NÚMERO OPERATIVO]],Table1[[#This Row],[OS (SGM)]]) -> 5710132070DLP-MPPA01 000006/2026 | C79: ETO | D79: 5710132070DLP-MPPA01 000006/2026 | E79: CENTRO | F79: PALMAS | G79: RIO SONO | H79: RURAL | I79: LD02065015 | J79: 5710132070 | K79: =_xlfn.XLOOKUP(Table1[[#This Row],[NÚMERO OPERATIVO]],#REF!,#REF!) -> #REF! | L79: 20264064490284 | M79: =_xlfn.CONCAT(Table1[[#This Row],[NÚMERO OPERATIVO]],Table1[[#This Row],[DATA OC]]) -> 571013207046025,7654050926 | N79: 46025.765 | O79: QUEIMADO | P79: DESCARGA ATMOSFÉRICA | Q79: QUEIMADO | R79: 319620 | S79: 134589 | T79: TRAEL | U79: 01/11/2019 16:08:25 | V79: 3F | W79: 34.5 | X79: 45 | Y79: NÃO É REFORMADO | Z79: NÃO É REFORMADO | AA79: 08/01/2026 | AB79: 586777 | AC79: 147740 | AD79: 45 | AE79: DLP-MPPA01 000006/2026 | AF79: DOLP-RD-PA | AG79: 112600055 | AH79: 1
A80: =_xlfn.CONCAT(Table1[[#This Row],[NÚMERO OPERATIVO]],Table1[[#This Row],[OS (SGM)]]) -> 5720051070DLP-MLPA01 000065/2026 | C80: ETO | D80: 5720051070DLP-MLPA01 000065/2026 | E80: CENTRO | F80: PALMAS | G80: RIO SONO | H80: RURAL | I80: LD02065015 | J80: 5720051070 | K80: =_xlfn.XLOOKUP(Table1[[#This Row],[NÚMERO OPERATIVO]],#REF!,#REF!) -> #REF! | L80: 20264128088092 | M80: =_xlfn.CONCAT(Table1[[#This Row],[NÚMERO OPERATIVO]],Table1[[#This Row],[DATA OC]]) -> 572005107046068,5126041667 | N80: 46068.513 | O80: QUEIMADO | P80: DESCARGA ATMOSFÉRICA | Q80: QUEIMADO | R80: 368898 | S80: 0 | T80: TOSHIBA | U80: 01/09/1999 15:26:08 | V80: 1F | W80: 34.5 | X80: 15 | Y80: TRAEL | Z80: NÃO É REFORMADO | AA80: 11/04/2016 | AB80: 296104 | AC80: 148854 | AD80: 15 | AE80: DLP-MLPA01 000065/2026 | AF80: DOLP-RD-PA | AG80: 112600277 | AH80: 1
A81: =_xlfn.CONCAT(Table1[[#This Row],[NÚMERO OPERATIVO]],Table1[[#This Row],[OS (SGM)]]) -> 5735342070DLP-MLPA01 000069/2026 | C81: ETO | D81: 5735342070DLP-MLPA01 000069/2026 | E81: CENTRO | F81: PALMAS | G81: RIO SONO | H81: RURAL | I81: LD02065015 | J81: 5735342070 | K81: =_xlfn.XLOOKUP(Table1[[#This Row],[NÚMERO OPERATIVO]],#REF!,#REF!) -> #REF! | L81: 20264128657568 | M81: =_xlfn.CONCAT(Table1[[#This Row],[NÚMERO OPERATIVO]],Table1[[#This Row],[DATA OC]]) -> 573534207046069,4921412037 | N81: 46069.492 | O81: QUEIMADO | P81: DESCARGA ATMOSFÉRICA | Q81: QUEIMADO | V81: 1F | W81: 13.8 | X81: 15 | AD81: 15 | AE81: DLP-MLPA01 000069/2026 | AF81: DOLP-RD-PA | AG81: 112600413 | AH81: 1
A82: =_xlfn.CONCAT(Table1[[#This Row],[NÚMERO OPERATIVO]],Table1[[#This Row],[OS (SGM)]]) -> 5700095151DLP-MLPA01 000006/2026 | C82: ETO | D82: 5700095151DLP-MLPA01 000006/2026 | E82: CENTRO | F82: PALMAS | G82: SANTA TEREZA DO TOCANTINS | H82: RURAL | I82: LD02059122 | J82: 5700095151 | K82: =_xlfn.XLOOKUP(Table1[[#This Row],[NÚMERO OPERATIVO]],#REF!,#REF!) -> #REF! | L82: 20264070940996 | M82: =_xlfn.CONCAT(Table1[[#This Row],[NÚMERO OPERATIVO]],Table1[[#This Row],[DATA OC]]) -> 570009515146032,8476851852 | N82: 46032.848 | O82: QUEIMADO | P82: DESCARGA ATMOSFÉRICA | Q82: QUEIMADO | R82: 370615 | S82: ILEGIVEL | T82: TOSHIBA | U82: 01/06/1999 07:43:15 | V82: 1F | W82: 34.5 | X82: 15 | Y82: NÃO É REFORMADO | Z82: NÃO É REFORMADO | AA82: 16/01/2026 | AB82: 271325 | AC82: 145136 | AD82: 25 | AE82: DLP-MLPA01 000006/2026 | AF82: DOLP-RD-PA | AG82: 112600107 | AH82: 1
A83: =_xlfn.CONCAT(Table1[[#This Row],[NÚMERO OPERATIVO]],Table1[[#This Row],[OS (SGM)]]) -> 5700121151DLP-CTPA01 000001/2026 | C83: ETO | D83: 5700121151DLP-CTPA01 000001/2026 | E83: CENTRO | F83: PALMAS | G83: SANTA TEREZA DO TOCANTINS | H83: RURAL | I83: LD02059122 | J83: 5700121151 | K83: =_xlfn.XLOOKUP(Table1[[#This Row],[NÚMERO OPERATIVO]],#REF!,#REF!) -> #REF! | L83: 20264062540292 | M83: =_xlfn.CONCAT(Table1[[#This Row],[NÚMERO OPERATIVO]],Table1[[#This Row],[DATA OC]]) -> 570012115146024,6448726852 | N83: 46024.645 | O83: QUEIMADO | P83: NÃO IDENTIFICADO | Q83: QUEIMADO | R83: 0 | S83: 0 | T83: ABB | U83: 19/01/2026 09:36:39 | V83: 3F | W83: 34.5 | X83: 10 | Y83: CPFL | Z83: CPFL | AB83: 0 | AC83: 0 | AD83: 15 | AE83: DLP-CTPA01 000001/2026 | AF83: DOLP-RD-PA | AG83: 112600438 | AH83: 1
A84: =_xlfn.CONCAT(Table1[[#This Row],[NÚMERO OPERATIVO]],Table1[[#This Row],[OS (SGM)]]) -> 5700430151DLP-MLPA02 000019/2026 | C84: ETO | D84: 5700430151DLP-MLPA02 000019/2026 | E84: CENTRO | F84: PALMAS | G84: SANTA TEREZA DO TOCANTINS | H84: RURAL | I84: LD02059122 | J84: 5700430151 | K84: =_xlfn.XLOOKUP(Table1[[#This Row],[NÚMERO OPERATIVO]],#REF!,#REF!) -> #REF! | L84: 1H | M84: =_xlfn.CONCAT(Table1[[#This Row],[NÚMERO OPERATIVO]],Table1[[#This Row],[DATA OC]]) -> 570043015146076,9072800926 | N84: 46076.907 | O84: QUEIMADO | P84: NÃO IDENTIFICADO | Q84: QUEIMADO | V84: 1F | W84: 34.5 | X84: 15 | AD84: 15 | AE84: DLP-MLPA02 000019/2026 | AF84: DOLP-RD-PA | AG84: 112600294 | AH84: 1
A85: =_xlfn.CONCAT(Table1[[#This Row],[NÚMERO OPERATIVO]],Table1[[#This Row],[OS (SGM)]]) -> 5700545151DLP-MLPA01 000026/2026 | C85: ETO | D85: 5700545151DLP-MLPA01 000026/2026 | E85: CENTRO | F85: PALMAS | G85: SANTA TEREZA DO TOCANTINS | H85: RURAL | I85: LD02059122 | J85: 5700545151 | K85: =_xlfn.XLOOKUP(Table1[[#This Row],[NÚMERO OPERATIVO]],#REF!,#REF!) -> #REF! | L85: 20264100843636 | M85: =_xlfn.CONCAT(Table1[[#This Row],[NÚMERO OPERATIVO]],Table1[[#This Row],[DATA OC]]) -> 570054515146051,4372916667 | N85: 46051.437 | O85: QUEIMADO | P85: DESCARGA ATMOSFÉRICA | Q85: QUEIMADO | R85: 500269 | S85: 119959 | T85: TRAEL | U85: 01/04/2019 09:59:08 | V85: 1F | W85: 34.5 | X85: 15 | Y85: NÃO É REFORMADO | Z85: NÃO É REFORMADO | AA85: 04/02/2026 | AB85: 290378 | AC85: 149785 | AD85: 15 | AE85: DLP-MLPA01 000026/2026 | AF85: DOLP-RD-PA | AG85: 112600415 | AH85: 1
A86: =_xlfn.CONCAT(Table1[[#This Row],[NÚMERO OPERATIVO]],Table1[[#This Row],[OS (SGM)]]) -> 5700260006DLP-MLPA01 000075/2026 | C86: ETO | D86: 5700260006DLP-MLPA01 000075/2026 | E86: CENTRO | F86: PALMAS | G86: TOCANTINIA | H86: RURAL | I86: LD02065015 | J86: 5700260006 | K86: =_xlfn.XLOOKUP(Table1[[#This Row],[NÚMERO OPERATIVO]],#REF!,#REF!) -> #REF! | L86: 20264133311711 | M86: =_xlfn.CONCAT(Table1[[#This Row],[NÚMERO OPERATIVO]],Table1[[#This Row],[DATA OC]]) -> 570026000646074,6022106481 | N86: 46074.602 | O86: QUEIMADO | P86: NÃO IDENTIFICADO | Q86: QUEIMADO | V86: 1F | W86: 34.5 | X86: 15 | AD86: 15 | AE86: DLP-MLPA01 000075/2026 | AF86: DOLP-RD-PA | AH86: 1
A87: =_xlfn.CONCAT(Table1[[#This Row],[NÚMERO OPERATIVO]],Table1[[#This Row],[OS (SGM)]]) -> 5700226006DLP-MLPA01 000057/2026 | C87: ETO | D87: 5700226006DLP-MLPA01 000057/2026 | E87: CENTRO | F87: PALMAS | G87: TOCANTINIA | H87: RURAL | I87: LD03059122 | J87: 5700226006 | K87: =_xlfn.XLOOKUP(Table1[[#This Row],[NÚMERO OPERATIVO]],#REF!,#REF!) -> #REF! | L87: 20264123852423 | M87: =_xlfn.CONCAT(Table1[[#This Row],[NÚMERO OPERATIVO]],Table1[[#This Row],[DATA OC]]) -> 570022600646064,5364930556 | N87: 46064.536 | O87: QUEIMADO | P87: NÃO IDENTIFICADO | Q87: QUEIMADO | V87: 1F | W87: 34.5 | X87: 15 | AD87: 15 | AE87: DLP-MLPA01 000057/2026 | AF87: DOLP-RD-PA | AG87: 112600405 | AH87: 1
A88: =_xlfn.CONCAT(Table1[[#This Row],[NÚMERO OPERATIVO]],Table1[[#This Row],[OS (SGM)]]) -> 5700837006DLP-MLPA01 000036/2026 | C88: ETO | D88: 5700837006DLP-MLPA01 000036/2026 | E88: CENTRO | F88: PALMAS | G88: TOCANTINIA | H88: RURAL | I88: LD03059122 | J88: 5700837006 | K88: =_xlfn.XLOOKUP(Table1[[#This Row],[NÚMERO OPERATIVO]],#REF!,#REF!) -> #REF! | L88: 20264117069417 | M88: =_xlfn.CONCAT(Table1[[#This Row],[NÚMERO OPERATIVO]],Table1[[#This Row],[DATA OC]]) -> 570083700646056,7833564815 | N88: 46056.783 | O88: QUEIMADO | P88: NÃO IDENTIFICADO | Q88: QUEIMADO | R88: 464670 | S88: 113663 | T88: TRAEL | U88: 01/04/2018 15:42:08 | V88: 1F | W88: 34.5 | X88: 15 | Y88: NÃO É REFORMADO | Z88: NÃO É REFORMADO | AB88: 464856 | AC88: 113849 | AD88: 15 | AE88: DLP-MLPA01 000036/2026 | AF88: DOLP-RD-PA | AG88: 112600257 | AH88: 1
A89: =_xlfn.CONCAT(Table1[[#This Row],[NÚMERO OPERATIVO]],Table1[[#This Row],[OS (SGM)]]) -> 5709566006DLP-MLPA02 000008/2026 | C89: ETO | D89: 5709566006DLP-MLPA02 000008/2026 | E89: CENTRO | F89: PALMAS | G89: TOCANTINIA | H89: RURAL | I89: LD03059122 | J89: 5709566006 | K89: =_xlfn.XLOOKUP(Table1[[#This Row],[NÚMERO OPERATIVO]],#REF!,#REF!) -> #REF! | L89: 20264092651718 | M89: =_xlfn.CONCAT(Table1[[#This Row],[NÚMERO OPERATIVO]],Table1[[#This Row],[DATA OC]]) -> 570956600646044,8860648148 | N89: 46044.886 | O89: QUEIMADO | P89: VAZAMENTO DE ÓLEO | Q89: QUEIMADO | R89: 389722 | S89: 130842 | T89: TRAEL | U89: 01/02/2022 09:28:21 | V89: 1F | W89: 13.8 | X89: 15 | Y89: NÃO É REFORMADO | Z89: NÃO É REFORMADO | AA89: 30/01/2026 | AB89: 799480 | AC89: 149131 | AD89: 15 | AE89: DLP-MLPA02 000008/2026 | AF89: DOLP-RD-PA | AH89: 1
A90: =_xlfn.CONCAT(Table1[[#This Row],[NÚMERO OPERATIVO]],Table1[[#This Row],[OS (SGM)]]) -> 5710112006DLP-MLPA01 000010/2026 | C90: ETO | D90: 5710112006DLP-MLPA01 000010/2026 | E90: CENTRO | F90: PALMAS | G90: TOCANTINIA | H90: RURAL | I90: LD03059122 | J90: 5710112006 | K90: =_xlfn.XLOOKUP(Table1[[#This Row],[NÚMERO OPERATIVO]],#REF!,#REF!) -> #REF! | L90: 20264080749923 | M90: =_xlfn.CONCAT(Table1[[#This Row],[NÚMERO OPERATIVO]],Table1[[#This Row],[DATA OC]]) -> 571011200646036,9109606482 | N90: 46036.911 | O90: QUEIMADO | P90: DESCARGA ATMOSFÉRICA | Q90: QUEIMADO | R90: 370612 | S90: ILEGIVEL | T90: INTEL | U90: 01/11/1999 09:57:39 | V90: 1F | W90: 34.5 | X90: 15 | Y90: NÃO É REFORMADO | Z90: NÃO É REFORMADO | AA90: 19/01/2026 | AB90: 1800587 | AC90: 144167 | AD90: 15 | AE90: DLP-MLPA01 000010/2026 | AF90: DOLP-RD-PA | AG90: 112600276 | AH90: 1
A91: =_xlfn.CONCAT(Table1[[#This Row],[NÚMERO OPERATIVO]],Table1[[#This Row],[OS (SGM)]]) -> 5722285006DLP-MPPA01 000076/2026 | C91: ETO | D91: 5722285006DLP-MPPA01 000076/2026 | E91: CENTRO | F91: PALMAS | G91: TOCANTINIA | H91: RURAL | I91: LD03059122 | J91: 5722285006 | K91: =_xlfn.XLOOKUP(Table1[[#This Row],[NÚMERO OPERATIVO]],#REF!,#REF!) -> #REF! | L91: será aberta em campo | M91: =_xlfn.CONCAT(Table1[[#This Row],[NÚMERO OPERATIVO]],Table1[[#This Row],[DATA OC]]) -> 572228500646081,3366203704 | N91: 46081.337 | O91: QUEIMADO | P91: VAZAMENTO DE ÓLEO | Q91: QUEIMADO | V91: 3F | W91: 34.5 | X91: 30 | AD91: 30 | AE91: DLP-MPPA01 000076/2026 | AF91: DOLP-RD-PA | AG91: 112600434 | AH91: 1
A92: =_xlfn.CONCAT(Table1[[#This Row],[NÚMERO OPERATIVO]],Table1[[#This Row],[OS (SGM)]]) -> 5710162006DLP-MLPA01 000008/2026 | C92: ETO | D92: 5710162006DLP-MLPA01 000008/2026 | E92: CENTRO | F92: PALMAS | G92: TOCANTINIA | H92: RURAL | I92: LD05050008 | J92: 5710162006 | K92: =_xlfn.XLOOKUP(Table1[[#This Row],[NÚMERO OPERATIVO]],#REF!,#REF!) -> #REF! | L92: 20264079469262 | M92: =_xlfn.CONCAT(Table1[[#This Row],[NÚMERO OPERATIVO]],Table1[[#This Row],[DATA OC]]) -> 571016200646035,646087963 | N92: 46035.646 | O92: QUEIMADO | P92: DESCARGA ATMOSFÉRICA | Q92: QUEIMADO | R92: 437885 | S92: 107963 | T92: TRAEL | U92: 01/08/2017 08:40:40 | V92: 1F | W92: 34.5 | X92: 15 | Y92: NÃO É REFORMADO | Z92: NÃO É REFORMADO | AA92: 16/01/2026 | AB92: 1615862 | AC92: 146340 | AD92: 15 | AE92: DLP-MLPA01 000008/2026 | AF92: DOLP-RD-PA | AG92: 112600120 | AH92: 1
A93: =_xlfn.CONCAT(Table1[[#This Row],[NÚMERO OPERATIVO]],Table1[[#This Row],[OS (SGM)]]) -> 5710169006DLP-MLPA01 000020/2026 | C93: ETO | D93: 5710169006DLP-MLPA01 000020/2026 | E93: CENTRO | F93: PALMAS | G93: TOCANTINIA | H93: RURAL | I93: LD05050008 | J93: 5710169006 | K93: =_xlfn.XLOOKUP(Table1[[#This Row],[NÚMERO OPERATIVO]],#REF!,#REF!) -> #REF! | L93: 20264097251487 | M93: =_xlfn.CONCAT(Table1[[#This Row],[NÚMERO OPERATIVO]],Table1[[#This Row],[DATA OC]]) -> 571016900646047,4262847222 | N93: 46047.426 | O93: QUEIMADO | P93: NÃO IDENTIFICADO | Q93: QUEIMADO | R93: 358539 | S93: ILEGIVEL | T93: ITB | U93: 01/10/2005 17:45:54 | V93: 1F | W93: 34.5 | X93: 15 | Y93: NÃO É REFORMADO | Z93: NÃO É REFORMADO | AA93: 29/01/2026 | AB93: 464890 | AC93: ILEGIVEL | AD93: 15 | AE93: DLP-MLPA01 000020/2026 | AF93: DOLP-RD-PA | AG93: 112600156 | AH93: 1
A94: =_xlfn.CONCAT(Table1[[#This Row],[NÚMERO OPERATIVO]],Table1[[#This Row],[OS (SGM)]]) -> 5700278055ENC-LMPS03 000044/2026 | C94: ETO | D94: 5700278055ENC-LMPS03 000044/2026 | E94: CENTRO | F94: PARAISO | G94: ARAGUACEMA | H94: RURAL | I94: LD01434149 | J94: 5700278055 | K94: =_xlfn.XLOOKUP(Table1[[#This Row],[NÚMERO OPERATIVO]],#REF!,#REF!) -> #REF! | L94: 20264127786599 | M94: =_xlfn.CONCAT(Table1[[#This Row],[NÚMERO OPERATIVO]],Table1[[#This Row],[DATA OC]]) -> 570027805546067,5030787037 | N94: 46067.503 | O94: QUEIMADO | P94: DESCARGA ATMOSFÉRICA | Q94: QUEIMADO | R94: 304519 | S94: ILEGÍVEL | T94: ITB | U94: 01/01/2005 08:26:08 | V94: 1F | W94: 34.5 | X94: 15 | Y94: INTEL | Z94: TRAEL | AB94: 1015827 | AC94: 100026 | AD94: 15 | AE94: ENC-LMPS03 000044/2026 | AF94: ENC-RD-PS | AG94: 212600204 | AH94: 1
A95: =_xlfn.CONCAT(Table1[[#This Row],[NÚMERO OPERATIVO]],Table1[[#This Row],[OS (SGM)]]) -> 5700288055ENC-LMPS03 000014/2026 | C95: ETO | D95: 5700288055ENC-LMPS03 000014/2026 | E95: CENTRO | F95: PARAISO | G95: ARAGUACEMA | H95: RURAL | I95: LD01434149 | J95: 5700288055 | K95: =_xlfn.XLOOKUP(Table1[[#This Row],[NÚMERO OPERATIVO]],#REF!,#REF!) -> #REF! | L95: 20264074259909 | M95: =_xlfn.CONCAT(Table1[[#This Row],[NÚMERO OPERATIVO]],Table1[[#This Row],[DATA OC]]) -> 570028805546035,4169212963 | N95: 46035.417 | O95: QUEIMADO | P95: DESCARGA ATMOSFÉRICA | Q95: QUEIMADO | R95: 1236642 | S95: 124736 | T95: ROMAGNOLE | U95: 01/06/2020 16:10:15 | V95: 3F | W95: 34.5 | X95: 30 | Y95: NÃO É REFORMADO | Z95: CPFL | AB95: 1219871 | AC95: 122290 | AD95: 30 | AE95: ENC-LMPS03 000014/2026 | AF95: ENC-RD-PS | AG95: 212600081 | AH95: 1
A96: =_xlfn.CONCAT(Table1[[#This Row],[NÚMERO OPERATIVO]],Table1[[#This Row],[OS (SGM)]]) -> 5700561055ENC-LMPS03 000026/2026 | C96: ETO | D96: 5700561055ENC-LMPS03 000026/2026 | E96: CENTRO | F96: PARAISO | G96: ARAGUACEMA | H96: RURAL | I96: LD01434149 | J96: 5700561055 | K96: =_xlfn.XLOOKUP(Table1[[#This Row],[NÚMERO OPERATIVO]],#REF!,#REF!) -> #REF! | L96: 20264100883502 | M96: =_xlfn.CONCAT(Table1[[#This Row],[NÚMERO OPERATIVO]],Table1[[#This Row],[DATA OC]]) -> 570056105546049,563900463 | N96: 46049.564 | O96: QUEIMADO | P96: DESCARGA ATMOSFÉRICA | Q96: QUEIMADO | R96: 449538 | S96: 109716 | T96: TRAEL | U96: 01/11/2017 08:54:54 | V96: 1F | W96: 34.5 | X96: 15 | Y96: NÃO É REFORMADO | AB96: Z275779 | AC96: 146642 | AD96: 25 | AE96: ENC-LMPS03 000026/2026 | AF96: ENC-RD-PS | AG96: 212600122 | AH96: 1
A97: =_xlfn.CONCAT(Table1[[#This Row],[NÚMERO OPERATIVO]],Table1[[#This Row],[OS (SGM)]]) -> 5700809055ENC-LMPS03 000017/2026 | C97: ETO | D97: 5700809055ENC-LMPS03 000017/2026 | E97: CENTRO | F97: PARAISO | G97: ARAGUACEMA | H97: RURAL | I97: LD01434149 | J97: 5700809055 | K97: =_xlfn.XLOOKUP(Table1[[#This Row],[NÚMERO OPERATIVO]],#REF!,#REF!) -> #REF! | L97: 20264084940883 | M97: =_xlfn.CONCAT(Table1[[#This Row],[NÚMERO OPERATIVO]],Table1[[#This Row],[DATA OC]]) -> 570080905546038,841087963 | N97: 46038.841 | O97: QUEIMADO | P97: DESCARGA ATMOSFÉRICA | Q97: QUEIMADO | R97: 431703 | S97: 104933 | T97: TRAEL | U97: 01/06/2017 14:24:36 | V97: 1F | W97: 34.5 | X97: 15 | Y97: NÃO É REFORMADO | AB97: C290404 | AC97: 149811 | AD97: 15 | AE97: ENC-LMPS03 000017/2026 | AF97: ENC-RD-PS | AG97: 212600086 | AH97: 1
A98: =_xlfn.CONCAT(Table1[[#This Row],[NÚMERO OPERATIVO]],Table1[[#This Row],[OS (SGM)]]) -> 5701204055ENC-LMPS04 000002/2026 | C98: ETO | D98: 5701204055ENC-LMPS04 000002/2026 | E98: CENTRO | F98: PARAISO | G98: ARAGUACEMA | H98: RURAL | I98: LD01434149 | J98: 5701204055 | K98: =_xlfn.XLOOKUP(Table1[[#This Row],[NÚMERO OPERATIVO]],#REF!,#REF!) -> #REF! | L98: 20264064931219 | M98: =_xlfn.CONCAT(Table1[[#This Row],[NÚMERO OPERATIVO]],Table1[[#This Row],[DATA OC]]) -> 570120405546027,7132407407 | N98: 46027.713 | O98: QUEIMADO | P98: DESCARGA ATMOSFÉRICA | Q98: QUEIMADO | R98: 181043 | S98: 134748 | T98: ABB | U98: 01/11/2009 09:52:53 | V98: 1F | W98: 13.8 | X98: 15 | Y98: TRAEL | AB98: Z260806 | AC98: 144275 | AD98: 25 | AE98: ENC-LMPS04 000002/2026 | AF98: ENC-RD-PS | AG98: 212600051 | AH98: 1
A99: =_xlfn.CONCAT(Table1[[#This Row],[NÚMERO OPERATIVO]],Table1[[#This Row],[OS (SGM)]]) -> 5701249055ENC-LMPS03 000037/2026 | C99: ETO | D99: 5701249055ENC-LMPS03 000037/2026 | E99: CENTRO | F99: PARAISO | G99: ARAGUACEMA | H99: RURAL | I99: LD01434149 | J99: 5701249055 | K99: =_xlfn.XLOOKUP(Table1[[#This Row],[NÚMERO OPERATIVO]],#REF!,#REF!) -> #REF! | L99: 20264117766169 | M99: =_xlfn.CONCAT(Table1[[#This Row],[NÚMERO OPERATIVO]],Table1[[#This Row],[DATA OC]]) -> 570124905546057,7369791667 | N99: 46057.737 | O99: QUEIMADO | P99: DESCARGA ATMOSFÉRICA | Q99: QUEIMADO | R99: 217368 | S99: 002249 | T99: TRAEL | U99: 01/03/2011 11:01:39 | V99: 1F | W99: 34.5 | X99: 5 | Y99: NÃO É REFORMADO | AA99: 09/02/2026 | AB99: 297826 | AC99: 149867 | AD99: 15 | AE99: ENC-LMPS03 000037/2026 | AF99: ENC-RD-PS | AG99: 212600166 | AH99: 1
A100: =_xlfn.CONCAT(Table1[[#This Row],[NÚMERO OPERATIVO]],Table1[[#This Row],[OS (SGM)]]) -> 5701380055ENC-LMPS04 000040/2026 | C100: ETO | D100: 5701380055ENC-LMPS04 000040/2026 | E100: CENTRO | F100: PARAISO | G100: ARAGUACEMA | H100: RURAL | I100: LD01434149 | J100: 5701380055 | K100: =_xlfn.XLOOKUP(Table1[[#This Row],[NÚMERO OPERATIVO]],#REF!,#REF!) -> #REF! | L100: 20264131935591 | M100: =_xlfn.CONCAT(Table1[[#This Row],[NÚMERO OPERATIVO]],Table1[[#This Row],[DATA OC]]) -> 570138005546072,7938310185 | N100: 46072.794 | O100: QUEIMADO | P100: DESCARGA ATMOSFÉRICA | Q100: QUEIMADO | R100: 203587 | S100: ILEGÍVEL | T100: VIJAI | U100: 01/01/2012 10:45:46 | V100: 1F | W100: 34.5 | X100: 5 | Y100: NÃO É REFORMADO | AB100: 1622915 | AC100: 143216 | AD100: 15 | AE100: ENC-LMPS04 000040/2026 | AF100: ENC-RD-PS | AG100: 212600231 | AH100: 1
...

Sheet Planilha1
A1: NUMERO_OS | B1: (Tudo)
A2: MATHEUS | B2: #N/D
B4: Rótulos de Coluna
B5: jan | C5: fev | D5: mar | E5: abr | F5: mai | G5: jun | H5: Total Geral
A6: Contagem de NUMERO_SS | B6: 47 | C6: 53 | D6: 40 | E6: 24 | F6: 19 | G6: 26 | H6: 209

Sheet Planilha4
A1: VALIDAÇÃO | B1: ÑOK
B3: Rótulos de Coluna
B4: jan | C4: fev | D4: mar | E4: abr | F4: mai | G4: jun | H4: Total Geral
A7: Contagem de NUMERO_SS | B7: 32 | C7: 38 | D7: 31 | E7: 10 | F7: 9 | G7: 13 | H7: 133

Sheet BASE GERAL
A1: NUMERO_SS | B1: NUMERO_OS | C1: NUM_OBRA | D1: SIGCO | E1: Coluna1 | F1: ORIGEM_SS | G1: DEFEITO_SS | H1: ORIGEM | I1: DEFEITO | J1: ESQUEMA | K1: TASK | L1: ANO | M1: ORG_SOLIC | N1: COD_EQUIPE | O1: ALIMENTADOR | P1: NUM_TRAFO | Q1: MATHEUS | R1: Coluna2 | S1: COORD_X | T1: COORD_Y | U1: COD_GIS | V1: CRITICIDADE_SS | W1: SITUACAO_SS | X1: DATA_ABERTURA_SS | Y1: DATA_TERMINO_SS | Z1: DATA_LIMITE_SS | AA1: DESCICAO_DO_ATIVO | AB1: LOCALIDADE | AC1: SOLICITANTE | AD1: RURA_URBANO | AE1: TIPOSS | AF1: DESCRIPTION | AG1: POTENCIA_INST | AH1: POTENCIA_RET | AI1: POT_RET | AJ1: DATA_ATUALIZACAO | AK1: VALIDAÇÃO | AL1: MOTIVO | AM1: SIGCO CORRETO?
A2: ETO-RD-GR 00405/2026 | B2: ENC-MLGR03 000150/2026 | C2: 712600284 | D2: 8812 | E2: FORMS | F2: AVARIADO | G2: BUCHA DANIFICADA | H2: AVARIADO | I2: VAZAMENTO DE ÓLEO | J2: MC - SUBSTITUIÇÃO DE TRANSFORMADOR | K2: 1327652 | L2: 2026 | M2: COI | N2: ETO-RD-GR | O2: LD03022033 | P2: 5700001112 | Q2: LD03022033 | S2: 736517 | T2: 9042906 | U2: 190-13711017 | V2: EMERGENCIAL | W2: SS ATENDIDA | X2: 46118.706 | Y2: 46119.062 | Z2: 46121.706 | AA2: BLOCO TRANSFORMADOR DE DISTRIBUIÇÃO | AB2: COLMEIA | AC2: CLEIBER DA SILVA | AD2: RURAL | AE2: FORMS SUBST DE TRANSFORMADOR | AF2: acionar equipe de manutencao para troca de trafo avariado na RDU de Goainir dos campos e chave danificada fase Atrafo 5700001112Equipe 033po01 | AG2: 1125 | AH2: 1125 | AI2: 112 | AJ2: 46224.798 | AN2: =_xlfn.XLOOKUP(B2,'Exportar Planilha'!B:B,'Exportar Planilha'!E:E) -> 0
A3: ETO-RD-GR 00530/2026 | B3: ENC-MPGR01 000085/2026 | C3: 712600361 | D3: 8812 | E3: FORMS | F3: AVARIADO | G3: VAZAMENTO DE ÓLEO | H3: AVARIADO | I3: VAZAMENTO DE ÓLEO | J3: MC - SUBSTITUIÇÃO DE TRANSFORMADOR | K3: 1345879 | L3: 2026 | M3: COI | N3: ETO-RD-GR | O3: LD03022033 | P3: 5700001112 | Q3: LD03022033 | S3: 736517 | T3: 9042906 | U3: 190-13711017 | V3: EMERGENCIAL | W3: SS ATENDIDA | X3: 46157.752 | Y3: 46158.639 | Z3: 46160.752 | AA3: BLOCO TRANSFORMADOR DE DISTRIBUIÇÃO | AB3: COLMEIA | AC3: SIRDEIS ALVES MONTEIRO | AD3: RURAL | AE3: FORMS SUBST DE TRANSFORMADOR | AF3: por favor deslocar equipe da manutenção pesada no trafo 5700001112 com vazamento de oleo substituir o mesmo 112,5 kva 34,5 kv acesso bom | AG3: 150 | AH3: 1125 | AI3: 112,5 kv | AJ3: 46224.798 | AN3: =_xlfn.XLOOKUP(B3,'Exportar Planilha'!B:B,'Exportar Planilha'!E:E) -> 0
A4: ETO-RD-AG 00721/2026 | B4: ENC-MPAG02 000126/2026 | C4: 662600453 | D4: 0 | E4: FORMS | F4: AVARIADO | G4: SOBRECARGA | H4: QUEIMADO | I4: DESCARGA ATMOSFÉRICA | J4: MC - SUBSTITUIÇÃO DE TRANSFORMADOR | K4: 1367207 | L4: 2026 | M4: MANUT | N4: ETO-RD-AG | O4: LD02014045 | P4: 5700021133 | Q4: #N/A | S4: 839120 | T4: 9407529 | U4: 190-13649332 | V4: EMERGENCIAL | W4: SS ATENDIDA | X4: 46218.659 | Y4: 46218.931 | Z4: 46221.659 | AA4: BLOCO TRANSFORMADOR DE DISTRIBUIÇÃO | AB4: CARRASCO BONITO | AC4: LEANDRO BISPO DE BARROS | AD4: RURAL | AE4: FORMS SUBST DE TRANSFORMADOR | AF4: trafo 5700021133 queimado 43 UC's ligadas em campo., favor realizar melhoria de aterramento. SOBRECARGA - Trafo de 25 Kva com 43 UC's ligadas em campo. | AG4: 25 | AH4: 25 | AI4: 25kva | AJ4: 46224.798
A5: ENC-RD-PS 00364/2026 | B5: ETO-RD-PS 000755/2026 | D5: #N/A | E5: FORMS | F5: AVARIADO | G5: BUCHA DANIFICADA | H5: AVARIADO | I5: COLA E FITA | J5: MC - EQUIPAMENTOS | K5: 1322338 | L5: 2026 | M5: COI | N5: ENC-RD-PS | O5: LD01062013 | P5: 5700001180 | Q5: LD01062013 | S5: 731158 | T5: 8864197 | U5: 190-13679907 | V5: EMERGENCIAL | W5: SS ATENDIDA | X5: 46100.667 | Y5: 46101.521 | Z5: 46103.667 | AA5: BLOCO TRANSFORMADOR DE DISTRIBUIÇÃO | AB5: PARAISO DO TOCANTINS | AC5: THIAGO BORGES DE OLIVEIRA | AD5: RURAL | AE5: FORMS SUBST DE TRANSFORMADOR | AF5: Segue ss para tratativa com equipe de manutençao o quanto antessubstituir trafo 5700001180 com vazamento de oleo na santana | AI5: 25 | AJ5: 46224.798 | AN5: =_xlfn.XLOOKUP(B5,'Exportar Planilha'!B:B,'Exportar Planilha'!E:E) -> 0
